{
  "type": "Feature",
  "properties": {
    "gn:admin1_code":"8.0",
    "gn:admin2_code":"702.0",
    "gn:admin3_code":"70250.0",
    "gn:asciiname":"Playas",
    "gn:country_code":"EC",
    "gn:dem":116,
    "gn:feature_class":"P",
    "gn:feature_code":"PPL",
    "gn:name":"Playas",
    "gn:population":0,
    "gn:timezone":"America/Guayaquil",
    "iso:country":"EC",
    "wof:name":"Playas",
    "wof:placetype":"locality"
},
  "geometry": {"coordinates":[-79.96061999999998,-3.63333],"type":"Point"}
}