{
  "type": "Feature",
  "properties": {
    "gn:admin1_code":"2.0",
    "gn:admin2_code":"109.0",
    "gn:admin3_code":"10951.0",
    "gn:asciiname":"Zhuczhuc",
    "gn:country_code":"EC",
    "gn:dem":2449,
    "gn:feature_class":"P",
    "gn:feature_code":"PPL",
    "gn:name":"Zhuczhuc",
    "gn:population":0,
    "gn:timezone":"America/Guayaquil",
    "iso:country":"EC",
    "wof:name":"Zhuczhuc",
    "wof:placetype":"locality"
},
  "geometry": {"coordinates":[-78.78333000000001,-3.08333],"type":"Point"}
}