{
  "type": "Feature",
  "properties": {
    "gn:admin1_code":"2.0",
    "gn:admin2_code":"101.0",
    "gn:admin3_code":"10165.0",
    "gn:asciiname":"Miguir",
    "gn:country_code":"EC",
    "gn:dem":3478,
    "gn:feature_class":"P",
    "gn:feature_code":"PPL",
    "gn:name":"Miguir",
    "gn:population":0,
    "gn:timezone":"America/Guayaquil",
    "iso:country":"EC",
    "wof:name":"Miguir",
    "wof:placetype":"locality"
},
  "geometry": {"coordinates":[-79.30316999999999,-2.80204],"type":"Point"}
}