{
  "type": "Feature",
  "properties": {
    "gn:admin1_code":"2.0",
    "gn:admin2_code":"106.0",
    "gn:admin3_code":"10650.0",
    "gn:asciiname":"La Cria",
    "gn:country_code":"EC",
    "gn:dem":3339,
    "gn:feature_class":"P",
    "gn:feature_code":"PPL",
    "gn:name":"La Cr\u00eda",
    "gn:population":0,
    "gn:timezone":"America/Guayaquil",
    "iso:country":"EC",
    "wof:name":"La Cria",
    "wof:placetype":"locality"
},
  "geometry": {"coordinates":[-79.55,-3.16667],"type":"Point"}
}