{
  "type": "Feature",
  "properties": {
    "gn:admin1_code":"2.0",
    "gn:admin2_code":"109.0",
    "gn:admin3_code":"10956.0",
    "gn:asciiname":"San Jose de Raranga",
    "gn:country_code":"EC",
    "gn:dem":2850,
    "gn:feature_class":"P",
    "gn:feature_code":"PPL",
    "gn:name":"San Jos\u00e9 de Raranga",
    "gn:population":0,
    "gn:timezone":"America/Guayaquil",
    "iso:country":"EC",
    "wof:name":"San Jose de Raranga",
    "wof:placetype":"locality"
},
  "geometry": {"coordinates":[-78.96918000000002,-3.13939],"type":"Point"}
}