{
  "type": "Feature",
  "properties": {
    "gn:admin1_code":"14.0",
    "gn:admin2_code":"1304.0",
    "gn:admin3_code":"130452.0",
    "gn:asciiname":"El Comunal",
    "gn:country_code":"EC",
    "gn:dem":182,
    "gn:feature_class":"P",
    "gn:feature_code":"PPL",
    "gn:name":"El Comunal",
    "gn:population":0,
    "gn:timezone":"America/Guayaquil",
    "iso:country":"EC",
    "wof:name":"El Comunal",
    "wof:placetype":"locality"
},
  "geometry": {"coordinates":[-79.57013000000001,-0.14439],"type":"Point"}
}