{
  "type": "Feature",
  "properties": {
    "gn:admin1_code":"20.0",
    "gn:admin2_code":"1903.0",
    "gn:admin3_code":"190351.0",
    "gn:asciiname":"La Guantza",
    "gn:country_code":"EC",
    "gn:dem":855,
    "gn:feature_class":"P",
    "gn:feature_code":"PPL",
    "gn:name":"La Guantza",
    "gn:population":0,
    "gn:timezone":"America/Guayaquil",
    "iso:country":"EC",
    "wof:name":"La Guantza",
    "wof:placetype":"locality"
},
  "geometry": {"coordinates":[-78.64261999999999,-4.16308],"type":"Point"}
}