{
  "type": "Feature",
  "properties": {
    "gn:admin1_code":"11.0",
    "gn:admin2_code":"1005.0",
    "gn:admin3_code":"100550.0",
    "gn:asciiname":"El Cebadal",
    "gn:country_code":"EC",
    "gn:dem":2399,
    "gn:feature_class":"P",
    "gn:feature_code":"PPL",
    "gn:name":"El Cebadal",
    "gn:population":0,
    "gn:timezone":"America/Guayaquil",
    "iso:country":"EC",
    "wof:name":"El Cebadal",
    "wof:placetype":"locality"
},
  "geometry": {"coordinates":[-77.89830000000001,0.35107],"type":"Point"}
}