{
  "type": "Feature",
  "properties": {
    "iso:country":"EC",
    "name:cat_x_preferred":[
        "S\u00e3o Jo\u00e3o Baptista"
    ],
    "name:por_x_preferred":[
        "S\u00e3o Jo\u00e3o Batista"
    ],
    "qs:gn_pop":0,
    "qs:name":"Tabuga",
    "qs:name_adm0":"Ecuador",
    "qs:name_adm1":"Manabi",
    "qs:photos":26,
    "qs:photos_1k":5,
    "qs:photos_9k":1,
    "qs:photos_9r":2,
    "qs:photos_all":26,
    "qs:photos_sr":2,
    "qs:placetype":"Town",
    "qs:pop_sr":"0",
    "qs:woe_adm0":23424801,
    "wof:name":"Tabuga",
    "wof:placetype":"locality"
},
  "geometry": {"coordinates":[-80.151443,-0.058364],"type":"Point"}
}