{
  "type": "Feature",
  "properties": {
    "gn:admin1_code":"10.0",
    "gn:admin2_code":"916.0",
    "gn:admin3_code":"91650.0",
    "gn:asciiname":"Carmelita",
    "gn:country_code":"EC",
    "gn:dem":4,
    "gn:feature_class":"P",
    "gn:feature_code":"PPL",
    "gn:name":"Carmelita",
    "gn:population":0,
    "gn:timezone":"America/Guayaquil",
    "iso:country":"EC",
    "name:ceb_x_preferred":[
        "Carmelita"
    ],
    "name:fra_x_preferred":[
        "Carmelita"
    ],
    "name:nds_x_preferred":[
        "Carmelita"
    ],
    "name:por_x_preferred":[
        "Carmelita"
    ],
    "name:spa_x_preferred":[
        "Carmelita"
    ],
    "name:swe_x_preferred":[
        "Carmelita"
    ],
    "wof:name":"Carmelita",
    "wof:placetype":"locality"
},
  "geometry": {"coordinates":[-79.66667,-1.93333],"type":"Point"}
}