{
  "type": "Feature",
  "properties": {
    "gn:admin1_code":"18.0",
    "gn:admin2_code":"1702.0",
    "gn:admin3_code":"170252.0",
    "gn:asciiname":"Hacienda Quinchucajas",
    "gn:cc2":"EC",
    "gn:country_code":"EC",
    "gn:dem":3601,
    "gn:feature_class":"P",
    "gn:feature_code":"PPL",
    "gn:name":"Hacienda Quinchucajas",
    "gn:population":0,
    "gn:timezone":"America/Guayaquil",
    "iso:country":"EC",
    "wof:name":"Hacienda Quinchucajas",
    "wof:placetype":"locality"
},
  "geometry": {"coordinates":[-78.21666999999999,-0.11667],"type":"Point"}
}