{
  "type": "Feature",
  "properties": {
    "gn:admin1_code":"9.0",
    "gn:admin2_code":"801.0",
    "gn:admin3_code":"80166.0",
    "gn:asciiname":"Tachina",
    "gn:country_code":"EC",
    "gn:dem":12,
    "gn:feature_class":"P",
    "gn:feature_code":"PPL",
    "gn:name":"Tachina",
    "gn:population":0,
    "gn:timezone":"America/Guayaquil",
    "iso:country":"EC",
    "wof:name":"Tachina",
    "wof:placetype":"locality"
},
  "geometry": {"coordinates":[-79.62808000000003,0.96248],"type":"Point"}
}