{
  "type": "Feature",
  "properties": {
    "gn:admin1_code":"9.0",
    "gn:admin2_code":"801.0",
    "gn:admin3_code":"80166.0",
    "gn:asciiname":"Tachina",
    "gn:country_code":"EC",
    "gn:dem":12,
    "gn:feature_class":"P",
    "gn:feature_code":"PPL",
    "gn:name":"Tachina",
    "gn:population":0,
    "gn:timezone":"America/Guayaquil",
    "iso:country":"EC",
    "name:ceb_x_preferred":[
        "Tachina"
    ],
    "name:fas_x_preferred":[
        "\u062a\u0647\u200c\u067e\u0634\u0645\u06cc"
    ],
    "name:fra_x_preferred":[
        "Tachina"
    ],
    "name:nld_x_preferred":[
        "Tachina"
    ],
    "name:spa_x_preferred":[
        "Tachina"
    ],
    "name:swe_x_preferred":[
        "Tachina"
    ],
    "name:vie_x_preferred":[
        "Tachina"
    ],
    "name:war_x_preferred":[
        "Tachina"
    ],
    "wof:name":"Tachina",
    "wof:placetype":"locality"
},
  "geometry": {"coordinates":[-79.62808000000003,0.96248],"type":"Point"}
}