{
  "type": "Feature",
  "properties": {
    "gn:admin1_code":"10.0",
    "gn:asciiname":"Gala de Arriba",
    "gn:country_code":"EC",
    "gn:dem":100,
    "gn:feature_class":"P",
    "gn:feature_code":"PPL",
    "gn:name":"Gala de Arriba",
    "gn:population":0,
    "gn:timezone":"America/Guayaquil",
    "iso:country":"EC",
    "wof:name":"Gala de Arriba",
    "wof:placetype":"locality"
},
  "geometry": {"coordinates":[-79.71666999999999,-3.01667],"type":"Point"}
}