{
  "type": "Feature",
  "properties": {
    "gn:admin1_code":"15.0",
    "gn:admin2_code":"1412.0",
    "gn:admin3_code":"141250.0",
    "gn:asciiname":"Chinkianas",
    "gn:country_code":"EC",
    "gn:dem":280,
    "gn:feature_class":"P",
    "gn:feature_code":"PPL",
    "gn:name":"Chinkianas",
    "gn:population":0,
    "gn:timezone":"America/Guayaquil",
    "iso:country":"EC",
    "wof:name":"Chinkianas",
    "wof:placetype":"locality"
},
  "geometry": {"coordinates":[-77.91946999999998,-2.94213],"type":"Point"}
}