{
  "type": "Feature",
  "properties": {
    "gn:admin1_code":"11.0",
    "gn:admin2_code":"1006.0",
    "gn:admin3_code":"100655.0",
    "gn:asciiname":"Tumbabiro",
    "gn:country_code":"EC",
    "gn:dem":2088,
    "gn:feature_class":"P",
    "gn:feature_code":"PPL",
    "gn:name":"Tumbabiro",
    "gn:population":0,
    "gn:timezone":"America/Guayaquil",
    "iso:country":"EC",
    "wof:name":"Tumbabiro",
    "wof:placetype":"locality"
},
  "geometry": {"coordinates":[-78.18980000000001,0.4612],"type":"Point"}
}