{
  "type": "Feature",
  "properties": {
    "gn:admin1_code":"24.0",
    "gn:admin2_code":"2201.0",
    "gn:admin3_code":"220159.0",
    "gn:asciiname":"Estrella Yacu",
    "gn:country_code":"EC",
    "gn:dem":266,
    "gn:feature_class":"P",
    "gn:feature_code":"PPL",
    "gn:name":"Estrella Yacu",
    "gn:population":0,
    "gn:timezone":"America/Guayaquil",
    "iso:country":"EC",
    "wof:name":"Estrella Yacu",
    "wof:placetype":"locality"
},
  "geometry": {"coordinates":[-77.11667,-0.43333],"type":"Point"}
}