{
  "type": "Feature",
  "properties": {
    "gn:admin1_code":"12.0",
    "gn:admin2_code":"1102.0",
    "gn:admin3_code":"110250.0",
    "gn:asciiname":"Hacienda San Joaquin",
    "gn:cc2":"EC",
    "gn:country_code":"EC",
    "gn:dem":2173,
    "gn:feature_class":"P",
    "gn:feature_code":"PPL",
    "gn:name":"Hacienda San Joaqu\u00edn",
    "gn:population":0,
    "gn:timezone":"America/Guayaquil",
    "iso:country":"EC",
    "wof:name":"Hacienda San Joaquin",
    "wof:placetype":"locality"
},
  "geometry": {"coordinates":[-79.51666999999998,-4.33333],"type":"Point"}
}