{
  "type": "Feature",
  "properties": {
    "gn:admin1_code":"15.0",
    "gn:admin2_code":"1409.0",
    "gn:admin3_code":"140954.0",
    "gn:asciiname":"Yasnunka",
    "gn:country_code":"EC",
    "gn:dem":253,
    "gn:feature_class":"P",
    "gn:feature_code":"PPL",
    "gn:name":"Yasnunka",
    "gn:population":0,
    "gn:timezone":"America/Guayaquil",
    "iso:country":"EC",
    "wof:name":"Yasnunka",
    "wof:placetype":"locality"
},
  "geometry": {"coordinates":[-77.32389000000001,-2.67694],"type":"Point"}
}