{
  "type": "Feature",
  "properties": {
    "gn:admin1_code":"11.0",
    "gn:admin2_code":"1005.0",
    "gn:admin3_code":"100553.0",
    "gn:asciiname":"San Jose",
    "gn:country_code":"EC",
    "gn:dem":2465,
    "gn:feature_class":"P",
    "gn:feature_code":"PPL",
    "gn:name":"San Jos\u00e9",
    "gn:population":0,
    "gn:timezone":"America/Guayaquil",
    "iso:country":"EC",
    "wof:name":"San Jose",
    "wof:placetype":"locality"
},
  "geometry": {"coordinates":[-77.93934,0.30813],"type":"Point"}
}