{
  "type": "Feature",
  "properties": {
    "gn:admin1_code":"15.0",
    "gn:admin2_code":"1403.0",
    "gn:admin3_code":"140353.0",
    "gn:asciiname":"Warintza",
    "gn:country_code":"EC",
    "gn:dem":984,
    "gn:feature_class":"P",
    "gn:feature_code":"PPL",
    "gn:name":"Warintza",
    "gn:population":0,
    "gn:timezone":"America/Guayaquil",
    "iso:country":"EC",
    "wof:name":"Warintza",
    "wof:placetype":"locality"
},
  "geometry": {"coordinates":[-78.27028,-3.18472],"type":"Point"}
}