{
  "type": "Feature",
  "properties": {
    "gn:admin1_code":"4.0",
    "gn:admin2_code":"303.0",
    "gn:admin3_code":"30361.0",
    "gn:asciiname":"Pucango",
    "gn:country_code":"EC",
    "gn:dem":3004,
    "gn:feature_class":"P",
    "gn:feature_code":"PPL",
    "gn:name":"Pucango",
    "gn:population":0,
    "gn:timezone":"America/Guayaquil",
    "iso:country":"EC",
    "wof:name":"Pucango",
    "wof:placetype":"locality"
},
  "geometry": {"coordinates":[-79.01666999999998,-2.45],"type":"Point"}
}