{
  "type": "Feature",
  "properties": {
    "gn:admin1_code":"6.0",
    "gn:admin2_code":"602.0",
    "gn:admin3_code":"60254.0",
    "gn:asciiname":"Huigra",
    "gn:country_code":"EC",
    "gn:dem":1267,
    "gn:feature_class":"P",
    "gn:feature_code":"PPL",
    "gn:name":"Huigra",
    "gn:population":0,
    "gn:timezone":"America/Guayaquil",
    "iso:country":"EC",
    "wof:name":"Huigra",
    "wof:placetype":"locality"
},
  "geometry": {"coordinates":[-78.98329,-2.28902],"type":"Point"}
}