{
  "type": "Feature",
  "properties": {
    "gn:admin1_code":"19.0",
    "gn:admin2_code":"1805.0",
    "gn:admin3_code":"180550.0",
    "gn:asciiname":"Yamate",
    "gn:country_code":"EC",
    "gn:dem":2441,
    "gn:feature_class":"P",
    "gn:feature_code":"PPL",
    "gn:name":"Yamate",
    "gn:population":0,
    "gn:timezone":"America/Guayaquil",
    "iso:country":"EC",
    "name:fra_x_preferred":[
        "Yamate"
    ],
    "name:jpn_x_preferred":[
        "\u5c71\u624b"
    ],
    "name:nld_x_preferred":[
        "Yamate"
    ],
    "name:rus_x_preferred":[
        "\u042f\u043c\u0430\u0442\u044d"
    ],
    "name:spa_x_preferred":[
        "Yamate"
    ],
    "wof:name":"Yamate",
    "wof:placetype":"locality"
},
  "geometry": {"coordinates":[-78.49509999999999,-1.31453],"type":"Point"}
}