{
  "type": "Feature",
  "properties": {
    "gn:admin1_code":"14.0",
    "gn:admin2_code":"1304.0",
    "gn:admin3_code":"130450.0",
    "gn:asciiname":"Pupusa",
    "gn:country_code":"EC",
    "gn:dem":157,
    "gn:feature_class":"P",
    "gn:feature_code":"PPL",
    "gn:name":"Pupusa",
    "gn:population":0,
    "gn:timezone":"America/Guayaquil",
    "iso:country":"EC",
    "wof:name":"Pupusa",
    "wof:placetype":"locality"
},
  "geometry": {"coordinates":[-79.49772,-0.41033],"type":"Point"}
}