{
  "type": "Feature",
  "properties": {
    "gn:admin1_code":"14.0",
    "gn:admin2_code":"1304.0",
    "gn:admin3_code":"130450.0",
    "gn:asciiname":"Pupusa",
    "gn:country_code":"EC",
    "gn:dem":157,
    "gn:feature_class":"P",
    "gn:feature_code":"PPL",
    "gn:name":"Pupusa",
    "gn:population":0,
    "gn:timezone":"America/Guayaquil",
    "iso:country":"EC",
    "name:ara_x_preferred":[
        "\u0628\u0648\u0628\u0648\u0633\u0627"
    ],
    "name:cat_x_preferred":[
        "Pupusa"
    ],
    "name:ces_x_preferred":[
        "Pupusa"
    ],
    "name:deu_x_preferred":[
        "Pupusa"
    ],
    "name:fra_x_preferred":[
        "Pupusa"
    ],
    "name:glg_x_preferred":[
        "Pupusa"
    ],
    "name:hun_x_preferred":[
        "Pupusa"
    ],
    "name:ita_x_preferred":[
        "Pupusa"
    ],
    "name:nor_x_preferred":[
        "Pupusa"
    ],
    "name:por_x_preferred":[
        "Pupusa"
    ],
    "name:spa_x_preferred":[
        "Pupusa"
    ],
    "name:zho_x_preferred":[
        "\u666e\u666e\u6c99"
    ],
    "wof:name":"Pupusa",
    "wof:placetype":"locality"
},
  "geometry": {"coordinates":[-79.49772,-0.41033],"type":"Point"}
}