{
  "type": "Feature",
  "properties": {
    "gn:admin1_code":"13.0",
    "gn:admin2_code":"1201.0",
    "gn:admin3_code":"120154.0",
    "gn:asciiname":"Julia",
    "gn:country_code":"EC",
    "gn:dem":9,
    "gn:feature_class":"P",
    "gn:feature_code":"PPL",
    "gn:name":"Julia",
    "gn:population":0,
    "gn:timezone":"America/Guayaquil",
    "iso:country":"EC",
    "name:deu_x_preferred":[
        "Julia"
    ],
    "name:est_x_preferred":[
        "Julia"
    ],
    "name:fin_x_preferred":[
        "Julia"
    ],
    "name:lat_x_preferred":[
        "Julia"
    ],
    "name:nld_x_preferred":[
        "Julia"
    ],
    "name:nor_x_preferred":[
        "Julia"
    ],
    "name:pol_x_preferred":[
        "Julia"
    ],
    "name:slv_x_preferred":[
        "Julia"
    ],
    "name:spa_x_preferred":[
        "Julia"
    ],
    "name:swe_x_preferred":[
        "Julia"
    ],
    "wof:name":"Julia",
    "wof:placetype":"locality"
},
  "geometry": {"coordinates":[-79.54694000000001,-1.70446],"type":"Point"}
}