{
  "type": "Feature",
  "properties": {
    "gn:admin1_code":"2.0",
    "gn:admin2_code":"101.0",
    "gn:admin3_code":"10170.0",
    "gn:asciiname":"Guncay",
    "gn:country_code":"EC",
    "gn:dem":2532,
    "gn:feature_class":"P",
    "gn:feature_code":"PPL",
    "gn:name":"Guncay",
    "gn:population":0,
    "gn:timezone":"America/Guayaquil",
    "iso:country":"EC",
    "wof:name":"Guncay",
    "wof:placetype":"locality"
},
  "geometry": {"coordinates":[-78.96589,-2.92574],"type":"Point"}
}