{
  "type": "Feature",
  "properties": {
    "gn:admin1_code":"13.0",
    "gn:admin2_code":"1208.0",
    "gn:admin3_code":"120850.0",
    "gn:asciiname":"La Tira",
    "gn:country_code":"EC",
    "gn:dem":9,
    "gn:feature_class":"P",
    "gn:feature_code":"PPL",
    "gn:name":"La Tira",
    "gn:population":0,
    "gn:timezone":"America/Guayaquil",
    "iso:country":"EC",
    "wof:name":"La Tira",
    "wof:placetype":"locality"
},
  "geometry": {"coordinates":[-79.71666999999999,-1.58333],"type":"Point"}
}