{
  "type": "Feature",
  "properties": {
    "gn:admin1_code":"15.0",
    "gn:admin2_code":"1407.0",
    "gn:admin3_code":"140751.0",
    "gn:asciiname":"Chiguaza",
    "gn:cc2":"EC",
    "gn:country_code":"EC",
    "gn:dem":790,
    "gn:feature_class":"P",
    "gn:feature_code":"PPL",
    "gn:name":"Chiguaza",
    "gn:population":0,
    "gn:timezone":"America/Guayaquil",
    "iso:country":"EC",
    "wof:name":"Chiguaza",
    "wof:placetype":"locality"
},
  "geometry": {"coordinates":[-77.83333,-1.93333],"type":"Point"}
}