{
  "type": "Feature",
  "properties": {
    "gn:admin1_code":"11.0",
    "gn:admin2_code":"1006.0",
    "gn:admin3_code":"100654.0",
    "gn:asciiname":"Hacienda El Hospital",
    "gn:country_code":"EC",
    "gn:dem":2444,
    "gn:feature_class":"P",
    "gn:feature_code":"PPL",
    "gn:name":"Hacienda El Hospital",
    "gn:population":0,
    "gn:timezone":"America/Guayaquil",
    "iso:country":"EC",
    "wof:name":"Hacienda El Hospital",
    "wof:placetype":"locality"
},
  "geometry": {"coordinates":[-78.25778000000003,0.39912],"type":"Point"}
}