{
  "type": "Feature",
  "properties": {
    "gn:admin1_code":"11.0",
    "gn:admin2_code":"1006.0",
    "gn:admin3_code":"100650.0",
    "gn:asciiname":"Hacienda Santa Isabel",
    "gn:country_code":"EC",
    "gn:dem":1962,
    "gn:feature_class":"P",
    "gn:feature_code":"PPL",
    "gn:name":"Hacienda Santa Isabel",
    "gn:population":0,
    "gn:timezone":"America/Guayaquil",
    "iso:country":"EC",
    "wof:name":"Hacienda Santa Isabel",
    "wof:placetype":"locality"
},
  "geometry": {"coordinates":[-78.16578,0.43297],"type":"Point"}
}