{
  "type": "Feature",
  "properties": {
    "gn:admin1_code":"14.0",
    "gn:admin2_code":"1306.0",
    "gn:admin3_code":"130658.0",
    "gn:asciiname":"Cantagallo",
    "gn:country_code":"EC",
    "gn:dem":54,
    "gn:feature_class":"P",
    "gn:feature_code":"PPL",
    "gn:name":"Cantagallo",
    "gn:population":0,
    "gn:timezone":"America/Guayaquil",
    "iso:country":"EC",
    "name:ceb_x_preferred":[
        "Cantagallo"
    ],
    "name:deu_x_preferred":[
        "Cantagallo"
    ],
    "name:est_x_preferred":[
        "Cantagallo"
    ],
    "name:eus_x_preferred":[
        "Cantagallo"
    ],
    "name:fra_x_preferred":[
        "Cantagallo"
    ],
    "name:glg_x_preferred":[
        "Cantagallo"
    ],
    "name:hun_x_preferred":[
        "Cantagallo"
    ],
    "name:ina_x_preferred":[
        "Cantagallo"
    ],
    "name:ita_x_preferred":[
        "Cantagallo"
    ],
    "name:nld_x_preferred":[
        "Cantagallo"
    ],
    "name:scn_x_preferred":[
        "Cantagallu"
    ],
    "name:sco_x_preferred":[
        "Cantagallo"
    ],
    "name:spa_x_preferred":[
        "Cantagallo"
    ],
    "name:swe_x_preferred":[
        "Cantagallo"
    ],
    "wof:name":"Cantagallo",
    "wof:placetype":"locality"
},
  "geometry": {"coordinates":[-80.74372,-1.29133],"type":"Point"}
}