{
  "type": "Feature",
  "properties": {
    "gn:admin1_code":"12.0",
    "gn:admin2_code":"1102.0",
    "gn:admin3_code":"110250.0",
    "gn:asciiname":"Taparuca",
    "gn:country_code":"EC",
    "gn:dem":1787,
    "gn:feature_class":"P",
    "gn:feature_code":"PPL",
    "gn:name":"Taparuca",
    "gn:population":0,
    "gn:timezone":"America/Guayaquil",
    "iso:country":"EC",
    "wof:name":"Taparuca",
    "wof:placetype":"locality"
},
  "geometry": {"coordinates":[-79.60295000000001,-4.38719],"type":"Point"}
}