{
  "type": "Feature",
  "properties": {
    "gn:admin1_code":"3.0",
    "gn:admin2_code":"201.0",
    "gn:admin3_code":"20159.0",
    "gn:asciiname":"Talagua",
    "gn:country_code":"EC",
    "gn:dem":2750,
    "gn:feature_class":"P",
    "gn:feature_code":"PPL",
    "gn:name":"Talagua",
    "gn:population":0,
    "gn:timezone":"America/Guayaquil",
    "iso:country":"EC",
    "wof:name":"Talagua",
    "wof:placetype":"locality"
},
  "geometry": {"coordinates":[-78.98333000000002,-1.26667],"type":"Point"}
}