{
  "type": "Feature",
  "properties": {
    "gn:admin1_code":"14.0",
    "gn:admin2_code":"1303.0",
    "gn:admin3_code":"130357.0",
    "gn:asciiname":"Los Bravos Grandes",
    "gn:country_code":"EC",
    "gn:dem":85,
    "gn:feature_class":"P",
    "gn:feature_code":"PPL",
    "gn:name":"Los Bravos Grandes",
    "gn:population":0,
    "gn:timezone":"America/Guayaquil",
    "iso:country":"EC",
    "wof:name":"Los Bravos Grandes",
    "wof:placetype":"locality"
},
  "geometry": {"coordinates":[-80.14655999999999,-0.62406],"type":"Point"}
}