{
  "type": "Feature",
  "properties": {
    "gn:admin1_code":"10.0",
    "gn:admin2_code":"905.0",
    "gn:admin3_code":"90550.0",
    "gn:asciiname":"Hacienda Buenaventura",
    "gn:cc2":"EC",
    "gn:country_code":"EC",
    "gn:dem":57,
    "gn:feature_class":"P",
    "gn:feature_code":"PPL",
    "gn:name":"Hacienda Buenaventura",
    "gn:population":0,
    "gn:timezone":"America/Guayaquil",
    "iso:country":"EC",
    "wof:name":"Hacienda Buenaventura",
    "wof:placetype":"locality"
},
  "geometry": {"coordinates":[-80.09999999999999,-1.46667],"type":"Point"}
}