{
  "type": "Feature",
  "properties": {
    "gn:admin1_code":"7.0",
    "gn:admin2_code":"501.0",
    "gn:admin3_code":"50159.0",
    "gn:asciiname":"Hacienda San Jose",
    "gn:cc2":"EC",
    "gn:country_code":"EC",
    "gn:dem":3053,
    "gn:feature_class":"P",
    "gn:feature_code":"PPL",
    "gn:name":"Hacienda San Jos\u00e9",
    "gn:population":0,
    "gn:timezone":"America/Guayaquil",
    "iso:country":"EC",
    "wof:name":"Hacienda San Jose",
    "wof:placetype":"locality"
},
  "geometry": {"coordinates":[-78.63333,-0.75],"type":"Point"}
}