{
  "type": "Feature",
  "properties": {
    "gn:admin1_code":"6.0",
    "gn:admin2_code":"601.0",
    "gn:admin3_code":"60159.0",
    "gn:asciiname":"Hacienda Pucara",
    "gn:country_code":"EC",
    "gn:dem":2528,
    "gn:feature_class":"P",
    "gn:feature_code":"PPL",
    "gn:name":"Hacienda Pucar\u00e1",
    "gn:population":0,
    "gn:timezone":"America/Guayaquil",
    "iso:country":"EC",
    "wof:name":"Hacienda Pucara",
    "wof:placetype":"locality"
},
  "geometry": {"coordinates":[-78.59711,-1.6808],"type":"Point"}
}