{
  "type": "Feature",
  "properties": {
    "gn:admin1_code":"8.0",
    "gn:admin2_code":"701.0",
    "gn:admin3_code":"70150.0",
    "gn:asciiname":"La Providencia",
    "gn:country_code":"EC",
    "gn:dem":5,
    "gn:feature_class":"P",
    "gn:feature_code":"PPL",
    "gn:name":"La Providencia",
    "gn:population":0,
    "gn:timezone":"America/Guayaquil",
    "iso:country":"EC",
    "wof:name":"La Providencia",
    "wof:placetype":"locality"
},
  "geometry": {"coordinates":[-79.95,-3.28333],"type":"Point"}
}