{
  "type": "Feature",
  "properties": {
    "gn:admin1_code":"12.0",
    "gn:admin2_code":"1103.0",
    "gn:admin3_code":"110350.0",
    "gn:asciiname":"Chichaca",
    "gn:country_code":"EC",
    "gn:dem":1730,
    "gn:feature_class":"P",
    "gn:feature_code":"PPL",
    "gn:name":"Chichaca",
    "gn:population":0,
    "gn:timezone":"America/Guayaquil",
    "iso:country":"EC",
    "wof:name":"Chichaca",
    "wof:placetype":"locality"
},
  "geometry": {"coordinates":[-79.32491,-3.9223],"type":"Point"}
}