{
  "type": "Feature",
  "properties": {
    "gn:admin1_code":"10.0",
    "gn:admin2_code":"901.0",
    "gn:admin3_code":"90152.0",
    "gn:asciiname":"Aguas Verdes",
    "gn:country_code":"EC",
    "gn:dem":66,
    "gn:feature_class":"P",
    "gn:feature_code":"PPL",
    "gn:name":"Aguas Verdes",
    "gn:population":0,
    "gn:timezone":"America/Guayaquil",
    "iso:country":"EC",
    "name:ceb_x_preferred":[
        "Aguas Verdes"
    ],
    "name:spa_x_preferred":[
        "Aguas Verdes"
    ],
    "wof:name":"Aguas Verdes",
    "wof:placetype":"locality"
},
  "geometry": {"coordinates":[-80.26545,-2.29362],"type":"Point"}
}