{
  "type": "Feature",
  "properties": {
    "gn:admin1_code":"11.0",
    "gn:admin2_code":"1003.0",
    "gn:admin3_code":"100353.0",
    "gn:asciiname":"Hacienda El Molino",
    "gn:cc2":"EC",
    "gn:country_code":"EC",
    "gn:dem":2371,
    "gn:feature_class":"P",
    "gn:feature_code":"PPL",
    "gn:name":"Hacienda El Molino",
    "gn:population":0,
    "gn:timezone":"America/Guayaquil",
    "iso:country":"EC",
    "wof:name":"Hacienda El Molino",
    "wof:placetype":"locality"
},
  "geometry": {"coordinates":[-78.25,0.36667],"type":"Point"}
}