{
  "type": "Feature",
  "properties": {
    "gn:admin1_code":"19.0",
    "gn:admin2_code":"1802.0",
    "gn:admin3_code":"180253.0",
    "gn:asciiname":"Rio Chico",
    "gn:country_code":"EC",
    "gn:dem":2752,
    "gn:feature_class":"P",
    "gn:feature_code":"PPL",
    "gn:name":"R\u00edo Chico",
    "gn:population":0,
    "gn:timezone":"America/Guayaquil",
    "iso:country":"EC",
    "wof:name":"Rio Chico",
    "wof:placetype":"locality"
},
  "geometry": {"coordinates":[-78.31667,-1.31667],"type":"Point"}
}