{
  "type": "Feature",
  "properties": {
    "gn:admin1_code":"2.0",
    "gn:admin2_code":"101.0",
    "gn:admin3_code":"10164.0",
    "gn:asciiname":"Membrillo",
    "gn:country_code":"EC",
    "gn:dem":2694,
    "gn:feature_class":"P",
    "gn:feature_code":"PPL",
    "gn:name":"Membrillo",
    "gn:population":0,
    "gn:timezone":"America/Guayaquil",
    "iso:country":"EC",
    "wof:name":"Membrillo",
    "wof:placetype":"locality"
},
  "geometry": {"coordinates":[-78.91667,-2.98333],"type":"Point"}
}