{
  "type": "Feature",
  "properties": {
    "gn:admin1_code":"18.0",
    "gn:admin2_code":"1702.0",
    "gn:admin3_code":"170250.0",
    "gn:asciiname":"Hacienda Isigcho",
    "gn:cc2":"EC",
    "gn:country_code":"EC",
    "gn:dem":2810,
    "gn:feature_class":"P",
    "gn:feature_code":"PPL",
    "gn:name":"Hacienda Isigcho",
    "gn:population":0,
    "gn:timezone":"America/Guayaquil",
    "iso:country":"EC",
    "wof:name":"Hacienda Isigcho",
    "wof:placetype":"locality"
},
  "geometry": {"coordinates":[-78.15000000000001,0.01667],"type":"Point"}
}