{
  "type": "Feature",
  "properties": {
    "gn:admin1_code":"7.0",
    "gn:admin2_code":"501.0",
    "gn:admin3_code":"50161.0",
    "gn:asciiname":"Hacienda Luzun Chico",
    "gn:cc2":"EC",
    "gn:country_code":"EC",
    "gn:dem":3091,
    "gn:feature_class":"P",
    "gn:feature_code":"PPL",
    "gn:name":"Hacienda Luz\u00fan Chico",
    "gn:population":0,
    "gn:timezone":"America/Guayaquil",
    "iso:country":"EC",
    "wof:name":"Hacienda Luzun Chico",
    "wof:placetype":"locality"
},
  "geometry": {"coordinates":[-78.65000000000001,-0.75],"type":"Point"}
}