{
  "type": "Feature",
  "properties": {
    "gn:admin1_code":"4.0",
    "gn:admin2_code":"303.0",
    "gn:admin3_code":"30351.0",
    "gn:asciiname":"Chontamarca",
    "gn:country_code":"EC",
    "gn:dem":2211,
    "gn:feature_class":"P",
    "gn:feature_code":"PPL",
    "gn:name":"Chontamarca",
    "gn:population":0,
    "gn:timezone":"America/Guayaquil",
    "iso:country":"EC",
    "wof:name":"Chontamarca",
    "wof:placetype":"locality"
},
  "geometry": {"coordinates":[-79.09376,-2.44095],"type":"Point"}
}