{
  "type": "Feature",
  "properties": {
    "gn:admin1_code":"2.0",
    "gn:admin2_code":"101.0",
    "gn:admin3_code":"10157.0",
    "gn:asciiname":"Pan de Azucar",
    "gn:country_code":"EC",
    "gn:dem":2122,
    "gn:feature_class":"P",
    "gn:feature_code":"PPL",
    "gn:name":"Pan de Az\u00facar",
    "gn:population":0,
    "gn:timezone":"America/Guayaquil",
    "iso:country":"EC",
    "wof:name":"Pan de Azucar",
    "wof:placetype":"locality"
},
  "geometry": {"coordinates":[-79.48911,-2.77849],"type":"Point"}
}