{
  "type": "Feature",
  "properties": {
    "gn:admin1_code":"20.0",
    "gn:admin2_code":"1904.0",
    "gn:admin3_code":"190450.0",
    "gn:asciiname":"El Cisne",
    "gn:country_code":"EC",
    "gn:dem":1374,
    "gn:feature_class":"P",
    "gn:feature_code":"PPL",
    "gn:name":"El Cisne",
    "gn:population":0,
    "gn:timezone":"America/Guayaquil",
    "iso:country":"EC",
    "name:ceb_x_preferred":[
        "El Cisne"
    ],
    "name:que_x_preferred":[
        "El Cisne"
    ],
    "name:swe_x_preferred":[
        "El Cisne"
    ],
    "wof:name":"El Cisne",
    "wof:placetype":"locality"
},
  "geometry": {"coordinates":[-78.90635999999998,-3.64627],"type":"Point"}
}