{
  "type": "Feature",
  "properties": {
    "gn:admin1_code":"10.0",
    "gn:admin2_code":"903.0",
    "gn:admin3_code":"90350.0",
    "gn:asciiname":"Puerto Balao Grande",
    "gn:country_code":"EC",
    "gn:dem":0,
    "gn:feature_class":"P",
    "gn:feature_code":"PPL",
    "gn:name":"Puerto Balao Grande",
    "gn:population":0,
    "gn:timezone":"America/Guayaquil",
    "iso:country":"EC",
    "wof:name":"Puerto Balao Grande",
    "wof:placetype":"locality"
},
  "geometry": {"coordinates":[-79.83360999999999,-2.89343],"type":"Point"}
}