{
  "type": "Feature",
  "properties": {
    "gn:admin1_code":"11.0",
    "gn:admin2_code":"1004.0",
    "gn:admin3_code":"100450.0",
    "gn:asciiname":"Hacienda Cotama",
    "gn:country_code":"EC",
    "gn:dem":2593,
    "gn:feature_class":"P",
    "gn:feature_code":"PPL",
    "gn:name":"Hacienda Cotama",
    "gn:population":0,
    "gn:timezone":"America/Guayaquil",
    "iso:country":"EC",
    "wof:name":"Hacienda Cotama",
    "wof:placetype":"locality"
},
  "geometry": {"coordinates":[-78.26326999999998,0.25154],"type":"Point"}
}