{
  "type": "Feature",
  "properties": {
    "gn:admin1_code":"10.0",
    "gn:admin2_code":"911.0",
    "gn:admin3_code":"91150.0",
    "gn:asciiname":"La Dolores",
    "gn:country_code":"EC",
    "gn:dem":28,
    "gn:feature_class":"P",
    "gn:feature_code":"PPL",
    "gn:name":"La Dolores",
    "gn:population":0,
    "gn:timezone":"America/Guayaquil",
    "iso:country":"EC",
    "name:cat_x_preferred":[
        "La Dolores"
    ],
    "name:spa_x_preferred":[
        "La Dolores"
    ],
    "wof:name":"La Dolores",
    "wof:placetype":"locality"
},
  "geometry": {"coordinates":[-79.65000000000001,-2.68333],"type":"Point"}
}