{
  "type": "Feature",
  "properties": {
    "gn:admin1_code":"18.0",
    "gn:admin2_code":"1708.0",
    "gn:admin3_code":"170850.0",
    "gn:asciiname":"Paraiso Alto",
    "gn:country_code":"EC",
    "gn:dem":454,
    "gn:feature_class":"P",
    "gn:feature_code":"PPL",
    "gn:name":"Para\u00edso Alto",
    "gn:population":0,
    "gn:timezone":"America/Guayaquil",
    "iso:country":"EC",
    "wof:name":"Paraiso Alto",
    "wof:placetype":"locality"
},
  "geometry": {"coordinates":[-79.13625,0.06251],"type":"Point"}
}