{
  "type": "Feature",
  "properties": {
    "gn:admin1_code":"13.0",
    "gn:admin2_code":"1202.0",
    "gn:admin3_code":"120252.0",
    "gn:asciiname":"Isla de Bejucal",
    "gn:country_code":"EC",
    "gn:dem":9,
    "gn:feature_class":"P",
    "gn:feature_code":"PPL",
    "gn:name":"Isla de Bejucal",
    "gn:population":0,
    "gn:timezone":"America/Guayaquil",
    "iso:country":"EC",
    "wof:name":"Isla de Bejucal",
    "wof:placetype":"locality"
},
  "geometry": {"coordinates":[-79.64480999999998,-1.67721],"type":"Point"}
}