{
  "type": "Feature",
  "properties": {
    "gn:admin1_code":"20.0",
    "gn:admin2_code":"1901.0",
    "gn:admin3_code":"190152.0",
    "gn:asciiname":"San Antonio del Vergel",
    "gn:country_code":"EC",
    "gn:dem":870,
    "gn:feature_class":"P",
    "gn:feature_code":"PPL",
    "gn:name":"San Antonio del Vergel",
    "gn:population":0,
    "gn:timezone":"America/Guayaquil",
    "iso:country":"EC",
    "wof:name":"San Antonio del Vergel",
    "wof:placetype":"locality"
},
  "geometry": {"coordinates":[-78.89816999999999,-3.80563],"type":"Point"}
}