{
  "type": "Feature",
  "properties": {
    "gn:admin1_code":"2.0",
    "gn:admin2_code":"102.0",
    "gn:admin3_code":"10250.0",
    "gn:asciiname":"Hacienda La Victoria",
    "gn:cc2":"EC",
    "gn:country_code":"EC",
    "gn:dem":2347,
    "gn:feature_class":"P",
    "gn:feature_code":"PPL",
    "gn:name":"Hacienda La Victoria",
    "gn:population":0,
    "gn:timezone":"America/Guayaquil",
    "iso:country":"EC",
    "wof:name":"Hacienda La Victoria",
    "wof:placetype":"locality"
},
  "geometry": {"coordinates":[-79.13333,-3.13333],"type":"Point"}
}