{
  "type": "Feature",
  "properties": {
    "gn:admin1_code":"12.0",
    "gn:admin2_code":"1111.0",
    "gn:admin3_code":"111154.0",
    "gn:asciiname":"Guambusari",
    "gn:country_code":"EC",
    "gn:dem":3429,
    "gn:feature_class":"P",
    "gn:feature_code":"PPL",
    "gn:name":"Guambusari",
    "gn:population":0,
    "gn:timezone":"America/Guayaquil",
    "iso:country":"EC",
    "wof:name":"Guambusari",
    "wof:placetype":"locality"
},
  "geometry": {"coordinates":[-79.40000000000001,-3.55],"type":"Point"}
}