{
  "type": "Feature",
  "properties": {
    "gn:admin1_code":"19.0",
    "gn:admin2_code":"1802.0",
    "gn:admin3_code":"180253.0",
    "gn:asciiname":"San Pedro",
    "gn:country_code":"EC",
    "gn:dem":1574,
    "gn:feature_class":"P",
    "gn:feature_code":"PPL",
    "gn:name":"San Pedro",
    "gn:population":0,
    "gn:timezone":"America/Guayaquil",
    "iso:country":"EC",
    "wof:name":"San Pedro",
    "wof:placetype":"locality"
},
  "geometry": {"coordinates":[-78.3258,-1.4091],"type":"Point"}
}