{
  "type": "Feature",
  "properties": {
    "gn:admin1_code":"23.0",
    "gn:admin2_code":"1504.0",
    "gn:admin3_code":"150451.0",
    "gn:asciiname":"Diaz de Pineda",
    "gn:country_code":"EC",
    "gn:dem":2148,
    "gn:feature_class":"P",
    "gn:feature_code":"PPL",
    "gn:name":"D\u00edaz de Pineda",
    "gn:population":0,
    "gn:timezone":"America/Guayaquil",
    "iso:country":"EC",
    "wof:name":"Diaz de Pineda",
    "wof:placetype":"locality"
},
  "geometry": {"coordinates":[-77.71666999999999,-0.28333],"type":"Point"}
}