{
  "type": "Feature",
  "properties": {
    "gn:admin1_code":"20.0",
    "gn:admin2_code":"1901.0",
    "gn:admin3_code":"190155.0",
    "gn:asciiname":"Sabanilla",
    "gn:country_code":"EC",
    "gn:dem":1139,
    "gn:feature_class":"P",
    "gn:feature_code":"PPL",
    "gn:name":"Sabanilla",
    "gn:population":0,
    "gn:timezone":"America/Guayaquil",
    "iso:country":"EC",
    "wof:name":"Sabanilla",
    "wof:placetype":"locality"
},
  "geometry": {"coordinates":[-79.00876,-4.03481],"type":"Point"}
}