{
  "type": "Feature",
  "properties": {
    "gn:admin1_code":"18.0",
    "gn:admin2_code":"1703.0",
    "gn:admin3_code":"170351.0",
    "gn:asciiname":"Piliche",
    "gn:country_code":"EC",
    "gn:dem":3019,
    "gn:feature_class":"P",
    "gn:feature_code":"PPL",
    "gn:name":"Piliche",
    "gn:population":0,
    "gn:timezone":"America/Guayaquil",
    "iso:country":"EC",
    "wof:name":"Piliche",
    "wof:placetype":"locality"
},
  "geometry": {"coordinates":[-78.59999999999999,-0.46667],"type":"Point"}
}