{
  "type": "Feature",
  "properties": {
    "gn:admin1_code":"12.0",
    "gn:admin2_code":"1108.0",
    "gn:admin3_code":"110850.0",
    "gn:asciiname":"El Coco",
    "gn:country_code":"EC",
    "gn:dem":548,
    "gn:feature_class":"P",
    "gn:feature_code":"PPL",
    "gn:name":"El Coco",
    "gn:population":0,
    "gn:timezone":"America/Lima",
    "iso:country":"EC",
    "wof:name":"El Coco",
    "wof:placetype":"locality"
},
  "geometry": {"coordinates":[-79.87408000000001,-4.41037],"type":"Point"}
}