{
  "type": "Feature",
  "properties": {
    "gn:admin1_code":"23.0",
    "gn:admin2_code":"1503.0",
    "gn:admin3_code":"150352.0",
    "gn:asciiname":"Narupa",
    "gn:country_code":"EC",
    "gn:dem":1213,
    "gn:feature_class":"P",
    "gn:feature_code":"PPL",
    "gn:name":"Narupa",
    "gn:population":0,
    "gn:timezone":"America/Guayaquil",
    "iso:country":"EC",
    "wof:name":"Narupa",
    "wof:placetype":"locality"
},
  "geometry": {"coordinates":[-77.78468000000002,-0.72834],"type":"Point"}
}