{
  "type": "Feature",
  "properties": {
    "gn:admin1_code":"18.0",
    "gn:admin2_code":"1701.0",
    "gn:admin3_code":"170184.0",
    "gn:asciiname":"Hacienda Santa Rosa",
    "gn:country_code":"EC",
    "gn:dem":2387,
    "gn:feature_class":"P",
    "gn:feature_code":"PPL",
    "gn:name":"Hacienda Santa Rosa",
    "gn:population":0,
    "gn:timezone":"America/Guayaquil",
    "iso:country":"EC",
    "wof:name":"Hacienda Santa Rosa",
    "wof:placetype":"locality"
},
  "geometry": {"coordinates":[-78.38176,-0.20142],"type":"Point"}
}