{
  "type": "Feature",
  "properties": {
    "gn:admin1_code":"22.0",
    "gn:admin2_code":"2103.0",
    "gn:admin3_code":"210351.0",
    "gn:asciiname":"Tase",
    "gn:country_code":"EC",
    "gn:dem":231,
    "gn:feature_class":"P",
    "gn:feature_code":"PPL",
    "gn:name":"Tase",
    "gn:population":0,
    "gn:timezone":"America/Guayaquil",
    "iso:country":"EC",
    "wof:name":"Tase",
    "wof:placetype":"locality"
},
  "geometry": {"coordinates":[-76.10489,0.13197],"type":"Point"}
}