{
  "type": "Feature",
  "properties": {
    "gn:admin1_code":"10.0",
    "gn:admin2_code":"925.0",
    "gn:admin3_code":"92550.0",
    "gn:asciiname":"La Delicia",
    "gn:cc2":"EC",
    "gn:country_code":"EC",
    "gn:dem":26,
    "gn:feature_class":"P",
    "gn:feature_code":"PPL",
    "gn:name":"La Delicia",
    "gn:population":0,
    "gn:timezone":"America/Guayaquil",
    "iso:country":"EC",
    "wof:name":"La Delicia",
    "wof:placetype":"locality"
},
  "geometry": {"coordinates":[-80.01666999999998,-1.95],"type":"Point"}
}