{
  "type": "Feature",
  "properties": {
    "gn:admin1_code":"26.0",
    "gn:admin2_code":"2301.0",
    "gn:admin3_code":"230150.0",
    "gn:asciiname":"Tres Rios",
    "gn:country_code":"EC",
    "gn:dem":395,
    "gn:feature_class":"P",
    "gn:feature_code":"PPL",
    "gn:name":"Tres R\u00edos",
    "gn:population":0,
    "gn:timezone":"America/Guayaquil",
    "iso:country":"EC",
    "name:ceb_x_preferred":[
        "Tres Rios"
    ],
    "name:ita_x_preferred":[
        "Tres Rios"
    ],
    "name:lit_x_preferred":[
        "Tres Riosas"
    ],
    "name:srp_x_preferred":[
        "\u0422\u0440\u0435\u0441 \u0420\u0438\u043e\u0441"
    ],
    "name:swe_x_preferred":[
        "Tres Rios"
    ],
    "wof:name":"Tres Rios",
    "wof:placetype":"locality"
},
  "geometry": {"coordinates":[-79.20548000000002,-0.11585],"type":"Point"}
}