{
  "type": "Feature",
  "properties": {
    "gn:admin1_code":"26.0",
    "gn:admin2_code":"2301.0",
    "gn:admin3_code":"230150.0",
    "gn:asciiname":"Tres Rios",
    "gn:country_code":"EC",
    "gn:dem":395,
    "gn:feature_class":"P",
    "gn:feature_code":"PPL",
    "gn:name":"Tres R\u00edos",
    "gn:population":0,
    "gn:timezone":"America/Guayaquil",
    "iso:country":"EC",
    "wof:name":"Tres Rios",
    "wof:placetype":"locality"
},
  "geometry": {"coordinates":[-79.20548000000002,-0.11585],"type":"Point"}
}