{
  "type": "Feature",
  "properties": {
    "gn:admin1_code":"12.0",
    "gn:admin2_code":"1101.0",
    "gn:admin3_code":"110156.0",
    "gn:asciiname":"Rumishitana",
    "gn:cc2":"EC",
    "gn:country_code":"EC",
    "gn:dem":2111,
    "gn:feature_class":"P",
    "gn:feature_code":"PPL",
    "gn:name":"Rumishitana",
    "gn:population":0,
    "gn:timezone":"America/Guayaquil",
    "iso:country":"EC",
    "wof:name":"Rumishitana",
    "wof:placetype":"locality"
},
  "geometry": {"coordinates":[-79.21666999999999,-4.15],"type":"Point"}
}