{
  "type": "Feature",
  "properties": {
    "gn:admin1_code":"7.0",
    "gn:admin2_code":"501.0",
    "gn:admin3_code":"50153.0",
    "gn:asciiname":"Hacienda Nintanga Alto",
    "gn:country_code":"EC",
    "gn:dem":2893,
    "gn:feature_class":"P",
    "gn:feature_code":"PPL",
    "gn:name":"Hacienda Nintanga Alto",
    "gn:population":0,
    "gn:timezone":"America/Guayaquil",
    "iso:country":"EC",
    "wof:name":"Hacienda Nintanga Alto",
    "wof:placetype":"locality"
},
  "geometry": {"coordinates":[-78.63786,-0.84382],"type":"Point"}
}