{
  "type": "Feature",
  "properties": {
    "gn:admin1_code":"19.0",
    "gn:admin2_code":"1801.0",
    "gn:admin3_code":"180165.0",
    "gn:asciiname":"Santa Rosa",
    "gn:country_code":"EC",
    "gn:dem":3014,
    "gn:feature_class":"P",
    "gn:feature_code":"PPL",
    "gn:name":"Santa Rosa",
    "gn:population":0,
    "gn:timezone":"America/Guayaquil",
    "iso:country":"EC",
    "name:cat_x_preferred":[
        "Santa Rosa"
    ],
    "name:ceb_x_preferred":[
        "Santa Rosa"
    ],
    "name:ces_x_preferred":[
        "Santa Rosa"
    ],
    "name:deu_x_preferred":[
        "Santa Rosa"
    ],
    "name:epo_x_preferred":[
        "Santa Rosa"
    ],
    "name:fin_x_preferred":[
        "Santa Rosa"
    ],
    "name:fra_x_preferred":[
        "Santa Rosa"
    ],
    "name:glg_x_preferred":[
        "Santa Rosa"
    ],
    "name:heb_x_preferred":[
        "\u05e1\u05e0\u05d8\u05d4 \u05e8\u05d5\u05d6\u05d4"
    ],
    "name:heb_x_variant":[
        "\u05e1\u05e0\u05d8\u05d4 \u05e8\u05d5\u05e1\u05d4"
    ],
    "name:hin_x_preferred":[
        "\u0938\u0948\u0902\u091f\u093e \u0930\u094b\u091c\u093c\u093e"
    ],
    "name:hun_x_preferred":[
        "Santa Rosa"
    ],
    "name:ilo_x_preferred":[
        "Santa Rosa"
    ],
    "name:ind_x_preferred":[
        "Santa Rosa"
    ],
    "name:ita_x_preferred":[
        "Santa Rosa"
    ],
    "name:jpn_x_preferred":[
        "\u30b5\u30f3\u30bf\u30ed\u30fc\u30b6"
    ],
    "name:kor_x_preferred":[
        "\uc0b0\ud0c0\ub85c\uc0ac"
    ],
    "name:lit_x_preferred":[
        "Santa Rosa"
    ],
    "name:mlg_x_preferred":[
        "Santa Rosa"
    ],
    "name:nds_x_preferred":[
        "Santa Rosa"
    ],
    "name:nld_x_preferred":[
        "Santa Rosa"
    ],
    "name:nor_x_preferred":[
        "Santa Rosa"
    ],
    "name:pol_x_preferred":[
        "Santa Rosa"
    ],
    "name:por_x_preferred":[
        "Santa Rosa"
    ],
    "name:rus_x_preferred":[
        "\u0421\u0430\u043d\u0442\u0430-\u0420\u043e\u0437\u0430"
    ],
    "name:sco_x_preferred":[
        "Santa Rosa"
    ],
    "name:slk_x_preferred":[
        "Santa Rosa"
    ],
    "name:spa_x_preferred":[
        "Santa Rosa"
    ],
    "name:srp_x_preferred":[
        "\u0421\u0430\u043d\u0442\u0430 \u0420\u043e\u0441\u0430"
    ],
    "name:swa_x_preferred":[
        "Santa Rosa"
    ],
    "name:swe_x_preferred":[
        "Santa Rosa"
    ],
    "name:tur_x_preferred":[
        "Santa Rosa"
    ],
    "name:urd_x_preferred":[
        "\u0633\u06cc\u0646\u0679\u0627 \u0631\u0648\u0633\u0627"
    ],
    "name:vol_x_preferred":[
        "Santa Rosa"
    ],
    "name:war_x_preferred":[
        "Santa Rosa"
    ],
    "wof:name":"Santa Rosa",
    "wof:placetype":"locality"
},
  "geometry": {"coordinates":[-78.6641,-1.28295],"type":"Point"}
}