{
  "type": "Feature",
  "properties": {
    "gn:admin1_code":"18.0",
    "gn:asciiname":"Manipili",
    "gn:country_code":"EC",
    "gn:dem":329,
    "gn:feature_class":"P",
    "gn:feature_code":"PPL",
    "gn:name":"Manipili",
    "gn:population":0,
    "gn:timezone":"America/Guayaquil",
    "iso:country":"EC",
    "wof:name":"Manipili",
    "wof:placetype":"locality"
},
  "geometry": {"coordinates":[-79.33575999999999,-0.24414],"type":"Point"}
}