{
  "type": "Feature",
  "properties": {
    "gn:admin1_code":"6.0",
    "gn:admin2_code":"603.0",
    "gn:admin3_code":"60354.0",
    "gn:asciiname":"Venecia",
    "gn:country_code":"EC",
    "gn:dem":3311,
    "gn:feature_class":"P",
    "gn:feature_code":"PPL",
    "gn:name":"Venecia",
    "gn:population":0,
    "gn:timezone":"America/Guayaquil",
    "iso:country":"EC",
    "name:ceb_x_preferred":[
        "Venecia"
    ],
    "name:ita_x_preferred":[
        "Venecia"
    ],
    "name:msa_x_preferred":[
        "Venecia"
    ],
    "name:nld_x_preferred":[
        "Venecia"
    ],
    "name:spa_x_preferred":[
        "Venecia"
    ],
    "name:srp_x_preferred":[
        "\u0412\u0435\u043d\u0435\u0441\u0438\u0458\u0430"
    ],
    "name:swe_x_preferred":[
        "Venecia"
    ],
    "name:war_x_preferred":[
        "Venecia"
    ],
    "wof:name":"Venecia",
    "wof:placetype":"locality"
},
  "geometry": {"coordinates":[-78.75,-1.75],"type":"Point"}
}