{
  "type": "Feature",
  "properties": {
    "gn:admin1_code":"10.0",
    "gn:asciiname":"Engunga",
    "gn:country_code":"EC",
    "gn:dem":15,
    "gn:feature_class":"P",
    "gn:feature_code":"PPL",
    "gn:name":"Engunga",
    "gn:population":0,
    "gn:timezone":"America/Guayaquil",
    "iso:country":"EC",
    "wof:name":"Engunga",
    "wof:placetype":"locality"
},
  "geometry": {"coordinates":[-80.56416,-2.46824],"type":"Point"}
}