{
  "type": "Feature",
  "properties": {
    "gn:admin1_code":"9.0",
    "gn:admin2_code":"803.0",
    "gn:admin3_code":"80351.0",
    "gn:asciiname":"Bolivar",
    "gn:country_code":"EC",
    "gn:dem":7,
    "gn:feature_class":"P",
    "gn:feature_code":"PPL",
    "gn:name":"Bol\u00edvar",
    "gn:population":0,
    "gn:timezone":"America/Guayaquil",
    "iso:country":"EC",
    "wof:name":"Bolivar",
    "wof:placetype":"locality"
},
  "geometry": {"coordinates":[-80.04396,0.44575],"type":"Point"}
}