{
  "type": "Feature",
  "properties": {
    "gn:admin1_code":"20.0",
    "gn:admin2_code":"1901.0",
    "gn:admin3_code":"190150.0",
    "gn:asciiname":"La Colina",
    "gn:country_code":"EC",
    "gn:dem":930,
    "gn:feature_class":"P",
    "gn:feature_code":"PPL",
    "gn:name":"La Colina",
    "gn:population":0,
    "gn:timezone":"America/Guayaquil",
    "iso:country":"EC",
    "wof:name":"La Colina",
    "wof:placetype":"locality"
},
  "geometry": {"coordinates":[-78.94401999999999,-4.05704],"type":"Point"}
}