{
  "type": "Feature",
  "properties": {
    "gn:admin1_code":"6.0",
    "gn:asciiname":"Cubillin",
    "gn:country_code":"EC",
    "gn:dem":4129,
    "gn:feature_class":"P",
    "gn:feature_code":"PPL",
    "gn:name":"Cubill\u00edn",
    "gn:population":0,
    "gn:timezone":"America/Guayaquil",
    "iso:country":"EC",
    "wof:name":"Cubillin",
    "wof:placetype":"locality"
},
  "geometry": {"coordinates":[-78.41667,-1.83333],"type":"Point"}
}