{
  "type": "Feature",
  "properties": {
    "iso:country":"EC",
    "qs:gn_country":"EC",
    "qs:gn_fcode":"PPL",
    "qs:gn_pop":0,
    "qs:name":"Ballenita",
    "qs:name_adm0":"Ecuador",
    "qs:name_adm1":"Santa Elena",
    "qs:photos":119,
    "qs:photos_1k":24,
    "qs:photos_9k":1,
    "qs:photos_9r":3,
    "qs:photos_all":119,
    "qs:photos_sr":3,
    "qs:placetype":"Town",
    "qs:pop_sr":"0",
    "qs:woe_adm0":23424801,
    "wof:name":"Ballenita",
    "wof:placetype":"locality"
},
  "geometry": {"coordinates":[-80.87305000000001,-2.20528],"type":"Point"}
}