{
  "type": "Feature",
  "properties": {
    "gn:admin1_code":"14.0",
    "gn:admin2_code":"1306.0",
    "gn:admin3_code":"130653.0",
    "gn:asciiname":"Las Pinas",
    "gn:cc2":"EC",
    "gn:country_code":"EC",
    "gn:dem":359,
    "gn:feature_class":"P",
    "gn:feature_code":"PPL",
    "gn:name":"Las Pi\u00f1as",
    "gn:population":0,
    "gn:timezone":"America/Guayaquil",
    "iso:country":"EC",
    "wof:name":"Las Pinas",
    "wof:placetype":"locality"
},
  "geometry": {"coordinates":[-80.61667,-1.53333],"type":"Point"}
}