{
  "type": "Feature",
  "properties": {
    "gn:admin1_code":"10.0",
    "gn:admin2_code":"901.0",
    "gn:admin3_code":"90158.0",
    "gn:asciiname":"Hacienda Valparaiso",
    "gn:cc2":"EC",
    "gn:country_code":"EC",
    "gn:dem":8,
    "gn:feature_class":"P",
    "gn:feature_code":"PPL",
    "gn:name":"Hacienda Valpara\u00edso",
    "gn:population":0,
    "gn:timezone":"America/Guayaquil",
    "iso:country":"EC",
    "wof:name":"Hacienda Valparaiso",
    "wof:placetype":"locality"
},
  "geometry": {"coordinates":[-79.78333000000001,-2.95],"type":"Point"}
}