{
  "type": "Feature",
  "properties": {
    "gn:admin1_code":"11.0",
    "gn:admin2_code":"1001.0",
    "gn:admin3_code":"100150.0",
    "gn:asciiname":"Caranqui",
    "gn:country_code":"EC",
    "gn:dem":2297,
    "gn:feature_class":"P",
    "gn:feature_code":"PPL",
    "gn:name":"Caranqui",
    "gn:population":0,
    "gn:timezone":"America/Guayaquil",
    "iso:country":"EC",
    "wof:name":"Caranqui",
    "wof:placetype":"locality"
},
  "geometry": {"coordinates":[-78.12173,0.32287],"type":"Point"}
}