{
  "type": "Feature",
  "properties": {
    "gn:admin1_code":"12.0",
    "gn:admin2_code":"1102.0",
    "gn:admin3_code":"110251.0",
    "gn:asciiname":"Papaca",
    "gn:country_code":"EC",
    "gn:dem":1757,
    "gn:feature_class":"P",
    "gn:feature_code":"PPL",
    "gn:name":"Papaca",
    "gn:population":0,
    "gn:timezone":"America/Guayaquil",
    "iso:country":"EC",
    "wof:name":"Papaca",
    "wof:placetype":"locality"
},
  "geometry": {"coordinates":[-79.72038000000001,-4.31996],"type":"Point"}
}