{
  "type": "Feature",
  "properties": {
    "gn:admin1_code":"6.0",
    "gn:admin2_code":"603.0",
    "gn:admin3_code":"60350.0",
    "gn:asciiname":"Yanacocha",
    "gn:country_code":"EC",
    "gn:dem":3353,
    "gn:feature_class":"P",
    "gn:feature_code":"PPL",
    "gn:name":"Yanacocha",
    "gn:population":0,
    "gn:timezone":"America/Guayaquil",
    "iso:country":"EC",
    "name:dan_x_preferred":[
        "Yanacocha"
    ],
    "name:deu_x_preferred":[
        "Yanacocha"
    ],
    "name:epo_x_preferred":[
        "\u011canako\u0109o"
    ],
    "name:nld_x_preferred":[
        "Yanacocha"
    ],
    "name:que_x_preferred":[
        "Yanaqucha qhuya"
    ],
    "name:ron_x_preferred":[
        "Yanacocha"
    ],
    "name:ukr_x_preferred":[
        "\u042f\u043d\u0430\u043a\u043e\u0447\u0430"
    ],
    "wof:name":"Yanacocha",
    "wof:placetype":"locality"
},
  "geometry": {"coordinates":[-78.76085,-1.75031],"type":"Point"}
}