{
  "type": "Feature",
  "properties": {
    "gn:admin1_code":"18.0",
    "gn:admin2_code":"1703.0",
    "gn:admin3_code":"170355.0",
    "gn:asciiname":"Canzacoto",
    "gn:country_code":"EC",
    "gn:dem":1976,
    "gn:feature_class":"P",
    "gn:feature_code":"PPL",
    "gn:name":"Canzacoto",
    "gn:population":0,
    "gn:timezone":"America/Guayaquil",
    "iso:country":"EC",
    "wof:name":"Canzacoto",
    "wof:placetype":"locality"
},
  "geometry": {"coordinates":[-78.75559,-0.43138],"type":"Point"}
}