{
  "type": "Feature",
  "properties": {
    "gn:admin1_code":"2.0",
    "gn:admin2_code":"105.0",
    "gn:admin3_code":"10552.0",
    "gn:asciiname":"Hacienda Tablacao",
    "gn:country_code":"EC",
    "gn:dem":2542,
    "gn:feature_class":"P",
    "gn:feature_code":"PPL",
    "gn:name":"Hacienda Tablacao",
    "gn:population":0,
    "gn:timezone":"America/Guayaquil",
    "iso:country":"EC",
    "wof:name":"Hacienda Tablacao",
    "wof:placetype":"locality"
},
  "geometry": {"coordinates":[-78.77224,-2.72161],"type":"Point"}
}