{
  "type": "Feature",
  "properties": {
    "gn:admin1_code":"6.0",
    "gn:admin2_code":"607.0",
    "gn:admin3_code":"60750.0",
    "gn:asciiname":"Hacienda San Miguel",
    "gn:cc2":"EC",
    "gn:country_code":"EC",
    "gn:dem":2826,
    "gn:feature_class":"P",
    "gn:feature_code":"PPL",
    "gn:name":"Hacienda San Miguel",
    "gn:population":0,
    "gn:timezone":"America/Guayaquil",
    "iso:country":"EC",
    "wof:name":"Hacienda San Miguel",
    "wof:placetype":"locality"
},
  "geometry": {"coordinates":[-78.65000000000001,-1.63333],"type":"Point"}
}