{
  "type": "Feature",
  "properties": {
    "gn:admin1_code":"5.0",
    "gn:admin2_code":"401.0",
    "gn:admin3_code":"40157.0",
    "gn:asciiname":"Hacienda La Joya Vieja",
    "gn:country_code":"EC",
    "gn:dem":3034,
    "gn:feature_class":"P",
    "gn:feature_code":"PPL",
    "gn:name":"Hacienda La Joya Vieja",
    "gn:population":0,
    "gn:timezone":"America/Guayaquil",
    "iso:country":"EC",
    "wof:name":"Hacienda La Joya Vieja",
    "wof:placetype":"locality"
},
  "geometry": {"coordinates":[-77.78494999999999,0.82224],"type":"Point"}
}