{
  "type": "Feature",
  "properties": {
    "gn:admin1_code":"2.0",
    "gn:admin2_code":"101.0",
    "gn:admin3_code":"10165.0",
    "gn:asciiname":"Sayausi",
    "gn:country_code":"EC",
    "gn:dem":2771,
    "gn:feature_class":"P",
    "gn:feature_code":"PPL",
    "gn:name":"Sayaus\u00ed",
    "gn:population":0,
    "gn:timezone":"America/Guayaquil",
    "iso:country":"EC",
    "name:que_x_preferred":[
        "Sayawsi kitilli"
    ],
    "name:spa_x_preferred":[
        "Sayaus\u00ed"
    ],
    "wof:name":"Sayausi",
    "wof:placetype":"locality"
},
  "geometry": {"coordinates":[-79.07225,-2.87142],"type":"Point"}
}