{
  "type": "Feature",
  "properties": {
    "gn:admin1_code":"7.0",
    "gn:admin2_code":"507.0",
    "gn:admin3_code":"50750.0",
    "gn:asciiname":"La Cocha de San Isidro",
    "gn:country_code":"EC",
    "gn:dem":2282,
    "gn:feature_class":"P",
    "gn:feature_code":"PPL",
    "gn:name":"La Cocha de San Isidro",
    "gn:population":0,
    "gn:timezone":"America/Guayaquil",
    "iso:country":"EC",
    "wof:name":"La Cocha de San Isidro",
    "wof:placetype":"locality"
},
  "geometry": {"coordinates":[-79.01994999999999,-0.58296],"type":"Point"}
}