{
  "type": "Feature",
  "properties": {
    "gn:admin1_code":"15.0",
    "gn:admin2_code":"1401.0",
    "gn:admin3_code":"140157.0",
    "gn:asciiname":"Miazal",
    "gn:country_code":"EC",
    "gn:dem":277,
    "gn:feature_class":"P",
    "gn:feature_code":"PPL",
    "gn:name":"Miazal",
    "gn:population":0,
    "gn:timezone":"America/Guayaquil",
    "iso:country":"EC",
    "wof:name":"Miazal",
    "wof:placetype":"locality"
},
  "geometry": {"coordinates":[-77.77803,-2.59578],"type":"Point"}
}