{
  "type": "Feature",
  "properties": {
    "gn:admin1_code":"2.0",
    "gn:admin2_code":"110.0",
    "gn:admin3_code":"11050.0",
    "gn:asciiname":"Cuchipirca",
    "gn:country_code":"EC",
    "gn:dem":2291,
    "gn:feature_class":"P",
    "gn:feature_code":"PPL",
    "gn:name":"Cuchipirca",
    "gn:population":0,
    "gn:timezone":"America/Guayaquil",
    "iso:country":"EC",
    "wof:name":"Cuchipirca",
    "wof:placetype":"locality"
},
  "geometry": {"coordinates":[-79.11535000000001,-3.43246],"type":"Point"}
}