{
  "type": "Feature",
  "properties": {
    "gn:admin1_code":"15.0",
    "gn:admin2_code":"1401.0",
    "gn:admin3_code":"140160.0",
    "gn:asciiname":"Zunac",
    "gn:country_code":"EC",
    "gn:dem":2197,
    "gn:feature_class":"P",
    "gn:feature_code":"PPL",
    "gn:name":"Z\u00fa\u00f1ac",
    "gn:population":0,
    "gn:timezone":"America/Guayaquil",
    "iso:country":"EC",
    "wof:name":"Zunac",
    "wof:placetype":"locality"
},
  "geometry": {"coordinates":[-78.36872,-2.20046],"type":"Point"}
}