{
  "type": "Feature",
  "properties": {
    "gn:admin1_code":"7.0",
    "gn:admin2_code":"501.0",
    "gn:admin3_code":"50156.0",
    "gn:asciiname":"Rumipamba de Espinoza",
    "gn:country_code":"EC",
    "gn:dem":2958,
    "gn:feature_class":"P",
    "gn:feature_code":"PPL",
    "gn:name":"Rumipamba de Espinoza",
    "gn:population":0,
    "gn:timezone":"America/Guayaquil",
    "iso:country":"EC",
    "wof:name":"Rumipamba de Espinoza",
    "wof:placetype":"locality"
},
  "geometry": {"coordinates":[-78.59907,-0.79128],"type":"Point"}
}