{
  "type": "Feature",
  "properties": {
    "gn:admin1_code":"18.0",
    "gn:admin2_code":"1709.0",
    "gn:admin3_code":"170950.0",
    "gn:asciiname":"Nuestra Patria",
    "gn:country_code":"EC",
    "gn:dem":188,
    "gn:feature_class":"P",
    "gn:feature_code":"PPL",
    "gn:name":"Nuestra Patria",
    "gn:population":0,
    "gn:timezone":"America/Guayaquil",
    "iso:country":"EC",
    "wof:name":"Nuestra Patria",
    "wof:placetype":"locality"
},
  "geometry": {"coordinates":[-79.20944,0.08998],"type":"Point"}
}