{
  "type": "Feature",
  "properties": {
    "gn:admin1_code":"8.0",
    "gn:admin2_code":"712.0",
    "gn:admin3_code":"71252.0",
    "gn:asciiname":"Los Corazones",
    "gn:country_code":"EC",
    "gn:dem":8,
    "gn:feature_class":"P",
    "gn:feature_code":"PPL",
    "gn:name":"Los Corazones",
    "gn:population":0,
    "gn:timezone":"America/Guayaquil",
    "iso:country":"EC",
    "wof:name":"Los Corazones",
    "wof:placetype":"locality"
},
  "geometry": {"coordinates":[-80.22043000000002,-3.3456],"type":"Point"}
}