{
  "type": "Feature",
  "properties": {
    "iso:country":"EC",
    "name:ceb_x_preferred":[
        "Tosagua"
    ],
    "name:eng_x_preferred":[
        "Tosagua"
    ],
    "name:fra_x_preferred":[
        "Tosagua"
    ],
    "name:nld_x_preferred":[
        "Tosagua"
    ],
    "name:pol_x_preferred":[
        "Tosagua"
    ],
    "name:que_x_preferred":[
        "Tosagua"
    ],
    "name:spa_x_preferred":[
        "Tosagua"
    ],
    "name:swe_x_preferred":[
        "Tosagua"
    ],
    "name:zho_x_preferred":[
        "\u6258\u85a9\u74dc"
    ],
    "qs:gn_country":"EC",
    "qs:gn_fcode":"PPL",
    "qs:gn_pop":14680,
    "qs:name":"Tosagua",
    "qs:name_adm0":"Ecuador",
    "qs:name_adm1":"Manabi",
    "qs:photos":1,
    "qs:photos_1k":1,
    "qs:photos_9k":1,
    "qs:photos_9r":1,
    "qs:photos_all":1,
    "qs:photos_sr":1,
    "qs:placetype":"LocalAdmin",
    "qs:pop_sr":"6",
    "qs:woe_adm0":23424801,
    "wd:wordcount":119,
    "wof:name":"Tosagua",
    "wof:placetype":"localadmin",
    "wof:population":14680
},
  "geometry": {"coordinates":[-80.23473,-0.78679],"type":"Point"}
}