{
  "type": "Feature",
  "properties": {
    "gn:admin1_code":"19.0",
    "gn:admin2_code":"1805.0",
    "gn:admin3_code":"180552.0",
    "gn:asciiname":"Hacienda Choyata",
    "gn:country_code":"EC",
    "gn:dem":2703,
    "gn:feature_class":"P",
    "gn:feature_code":"PPL",
    "gn:name":"Hacienda Choyata",
    "gn:population":0,
    "gn:timezone":"America/Guayaquil",
    "iso:country":"EC",
    "wof:name":"Hacienda Choyata",
    "wof:placetype":"locality"
},
  "geometry": {"coordinates":[-78.49524,-1.24129],"type":"Point"}
}