{
  "type": "Feature",
  "properties": {
    "gn:admin1_code":"12.0",
    "gn:asciiname":"La Bocana",
    "gn:country_code":"EC",
    "gn:dem":145,
    "gn:feature_class":"P",
    "gn:feature_code":"PPL",
    "gn:name":"La Bocana",
    "gn:population":0,
    "gn:timezone":"America/Lima",
    "iso:country":"EC",
    "wof:name":"La Bocana",
    "wof:placetype":"locality"
},
  "geometry": {"coordinates":[-80.41667,-4.46667],"type":"Point"}
}