{
  "type": "Feature",
  "properties": {
    "gn:admin1_code":"2.0",
    "gn:admin2_code":"105.0",
    "gn:admin3_code":"10562.0",
    "gn:asciiname":"Hacienda Huanuchi",
    "gn:country_code":"EC",
    "gn:dem":2704,
    "gn:feature_class":"P",
    "gn:feature_code":"PPL",
    "gn:name":"Hacienda Huanuchi",
    "gn:population":0,
    "gn:timezone":"America/Guayaquil",
    "iso:country":"EC",
    "wof:name":"Hacienda Huanuchi",
    "wof:placetype":"locality"
},
  "geometry": {"coordinates":[-78.72429,-2.72118],"type":"Point"}
}