{
  "type": "Feature",
  "properties": {
    "gn:admin1_code":"12.0",
    "gn:admin2_code":"1103.0",
    "gn:admin3_code":"110350.0",
    "gn:asciiname":"Jatishapa",
    "gn:country_code":"EC",
    "gn:dem":2022,
    "gn:feature_class":"P",
    "gn:feature_code":"PPL",
    "gn:name":"Jatishapa",
    "gn:population":0,
    "gn:timezone":"America/Guayaquil",
    "iso:country":"EC",
    "wof:name":"Jatishapa",
    "wof:placetype":"locality"
},
  "geometry": {"coordinates":[-79.36667,-3.91667],"type":"Point"}
}