{
  "type": "Feature",
  "properties": {
    "gn:admin1_code":"10.0",
    "gn:admin2_code":"919.0",
    "gn:admin3_code":"91950.0",
    "gn:asciiname":"La Mercedes",
    "gn:cc2":"EC",
    "gn:country_code":"EC",
    "gn:dem":3,
    "gn:feature_class":"P",
    "gn:feature_code":"PPL",
    "gn:name":"La Mercedes",
    "gn:population":0,
    "gn:timezone":"America/Guayaquil",
    "iso:country":"EC",
    "wof:name":"La Mercedes",
    "wof:placetype":"locality"
},
  "geometry": {"coordinates":[-79.83333,-1.83333],"type":"Point"}
}