{
  "type": "Feature",
  "properties": {
    "gn:admin1_code":"4.0",
    "gn:admin2_code":"303.0",
    "gn:admin3_code":"30354.0",
    "gn:asciiname":"Gun Grande",
    "gn:country_code":"EC",
    "gn:dem":2541,
    "gn:feature_class":"P",
    "gn:feature_code":"PPL",
    "gn:name":"Gun Grande",
    "gn:population":0,
    "gn:timezone":"America/Guayaquil",
    "iso:country":"EC",
    "wof:name":"Gun Grande",
    "wof:placetype":"locality"
},
  "geometry": {"coordinates":[-79.06667,-2.53333],"type":"Point"}
}