{
  "type": "Feature",
  "properties": {
    "gn:admin1_code":"26.0",
    "gn:admin2_code":"2301.0",
    "gn:admin3_code":"230154.0",
    "gn:asciiname":"San Vicente de Bua",
    "gn:country_code":"EC",
    "gn:dem":217,
    "gn:feature_class":"P",
    "gn:feature_code":"PPL",
    "gn:name":"San Vicente de B\u00faa",
    "gn:population":0,
    "gn:timezone":"America/Guayaquil",
    "iso:country":"EC",
    "wof:name":"San Vicente de Bua",
    "wof:placetype":"locality"
},
  "geometry": {"coordinates":[-79.45016,-0.11696],"type":"Point"}
}