{
  "type": "Feature",
  "properties": {
    "gn:admin1_code":"13.0",
    "gn:admin2_code":"1201.0",
    "gn:admin3_code":"120154.0",
    "gn:asciiname":"Pimocha",
    "gn:country_code":"EC",
    "gn:dem":9,
    "gn:feature_class":"P",
    "gn:feature_code":"PPL",
    "gn:name":"Pimocha",
    "gn:population":0,
    "gn:timezone":"America/Guayaquil",
    "iso:country":"EC",
    "wof:name":"Pimocha",
    "wof:placetype":"locality"
},
  "geometry": {"coordinates":[-79.60645,-1.83333],"type":"Point"}
}