{
  "type": "Feature",
  "properties": {
    "gn:admin1_code":"6.0",
    "gn:admin2_code":"601.0",
    "gn:admin3_code":"60153.0",
    "gn:asciiname":"Hacienda Tamaute",
    "gn:cc2":"EC",
    "gn:country_code":"EC",
    "gn:dem":2517,
    "gn:feature_class":"P",
    "gn:feature_code":"PPL",
    "gn:name":"Hacienda Tamaute",
    "gn:population":0,
    "gn:timezone":"America/Guayaquil",
    "iso:country":"EC",
    "wof:name":"Hacienda Tamaute",
    "wof:placetype":"locality"
},
  "geometry": {"coordinates":[-78.58333,-1.65],"type":"Point"}
}