{
  "type": "Feature",
  "properties": {
    "gn:admin1_code":"12.0",
    "gn:admin2_code":"1101.0",
    "gn:admin3_code":"110157.0",
    "gn:asciiname":"Vinoyacu",
    "gn:country_code":"EC",
    "gn:dem":2545,
    "gn:feature_class":"P",
    "gn:feature_code":"PPL",
    "gn:name":"Vinoyacu",
    "gn:population":0,
    "gn:timezone":"America/Guayaquil",
    "iso:country":"EC",
    "wof:name":"Vinoyacu",
    "wof:placetype":"locality"
},
  "geometry": {"coordinates":[-79.24290999999999,-3.75101],"type":"Point"}
}