{
  "type": "Feature",
  "properties": {
    "gn:admin1_code":"18.0",
    "gn:admin2_code":"1701.0",
    "gn:admin3_code":"170166.0",
    "gn:asciiname":"Salvador",
    "gn:country_code":"EC",
    "gn:dem":2661,
    "gn:feature_class":"P",
    "gn:feature_code":"PPL",
    "gn:name":"Salvador",
    "gn:population":0,
    "gn:timezone":"America/Guayaquil",
    "iso:country":"EC",
    "wof:name":"Salvador",
    "wof:placetype":"locality"
},
  "geometry": {"coordinates":[-78.68333,-0.28333],"type":"Point"}
}