{
  "type": "Feature",
  "properties": {
    "gn:admin1_code":"2.0",
    "gn:admin2_code":"102.0",
    "gn:admin3_code":"10252.0",
    "gn:asciiname":"Shishi",
    "gn:country_code":"EC",
    "gn:dem":3033,
    "gn:feature_class":"P",
    "gn:feature_code":"PPL",
    "gn:name":"Shishi",
    "gn:population":0,
    "gn:timezone":"America/Guayaquil",
    "iso:country":"EC",
    "name:ceb_x_preferred":[
        "Shishi"
    ],
    "name:cym_x_preferred":[
        "Shishi"
    ],
    "name:deu_x_preferred":[
        "Shishi"
    ],
    "name:nor_x_preferred":[
        "Shishi"
    ],
    "name:swe_x_preferred":[
        "Shishi"
    ],
    "wof:name":"Shishi",
    "wof:placetype":"locality"
},
  "geometry": {"coordinates":[-79.21666999999999,-3.11667],"type":"Point"}
}