{
  "type": "Feature",
  "properties": {
    "gn:admin1_code":"9.0",
    "gn:asciiname":"La Villegas",
    "gn:country_code":"EC",
    "gn:dem":229,
    "gn:feature_class":"P",
    "gn:feature_code":"PPL",
    "gn:name":"La Villegas",
    "gn:population":0,
    "gn:timezone":"America/Guayaquil",
    "iso:country":"EC",
    "wof:name":"La Villegas",
    "wof:placetype":"locality"
},
  "geometry": {"coordinates":[-79.44247,-0.05536],"type":"Point"}
}