{
  "type": "Feature",
  "properties": {
    "gn:admin1_code":"4.0",
    "gn:admin2_code":"304.0",
    "gn:admin3_code":"30451.0",
    "gn:asciiname":"Hacienda Capricho",
    "gn:cc2":"EC",
    "gn:country_code":"EC",
    "gn:dem":45,
    "gn:feature_class":"P",
    "gn:feature_code":"PPL",
    "gn:name":"Hacienda Capricho",
    "gn:population":0,
    "gn:timezone":"America/Guayaquil",
    "iso:country":"EC",
    "wof:name":"Hacienda Capricho",
    "wof:placetype":"locality"
},
  "geometry": {"coordinates":[-79.40000000000001,-2.35],"type":"Point"}
}