{
  "type": "Feature",
  "properties": {
    "gn:admin1_code":"10.0",
    "gn:asciiname":"Isabel Ana",
    "gn:country_code":"EC",
    "gn:dem":2,
    "gn:feature_class":"P",
    "gn:feature_code":"PPL",
    "gn:name":"Isabel Ana",
    "gn:population":0,
    "gn:timezone":"America/Guayaquil",
    "iso:country":"EC",
    "wof:name":"Isabel Ana",
    "wof:placetype":"locality"
},
  "geometry": {"coordinates":[-79.84999999999999,-2.13333],"type":"Point"}
}