{
  "type": "Feature",
  "properties": {
    "gn:admin1_code":"2.0",
    "gn:admin2_code":"101.0",
    "gn:admin3_code":"10152.0",
    "gn:asciiname":"Salado",
    "gn:country_code":"EC",
    "gn:dem":2859,
    "gn:feature_class":"P",
    "gn:feature_code":"PPL",
    "gn:name":"Salado",
    "gn:population":0,
    "gn:timezone":"America/Guayaquil",
    "iso:country":"EC",
    "name:ceb_x_preferred":[
        "Salado"
    ],
    "name:ces_x_preferred":[
        "Salado"
    ],
    "name:deu_x_preferred":[
        "Salado"
    ],
    "name:ita_x_preferred":[
        "Salado"
    ],
    "name:nld_x_preferred":[
        "Salado"
    ],
    "name:pol_x_preferred":[
        "Salado"
    ],
    "name:rus_x_preferred":[
        "\u0440\u0435\u043a\u0430 \u0420\u0438\u043e-\u0421\u0430\u043b\u0430\u0434\u043e"
    ],
    "name:rus_x_variant":[
        "\u0420\u0438\u043e-\u0421\u0430\u043b\u0430\u0434\u043e"
    ],
    "name:spa_x_preferred":[
        "Salado"
    ],
    "name:swe_x_preferred":[
        "Salado"
    ],
    "name:tur_x_preferred":[
        "Salado"
    ],
    "name:ukr_x_preferred":[
        "\u0421\u0430\u043b\u0430\u0434\u043e"
    ],
    "name:urd_x_preferred":[
        "\u0633\u0627\u0644\u0627\u062f\u0648"
    ],
    "name:vie_x_preferred":[
        "S\u00f4ng Salado"
    ],
    "name:zho_cn_x_preferred":[
        "\u8428\u62c9\u591a\u6cb3"
    ],
    "name:zho_tw_x_preferred":[
        "\u96a1\u62c9\u591a\u6cb3"
    ],
    "wof:name":"Salado",
    "wof:placetype":"locality"
},
  "geometry": {"coordinates":[-79.01797999999999,-3.09612],"type":"Point"}
}