{
  "type": "Feature",
  "properties": {
    "gn:admin1_code":"12.0",
    "gn:admin2_code":"1110.0",
    "gn:admin3_code":"111053.0",
    "gn:asciiname":"Pitayo",
    "gn:country_code":"EC",
    "gn:dem":655,
    "gn:feature_class":"P",
    "gn:feature_code":"PPL",
    "gn:name":"Pitayo",
    "gn:population":0,
    "gn:timezone":"America/Guayaquil",
    "iso:country":"EC",
    "name:tam_x_preferred":[
        "\u0baa\u0bbf\u0b9f\u0baf\u0bcb"
    ],
    "wof:name":"Pitayo",
    "wof:placetype":"locality"
},
  "geometry": {"coordinates":[-80.18536999999998,-4.01003],"type":"Point"}
}