{
  "type": "Feature",
  "properties": {
    "gn:admin1_code":"2.0",
    "gn:asciiname":"Amaluza",
    "gn:country_code":"EC",
    "gn:dem":2959,
    "gn:feature_class":"P",
    "gn:feature_code":"PPL",
    "gn:name":"Amaluza",
    "gn:population":0,
    "gn:timezone":"America/Guayaquil",
    "iso:country":"EC",
    "wof:name":"Amaluza",
    "wof:placetype":"locality"
},
  "geometry": {"coordinates":[-78.48333000000002,-2.83333],"type":"Point"}
}