{
  "type": "Feature",
  "properties": {
    "gn:admin1_code":"23.0",
    "gn:admin2_code":"1504.0",
    "gn:admin3_code":"150450.0",
    "gn:asciiname":"El Chaco",
    "gn:country_code":"EC",
    "gn:dem":1600,
    "gn:feature_class":"P",
    "gn:feature_code":"PPL",
    "gn:name":"El Chaco",
    "gn:population":0,
    "gn:timezone":"America/Guayaquil",
    "iso:country":"EC",
    "wof:name":"El Chaco",
    "wof:placetype":"locality"
},
  "geometry": {"coordinates":[-77.81018,-0.33822],"type":"Point"}
}