{
  "type": "Feature",
  "properties": {
    "gn:admin1_code":"9.0",
    "gn:admin2_code":"804.0",
    "gn:admin3_code":"80455.0",
    "gn:asciiname":"El Paisaje",
    "gn:country_code":"EC",
    "gn:dem":148,
    "gn:feature_class":"P",
    "gn:feature_code":"PPL",
    "gn:name":"El Paisaje",
    "gn:population":0,
    "gn:timezone":"America/Guayaquil",
    "iso:country":"EC",
    "wof:name":"El Paisaje",
    "wof:placetype":"locality"
},
  "geometry": {"coordinates":[-79.42958,0.1747],"type":"Point"}
}