{
  "type": "Feature",
  "properties": {
    "gn:admin1_code":"20.0",
    "gn:admin2_code":"1906.0",
    "gn:admin3_code":"190652.0",
    "gn:asciiname":"El Cedro",
    "gn:country_code":"EC",
    "gn:dem":762,
    "gn:feature_class":"P",
    "gn:feature_code":"PPL",
    "gn:name":"El Cedro",
    "gn:population":0,
    "gn:timezone":"America/Guayaquil",
    "iso:country":"EC",
    "wof:name":"El Cedro",
    "wof:placetype":"locality"
},
  "geometry": {"coordinates":[-78.54593,-3.67875],"type":"Point"}
}