{
  "type": "Feature",
  "properties": {
    "gn:admin1_code":"12.0",
    "gn:admin2_code":"1104.0",
    "gn:admin3_code":"110456.0",
    "gn:asciiname":"Guineo Grande",
    "gn:country_code":"EC",
    "gn:dem":637,
    "gn:feature_class":"P",
    "gn:feature_code":"PPL",
    "gn:name":"Guineo Grande",
    "gn:population":0,
    "gn:timezone":"America/Guayaquil",
    "iso:country":"EC",
    "wof:name":"Guineo Grande",
    "wof:placetype":"locality"
},
  "geometry": {"coordinates":[-80.14544000000002,-4.16606],"type":"Point"}
}