{
  "type": "Feature",
  "properties": {
    "gn:admin1_code":"10.0",
    "gn:admin2_code":"922.0",
    "gn:admin3_code":"92250.0",
    "gn:asciiname":"Jesus Teresa",
    "gn:country_code":"EC",
    "gn:dem":28,
    "gn:feature_class":"P",
    "gn:feature_code":"PPL",
    "gn:name":"Jes\u00fas Teresa",
    "gn:population":0,
    "gn:timezone":"America/Guayaquil",
    "iso:country":"EC",
    "wof:name":"Jesus Teresa",
    "wof:placetype":"locality"
},
  "geometry": {"coordinates":[-79.45,-2.03333],"type":"Point"}
}