{
  "type": "Feature",
  "properties": {
    "gn:admin1_code":"22.0",
    "gn:admin2_code":"2101.0",
    "gn:admin3_code":"210150.0",
    "gn:asciiname":"Union y Progreso",
    "gn:country_code":"EC",
    "gn:dem":302,
    "gn:feature_class":"P",
    "gn:feature_code":"PPL",
    "gn:name":"Uni\u00f3n y Progreso",
    "gn:population":0,
    "gn:timezone":"America/Guayaquil",
    "iso:country":"EC",
    "wof:name":"Union y Progreso",
    "wof:placetype":"locality"
},
  "geometry": {"coordinates":[-76.8926,0.08091],"type":"Point"}
}