{
  "type": "Feature",
  "properties": {
    "gn:admin1_code":"18.0",
    "gn:admin2_code":"1703.0",
    "gn:admin3_code":"170350.0",
    "gn:asciiname":"San Agustin",
    "gn:country_code":"EC",
    "gn:dem":2838,
    "gn:feature_class":"P",
    "gn:feature_code":"PPL",
    "gn:name":"San Agust\u00edn",
    "gn:population":0,
    "gn:timezone":"America/Guayaquil",
    "iso:country":"EC",
    "wof:name":"San Agustin",
    "wof:placetype":"locality"
},
  "geometry": {"coordinates":[-78.54649999999999,-0.47968],"type":"Point"}
}