{
  "type": "Feature",
  "properties": {
    "gn:admin1_code":"15.0",
    "gn:admin2_code":"1402.0",
    "gn:admin3_code":"140251.0",
    "gn:asciiname":"Amazonas",
    "gn:country_code":"EC",
    "gn:dem":2341,
    "gn:feature_class":"P",
    "gn:feature_code":"PPL",
    "gn:name":"Amazonas",
    "gn:population":0,
    "gn:timezone":"America/Guayaquil",
    "iso:country":"EC",
    "wof:name":"Amazonas",
    "wof:placetype":"locality"
},
  "geometry": {"coordinates":[-78.77727,-3.38905],"type":"Point"}
}