{
  "type": "Feature",
  "properties": {
    "gn:admin1_code":"20.0",
    "gn:admin2_code":"1905.0",
    "gn:admin3_code":"190551.0",
    "gn:asciiname":"Chicana Bajo",
    "gn:country_code":"EC",
    "gn:dem":833,
    "gn:feature_class":"P",
    "gn:feature_code":"PPL",
    "gn:name":"Chica\u00f1a Bajo",
    "gn:population":0,
    "gn:timezone":"America/Guayaquil",
    "iso:country":"EC",
    "wof:name":"Chicana Bajo",
    "wof:placetype":"locality"
},
  "geometry": {"coordinates":[-78.73503000000002,-3.75353],"type":"Point"}
}