{
  "type": "Feature",
  "properties": {
    "gn:admin1_code":"4.0",
    "gn:admin2_code":"301.0",
    "gn:admin3_code":"30150.0",
    "gn:asciiname":"Chischiguin",
    "gn:country_code":"EC",
    "gn:dem":2486,
    "gn:feature_class":"P",
    "gn:feature_code":"PPL",
    "gn:name":"Chischigu\u00edn",
    "gn:population":0,
    "gn:timezone":"America/Guayaquil",
    "iso:country":"EC",
    "wof:name":"Chischiguin",
    "wof:placetype":"locality"
},
  "geometry": {"coordinates":[-78.84999999999999,-2.73333],"type":"Point"}
}