{
  "type": "Feature",
  "properties": {
    "gn:admin1_code":"22.0",
    "gn:admin2_code":"2106.0",
    "gn:admin3_code":"210650.0",
    "gn:asciiname":"Shiris",
    "gn:country_code":"EC",
    "gn:dem":374,
    "gn:feature_class":"P",
    "gn:feature_code":"PPL",
    "gn:name":"Shiris",
    "gn:population":0,
    "gn:timezone":"America/Guayaquil",
    "iso:country":"EC",
    "wof:name":"Shiris",
    "wof:placetype":"locality"
},
  "geometry": {"coordinates":[-77.21287,0.05146],"type":"Point"}
}