{
  "type": "Feature",
  "properties": {
    "gn:admin1_code":"18.0",
    "gn:admin2_code":"1701.0",
    "gn:admin3_code":"170185.0",
    "gn:asciiname":"Hacienda Oyambaro",
    "gn:country_code":"EC",
    "gn:dem":2626,
    "gn:feature_class":"P",
    "gn:feature_code":"PPL",
    "gn:name":"Hacienda Oyambaro",
    "gn:population":0,
    "gn:timezone":"America/Guayaquil",
    "iso:country":"EC",
    "wof:name":"Hacienda Oyambaro",
    "wof:placetype":"locality"
},
  "geometry": {"coordinates":[-78.32525,-0.2061],"type":"Point"}
}