{
  "type": "Feature",
  "properties": {
    "gn:admin1_code":"10.0",
    "gn:admin2_code":"906.0",
    "gn:admin3_code":"90653.0",
    "gn:asciiname":"Valeriano",
    "gn:country_code":"EC",
    "gn:dem":4,
    "gn:feature_class":"P",
    "gn:feature_code":"PPL",
    "gn:name":"Valeriano",
    "gn:population":0,
    "gn:timezone":"America/Guayaquil",
    "iso:country":"EC",
    "wof:name":"Valeriano",
    "wof:placetype":"locality"
},
  "geometry": {"coordinates":[-79.90000000000001,-1.83333],"type":"Point"}
}