{
  "type": "Feature",
  "properties": {
    "gn:admin1_code":"7.0",
    "gn:admin2_code":"507.0",
    "gn:admin3_code":"50752.0",
    "gn:asciiname":"Guantualo",
    "gn:country_code":"EC",
    "gn:dem":3163,
    "gn:feature_class":"P",
    "gn:feature_code":"PPL",
    "gn:name":"Guantualo",
    "gn:population":0,
    "gn:timezone":"America/Guayaquil",
    "iso:country":"EC",
    "wof:name":"Guantualo",
    "wof:placetype":"locality"
},
  "geometry": {"coordinates":[-78.88014,-0.7794],"type":"Point"}
}