{
  "type": "Feature",
  "properties": {
    "gn:admin1_code":"14.0",
    "gn:asciiname":"Isabel",
    "gn:cc2":"EC",
    "gn:country_code":"EC",
    "gn:dem":47,
    "gn:feature_class":"P",
    "gn:feature_code":"PPL",
    "gn:name":"Isabel",
    "gn:population":0,
    "gn:timezone":"America/Guayaquil",
    "iso:country":"EC",
    "name:deu_x_preferred":[
        "Isabel"
    ],
    "name:est_x_preferred":[
        "Isabel"
    ],
    "name:fin_x_preferred":[
        "Isabel"
    ],
    "name:glg_x_preferred":[
        "Isabel"
    ],
    "name:heb_x_preferred":[
        "\u05d0\u05d9\u05d6\u05d1\u05dc"
    ],
    "name:hun_x_preferred":[
        "Isabel"
    ],
    "name:nor_x_preferred":[
        "Isabel"
    ],
    "name:rus_x_preferred":[
        "\u0418\u0437\u0430\u0431\u0435\u043b\u043b\u0430"
    ],
    "name:spa_x_preferred":[
        "Isabel"
    ],
    "name:srp_x_preferred":[
        "\u0418\u0437\u0430\u0431\u0435\u043b\u0430"
    ],
    "name:ukr_x_preferred":[
        "\u0406\u0437\u0430\u0431\u0435\u043b\u0430"
    ],
    "wof:name":"Isabel",
    "wof:placetype":"locality"
},
  "geometry": {"coordinates":[-80.09999999999999,-1.48333],"type":"Point"}
}