{
  "type": "Feature",
  "properties": {
    "gn:admin1_code":"11.0",
    "gn:admin2_code":"1003.0",
    "gn:admin3_code":"100352.0",
    "gn:asciiname":"Galapagos",
    "gn:country_code":"EC",
    "gn:dem":1708,
    "gn:feature_class":"P",
    "gn:feature_code":"PPL",
    "gn:name":"Gal\u00e1pagos",
    "gn:population":0,
    "gn:timezone":"America/Guayaquil",
    "iso:country":"EC",
    "wof:name":"Galapagos",
    "wof:placetype":"locality"
},
  "geometry": {"coordinates":[-78.73333000000002,0.35],"type":"Point"}
}