{
  "type": "Feature",
  "properties": {
    "gn:admin1_code":"8.0",
    "gn:admin2_code":"711.0",
    "gn:admin3_code":"71151.0",
    "gn:asciiname":"Curtincapa",
    "gn:country_code":"EC",
    "gn:dem":1045,
    "gn:feature_class":"P",
    "gn:feature_code":"PPL",
    "gn:name":"Curtincapa",
    "gn:population":0,
    "gn:timezone":"America/Guayaquil",
    "iso:country":"EC",
    "wof:name":"Curtincapa",
    "wof:placetype":"locality"
},
  "geometry": {"coordinates":[-79.54977,-3.7306],"type":"Point"}
}