{
  "type": "Feature",
  "properties": {
    "gn:admin1_code":"19.0",
    "gn:admin2_code":"1807.0",
    "gn:admin3_code":"180750.0",
    "gn:asciiname":"Ladrillo",
    "gn:country_code":"EC",
    "gn:dem":2912,
    "gn:feature_class":"P",
    "gn:feature_code":"PPL",
    "gn:name":"Ladrillo",
    "gn:population":0,
    "gn:timezone":"America/Guayaquil",
    "iso:country":"EC",
    "wof:name":"Ladrillo",
    "wof:placetype":"locality"
},
  "geometry": {"coordinates":[-78.56667,-1.35],"type":"Point"}
}