{
  "type": "Feature",
  "properties": {
    "gn:admin1_code":"12.0",
    "gn:admin2_code":"1113.0",
    "gn:admin3_code":"111350.0",
    "gn:asciiname":"Chambarango",
    "gn:country_code":"EC",
    "gn:dem":196,
    "gn:feature_class":"P",
    "gn:feature_code":"PPL",
    "gn:name":"Chambarango",
    "gn:population":0,
    "gn:timezone":"America/Guayaquil",
    "iso:country":"EC",
    "wof:name":"Chambarango",
    "wof:placetype":"locality"
},
  "geometry": {"coordinates":[-80.26666999999998,-4.35],"type":"Point"}
}