{
  "type": "Feature",
  "properties": {
    "gn:admin1_code":"19.0",
    "gn:admin2_code":"1807.0",
    "gn:admin3_code":"180756.0",
    "gn:asciiname":"Garcia Moreno",
    "gn:country_code":"EC",
    "gn:dem":2569,
    "gn:feature_class":"P",
    "gn:feature_code":"PPL",
    "gn:name":"Garc\u00eda Moreno",
    "gn:population":0,
    "gn:timezone":"America/Guayaquil",
    "iso:country":"EC",
    "wof:name":"Garcia Moreno",
    "wof:placetype":"locality"
},
  "geometry": {"coordinates":[-78.54491999999998,-1.32311],"type":"Point"}
}