{
  "type": "Feature",
  "properties": {
    "gn:admin1_code":"10.0",
    "gn:asciiname":"Clementina",
    "gn:cc2":"EC",
    "gn:country_code":"EC",
    "gn:dem":3,
    "gn:feature_class":"P",
    "gn:feature_code":"PPL",
    "gn:name":"Clementina",
    "gn:population":0,
    "gn:timezone":"America/Guayaquil",
    "iso:country":"EC",
    "name:ceb_x_preferred":[
        "Clementina"
    ],
    "name:deu_x_preferred":[
        "Clementina"
    ],
    "name:ita_x_preferred":[
        "Clementina"
    ],
    "name:por_x_preferred":[
        "Clementina"
    ],
    "name:rus_x_preferred":[
        "\u041a\u043b\u0435\u043c\u0435\u043d\u0442\u0438\u043d\u0430"
    ],
    "name:spa_x_preferred":[
        "Clementina"
    ],
    "name:swe_x_preferred":[
        "Clementina"
    ],
    "wof:name":"Clementina",
    "wof:placetype":"locality"
},
  "geometry": {"coordinates":[-79.76666999999998,-2.03333],"type":"Point"}
}