{
  "type": "Feature",
  "properties": {
    "iso:country":"EC",
    "name:cat_x_preferred":[
        "Santa Elena"
    ],
    "name:ceb_x_preferred":[
        "Santa Elena"
    ],
    "name:deu_x_preferred":[
        "Santa Elena"
    ],
    "name:eus_x_preferred":[
        "Santa Elena"
    ],
    "name:fra_x_preferred":[
        "Santa Elena"
    ],
    "name:hye_x_preferred":[
        "\u054d\u0561\u0576\u057f\u0561 \u0537\u056c\u0565\u0576\u0561"
    ],
    "name:ita_x_preferred":[
        "Santa Elena"
    ],
    "name:lit_x_preferred":[
        "Santa Elena"
    ],
    "name:nds_x_preferred":[
        "Santa Elena"
    ],
    "name:nld_x_preferred":[
        "Santa Elena"
    ],
    "name:por_x_preferred":[
        "Santa Elena"
    ],
    "name:ron_x_preferred":[
        "Santa Elena"
    ],
    "name:rus_x_preferred":[
        "\u0421\u0430\u043d\u0442\u0430-\u042d\u043b\u0435\u043d\u0430"
    ],
    "name:sco_x_preferred":[
        "Santa Elena"
    ],
    "name:slk_x_preferred":[
        "Santa Elena"
    ],
    "name:spa_x_preferred":[
        "Santa Elena"
    ],
    "name:srp_x_preferred":[
        "\u0421\u0430\u043d\u0442\u0430 \u0415\u043b\u0435\u043d\u0430"
    ],
    "name:swe_x_preferred":[
        "Santa Elena"
    ],
    "name:tgl_x_preferred":[
        "Santa Elena"
    ],
    "name:vie_x_preferred":[
        "Santa Elena"
    ],
    "name:war_x_preferred":[
        "Santa Elena"
    ],
    "qs:gn_pop":0,
    "qs:name":"Santa Elena",
    "qs:name_adm0":"Ecuador",
    "qs:name_adm1":"Santa Elena",
    "qs:photos":1,
    "qs:photos_1k":1,
    "qs:photos_9k":2,
    "qs:photos_9r":5,
    "qs:photos_all":436,
    "qs:photos_sr":1,
    "qs:placetype":"LocalAdmin",
    "qs:pop_sr":"0",
    "qs:woe_adm0":23424801,
    "wof:name":"Santa Elena",
    "wof:placetype":"localadmin"
},
  "geometry": {"coordinates":[-80.848388,-2.210009],"type":"Point"}
}