{
  "type": "Feature",
  "properties": {
    "gn:admin1_code":"12.0",
    "gn:admin2_code":"1113.0",
    "gn:admin3_code":"111355.0",
    "gn:asciiname":"Vega del Centro",
    "gn:country_code":"EC",
    "gn:dem":435,
    "gn:feature_class":"P",
    "gn:feature_code":"PPL",
    "gn:name":"Vega del Centro",
    "gn:population":0,
    "gn:timezone":"America/Guayaquil",
    "iso:country":"EC",
    "wof:name":"Vega del Centro",
    "wof:placetype":"locality"
},
  "geometry": {"coordinates":[-80.36667,-4.18333],"type":"Point"}
}