{
  "type": "Feature",
  "properties": {
    "gn:admin1_code":"11.0",
    "gn:admin2_code":"1001.0",
    "gn:admin3_code":"100150.0",
    "gn:asciiname":"Hacienda Manzano Guarangui",
    "gn:country_code":"EC",
    "gn:dem":2732,
    "gn:feature_class":"P",
    "gn:feature_code":"PPL",
    "gn:name":"Hacienda Manzano Guarangu\u00ed",
    "gn:population":0,
    "gn:timezone":"America/Guayaquil",
    "iso:country":"EC",
    "wof:name":"Hacienda Manzano Guarangui",
    "wof:placetype":"locality"
},
  "geometry": {"coordinates":[-78.03098,0.34569],"type":"Point"}
}