{
  "type": "Feature",
  "properties": {
    "gn:admin1_code":"12.0",
    "gn:admin2_code":"1113.0",
    "gn:admin3_code":"111354.0",
    "gn:asciiname":"El Sauce",
    "gn:country_code":"EC",
    "gn:dem":466,
    "gn:feature_class":"P",
    "gn:feature_code":"PPL",
    "gn:name":"El Sauce",
    "gn:population":0,
    "gn:timezone":"America/Guayaquil",
    "iso:country":"EC",
    "name:ceb_x_preferred":[
        "El Sauce"
    ],
    "name:ita_x_preferred":[
        "El Sauce"
    ],
    "name:por_x_preferred":[
        "El Sauce"
    ],
    "name:spa_x_preferred":[
        "El Sauce"
    ],
    "name:zho_x_preferred":[
        "\u57c3\u723e\u7d39\u585e"
    ],
    "wof:name":"El Sauce",
    "wof:placetype":"locality"
},
  "geometry": {"coordinates":[-80.31734,-4.18743],"type":"Point"}
}