{
  "type": "Feature",
  "properties": {
    "gn:admin1_code":"18.0",
    "gn:admin2_code":"1701.0",
    "gn:admin3_code":"170169.0",
    "gn:asciiname":"Tulipe",
    "gn:country_code":"EC",
    "gn:dem":1487,
    "gn:feature_class":"P",
    "gn:feature_code":"PPL",
    "gn:name":"Tulipe",
    "gn:population":0,
    "gn:timezone":"America/Guayaquil",
    "iso:country":"EC",
    "wof:name":"Tulipe",
    "wof:placetype":"locality"
},
  "geometry": {"coordinates":[-78.73406999999997,0.08809],"type":"Point"}
}