{
  "type": "Feature",
  "properties": {
    "gn:admin1_code":"20.0",
    "gn:admin2_code":"1903.0",
    "gn:admin3_code":"190352.0",
    "gn:asciiname":"Campamento Agua Colorada",
    "gn:country_code":"EC",
    "gn:dem":1879,
    "gn:feature_class":"P",
    "gn:feature_code":"PPL",
    "gn:name":"Campamento Agua Colorada",
    "gn:population":0,
    "gn:timezone":"America/Lima",
    "iso:country":"EC",
    "wof:name":"Campamento Agua Colorada",
    "wof:placetype":"locality"
},
  "geometry": {"coordinates":[-78.66333,-4.57722],"type":"Point"}
}