{
  "type": "Feature",
  "properties": {
    "gn:admin1_code":"12.0",
    "gn:admin2_code":"1109.0",
    "gn:admin3_code":"110952.0",
    "gn:asciiname":"Panayal",
    "gn:country_code":"EC",
    "gn:dem":1156,
    "gn:feature_class":"P",
    "gn:feature_code":"PPL",
    "gn:name":"Panayal",
    "gn:population":0,
    "gn:timezone":"America/Guayaquil",
    "iso:country":"EC",
    "name:mal_x_preferred":[
        "\u0d2a\u0d28\u0d2f\u0d3e\u0d7d"
    ],
    "wof:name":"Panayal",
    "wof:placetype":"locality"
},
  "geometry": {"coordinates":[-79.85334,-4.0967],"type":"Point"}
}