{
  "type": "Feature",
  "properties": {
    "gn:admin1_code":"2.0",
    "gn:admin2_code":"106.0",
    "gn:admin3_code":"10650.0",
    "gn:asciiname":"Manzanilla",
    "gn:country_code":"EC",
    "gn:dem":2342,
    "gn:feature_class":"P",
    "gn:feature_code":"PPL",
    "gn:name":"Manzanilla",
    "gn:population":0,
    "gn:timezone":"America/Guayaquil",
    "iso:country":"EC",
    "name:bre_x_preferred":[
        "Manzanilla"
    ],
    "name:ceb_x_preferred":[
        "Manzanilla"
    ],
    "name:deu_x_preferred":[
        "Manzanilla"
    ],
    "name:fra_x_preferred":[
        "Manzanilla"
    ],
    "name:kor_x_preferred":[
        "\ub9cc\uc0ac\ub2c8\uc57c"
    ],
    "name:nld_x_preferred":[
        "Manzanilla"
    ],
    "name:spa_x_preferred":[
        "Manzanilla"
    ],
    "name:swe_x_preferred":[
        "Manzanilla"
    ],
    "wof:name":"Manzanilla",
    "wof:placetype":"locality"
},
  "geometry": {"coordinates":[-79.53333000000001,-3.21667],"type":"Point"}
}