{
  "type": "Feature",
  "properties": {
    "gn:admin1_code":"2.0",
    "gn:admin2_code":"110.0",
    "gn:admin3_code":"11051.0",
    "gn:asciiname":"Hacienda Shurapamba",
    "gn:country_code":"EC",
    "gn:dem":1918,
    "gn:feature_class":"P",
    "gn:feature_code":"PPL",
    "gn:name":"Hacienda Shurapamba",
    "gn:population":0,
    "gn:timezone":"America/Guayaquil",
    "iso:country":"EC",
    "wof:name":"Hacienda Shurapamba",
    "wof:placetype":"locality"
},
  "geometry": {"coordinates":[-79.19396999999999,-3.43531],"type":"Point"}
}