{
  "type": "Feature",
  "properties": {
    "gn:admin1_code":"2.0",
    "gn:admin2_code":"103.0",
    "gn:admin3_code":"10357.0",
    "gn:asciiname":"Jarata",
    "gn:country_code":"EC",
    "gn:dem":2731,
    "gn:feature_class":"P",
    "gn:feature_code":"PPL",
    "gn:name":"Jarata",
    "gn:population":0,
    "gn:timezone":"America/Guayaquil",
    "iso:country":"EC",
    "wof:name":"Jarata",
    "wof:placetype":"locality"
},
  "geometry": {"coordinates":[-78.81667,-2.95],"type":"Point"}
}