{
  "type": "Feature",
  "properties": {
    "iso:country":"EC",
    "name:ceb_x_preferred":[
        "P\u00edllaro"
    ],
    "name:fas_x_preferred":[
        "\u067e\u06cc\u0627\u0631\u0648"
    ],
    "name:ind_x_preferred":[
        "Pillaro"
    ],
    "name:pol_x_preferred":[
        "P\u00edllaro"
    ],
    "name:que_x_preferred":[
        "Pillaru"
    ],
    "name:spa_x_preferred":[
        "P\u00edllaro"
    ],
    "name:swe_x_preferred":[
        "P\u00edllaro"
    ],
    "qs:gn_pop":0,
    "qs:name":"Pillaro",
    "qs:name_adm0":"Ecuador",
    "qs:name_adm1":"Tungurahua",
    "qs:photos":5,
    "qs:photos_1k":1,
    "qs:photos_9k":1,
    "qs:photos_9r":3,
    "qs:photos_all":119,
    "qs:photos_sr":1,
    "qs:placetype":"LocalAdmin",
    "qs:pop_sr":"0",
    "qs:woe_adm0":23424801,
    "wof:name":"Pillaro",
    "wof:placetype":"localadmin"
},
  "geometry": {"coordinates":[-78.544006,-1.172708],"type":"Point"}
}