{
  "type": "Feature",
  "properties": {
    "gn:admin1_code":"4.0",
    "gn:admin2_code":"301.0",
    "gn:admin3_code":"30158.0",
    "gn:asciiname":"Loyola",
    "gn:country_code":"EC",
    "gn:dem":2504,
    "gn:feature_class":"P",
    "gn:feature_code":"PPL",
    "gn:name":"Loyola",
    "gn:population":0,
    "gn:timezone":"America/Guayaquil",
    "iso:country":"EC",
    "wof:name":"Loyola",
    "wof:placetype":"locality"
},
  "geometry": {"coordinates":[-78.85304000000002,-2.79145],"type":"Point"}
}