{
  "type": "Feature",
  "properties": {
    "gn:admin1_code":"2.0",
    "gn:admin2_code":"109.0",
    "gn:admin3_code":"10950.0",
    "gn:asciiname":"Rosas",
    "gn:country_code":"EC",
    "gn:dem":2990,
    "gn:feature_class":"P",
    "gn:feature_code":"PPL",
    "gn:name":"Rosas",
    "gn:population":0,
    "gn:timezone":"America/Guayaquil",
    "iso:country":"EC",
    "name:cat_x_preferred":[
        "Rosas"
    ],
    "name:ceb_x_preferred":[
        "Rosas"
    ],
    "name:deu_x_preferred":[
        "Rosas"
    ],
    "name:fin_x_preferred":[
        "Rosas"
    ],
    "name:fra_x_preferred":[
        "Rosas"
    ],
    "name:ita_x_preferred":[
        "Rosas"
    ],
    "name:nld_x_preferred":[
        "Rosas"
    ],
    "name:rus_x_preferred":[
        "\u0420\u043e\u0441\u0430\u0441"
    ],
    "name:spa_x_preferred":[
        "Rosas"
    ],
    "name:srp_x_preferred":[
        "\u0420\u043e\u0441\u0430\u0441"
    ],
    "name:swe_x_preferred":[
        "Rosas"
    ],
    "name:tgl_x_preferred":[
        "Rosas"
    ],
    "name:vie_x_preferred":[
        "Rosas"
    ],
    "wof:name":"Rosas",
    "wof:placetype":"locality"
},
  "geometry": {"coordinates":[-78.76666999999998,-3.08333],"type":"Point"}
}