{
  "type": "Feature",
  "properties": {
    "gn:admin1_code":"2.0",
    "gn:admin2_code":"115.0",
    "gn:admin3_code":"11551.0",
    "gn:asciiname":"Tucos",
    "gn:cc2":"EC",
    "gn:country_code":"EC",
    "gn:dem":2393,
    "gn:feature_class":"P",
    "gn:feature_code":"PPL",
    "gn:name":"Tucos",
    "gn:population":0,
    "gn:timezone":"America/Guayaquil",
    "iso:country":"EC",
    "wof:name":"Tucos",
    "wof:placetype":"locality"
},
  "geometry": {"coordinates":[-79.48333000000002,-2.95],"type":"Point"}
}