{
  "type": "Feature",
  "properties": {
    "gn:admin1_code":"19.0",
    "gn:admin2_code":"1808.0",
    "gn:admin3_code":"180854.0",
    "gn:asciiname":"Hacienda Saquitusa",
    "gn:cc2":"EC",
    "gn:country_code":"EC",
    "gn:dem":2823,
    "gn:feature_class":"P",
    "gn:feature_code":"PPL",
    "gn:name":"Hacienda Saquitusa",
    "gn:population":0,
    "gn:timezone":"America/Guayaquil",
    "iso:country":"EC",
    "wof:name":"Hacienda Saquitusa",
    "wof:placetype":"locality"
},
  "geometry": {"coordinates":[-78.55,-1.15],"type":"Point"}
}