{
  "type": "Feature",
  "properties": {
    "gn:admin1_code":"8.0",
    "gn:admin2_code":"713.0",
    "gn:admin3_code":"71351.0",
    "gn:asciiname":"Tunuyunga",
    "gn:country_code":"EC",
    "gn:dem":803,
    "gn:feature_class":"P",
    "gn:feature_code":"PPL",
    "gn:name":"Tunuyunga",
    "gn:population":0,
    "gn:timezone":"America/Guayaquil",
    "iso:country":"EC",
    "wof:name":"Tunuyunga",
    "wof:placetype":"locality"
},
  "geometry": {"coordinates":[-79.55587,-3.35326],"type":"Point"}
}