{
  "type": "Feature",
  "properties": {
    "gn:admin1_code":"13.0",
    "gn:admin2_code":"1208.0",
    "gn:admin3_code":"120850.0",
    "gn:asciiname":"Bombon",
    "gn:country_code":"EC",
    "gn:dem":24,
    "gn:feature_class":"P",
    "gn:feature_code":"PPL",
    "gn:name":"Bomb\u00f3n",
    "gn:population":0,
    "gn:timezone":"America/Guayaquil",
    "iso:country":"EC",
    "name:ceb_x_preferred":[
        "Bombon"
    ],
    "name:deu_x_preferred":[
        "Bombon"
    ],
    "name:fra_x_preferred":[
        "Bombon"
    ],
    "name:ita_x_preferred":[
        "Bombon"
    ],
    "name:jpn_x_preferred":[
        "\u30dc\u30f3\u30dc\u30f3"
    ],
    "name:nld_x_preferred":[
        "Bombon"
    ],
    "name:por_x_preferred":[
        "Bombon"
    ],
    "name:srp_x_preferred":[
        "\u0411\u043e\u043c\u0431\u043e\u043d"
    ],
    "name:war_x_preferred":[
        "Bombon"
    ],
    "wof:name":"Bombon",
    "wof:placetype":"locality"
},
  "geometry": {"coordinates":[-79.78333000000001,-1.48333],"type":"Point"}
}