{
  "type": "Feature",
  "properties": {
    "gn:admin1_code":"2.0",
    "gn:admin2_code":"101.0",
    "gn:admin3_code":"10152.0",
    "gn:asciiname":"Hacienda Rafael Guaico",
    "gn:cc2":"EC",
    "gn:country_code":"EC",
    "gn:dem":2964,
    "gn:feature_class":"P",
    "gn:feature_code":"PPL",
    "gn:name":"Hacienda Rafael Guaico",
    "gn:population":0,
    "gn:timezone":"America/Guayaquil",
    "iso:country":"EC",
    "wof:name":"Hacienda Rafael Guaico",
    "wof:placetype":"locality"
},
  "geometry": {"coordinates":[-79.01666999999998,-3.05],"type":"Point"}
}