{
  "type": "Feature",
  "properties": {
    "gn:admin1_code":"18.0",
    "gn:admin2_code":"1701.0",
    "gn:admin3_code":"170152.0",
    "gn:asciiname":"Hacienda Tena Grande",
    "gn:country_code":"EC",
    "gn:dem":2520,
    "gn:feature_class":"P",
    "gn:feature_code":"PPL",
    "gn:name":"Hacienda Tena Grande",
    "gn:population":0,
    "gn:timezone":"America/Guayaquil",
    "iso:country":"EC",
    "wof:name":"Hacienda Tena Grande",
    "wof:placetype":"locality"
},
  "geometry": {"coordinates":[-78.48398,-0.32701],"type":"Point"}
}