{
  "type": "Feature",
  "properties": {
    "gn:admin1_code":"20.0",
    "gn:admin2_code":"1908.0",
    "gn:admin3_code":"190851.0",
    "gn:asciiname":"Loyola",
    "gn:country_code":"EC",
    "gn:dem":1514,
    "gn:feature_class":"P",
    "gn:feature_code":"PPL",
    "gn:name":"Loyola",
    "gn:population":0,
    "gn:timezone":"America/Guayaquil",
    "iso:country":"EC",
    "name:ceb_x_preferred":[
        "Loyola"
    ],
    "name:deu_x_preferred":[
        "Loyola"
    ],
    "name:eus_x_preferred":[
        "Loiola"
    ],
    "name:fra_x_preferred":[
        "Loyola"
    ],
    "name:hun_x_preferred":[
        "Loyola"
    ],
    "name:nld_x_preferred":[
        "Loyola"
    ],
    "name:pol_x_preferred":[
        "Loyola"
    ],
    "name:por_x_preferred":[
        "Loyola"
    ],
    "name:rus_x_preferred":[
        "\u041b\u043e\u0439\u043e\u043b\u0430"
    ],
    "name:spa_x_preferred":[
        "Loyola"
    ],
    "name:swe_x_preferred":[
        "Loyola"
    ],
    "wof:name":"Loyola",
    "wof:placetype":"locality"
},
  "geometry": {"coordinates":[-79.01146999999997,-4.52087],"type":"Point"}
}