{
  "type": "Feature",
  "properties": {
    "gn:admin1_code":"14.0",
    "gn:admin2_code":"1317.0",
    "gn:admin3_code":"131752.0",
    "gn:asciiname":"Diez de Agosto",
    "gn:country_code":"EC",
    "gn:dem":103,
    "gn:feature_class":"P",
    "gn:feature_code":"PPL",
    "gn:name":"Diez de Agosto",
    "gn:population":0,
    "gn:timezone":"America/Guayaquil",
    "iso:country":"EC",
    "wof:name":"Diez de Agosto",
    "wof:placetype":"locality"
},
  "geometry": {"coordinates":[-80.07241999999999,-0.14476],"type":"Point"}
}