{
  "type": "Feature",
  "properties": {
    "gn:admin1_code":"2.0",
    "gn:admin2_code":"104.0",
    "gn:admin3_code":"10452.0",
    "gn:asciiname":"Shota",
    "gn:country_code":"EC",
    "gn:dem":2029,
    "gn:feature_class":"P",
    "gn:feature_code":"PPL",
    "gn:name":"Shota",
    "gn:population":0,
    "gn:timezone":"America/Guayaquil",
    "iso:country":"EC",
    "name:ita_x_preferred":[
        "Shota"
    ],
    "name:kat_x_preferred":[
        "\u10e8\u10dd\u10d7\u10d0"
    ],
    "wof:name":"Shota",
    "wof:placetype":"locality"
},
  "geometry": {"coordinates":[-79.23333000000002,-3.31667],"type":"Point"}
}