{
  "type": "Feature",
  "properties": {
    "iso:country":"EC",
    "name:ceb_x_preferred":[
        "Guayas"
    ],
    "name:deu_x_preferred":[
        "Guayas"
    ],
    "name:epo_x_preferred":[
        "Guayas"
    ],
    "name:fra_x_preferred":[
        "Guayas"
    ],
    "name:nld_x_preferred":[
        "Guayas"
    ],
    "name:spa_x_preferred":[
        "Guayas"
    ],
    "name:und_x_variant":[
        "Empalme"
    ],
    "qs:gn_country":"EC",
    "qs:gn_fcode":"PPL",
    "qs:gn_pop":48754,
    "qs:name":"Guayas",
    "qs:name_adm0":"Ecuador",
    "qs:name_adm1":"Guayas",
    "qs:photos":0,
    "qs:photos_1k":0,
    "qs:photos_9k":0,
    "qs:photos_9r":0,
    "qs:photos_all":0,
    "qs:photos_sr":0,
    "qs:placetype":"Town",
    "qs:pop_sr":"7",
    "qs:woe_adm0":23424801,
    "wd:wordcount":19,
    "wof:name":"Guayas",
    "wof:placetype":"locality",
    "wof:population":48754
},
  "geometry": {"coordinates":[-79.63836999999999,-1.04376],"type":"Point"}
}