{
  "type": "Feature",
  "properties": {
    "gn:admin1_code":"12.0",
    "gn:admin2_code":"1109.0",
    "gn:admin3_code":"110952.0",
    "gn:asciiname":"Masaconsa",
    "gn:country_code":"EC",
    "gn:dem":1649,
    "gn:feature_class":"P",
    "gn:feature_code":"PPL",
    "gn:name":"Masaconsa",
    "gn:population":0,
    "gn:timezone":"America/Guayaquil",
    "iso:country":"EC",
    "wof:name":"Masaconsa",
    "wof:placetype":"locality"
},
  "geometry": {"coordinates":[-79.96666999999999,-4.05],"type":"Point"}
}