{
  "type": "Feature",
  "properties": {
    "gn:admin1_code":"8.0",
    "gn:admin2_code":"710.0",
    "gn:admin3_code":"71056.0",
    "gn:asciiname":"Yucas",
    "gn:country_code":"EC",
    "gn:dem":154,
    "gn:feature_class":"P",
    "gn:feature_code":"PPL",
    "gn:name":"Yucas",
    "gn:population":0,
    "gn:timezone":"America/Guayaquil",
    "iso:country":"EC",
    "wof:name":"Yucas",
    "wof:placetype":"locality"
},
  "geometry": {"coordinates":[-79.88679,-3.64544],"type":"Point"}
}