{
  "type": "Feature",
  "properties": {
    "gn:admin1_code":"11.0",
    "gn:asciiname":"Hacienda San Nicolas",
    "gn:country_code":"EC",
    "gn:dem":2096,
    "gn:feature_class":"P",
    "gn:feature_code":"PPL",
    "gn:name":"Hacienda San Nicol\u00e1s",
    "gn:population":0,
    "gn:timezone":"America/Guayaquil",
    "iso:country":"EC",
    "wof:name":"Hacienda San Nicolas",
    "wof:placetype":"locality"
},
  "geometry": {"coordinates":[-78.0373,0.53464],"type":"Point"}
}