{
  "type": "Feature",
  "properties": {
    "gn:admin1_code":"17.0",
    "gn:admin2_code":"1604.0",
    "gn:admin3_code":"160451.0",
    "gn:asciiname":"Bombonaqui",
    "gn:country_code":"EC",
    "gn:dem":244,
    "gn:feature_class":"P",
    "gn:feature_code":"PPL",
    "gn:name":"Bombonaqui",
    "gn:population":0,
    "gn:timezone":"America/Guayaquil",
    "iso:country":"EC",
    "wof:name":"Bombonaqui",
    "wof:placetype":"locality"
},
  "geometry": {"coordinates":[-76.57405,-1.49072],"type":"Point"}
}