{
  "type": "Feature",
  "properties": {
    "gn:admin1_code":"7.0",
    "gn:admin2_code":"507.0",
    "gn:admin3_code":"50750.0",
    "gn:asciiname":"Lahuan",
    "gn:country_code":"EC",
    "gn:dem":1852,
    "gn:feature_class":"P",
    "gn:feature_code":"PPL",
    "gn:name":"Lahu\u00e1n",
    "gn:population":0,
    "gn:timezone":"America/Guayaquil",
    "iso:country":"EC",
    "wof:name":"Lahuan",
    "wof:placetype":"locality"
},
  "geometry": {"coordinates":[-78.91121,-0.5942],"type":"Point"}
}