{
  "type": "Feature",
  "properties": {
    "gn:admin1_code":"10.0",
    "gn:admin2_code":"906.0",
    "gn:admin3_code":"90650.0",
    "gn:asciiname":"Las Iguanas",
    "gn:country_code":"EC",
    "gn:dem":17,
    "gn:feature_class":"P",
    "gn:feature_code":"PPL",
    "gn:name":"Las Iguanas",
    "gn:population":0,
    "gn:timezone":"America/Guayaquil",
    "iso:country":"EC",
    "wof:name":"Las Iguanas",
    "wof:placetype":"locality"
},
  "geometry": {"coordinates":[-79.95,-1.88333],"type":"Point"}
}