{
  "type": "Feature",
  "properties": {
    "gn:admin1_code":"7.0",
    "gn:admin2_code":"505.0",
    "gn:admin3_code":"50555.0",
    "gn:asciiname":"Antonio Jose Holguin",
    "gn:country_code":"EC",
    "gn:dem":2694,
    "gn:feature_class":"P",
    "gn:feature_code":"PPL",
    "gn:name":"Antonio Jos\u00e9 Holgu\u00edn",
    "gn:population":0,
    "gn:timezone":"America/Guayaquil",
    "iso:country":"EC",
    "wof:name":"Antonio Jose Holguin",
    "wof:placetype":"locality"
},
  "geometry": {"coordinates":[-78.58333,-1.11667],"type":"Point"}
}