{
  "type": "Feature",
  "properties": {
    "gn:admin1_code":"14.0",
    "gn:admin2_code":"1301.0",
    "gn:admin3_code":"130156.0",
    "gn:asciiname":"San Placido",
    "gn:country_code":"EC",
    "gn:dem":78,
    "gn:feature_class":"P",
    "gn:feature_code":"PPL",
    "gn:name":"San Pl\u00e1cido",
    "gn:population":0,
    "gn:timezone":"America/Guayaquil",
    "iso:country":"EC",
    "wof:name":"San Placido",
    "wof:placetype":"locality"
},
  "geometry": {"coordinates":[-80.24495999999998,-1.06161],"type":"Point"}
}