{
  "type": "Feature",
  "properties": {
    "gn:admin1_code":"19.0",
    "gn:admin2_code":"1808.0",
    "gn:admin3_code":"180850.0",
    "gn:asciiname":"Hacienda La Elcira",
    "gn:country_code":"EC",
    "gn:dem":3496,
    "gn:feature_class":"P",
    "gn:feature_code":"PPL",
    "gn:name":"Hacienda La Elcira",
    "gn:population":0,
    "gn:timezone":"America/Guayaquil",
    "iso:country":"EC",
    "wof:name":"Hacienda La Elcira",
    "wof:placetype":"locality"
},
  "geometry": {"coordinates":[-78.48475000000001,-1.16001],"type":"Point"}
}