{
  "type": "Feature",
  "properties": {
    "gn:admin1_code":"19.0",
    "gn:admin2_code":"1805.0",
    "gn:admin3_code":"180552.0",
    "gn:asciiname":"Los Andes",
    "gn:country_code":"EC",
    "gn:dem":2335,
    "gn:feature_class":"P",
    "gn:feature_code":"PPL",
    "gn:name":"Los Andes",
    "gn:population":0,
    "gn:timezone":"America/Guayaquil",
    "iso:country":"EC",
    "wof:name":"Los Andes",
    "wof:placetype":"locality"
},
  "geometry": {"coordinates":[-78.51424,-1.25141],"type":"Point"}
}