{
  "type": "Feature",
  "properties": {
    "gn:admin1_code":"2.0",
    "gn:admin2_code":"103.0",
    "gn:admin3_code":"10353.0",
    "gn:asciiname":"Chicticay",
    "gn:country_code":"EC",
    "gn:dem":2585,
    "gn:feature_class":"P",
    "gn:feature_code":"PPL",
    "gn:name":"Chicticay",
    "gn:population":0,
    "gn:timezone":"America/Guayaquil",
    "iso:country":"EC",
    "wof:name":"Chicticay",
    "wof:placetype":"locality"
},
  "geometry": {"coordinates":[-78.83333,-2.86667],"type":"Point"}
}