{
  "type": "Feature",
  "properties": {
    "gn:admin1_code":"10.0",
    "gn:admin2_code":"916.0",
    "gn:admin3_code":"91651.0",
    "gn:asciiname":"Capone",
    "gn:country_code":"EC",
    "gn:dem":7,
    "gn:feature_class":"P",
    "gn:feature_code":"PPL",
    "gn:name":"Capone",
    "gn:population":0,
    "gn:timezone":"America/Guayaquil",
    "iso:country":"EC",
    "wof:name":"Capone",
    "wof:placetype":"locality"
},
  "geometry": {"coordinates":[-79.78333000000001,-1.98333],"type":"Point"}
}