{
  "type": "Feature",
  "properties": {
    "gn:admin1_code":"6.0",
    "gn:admin2_code":"603.0",
    "gn:admin3_code":"60353.0",
    "gn:asciiname":"Juan de Velasco",
    "gn:country_code":"EC",
    "gn:dem":3458,
    "gn:feature_class":"P",
    "gn:feature_code":"PPL",
    "gn:name":"Juan de Velasco",
    "gn:population":0,
    "gn:timezone":"America/Guayaquil",
    "iso:country":"EC",
    "name:ara_x_preferred":[
        "\u062e\u0648\u0627\u0646 \u062f\u064a \u0628\u064a\u0644\u0627\u0633\u0643\u0648"
    ],
    "wof:name":"Juan de Velasco",
    "wof:placetype":"locality"
},
  "geometry": {"coordinates":[-78.87340999999998,-1.82733],"type":"Point"}
}