{
  "type": "Feature",
  "properties": {
    "gn:admin1_code":"13.0",
    "gn:admin2_code":"1208.0",
    "gn:admin3_code":"120850.0",
    "gn:asciiname":"La Virginia",
    "gn:country_code":"EC",
    "gn:dem":35,
    "gn:feature_class":"P",
    "gn:feature_code":"PPL",
    "gn:name":"La Virginia",
    "gn:population":0,
    "gn:timezone":"America/Guayaquil",
    "iso:country":"EC",
    "name:cat_x_preferred":[
        "La Virginia"
    ],
    "name:ceb_x_preferred":[
        "La Virginia"
    ],
    "name:deu_x_preferred":[
        "La Virginia"
    ],
    "name:fas_x_preferred":[
        "\u0644\u0627 \u0648\u06cc\u0631\u062e\u06cc\u0646\u06cc\u0627"
    ],
    "name:fra_x_preferred":[
        "La Virginia"
    ],
    "name:ita_x_preferred":[
        "La Virginia"
    ],
    "name:kat_x_preferred":[
        "\u10da\u10d0-\u10d5\u10d8\u10e0\u10ee\u10d8\u10dc\u10d8\u10d0"
    ],
    "name:lit_x_preferred":[
        "La Virchinija"
    ],
    "name:msa_x_preferred":[
        "La Virginia"
    ],
    "name:nld_x_preferred":[
        "La Virginia"
    ],
    "name:spa_x_preferred":[
        "La Virginia"
    ],
    "name:swe_x_preferred":[
        "La Virginia"
    ],
    "name:tgl_x_preferred":[
        "La Virginia"
    ],
    "name:urd_x_preferred":[
        "\u0644\u0627 \u0648\u0631\u062c\u06cc\u0646\u06cc\u0627"
    ],
    "name:vie_x_preferred":[
        "La Virginia"
    ],
    "name:war_x_preferred":[
        "La Virginia"
    ],
    "name:zho_x_preferred":[
        "\u62c9\u6bd4\u5e0c\u5c3c\u4e9e"
    ],
    "wof:name":"La Virginia",
    "wof:placetype":"locality"
},
  "geometry": {"coordinates":[-79.58333,-1.36667],"type":"Point"}
}