{
  "type": "Feature",
  "properties": {
    "gn:admin1_code":"13.0",
    "gn:admin2_code":"1208.0",
    "gn:admin3_code":"120850.0",
    "gn:asciiname":"La Virginia",
    "gn:country_code":"EC",
    "gn:dem":35,
    "gn:feature_class":"P",
    "gn:feature_code":"PPL",
    "gn:name":"La Virginia",
    "gn:population":0,
    "gn:timezone":"America/Guayaquil",
    "iso:country":"EC",
    "wof:name":"La Virginia",
    "wof:placetype":"locality"
},
  "geometry": {"coordinates":[-79.58333,-1.36667],"type":"Point"}
}