{
  "type": "Feature",
  "properties": {
    "gn:admin1_code":"12.0",
    "gn:admin2_code":"1116.0",
    "gn:admin3_code":"111651.0",
    "gn:asciiname":"Veracruz",
    "gn:country_code":"EC",
    "gn:dem":1930,
    "gn:feature_class":"P",
    "gn:feature_code":"PPL",
    "gn:name":"Veracruz",
    "gn:population":0,
    "gn:timezone":"America/Guayaquil",
    "iso:country":"EC",
    "wof:name":"Veracruz",
    "wof:placetype":"locality"
},
  "geometry": {"coordinates":[-79.56667,-3.96667],"type":"Point"}
}