{
  "type": "Feature",
  "properties": {
    "gn:admin1_code":"4.0",
    "gn:admin2_code":"303.0",
    "gn:admin3_code":"30355.0",
    "gn:asciiname":"San Jose",
    "gn:country_code":"EC",
    "gn:dem":3083,
    "gn:feature_class":"P",
    "gn:feature_code":"PPL",
    "gn:name":"San Jos\u00e9",
    "gn:population":0,
    "gn:timezone":"America/Guayaquil",
    "iso:country":"EC",
    "wof:name":"San Jose",
    "wof:placetype":"locality"
},
  "geometry": {"coordinates":[-78.90000000000001,-2.55],"type":"Point"}
}