{
  "type": "Feature",
  "properties": {
    "gn:admin1_code":"8.0",
    "gn:admin2_code":"702.0",
    "gn:admin3_code":"70255.0",
    "gn:asciiname":"Guabillo",
    "gn:country_code":"EC",
    "gn:dem":39,
    "gn:feature_class":"P",
    "gn:feature_code":"PPL",
    "gn:name":"Guabillo",
    "gn:population":0,
    "gn:timezone":"America/Guayaquil",
    "iso:country":"EC",
    "wof:name":"Guabillo",
    "wof:placetype":"locality"
},
  "geometry": {"coordinates":[-80.18705,-3.59537],"type":"Point"}
}