{
  "type": "Feature",
  "properties": {
    "gn:admin1_code":"12.0",
    "gn:admin2_code":"1103.0",
    "gn:admin3_code":"110353.0",
    "gn:asciiname":"San Pedro de la Bendita",
    "gn:country_code":"EC",
    "gn:dem":1731,
    "gn:feature_class":"P",
    "gn:feature_code":"PPL",
    "gn:name":"San Pedro de la Bendita",
    "gn:population":0,
    "gn:timezone":"America/Guayaquil",
    "iso:country":"EC",
    "wof:name":"San Pedro de la Bendita",
    "wof:placetype":"locality"
},
  "geometry": {"coordinates":[-79.43566,-3.94157],"type":"Point"}
}