{
  "type": "Feature",
  "properties": {
    "gn:admin1_code":"13.0",
    "gn:admin2_code":"1208.0",
    "gn:admin3_code":"120850.0",
    "gn:asciiname":"Rincon de Juana",
    "gn:country_code":"EC",
    "gn:dem":19,
    "gn:feature_class":"P",
    "gn:feature_code":"PPL",
    "gn:name":"Rinc\u00f3n de Juana",
    "gn:population":0,
    "gn:timezone":"America/Guayaquil",
    "iso:country":"EC",
    "wof:name":"Rincon de Juana",
    "wof:placetype":"locality"
},
  "geometry": {"coordinates":[-79.86685,-1.52786],"type":"Point"}
}