{
  "type": "Feature",
  "properties": {
    "gn:admin1_code":"8.0",
    "gn:admin2_code":"709.0",
    "gn:admin3_code":"70950.0",
    "gn:asciiname":"Juana de Arco",
    "gn:country_code":"EC",
    "gn:dem":25,
    "gn:feature_class":"P",
    "gn:feature_code":"PPL",
    "gn:name":"Juana de Arco",
    "gn:population":0,
    "gn:timezone":"America/Guayaquil",
    "iso:country":"EC",
    "wof:name":"Juana de Arco",
    "wof:placetype":"locality"
},
  "geometry": {"coordinates":[-79.82811,-3.32516],"type":"Point"}
}