{
  "type": "Feature",
  "properties": {
    "gn:admin1_code":"10.0",
    "gn:asciiname":"Paila",
    "gn:country_code":"EC",
    "gn:dem":10,
    "gn:feature_class":"P",
    "gn:feature_code":"PPL",
    "gn:name":"Paila",
    "gn:population":0,
    "gn:timezone":"America/Guayaquil",
    "iso:country":"EC",
    "name:ara_x_preferred":[
        "\u0628\u0627\u064a\u0644\u0627"
    ],
    "name:jpn_x_preferred":[
        "\u30d1\u30a4\u30e9"
    ],
    "name:spa_x_preferred":[
        "Paila"
    ],
    "wof:name":"Paila",
    "wof:placetype":"locality"
},
  "geometry": {"coordinates":[-79.74623000000003,-1.73822],"type":"Point"}
}