{
  "type": "Feature",
  "properties": {
    "gn:admin1_code":"10.0",
    "gn:asciiname":"Paila",
    "gn:country_code":"EC",
    "gn:dem":10,
    "gn:feature_class":"P",
    "gn:feature_code":"PPL",
    "gn:name":"Paila",
    "gn:population":0,
    "gn:timezone":"America/Guayaquil",
    "iso:country":"EC",
    "wof:name":"Paila",
    "wof:placetype":"locality"
},
  "geometry": {"coordinates":[-79.74623000000003,-1.73822],"type":"Point"}
}