{
  "type": "Feature",
  "properties": {
    "gn:admin1_code":"12.0",
    "gn:admin2_code":"1109.0",
    "gn:admin3_code":"110954.0",
    "gn:asciiname":"Lauro Guerrero",
    "gn:country_code":"EC",
    "gn:dem":1930,
    "gn:feature_class":"P",
    "gn:feature_code":"PPL",
    "gn:name":"Lauro Guerrero",
    "gn:population":0,
    "gn:timezone":"America/Guayaquil",
    "iso:country":"EC",
    "wof:name":"Lauro Guerrero",
    "wof:placetype":"locality"
},
  "geometry": {"coordinates":[-79.76099000000001,-3.96652],"type":"Point"}
}