{
  "type": "Feature",
  "properties": {
    "gn:admin1_code":"24.0",
    "gn:admin2_code":"2202.0",
    "gn:admin3_code":"220251.0",
    "gn:asciiname":"Capitan Augosto Rivadeneira",
    "gn:cc2":"EC",
    "gn:country_code":"EC",
    "gn:dem":224,
    "gn:feature_class":"P",
    "gn:feature_code":"PPL",
    "gn:name":"Capit\u00e1n Augosto Rivadeneira",
    "gn:population":0,
    "gn:timezone":"America/Guayaquil",
    "iso:country":"EC",
    "wof:name":"Capitan Augosto Rivadeneira",
    "wof:placetype":"locality"
},
  "geometry": {"coordinates":[-75.88333,-0.61667],"type":"Point"}
}