{
  "type": "Feature",
  "properties": {
    "gn:admin1_code":"26.0",
    "gn:admin2_code":"2301.0",
    "gn:admin3_code":"230153.0",
    "gn:asciiname":"Treinta de Noviembre",
    "gn:country_code":"EC",
    "gn:dem":250,
    "gn:feature_class":"P",
    "gn:feature_code":"PPL",
    "gn:name":"Treinta de Noviembre",
    "gn:population":0,
    "gn:timezone":"America/Guayaquil",
    "iso:country":"EC",
    "wof:name":"Treinta de Noviembre",
    "wof:placetype":"locality"
},
  "geometry": {"coordinates":[-79.34618,-0.41267],"type":"Point"}
}