{
  "type": "Feature",
  "properties": {
    "gn:admin1_code":"10.0",
    "gn:admin2_code":"918.0",
    "gn:admin3_code":"91850.0",
    "gn:asciiname":"Estero Lagarto",
    "gn:country_code":"EC",
    "gn:dem":11,
    "gn:feature_class":"P",
    "gn:feature_code":"PPL",
    "gn:name":"Estero Lagarto",
    "gn:population":0,
    "gn:timezone":"America/Guayaquil",
    "iso:country":"EC",
    "wof:name":"Estero Lagarto",
    "wof:placetype":"locality"
},
  "geometry": {"coordinates":[-79.91667,-1.73333],"type":"Point"}
}