{
  "type": "Feature",
  "properties": {
    "gn:admin1_code":"4.0",
    "gn:admin2_code":"302.0",
    "gn:admin3_code":"30254.0",
    "gn:asciiname":"Carmela",
    "gn:country_code":"EC",
    "gn:dem":2980,
    "gn:feature_class":"P",
    "gn:feature_code":"PPL",
    "gn:name":"Carmela",
    "gn:population":0,
    "gn:timezone":"America/Guayaquil",
    "iso:country":"EC",
    "name:hun_x_preferred":[
        "Karm\u00e9la"
    ],
    "name:ita_x_preferred":[
        "Carmela"
    ],
    "name:slv_x_preferred":[
        "Karm\u00e9la"
    ],
    "wof:name":"Carmela",
    "wof:placetype":"locality"
},
  "geometry": {"coordinates":[-78.93576,-2.67689],"type":"Point"}
}