{
  "type": "Feature",
  "properties": {
    "gn:admin1_code":"19.0",
    "gn:admin2_code":"1807.0",
    "gn:admin3_code":"180758.0",
    "gn:asciiname":"Guangalo",
    "gn:country_code":"EC",
    "gn:dem":2733,
    "gn:feature_class":"P",
    "gn:feature_code":"PPL",
    "gn:name":"Guangalo",
    "gn:population":0,
    "gn:timezone":"America/Guayaquil",
    "iso:country":"EC",
    "wof:name":"Guangalo",
    "wof:placetype":"locality"
},
  "geometry": {"coordinates":[-78.56667,-1.31667],"type":"Point"}
}