{
  "type": "Feature",
  "properties": {
    "gn:admin1_code":"15.0",
    "gn:admin2_code":"1409.0",
    "gn:admin3_code":"140954.0",
    "gn:asciiname":"Mashumarentza Civil",
    "gn:country_code":"EC",
    "gn:dem":261,
    "gn:feature_class":"P",
    "gn:feature_code":"PPL",
    "gn:name":"Mashumarentza Civil",
    "gn:population":0,
    "gn:timezone":"America/Guayaquil",
    "iso:country":"EC",
    "wof:name":"Mashumarentza Civil",
    "wof:placetype":"locality"
},
  "geometry": {"coordinates":[-77.22778000000002,-2.75833],"type":"Point"}
}