{
  "type": "Feature",
  "properties": {
    "gn:admin1_code":"2.0",
    "gn:admin2_code":"102.0",
    "gn:admin3_code":"10250.0",
    "gn:asciiname":"Pilcapamba",
    "gn:country_code":"EC",
    "gn:dem":3211,
    "gn:feature_class":"P",
    "gn:feature_code":"PPL",
    "gn:name":"Pilcapamba",
    "gn:population":0,
    "gn:timezone":"America/Guayaquil",
    "iso:country":"EC",
    "wof:name":"Pilcapamba",
    "wof:placetype":"locality"
},
  "geometry": {"coordinates":[-79.06667,-3.23333],"type":"Point"}
}