{
  "type": "Feature",
  "properties": {
    "gn:admin1_code":"2.0",
    "gn:admin2_code":"110.0",
    "gn:admin3_code":"11050.0",
    "gn:asciiname":"Baejon",
    "gn:country_code":"EC",
    "gn:dem":2316,
    "gn:feature_class":"P",
    "gn:feature_code":"PPL",
    "gn:name":"Baej\u00f3n",
    "gn:population":0,
    "gn:timezone":"America/Guayaquil",
    "iso:country":"EC",
    "wof:name":"Baejon",
    "wof:placetype":"locality"
},
  "geometry": {"coordinates":[-79.10991,-3.44265],"type":"Point"}
}