{
  "type": "Feature",
  "properties": {
    "gn:admin1_code":"2.0",
    "gn:admin2_code":"104.0",
    "gn:admin3_code":"10450.0",
    "gn:asciiname":"Rosas",
    "gn:country_code":"EC",
    "gn:dem":3092,
    "gn:feature_class":"P",
    "gn:feature_code":"PPL",
    "gn:name":"Rosas",
    "gn:population":0,
    "gn:timezone":"America/Guayaquil",
    "iso:country":"EC",
    "wof:name":"Rosas",
    "wof:placetype":"locality"
},
  "geometry": {"coordinates":[-79.03333000000001,-3.25],"type":"Point"}
}