{
  "type": "Feature",
  "properties": {
    "gn:admin1_code":"18.0",
    "gn:admin2_code":"1702.0",
    "gn:admin3_code":"170253.0",
    "gn:asciiname":"Panecillo",
    "gn:cc2":"EC",
    "gn:country_code":"EC",
    "gn:dem":3250,
    "gn:feature_class":"P",
    "gn:feature_code":"PPL",
    "gn:name":"Panecillo",
    "gn:population":0,
    "gn:timezone":"America/Guayaquil",
    "iso:country":"EC",
    "wof:name":"Panecillo",
    "wof:placetype":"locality"
},
  "geometry": {"coordinates":[-78.05,0.13333],"type":"Point"}
}