{
  "type": "Feature",
  "properties": {
    "gn:admin1_code":"17.0",
    "gn:admin2_code":"1601.0",
    "gn:admin3_code":"160159.0",
    "gn:asciiname":"Guayusa",
    "gn:country_code":"EC",
    "gn:dem":231,
    "gn:feature_class":"P",
    "gn:feature_code":"PPL",
    "gn:name":"Guayusa",
    "gn:population":0,
    "gn:timezone":"America/Guayaquil",
    "iso:country":"EC",
    "wof:name":"Guayusa",
    "wof:placetype":"locality"
},
  "geometry": {"coordinates":[-76.31667,-1.85],"type":"Point"}
}