{
  "type": "Feature",
  "properties": {
    "gn:admin1_code":"26.0",
    "gn:admin2_code":"2301.0",
    "gn:admin3_code":"230153.0",
    "gn:asciiname":"Congona",
    "gn:country_code":"EC",
    "gn:dem":186,
    "gn:feature_class":"P",
    "gn:feature_code":"PPL",
    "gn:name":"Congona",
    "gn:population":0,
    "gn:timezone":"America/Guayaquil",
    "iso:country":"EC",
    "wof:name":"Congona",
    "wof:placetype":"locality"
},
  "geometry": {"coordinates":[-79.36924,-0.43858],"type":"Point"}
}