{
  "type": "Feature",
  "properties": {
    "gn:admin1_code":"9.0",
    "gn:admin2_code":"804.0",
    "gn:admin3_code":"80455.0",
    "gn:asciiname":"San Roque",
    "gn:country_code":"EC",
    "gn:dem":133,
    "gn:feature_class":"P",
    "gn:feature_code":"PPL",
    "gn:name":"San Roque",
    "gn:population":0,
    "gn:timezone":"America/Guayaquil",
    "iso:country":"EC",
    "wof:name":"San Roque",
    "wof:placetype":"locality"
},
  "geometry": {"coordinates":[-79.5359,0.14849],"type":"Point"}
}