{
  "type": "Feature",
  "properties": {
    "gn:admin1_code":"18.0",
    "gn:admin2_code":"1701.0",
    "gn:admin3_code":"170153.0",
    "gn:asciiname":"Mojanda Chico",
    "gn:country_code":"EC",
    "gn:dem":2531,
    "gn:feature_class":"P",
    "gn:feature_code":"PPL",
    "gn:name":"Mojanda Chico",
    "gn:population":0,
    "gn:timezone":"America/Guayaquil",
    "iso:country":"EC",
    "wof:name":"Mojanda Chico",
    "wof:placetype":"locality"
},
  "geometry": {"coordinates":[-78.33977,0.14303],"type":"Point"}
}