{
  "type": "Feature",
  "properties": {
    "gn:admin1_code":"5.0",
    "gn:admin2_code":"404.0",
    "gn:admin3_code":"40450.0",
    "gn:asciiname":"Hacienda El Hato",
    "gn:country_code":"EC",
    "gn:dem":2977,
    "gn:feature_class":"P",
    "gn:feature_code":"PPL",
    "gn:name":"Hacienda El Hato",
    "gn:population":0,
    "gn:timezone":"America/Guayaquil",
    "iso:country":"EC",
    "wof:name":"Hacienda El Hato",
    "wof:placetype":"locality"
},
  "geometry": {"coordinates":[-78.05225,0.58651],"type":"Point"}
}