{
  "type": "Feature",
  "properties": {
    "gn:admin1_code":"15.0",
    "gn:admin2_code":"1409.0",
    "gn:admin3_code":"140952.0",
    "gn:asciiname":"Ayuy",
    "gn:country_code":"EC",
    "gn:dem":569,
    "gn:feature_class":"P",
    "gn:feature_code":"PPL",
    "gn:name":"Ayuy",
    "gn:population":0,
    "gn:timezone":"America/Guayaquil",
    "iso:country":"EC",
    "wof:name":"Ayuy",
    "wof:placetype":"locality"
},
  "geometry": {"coordinates":[-77.56775999999998,-2.09215],"type":"Point"}
}