{
  "type": "Feature",
  "properties": {
    "gn:admin1_code":"18.0",
    "gn:admin2_code":"1703.0",
    "gn:admin3_code":"170352.0",
    "gn:asciiname":"Umbala",
    "gn:country_code":"EC",
    "gn:dem":3375,
    "gn:feature_class":"P",
    "gn:feature_code":"PPL",
    "gn:name":"Umbal\u00e1",
    "gn:population":0,
    "gn:timezone":"America/Guayaquil",
    "iso:country":"EC",
    "wof:name":"Umbala",
    "wof:placetype":"locality"
},
  "geometry": {"coordinates":[-78.62560000000001,-0.55713],"type":"Point"}
}