{
  "type": "Feature",
  "properties": {
    "gn:admin1_code":"2.0",
    "gn:asciiname":"Enramada",
    "gn:country_code":"EC",
    "gn:dem":746,
    "gn:feature_class":"P",
    "gn:feature_code":"PPL",
    "gn:name":"Enramada",
    "gn:population":0,
    "gn:timezone":"America/Guayaquil",
    "iso:country":"EC",
    "wof:name":"Enramada",
    "wof:placetype":"locality"
},
  "geometry": {"coordinates":[-79.66667,-3.26667],"type":"Point"}
}