{
  "type": "Feature",
  "properties": {
    "gn:admin1_code":"4.0",
    "gn:admin2_code":"301.0",
    "gn:admin3_code":"30150.0",
    "gn:asciiname":"Leguchupucun",
    "gn:country_code":"EC",
    "gn:dem":2893,
    "gn:feature_class":"P",
    "gn:feature_code":"PPL",
    "gn:name":"Leguchupucun",
    "gn:population":0,
    "gn:timezone":"America/Guayaquil",
    "iso:country":"EC",
    "wof:name":"Leguchupucun",
    "wof:placetype":"locality"
},
  "geometry": {"coordinates":[-78.81667,-2.71667],"type":"Point"}
}