{
  "type": "Feature",
  "properties": {
    "gn:admin1_code":"19.0",
    "gn:admin2_code":"1807.0",
    "gn:admin3_code":"180757.0",
    "gn:asciiname":"Hacienda La Merced",
    "gn:country_code":"EC",
    "gn:dem":2926,
    "gn:feature_class":"P",
    "gn:feature_code":"PPL",
    "gn:name":"Hacienda La Merced",
    "gn:population":0,
    "gn:timezone":"America/Guayaquil",
    "iso:country":"EC",
    "wof:name":"Hacienda La Merced",
    "wof:placetype":"locality"
},
  "geometry": {"coordinates":[-78.53793,-1.39851],"type":"Point"}
}