{
  "type": "Feature",
  "properties": {
    "gn:admin1_code":"4.0",
    "gn:asciiname":"Naranjapata",
    "gn:country_code":"EC",
    "gn:dem":577,
    "gn:feature_class":"P",
    "gn:feature_code":"PPL",
    "gn:name":"Naranjapata",
    "gn:population":0,
    "gn:timezone":"America/Guayaquil",
    "iso:country":"EC",
    "wof:name":"Naranjapata",
    "wof:placetype":"locality"
},
  "geometry": {"coordinates":[-79.08934000000001,-2.27885],"type":"Point"}
}