{
  "type": "Feature",
  "properties": {
    "iso:country":"EC",
    "qs:gn_pop":0,
    "qs:name":"Puerto Lopez",
    "qs:name_adm0":"Ecuador",
    "qs:name_adm1":"Manabi",
    "qs:photos":1,
    "qs:photos_1k":1,
    "qs:photos_9k":5,
    "qs:photos_9r":7,
    "qs:photos_all":1060,
    "qs:photos_sr":1,
    "qs:placetype":"LocalAdmin",
    "qs:pop_sr":"0",
    "qs:woe_adm0":23424801,
    "wof:name":"Puerto Lopez",
    "wof:placetype":"localadmin"
},
  "geometry": {"coordinates":[-80.81233899999999,-1.558493],"type":"Point"}
}