{
  "type": "Feature",
  "properties": {
    "gn:admin1_code":"7.0",
    "gn:admin2_code":"501.0",
    "gn:admin3_code":"50152.0",
    "gn:asciiname":"Hacienda Poalopos",
    "gn:country_code":"EC",
    "gn:dem":3172,
    "gn:feature_class":"P",
    "gn:feature_code":"PPL",
    "gn:name":"Hacienda Poalopos",
    "gn:population":0,
    "gn:timezone":"America/Guayaquil",
    "iso:country":"EC",
    "wof:name":"Hacienda Poalopos",
    "wof:placetype":"locality"
},
  "geometry": {"coordinates":[-78.5462,-0.94968],"type":"Point"}
}