{
  "type": "Feature",
  "properties": {
    "gn:admin1_code":"18.0",
    "gn:admin2_code":"1701.0",
    "gn:admin3_code":"170169.0",
    "gn:asciiname":"Armenia",
    "gn:country_code":"EC",
    "gn:dem":1723,
    "gn:feature_class":"P",
    "gn:feature_code":"PPL",
    "gn:name":"Armen\u00eda",
    "gn:population":0,
    "gn:timezone":"America/Guayaquil",
    "iso:country":"EC",
    "name:fas_x_preferred":[
        "\u0622\u0631\u0645\u0646\u06cc\u0627"
    ],
    "name:und_x_variant":[
        "Armen\u00eda"
    ],
    "wof:name":"Armenia",
    "wof:placetype":"locality"
},
  "geometry": {"coordinates":[-78.69343000000001,0.07314],"type":"Point"}
}