{
  "type": "Feature",
  "properties": {
    "gn:admin1_code":"2.0",
    "gn:admin2_code":"102.0",
    "gn:admin3_code":"10250.0",
    "gn:asciiname":"Ludo",
    "gn:country_code":"EC",
    "gn:dem":3343,
    "gn:feature_class":"P",
    "gn:feature_code":"PPL",
    "gn:name":"Ludo",
    "gn:population":0,
    "gn:timezone":"America/Guayaquil",
    "iso:country":"EC",
    "name:ceb_x_preferred":[
        "Ludo"
    ],
    "name:dan_x_preferred":[
        "Ludo"
    ],
    "name:fra_x_preferred":[
        "Ludo"
    ],
    "name:ita_x_preferred":[
        "Ludo"
    ],
    "name:nld_x_preferred":[
        "Ludo"
    ],
    "name:swe_x_preferred":[
        "Ludo"
    ],
    "wof:name":"Ludo",
    "wof:placetype":"locality"
},
  "geometry": {"coordinates":[-79.16667,-3.11667],"type":"Point"}
}