{
  "type": "Feature",
  "properties": {
    "gn:admin1_code":"11.0",
    "gn:admin2_code":"1003.0",
    "gn:admin3_code":"100352.0",
    "gn:asciiname":"Chalguayacu",
    "gn:country_code":"EC",
    "gn:dem":1115,
    "gn:feature_class":"P",
    "gn:feature_code":"PPL",
    "gn:name":"Chalguayacu",
    "gn:population":0,
    "gn:timezone":"America/Guayaquil",
    "iso:country":"EC",
    "wof:name":"Chalguayacu",
    "wof:placetype":"locality"
},
  "geometry": {"coordinates":[-78.67461,0.25698],"type":"Point"}
}