{
  "type": "Feature",
  "properties": {
    "gn:admin1_code":"15.0",
    "gn:admin2_code":"1403.0",
    "gn:admin3_code":"140350.0",
    "gn:asciiname":"General Leonidas Plaza Gutierrez",
    "gn:country_code":"EC",
    "gn:dem":1043,
    "gn:feature_class":"P",
    "gn:feature_code":"PPL",
    "gn:name":"General Leonidas Plaza Guti\u00e9rrez",
    "gn:population":0,
    "gn:timezone":"America/Guayaquil",
    "iso:country":"EC",
    "wof:name":"General Leonidas Plaza Gutierrez",
    "wof:placetype":"locality"
},
  "geometry": {"coordinates":[-78.43196999999998,-2.9655],"type":"Point"}
}