{
  "type": "Feature",
  "properties": {
    "gn:admin1_code":"2.0",
    "gn:admin2_code":"101.0",
    "gn:admin3_code":"10159.0",
    "gn:asciiname":"El Derrumbo",
    "gn:country_code":"EC",
    "gn:dem":2727,
    "gn:feature_class":"P",
    "gn:feature_code":"PPL",
    "gn:name":"El Derrumbo",
    "gn:population":0,
    "gn:timezone":"America/Guayaquil",
    "iso:country":"EC",
    "wof:name":"El Derrumbo",
    "wof:placetype":"locality"
},
  "geometry": {"coordinates":[-78.96666999999999,-2.78333],"type":"Point"}
}