{
  "type": "Feature",
  "properties": {
    "gn:admin1_code":"2.0",
    "gn:admin2_code":"105.0",
    "gn:admin3_code":"10550.0",
    "gn:asciiname":"Huacas",
    "gn:country_code":"EC",
    "gn:dem":2296,
    "gn:feature_class":"P",
    "gn:feature_code":"PPL",
    "gn:name":"Huacas",
    "gn:population":0,
    "gn:timezone":"America/Guayaquil",
    "iso:country":"EC",
    "wof:name":"Huacas",
    "wof:placetype":"locality"
},
  "geometry": {"coordinates":[-78.78617,-2.80949],"type":"Point"}
}