{
  "type": "Feature",
  "properties": {
    "gn:admin1_code":"10.0",
    "gn:admin2_code":"905.0",
    "gn:admin3_code":"90551.0",
    "gn:asciiname":"Hacienda Bella",
    "gn:cc2":"EC",
    "gn:country_code":"EC",
    "gn:dem":15,
    "gn:feature_class":"P",
    "gn:feature_code":"PPL",
    "gn:name":"Hacienda Bella",
    "gn:population":0,
    "gn:timezone":"America/Guayaquil",
    "iso:country":"EC",
    "wof:name":"Hacienda Bella",
    "wof:placetype":"locality"
},
  "geometry": {"coordinates":[-79.98333000000002,-1.61667],"type":"Point"}
}