{
  "type": "Feature",
  "properties": {
    "gn:admin1_code":"18.0",
    "gn:admin2_code":"1701.0",
    "gn:admin3_code":"170177.0",
    "gn:asciiname":"Hacienda Veintimilla",
    "gn:cc2":"EC",
    "gn:country_code":"EC",
    "gn:dem":2437,
    "gn:feature_class":"P",
    "gn:feature_code":"PPL",
    "gn:name":"Hacienda Veintimilla",
    "gn:population":0,
    "gn:timezone":"America/Guayaquil",
    "iso:country":"EC",
    "wof:name":"Hacienda Veintimilla",
    "wof:placetype":"locality"
},
  "geometry": {"coordinates":[-78.45,-0.05],"type":"Point"}
}