{
  "type": "Feature",
  "properties": {
    "gn:admin1_code":"18.0",
    "gn:admin2_code":"1708.0",
    "gn:admin3_code":"170850.0",
    "gn:asciiname":"Cooperativa Bonanza",
    "gn:country_code":"EC",
    "gn:dem":468,
    "gn:feature_class":"P",
    "gn:feature_code":"PPL",
    "gn:name":"Cooperativa Bonanza",
    "gn:population":0,
    "gn:timezone":"America/Guayaquil",
    "iso:country":"EC",
    "wof:name":"Cooperativa Bonanza",
    "wof:placetype":"locality"
},
  "geometry": {"coordinates":[-79.10129999999999,0.14096],"type":"Point"}
}