{
  "type": "Feature",
  "properties": {
    "gn:admin1_code":"10.0",
    "gn:admin2_code":"916.0",
    "gn:admin3_code":"91650.0",
    "gn:asciiname":"Guachapeli",
    "gn:country_code":"EC",
    "gn:dem":6,
    "gn:feature_class":"P",
    "gn:feature_code":"PPL",
    "gn:name":"Guachapel\u00ed",
    "gn:population":0,
    "gn:timezone":"America/Guayaquil",
    "iso:country":"EC",
    "wof:name":"Guachapeli",
    "wof:placetype":"locality"
},
  "geometry": {"coordinates":[-79.73333000000002,-1.93333],"type":"Point"}
}