{
  "type": "Feature",
  "properties": {
    "gn:admin1_code":"2.0",
    "gn:asciiname":"Pachamama",
    "gn:country_code":"EC",
    "gn:dem":2562,
    "gn:feature_class":"P",
    "gn:feature_code":"PPL",
    "gn:name":"Pachamama",
    "gn:population":0,
    "gn:timezone":"America/Guayaquil",
    "iso:country":"EC",
    "wof:name":"Pachamama",
    "wof:placetype":"locality"
},
  "geometry": {"coordinates":[-78.91848,-2.82848],"type":"Point"}
}