{
  "type": "Feature",
  "properties": {
    "gn:admin1_code":"10.0",
    "gn:asciiname":"Tambo de Abajo",
    "gn:country_code":"EC",
    "gn:dem":22,
    "gn:feature_class":"P",
    "gn:feature_code":"PPL",
    "gn:name":"Tambo de Abajo",
    "gn:population":0,
    "gn:timezone":"America/Guayaquil",
    "iso:country":"EC",
    "wof:name":"Tambo de Abajo",
    "wof:placetype":"locality"
},
  "geometry": {"coordinates":[-80.85754,-2.2844],"type":"Point"}
}