{
  "type": "Feature",
  "properties": {
    "gn:admin1_code":"13.0",
    "gn:admin2_code":"1201.0",
    "gn:admin3_code":"120153.0",
    "gn:asciiname":"Chima",
    "gn:country_code":"EC",
    "gn:dem":21,
    "gn:feature_class":"P",
    "gn:feature_code":"PPL",
    "gn:name":"Chima",
    "gn:population":0,
    "gn:timezone":"America/Guayaquil",
    "iso:country":"EC",
    "wof:name":"Chima",
    "wof:placetype":"locality"
},
  "geometry": {"coordinates":[-79.30639000000002,-1.92613],"type":"Point"}
}