{
  "type": "Feature",
  "properties": {
    "gn:admin1_code":"14.0",
    "gn:admin2_code":"1319.0",
    "gn:admin3_code":"131950.0",
    "gn:asciiname":"Los Mieles",
    "gn:country_code":"EC",
    "gn:dem":190,
    "gn:feature_class":"P",
    "gn:feature_code":"PPL",
    "gn:name":"Los Mieles",
    "gn:population":0,
    "gn:timezone":"America/Guayaquil",
    "iso:country":"EC",
    "wof:name":"Los Mieles",
    "wof:placetype":"locality"
},
  "geometry": {"coordinates":[-80.78333000000001,-1.59167],"type":"Point"}
}