{
  "type": "Feature",
  "properties": {
    "iso:country":"EC",
    "qs:gn_pop":0,
    "qs:name":"Salinas",
    "qs:name_adm0":"Ecuador",
    "qs:name_adm1":"Santa Elena",
    "qs:photos":110,
    "qs:photos_1k":22,
    "qs:photos_9k":5,
    "qs:photos_9r":7,
    "qs:photos_all":1099,
    "qs:photos_sr":3,
    "qs:placetype":"LocalAdmin",
    "qs:pop_sr":"0",
    "qs:woe_adm0":23424801,
    "wof:name":"Salinas",
    "wof:placetype":"localadmin"
},
  "geometry": {"coordinates":[-80.98056699999999,-2.198442],"type":"Point"}
}