{
  "type": "Feature",
  "properties": {
    "gn:admin1_code":"2.0",
    "gn:admin2_code":"101.0",
    "gn:admin3_code":"10153.0",
    "gn:asciiname":"Gurgur",
    "gn:country_code":"EC",
    "gn:dem":1974,
    "gn:feature_class":"P",
    "gn:feature_code":"PPL",
    "gn:name":"Gurgur",
    "gn:population":0,
    "gn:timezone":"America/Guayaquil",
    "iso:country":"EC",
    "wof:name":"Gurgur",
    "wof:placetype":"locality"
},
  "geometry": {"coordinates":[-79.39929000000002,-2.92207],"type":"Point"}
}