{
  "type": "Feature",
  "properties": {
    "gn:admin1_code":"18.0",
    "gn:admin2_code":"1702.0",
    "gn:admin3_code":"170250.0",
    "gn:asciiname":"El Verde",
    "gn:country_code":"EC",
    "gn:dem":3782,
    "gn:feature_class":"P",
    "gn:feature_code":"PPL",
    "gn:name":"El Verde",
    "gn:population":0,
    "gn:timezone":"America/Guayaquil",
    "iso:country":"EC",
    "wof:name":"El Verde",
    "wof:placetype":"locality"
},
  "geometry": {"coordinates":[-78.03333000000001,-0.03333],"type":"Point"}
}