{
  "type": "Feature",
  "properties": {
    "gn:admin1_code":"12.0",
    "gn:admin2_code":"1110.0",
    "gn:admin3_code":"111050.0",
    "gn:asciiname":"Guararas",
    "gn:country_code":"EC",
    "gn:dem":954,
    "gn:feature_class":"P",
    "gn:feature_code":"PPL",
    "gn:name":"Guararas",
    "gn:population":0,
    "gn:timezone":"America/Guayaquil",
    "iso:country":"EC",
    "wof:name":"Guararas",
    "wof:placetype":"locality"
},
  "geometry": {"coordinates":[-80.10914,-4.02675],"type":"Point"}
}