{
  "type": "Feature",
  "properties": {
    "gn:admin1_code":"6.0",
    "gn:asciiname":"Hacienda Moreta",
    "gn:cc2":"EC",
    "gn:country_code":"EC",
    "gn:dem":3195,
    "gn:feature_class":"P",
    "gn:feature_code":"PPL",
    "gn:name":"Hacienda Moreta",
    "gn:population":0,
    "gn:timezone":"America/Guayaquil",
    "iso:country":"EC",
    "wof:name":"Hacienda Moreta",
    "wof:placetype":"locality"
},
  "geometry": {"coordinates":[-78.93333,-0.81667],"type":"Point"}
}