{
  "type": "Feature",
  "properties": {
    "gn:admin1_code":"12.0",
    "gn:admin2_code":"1113.0",
    "gn:admin3_code":"111351.0",
    "gn:asciiname":"Tamarindo",
    "gn:country_code":"EC",
    "gn:dem":312,
    "gn:feature_class":"P",
    "gn:feature_code":"PPL",
    "gn:name":"Tamarindo",
    "gn:population":0,
    "gn:timezone":"America/Guayaquil",
    "iso:country":"EC",
    "wof:name":"Tamarindo",
    "wof:placetype":"locality"
},
  "geometry": {"coordinates":[-80.41667,-4.18333],"type":"Point"}
}