{
  "type": "Feature",
  "properties": {
    "gn:admin1_code":"19.0",
    "gn:admin2_code":"1802.0",
    "gn:admin3_code":"180254.0",
    "gn:asciiname":"Ulvilla",
    "gn:country_code":"EC",
    "gn:dem":1813,
    "gn:feature_class":"P",
    "gn:feature_code":"PPL",
    "gn:name":"Ulvilla",
    "gn:population":0,
    "gn:timezone":"America/Guayaquil",
    "iso:country":"EC",
    "wof:name":"Ulvilla",
    "wof:placetype":"locality"
},
  "geometry": {"coordinates":[-78.40109,-1.40153],"type":"Point"}
}