{
  "type": "Feature",
  "properties": {
    "gn:admin1_code":"9.0",
    "gn:admin2_code":"801.0",
    "gn:admin3_code":"80150.0",
    "gn:asciiname":"Puerto Balao",
    "gn:country_code":"EC",
    "gn:dem":9,
    "gn:feature_class":"P",
    "gn:feature_code":"PPL",
    "gn:name":"Puerto Balao",
    "gn:population":0,
    "gn:timezone":"America/Guayaquil",
    "iso:country":"EC",
    "wof:name":"Puerto Balao",
    "wof:placetype":"locality"
},
  "geometry": {"coordinates":[-79.67761999999998,0.98155],"type":"Point"}
}