{
  "type": "Feature",
  "properties": {
    "gn:admin1_code":"20.0",
    "gn:admin2_code":"1905.0",
    "gn:admin3_code":"190553.0",
    "gn:asciiname":"Las Penas",
    "gn:country_code":"EC",
    "gn:dem":1481,
    "gn:feature_class":"P",
    "gn:feature_code":"PPL",
    "gn:name":"Las Pe\u00f1as",
    "gn:population":0,
    "gn:timezone":"America/Guayaquil",
    "iso:country":"EC",
    "wof:name":"Las Penas",
    "wof:placetype":"locality"
},
  "geometry": {"coordinates":[-78.48944,-3.78],"type":"Point"}
}