{
  "type": "Feature",
  "properties": {
    "gn:admin1_code":"10.0",
    "gn:admin2_code":"911.0",
    "gn:admin3_code":"91153.0",
    "gn:asciiname":"Puerto Triunfo",
    "gn:country_code":"EC",
    "gn:dem":0,
    "gn:feature_class":"P",
    "gn:feature_code":"PPL",
    "gn:name":"Puerto Triunfo",
    "gn:population":0,
    "gn:timezone":"America/Guayaquil",
    "iso:country":"EC",
    "name:ceb_x_preferred":[
        "Puerto Triunfo"
    ],
    "name:deu_x_preferred":[
        "Puerto Triunfo"
    ],
    "name:fra_x_preferred":[
        "Puerto Triunfo"
    ],
    "name:ile_x_preferred":[
        "Puerto Triunfo"
    ],
    "name:ilo_x_preferred":[
        "Puerto Triunfo"
    ],
    "name:ita_x_preferred":[
        "Puerto Triunfo"
    ],
    "name:kat_x_preferred":[
        "\u10de\u10e3\u10d4\u10e0\u10e2\u10dd-\u10e2\u10e0\u10d8\u10e3\u10dc\u10e4\u10dd"
    ],
    "name:msa_x_preferred":[
        "Puerto Triunfo"
    ],
    "name:nld_x_preferred":[
        "Puerto Triunfo"
    ],
    "name:por_x_preferred":[
        "Puerto Triunfo"
    ],
    "name:ron_x_preferred":[
        "Puerto Triunfo"
    ],
    "name:rus_x_preferred":[
        "\u041f\u0443\u044d\u0440\u0442\u043e-\u0422\u0440\u0438\u0443\u043d\u0444\u043e"
    ],
    "name:spa_x_preferred":[
        "Puerto Triunfo"
    ],
    "name:swe_x_preferred":[
        "Puerto Triunfo"
    ],
    "name:tgl_x_preferred":[
        "Puerto Triunfo"
    ],
    "name:vie_x_preferred":[
        "Puerto Triunfo"
    ],
    "name:war_x_preferred":[
        "Puerto Triunfo"
    ],
    "name:zho_x_preferred":[
        "\u7279\u91cc\u6eab\u798f\u6e2f"
    ],
    "wof:name":"Puerto Triunfo",
    "wof:placetype":"locality"
},
  "geometry": {"coordinates":[-79.73333000000002,-2.66667],"type":"Point"}
}