{
  "type": "Feature",
  "properties": {
    "gn:admin1_code":"11.0",
    "gn:admin2_code":"1001.0",
    "gn:admin3_code":"100150.0",
    "gn:asciiname":"Hacienda Chorlavicito",
    "gn:cc2":"EC",
    "gn:country_code":"EC",
    "gn:dem":2294,
    "gn:feature_class":"P",
    "gn:feature_code":"PPL",
    "gn:name":"Hacienda Chorlavicito",
    "gn:population":0,
    "gn:timezone":"America/Guayaquil",
    "iso:country":"EC",
    "wof:name":"Hacienda Chorlavicito",
    "wof:placetype":"locality"
},
  "geometry": {"coordinates":[-78.15000000000001,0.31667],"type":"Point"}
}