{
  "type": "Feature",
  "properties": {
    "gn:admin1_code":"22.0",
    "gn:admin2_code":"2101.0",
    "gn:admin3_code":"210158.0",
    "gn:asciiname":"Veinticuatro de Mayo",
    "gn:country_code":"EC",
    "gn:dem":313,
    "gn:feature_class":"P",
    "gn:feature_code":"PPL",
    "gn:name":"Veinticuatro de Mayo",
    "gn:population":0,
    "gn:timezone":"America/Guayaquil",
    "iso:country":"EC",
    "wof:name":"Veinticuatro de Mayo",
    "wof:placetype":"locality"
},
  "geometry": {"coordinates":[-76.94410999999999,0.11974],"type":"Point"}
}