{
  "type": "Feature",
  "properties": {
    "gn:admin1_code":"19.0",
    "gn:admin2_code":"1807.0",
    "gn:admin3_code":"180750.0",
    "gn:asciiname":"Guantugsumo",
    "gn:country_code":"EC",
    "gn:dem":2730,
    "gn:feature_class":"P",
    "gn:feature_code":"PPL",
    "gn:name":"Guantugsumo",
    "gn:population":0,
    "gn:timezone":"America/Guayaquil",
    "iso:country":"EC",
    "wof:name":"Guantugsumo",
    "wof:placetype":"locality"
},
  "geometry": {"coordinates":[-78.55388000000001,-1.33974],"type":"Point"}
}