{
  "type": "Feature",
  "properties": {
    "gn:admin1_code":"3.0",
    "gn:admin2_code":"202.0",
    "gn:admin3_code":"20251.0",
    "gn:asciiname":"San Jose del Tambo",
    "gn:country_code":"EC",
    "gn:dem":158,
    "gn:feature_class":"P",
    "gn:feature_code":"PPL",
    "gn:name":"San Jos\u00e9 del Tambo",
    "gn:population":0,
    "gn:timezone":"America/Guayaquil",
    "iso:country":"EC",
    "wof:name":"San Jose del Tambo",
    "wof:placetype":"locality"
},
  "geometry": {"coordinates":[-79.23602,-1.95587],"type":"Point"}
}