{
  "type": "Feature",
  "properties": {
    "iso:country":"EC",
    "qs:gn_pop":0,
    "qs:name":"Jambeli",
    "qs:name_adm0":"Ecuador",
    "qs:name_adm1":"El Oro",
    "qs:photos":1,
    "qs:photos_1k":1,
    "qs:photos_9k":1,
    "qs:photos_9r":3,
    "qs:photos_all":93,
    "qs:photos_sr":1,
    "qs:placetype":"LocalAdmin",
    "qs:pop_sr":"0",
    "qs:woe_adm0":23424801,
    "wof:name":"Jambeli",
    "wof:placetype":"localadmin"
},
  "geometry": {"coordinates":[-80.03437,-3.235812],"type":"Point"}
}