{
  "type": "Feature",
  "properties": {
    "gn:admin1_code":"12.0",
    "gn:admin2_code":"1108.0",
    "gn:admin3_code":"110853.0",
    "gn:asciiname":"Lamballe",
    "gn:country_code":"EC",
    "gn:dem":679,
    "gn:feature_class":"P",
    "gn:feature_code":"PPL",
    "gn:name":"Lamballe",
    "gn:population":0,
    "gn:timezone":"America/Guayaquil",
    "iso:country":"EC",
    "wof:name":"Lamballe",
    "wof:placetype":"locality"
},
  "geometry": {"coordinates":[-79.81667,-4.36667],"type":"Point"}
}