{
  "type": "Feature",
  "properties": {
    "gn:admin1_code":"12.0",
    "gn:admin2_code":"1108.0",
    "gn:admin3_code":"110853.0",
    "gn:asciiname":"Lamballe",
    "gn:country_code":"EC",
    "gn:dem":679,
    "gn:feature_class":"P",
    "gn:feature_code":"PPL",
    "gn:name":"Lamballe",
    "gn:population":0,
    "gn:timezone":"America/Guayaquil",
    "iso:country":"EC",
    "name:bug_x_preferred":[
        "Lamballe"
    ],
    "name:cat_x_preferred":[
        "Lamballe"
    ],
    "name:ceb_x_preferred":[
        "Lamballe"
    ],
    "name:cym_x_preferred":[
        "Lambal"
    ],
    "name:deu_x_preferred":[
        "Lamballe"
    ],
    "name:epo_x_preferred":[
        "Lamballe"
    ],
    "name:eus_x_preferred":[
        "Lamballe"
    ],
    "name:fas_x_preferred":[
        "\u0644\u0627\u0645\u0628\u0627\u0644"
    ],
    "name:fra_x_preferred":[
        "Lamballe"
    ],
    "name:glv_x_preferred":[
        "Lambal"
    ],
    "name:hun_x_preferred":[
        "Lamballe"
    ],
    "name:ind_x_preferred":[
        "Lamballe"
    ],
    "name:ita_x_preferred":[
        "Lamballe"
    ],
    "name:jpn_x_preferred":[
        "\u30e9\u30f3\u30d0\u30eb"
    ],
    "name:kaz_x_preferred":[
        "\u041b\u0430\u043c\u0431\u0430\u043b\u044c"
    ],
    "name:lat_x_preferred":[
        "Lampaulium"
    ],
    "name:msa_x_preferred":[
        "Lamballe"
    ],
    "name:nld_x_preferred":[
        "Lamballe"
    ],
    "name:nor_x_preferred":[
        "Lamballe"
    ],
    "name:oci_x_preferred":[
        "Lamballe"
    ],
    "name:pms_x_preferred":[
        "Lamballe"
    ],
    "name:pol_x_preferred":[
        "Lamballe"
    ],
    "name:por_x_preferred":[
        "Lamballe"
    ],
    "name:ron_x_preferred":[
        "Lamballe"
    ],
    "name:rus_x_preferred":[
        "\u041b\u0430\u043c\u0431\u0430\u043b\u044c"
    ],
    "name:slk_x_preferred":[
        "Lamballe"
    ],
    "name:slv_x_preferred":[
        "Lamballe"
    ],
    "name:spa_x_preferred":[
        "Lamballe"
    ],
    "name:swe_x_preferred":[
        "Lamballe"
    ],
    "name:tur_x_preferred":[
        "Lamballe"
    ],
    "name:ukr_x_preferred":[
        "\u041b\u0430\u043c\u0431\u0430\u043b\u044c"
    ],
    "name:urd_x_preferred":[
        "\u0644\u0627\u0645\u0628\u0627\u0644\u06cc"
    ],
    "name:uzb_x_preferred":[
        "Lamballe"
    ],
    "name:vie_x_preferred":[
        "Lamballe"
    ],
    "name:vol_x_preferred":[
        "Lamballe"
    ],
    "name:war_x_preferred":[
        "Lamballe"
    ],
    "wof:name":"Lamballe",
    "wof:placetype":"locality"
},
  "geometry": {"coordinates":[-79.81667,-4.36667],"type":"Point"}
}