{
  "type": "Feature",
  "properties": {
    "gn:admin1_code":"10.0",
    "gn:asciiname":"Achote",
    "gn:country_code":"EC",
    "gn:dem":5,
    "gn:feature_class":"P",
    "gn:feature_code":"PPL",
    "gn:name":"Achote",
    "gn:population":0,
    "gn:timezone":"America/Guayaquil",
    "iso:country":"EC",
    "wof:name":"Achote",
    "wof:placetype":"locality"
},
  "geometry": {"coordinates":[-79.63333,-1.91667],"type":"Point"}
}