{
  "type": "Feature",
  "properties": {
    "gn:admin1_code":"12.0",
    "gn:admin2_code":"1101.0",
    "gn:admin3_code":"110152.0",
    "gn:asciiname":"Tesalia",
    "gn:country_code":"EC",
    "gn:dem":2533,
    "gn:feature_class":"P",
    "gn:feature_code":"PPL",
    "gn:name":"Tesalia",
    "gn:population":0,
    "gn:timezone":"America/Guayaquil",
    "iso:country":"EC",
    "wof:name":"Tesalia",
    "wof:placetype":"locality"
},
  "geometry": {"coordinates":[-79.37124,-3.85427],"type":"Point"}
}