{
  "type": "Feature",
  "properties": {
    "gn:admin1_code":"12.0",
    "gn:admin2_code":"1101.0",
    "gn:admin3_code":"110152.0",
    "gn:asciiname":"Tesalia",
    "gn:country_code":"EC",
    "gn:dem":2533,
    "gn:feature_class":"P",
    "gn:feature_code":"PPL",
    "gn:name":"Tesalia",
    "gn:population":0,
    "gn:timezone":"America/Guayaquil",
    "iso:country":"EC",
    "name:ceb_x_preferred":[
        "Tesalia"
    ],
    "name:fra_x_preferred":[
        "Tesalia"
    ],
    "name:ita_x_preferred":[
        "Tesalia"
    ],
    "name:kat_x_preferred":[
        "\u10e2\u10d4\u10e1\u10d0\u10da\u10d8\u10d0"
    ],
    "name:msa_x_preferred":[
        "Tesalia"
    ],
    "name:nld_x_preferred":[
        "Tesalia"
    ],
    "name:por_x_preferred":[
        "Tesalia"
    ],
    "name:spa_x_preferred":[
        "Tesalia"
    ],
    "name:swe_x_preferred":[
        "Tesalia"
    ],
    "name:tgl_x_preferred":[
        "Tesalia"
    ],
    "name:vie_x_preferred":[
        "Tesalia"
    ],
    "name:war_x_preferred":[
        "Tesalia"
    ],
    "name:zho_x_preferred":[
        "\u7279\u85a9\u5229\u4e9e"
    ],
    "wof:name":"Tesalia",
    "wof:placetype":"locality"
},
  "geometry": {"coordinates":[-79.37124,-3.85427],"type":"Point"}
}