{
  "type": "Feature",
  "properties": {
    "gn:admin1_code":"22.0",
    "gn:admin2_code":"2101.0",
    "gn:admin3_code":"210155.0",
    "gn:asciiname":"Ron",
    "gn:country_code":"EC",
    "gn:dem":305,
    "gn:feature_class":"P",
    "gn:feature_code":"PPL",
    "gn:name":"Ron",
    "gn:population":0,
    "gn:timezone":"America/Guayaquil",
    "iso:country":"EC",
    "name:ceb_x_preferred":[
        "Ron"
    ],
    "name:ces_x_preferred":[
        "Ron"
    ],
    "name:deu_x_preferred":[
        "Ron"
    ],
    "name:hye_x_preferred":[
        "\u054c\u0578\u0576"
    ],
    "name:rus_x_preferred":[
        "\u0420\u043e\u043d"
    ],
    "name:spa_x_preferred":[
        "Ron"
    ],
    "name:swe_x_preferred":[
        "Ron"
    ],
    "wof:name":"Ron",
    "wof:placetype":"locality"
},
  "geometry": {"coordinates":[-76.789,-0.10852],"type":"Point"}
}