{
  "type": "Feature",
  "properties": {
    "gn:admin1_code":"7.0",
    "gn:admin2_code":"504.0",
    "gn:admin3_code":"50455.0",
    "gn:asciiname":"Hacienda El Tejar",
    "gn:country_code":"EC",
    "gn:dem":3055,
    "gn:feature_class":"P",
    "gn:feature_code":"PPL",
    "gn:name":"Hacienda El Tejar",
    "gn:population":0,
    "gn:timezone":"America/Guayaquil",
    "iso:country":"EC",
    "wof:name":"Hacienda El Tejar",
    "wof:placetype":"locality"
},
  "geometry": {"coordinates":[-78.69719000000001,-0.90468],"type":"Point"}
}