{
  "type": "Feature",
  "properties": {
    "gn:admin1_code":"11.0",
    "gn:admin2_code":"1004.0",
    "gn:admin3_code":"100455.0",
    "gn:asciiname":"Queseras",
    "gn:country_code":"EC",
    "gn:dem":3130,
    "gn:feature_class":"P",
    "gn:feature_code":"PPL",
    "gn:name":"Queseras",
    "gn:population":0,
    "gn:timezone":"America/Guayaquil",
    "iso:country":"EC",
    "wof:name":"Queseras",
    "wof:placetype":"locality"
},
  "geometry": {"coordinates":[-78.36870999999999,0.28059],"type":"Point"}
}