{
  "type": "Feature",
  "properties": {
    "iso:country":"EC",
    "name:deu_x_preferred":[
        "Salango"
    ],
    "name:eng_x_preferred":[
        "Salango"
    ],
    "name:nld_x_preferred":[
        "Salango"
    ],
    "name:que_x_preferred":[
        "Salango kitilli"
    ],
    "name:spa_x_preferred":[
        "Salango"
    ],
    "qs:gn_country":"EC",
    "qs:gn_fcode":"PPL",
    "qs:gn_pop":0,
    "qs:name":"Salango",
    "qs:name_adm0":"Ecuador",
    "qs:name_adm1":"Manabi",
    "qs:photos":530,
    "qs:photos_1k":107,
    "qs:photos_9k":2,
    "qs:photos_9r":5,
    "qs:photos_all":530,
    "qs:photos_sr":7,
    "qs:placetype":"Town",
    "qs:pop_sr":"0",
    "qs:woe_adm0":23424801,
    "wd:wordcount":1340,
    "wof:name":"Salango",
    "wof:placetype":"locality"
},
  "geometry": {"coordinates":[-80.8425,-1.59288],"type":"Point"}
}