{
  "type": "Feature",
  "properties": {
    "iso:country":"EC",
    "name:und_x_variant":[
        "Valladolid"
    ],
    "qs:gn_country":"EC",
    "qs:gn_fcode":"PPL",
    "qs:gn_pop":0,
    "qs:name":"Malacatos",
    "qs:name_adm0":"Ecuador",
    "qs:name_adm1":"Loja",
    "qs:photos":157,
    "qs:photos_1k":32,
    "qs:photos_9k":1,
    "qs:photos_9r":4,
    "qs:photos_all":157,
    "qs:photos_sr":4,
    "qs:placetype":"Town",
    "qs:pop_sr":"5",
    "qs:woe_adm0":23424801,
    "wof:name":"Malacatos",
    "wof:placetype":"locality"
},
  "geometry": {"coordinates":[-79.26008,-4.21901],"type":"Point"}
}