{
  "type": "Feature",
  "properties": {
    "gn:admin1_code":"24.0",
    "gn:admin2_code":"2202.0",
    "gn:admin3_code":"220255.0",
    "gn:asciiname":"Progreso",
    "gn:country_code":"EC",
    "gn:dem":192,
    "gn:feature_class":"P",
    "gn:feature_code":"PPL",
    "gn:name":"Progreso",
    "gn:population":0,
    "gn:timezone":"America/Guayaquil",
    "iso:country":"EC",
    "name:cat_x_preferred":[
        "Progreso"
    ],
    "name:ceb_x_preferred":[
        "Progreso"
    ],
    "name:deu_x_preferred":[
        "Progreso"
    ],
    "name:epo_x_preferred":[
        "Progreso"
    ],
    "name:fas_x_preferred":[
        "\u067e\u0631\u0648\u06af\u0631\u0633\u0648"
    ],
    "name:fra_x_preferred":[
        "Progreso"
    ],
    "name:ina_x_preferred":[
        "Progreso"
    ],
    "name:jpn_x_preferred":[
        "\u30d7\u30ed\u30b0\u30ec\u30c3\u30bd"
    ],
    "name:nds_x_preferred":[
        "Progreso"
    ],
    "name:nld_x_preferred":[
        "Progreso"
    ],
    "name:pol_x_preferred":[
        "Progreso"
    ],
    "name:por_x_preferred":[
        "Progreso"
    ],
    "name:rus_x_preferred":[
        "\u041f\u0440\u043e\u0433\u0440\u0435\u0441\u043e"
    ],
    "name:sco_x_preferred":[
        "Progreso"
    ],
    "name:spa_x_preferred":[
        "Progreso"
    ],
    "name:srp_x_preferred":[
        "\u041f\u0440\u043e\u0433\u0440\u0435\u0441\u043e"
    ],
    "name:swe_x_preferred":[
        "Progreso"
    ],
    "wof:name":"Progreso",
    "wof:placetype":"locality"
},
  "geometry": {"coordinates":[-75.26253,-0.81256],"type":"Point"}
}