{
  "type": "Feature",
  "properties": {
    "iso:country":"EC",
    "qs_pg:aaroncc":"EC",
    "qs_pg:name":"Puerto Misahualli",
    "qs_pg:name_adm0":"Ecuador",
    "qs_pg:name_adm1":"Napo",
    "qs_pg:photos":187,
    "qs_pg:photos_1k":38,
    "qs_pg:photos_9k":2,
    "qs_pg:photos_9r":5,
    "qs_pg:photos_all":490,
    "qs_pg:photos_sr":4,
    "qs_pg:pop_sr":0,
    "qs_pg:qs_pg_placetype":"localadmin",
    "qs_pg:qs_pg_placetype_gp":"LocalAdmin",
    "qs_pg:woe_adm0":23424801,
    "woe:adm0_id":23424801,
    "woe:name_adm0":"Ecuador",
    "woe:name_adm1":"Napo",
    "woe:placetype":"LocalAdmin",
    "wof:name":"Puerto Misahualli",
    "wof:placetype":"localadmin"
},
  "geometry": {"coordinates":[-77.666618,-1.035233],"type":"Point"}
}