{
  "type": "Feature",
  "properties": {
    "gn:admin1_code":"14.0",
    "gn:admin2_code":"1319.0",
    "gn:admin3_code":"131952.0",
    "gn:asciiname":"Puerto Rico",
    "gn:country_code":"EC",
    "gn:dem":8,
    "gn:feature_class":"P",
    "gn:feature_code":"PPL",
    "gn:name":"Puerto Rico",
    "gn:population":0,
    "gn:timezone":"America/Guayaquil",
    "iso:country":"EC",
    "wof:name":"Puerto Rico",
    "wof:placetype":"locality"
},
  "geometry": {"coordinates":[-80.83114,-1.63588],"type":"Point"}
}