{
  "type": "Feature",
  "properties": {
    "gn:admin1_code":"11.0",
    "gn:admin2_code":"1001.0",
    "gn:admin3_code":"100153.0",
    "gn:asciiname":"Cuambo",
    "gn:cc2":"EC",
    "gn:country_code":"EC",
    "gn:dem":1881,
    "gn:feature_class":"P",
    "gn:feature_code":"PPL",
    "gn:name":"Cuambo",
    "gn:population":0,
    "gn:timezone":"America/Guayaquil",
    "iso:country":"EC",
    "wof:name":"Cuambo",
    "wof:placetype":"locality"
},
  "geometry": {"coordinates":[-78.16667,0.58333],"type":"Point"}
}