{
  "type": "Feature",
  "properties": {
    "gn:admin1_code":"26.0",
    "gn:admin2_code":"2301.0",
    "gn:admin3_code":"230154.0",
    "gn:asciiname":"La Flecha",
    "gn:country_code":"EC",
    "gn:dem":266,
    "gn:feature_class":"P",
    "gn:feature_code":"PPL",
    "gn:name":"La Flecha",
    "gn:population":0,
    "gn:timezone":"America/Guayaquil",
    "iso:country":"EC",
    "wof:name":"La Flecha",
    "wof:placetype":"locality"
},
  "geometry": {"coordinates":[-79.39530999999999,-0.12666],"type":"Point"}
}