{
  "type": "Feature",
  "properties": {
    "gn:admin1_code":"11.0",
    "gn:admin2_code":"1003.0",
    "gn:admin3_code":"100353.0",
    "gn:asciiname":"Hacienda Quitumbe",
    "gn:country_code":"EC",
    "gn:dem":2244,
    "gn:feature_class":"P",
    "gn:feature_code":"PPL",
    "gn:name":"Hacienda Quitumbe",
    "gn:population":0,
    "gn:timezone":"America/Guayaquil",
    "iso:country":"EC",
    "wof:name":"Hacienda Quitumbe",
    "wof:placetype":"locality"
},
  "geometry": {"coordinates":[-78.24005,0.37688],"type":"Point"}
}