{
  "type": "Feature",
  "properties": {
    "gn:admin1_code":"24.0",
    "gn:admin2_code":"2202.0",
    "gn:admin3_code":"220250.0",
    "gn:asciiname":"Eloy Alfaro",
    "gn:country_code":"EC",
    "gn:dem":196,
    "gn:feature_class":"P",
    "gn:feature_code":"PPL",
    "gn:name":"Eloy Alfaro",
    "gn:population":0,
    "gn:timezone":"America/Guayaquil",
    "iso:country":"EC",
    "name:ara_x_preferred":[
        "\u0625\u0644\u0648\u064a \u0623\u0644\u0641\u0627\u0631\u0648"
    ],
    "name:ast_x_preferred":[
        "Eloy Alfaro"
    ],
    "name:cat_x_preferred":[
        "Eloy Alfaro"
    ],
    "name:deu_x_preferred":[
        "Eloy Alfaro"
    ],
    "name:epo_x_preferred":[
        "Eloy Alfaro"
    ],
    "name:fin_x_preferred":[
        "Eloy Alfaro"
    ],
    "name:fra_x_preferred":[
        "Eloy Alfaro"
    ],
    "name:ido_x_preferred":[
        "Eloy Alfaro"
    ],
    "name:ita_x_preferred":[
        "Eloy Alfaro"
    ],
    "name:nld_x_preferred":[
        "Jos\u00e9 Eloy Alfaro Delgado"
    ],
    "name:pol_x_preferred":[
        "Eloy Alfaro"
    ],
    "name:por_x_preferred":[
        "Eloy Alfaro"
    ],
    "name:que_x_preferred":[
        "Eloy Alfaro"
    ],
    "name:rus_x_preferred":[
        "\u0410\u043b\u044c\u0444\u0430\u0440\u043e"
    ],
    "name:sco_x_preferred":[
        "Eloy Alfaro"
    ],
    "name:slv_x_preferred":[
        "Eloy Alfaro"
    ],
    "name:spa_x_preferred":[
        "Eloy Alfaro"
    ],
    "name:ukr_x_preferred":[
        "\u0415\u043b\u043e\u0439 \u0410\u043b\u044c\u0444\u0430\u0440\u043e"
    ],
    "name:vie_x_preferred":[
        "Eloy Alfaro"
    ],
    "name:yor_x_preferred":[
        "Eloy Alfaro"
    ],
    "name:zho_x_preferred":[
        "\u57c3\u6d1b\u4f0a\u00b7\u963f\u5c14\u6cd5\u7f57"
    ],
    "wof:name":"Eloy Alfaro",
    "wof:placetype":"locality"
},
  "geometry": {"coordinates":[-75.4716,-0.8465],"type":"Point"}
}