{
  "type": "Feature",
  "properties": {
    "gn:admin1_code":"24.0",
    "gn:admin2_code":"2202.0",
    "gn:admin3_code":"220250.0",
    "gn:asciiname":"Eloy Alfaro",
    "gn:country_code":"EC",
    "gn:dem":196,
    "gn:feature_class":"P",
    "gn:feature_code":"PPL",
    "gn:name":"Eloy Alfaro",
    "gn:population":0,
    "gn:timezone":"America/Guayaquil",
    "iso:country":"EC",
    "wof:name":"Eloy Alfaro",
    "wof:placetype":"locality"
},
  "geometry": {"coordinates":[-75.4716,-0.8465],"type":"Point"}
}