{
  "type": "Feature",
  "properties": {
    "gn:admin1_code":"7.0",
    "gn:admin2_code":"501.0",
    "gn:admin3_code":"50150.0",
    "gn:asciiname":"Hacienda Laigua de Rivadeneira",
    "gn:cc2":"EC",
    "gn:country_code":"EC",
    "gn:dem":2831,
    "gn:feature_class":"P",
    "gn:feature_code":"PPL",
    "gn:name":"Hacienda Laigua de Rivadeneira",
    "gn:population":0,
    "gn:timezone":"America/Guayaquil",
    "iso:country":"EC",
    "wof:name":"Hacienda Laigua de Rivadeneira",
    "wof:placetype":"locality"
},
  "geometry": {"coordinates":[-78.61667,-0.88333],"type":"Point"}
}