{
  "type": "Feature",
  "properties": {
    "gn:admin1_code":"19.0",
    "gn:admin2_code":"1801.0",
    "gn:admin3_code":"180165.0",
    "gn:asciiname":"Mishquilli",
    "gn:country_code":"EC",
    "gn:dem":3204,
    "gn:feature_class":"P",
    "gn:feature_code":"PPL",
    "gn:name":"Mishquill\u00ed",
    "gn:population":0,
    "gn:timezone":"America/Guayaquil",
    "iso:country":"EC",
    "wof:name":"Mishquilli",
    "wof:placetype":"locality"
},
  "geometry": {"coordinates":[-78.68084,-1.32078],"type":"Point"}
}