{
  "type": "Feature",
  "properties": {
    "gn:admin1_code":"2.0",
    "gn:admin2_code":"101.0",
    "gn:admin3_code":"10152.0",
    "gn:asciiname":"Manzano",
    "gn:country_code":"EC",
    "gn:dem":2921,
    "gn:feature_class":"P",
    "gn:feature_code":"PPL",
    "gn:name":"Manzano",
    "gn:population":0,
    "gn:timezone":"America/Guayaquil",
    "iso:country":"EC",
    "name:ceb_x_preferred":[
        "Manzano"
    ],
    "name:deu_x_preferred":[
        "Manzano"
    ],
    "name:fra_x_preferred":[
        "Manzano"
    ],
    "name:ita_x_preferred":[
        "Manzano"
    ],
    "name:nld_x_preferred":[
        "Manzano"
    ],
    "name:rus_x_preferred":[
        "\u041c\u0430\u043d\u0441\u0430\u043d\u043e"
    ],
    "name:spa_x_preferred":[
        "Manzano"
    ],
    "name:srp_x_preferred":[
        "Mancano"
    ],
    "name:swe_x_preferred":[
        "Manzano"
    ],
    "name:vol_x_preferred":[
        "Manzano"
    ],
    "wof:name":"Manzano",
    "wof:placetype":"locality"
},
  "geometry": {"coordinates":[-79.01411999999998,-3.13063],"type":"Point"}
}