{
  "type": "Feature",
  "properties": {
    "gn:admin1_code":"17.0",
    "gn:admin2_code":"1601.0",
    "gn:admin3_code":"160161.0",
    "gn:asciiname":"Sarayacu",
    "gn:country_code":"EC",
    "gn:dem":369,
    "gn:feature_class":"P",
    "gn:feature_code":"PPL",
    "gn:name":"Sarayacu",
    "gn:population":0,
    "gn:timezone":"America/Guayaquil",
    "iso:country":"EC",
    "wof:name":"Sarayacu",
    "wof:placetype":"locality"
},
  "geometry": {"coordinates":[-77.48477,-1.73651],"type":"Point"}
}