{
  "type": "Feature",
  "properties": {
    "gn:admin1_code":"4.0",
    "gn:asciiname":"La Delicia",
    "gn:country_code":"EC",
    "gn:dem":874,
    "gn:feature_class":"P",
    "gn:feature_code":"PPL",
    "gn:name":"La Delicia",
    "gn:population":0,
    "gn:timezone":"America/Guayaquil",
    "iso:country":"EC",
    "wof:name":"La Delicia",
    "wof:placetype":"locality"
},
  "geometry": {"coordinates":[-79.33333,-2.56667],"type":"Point"}
}