{
  "type": "Feature",
  "properties": {
    "gn:admin1_code":"26.0",
    "gn:admin2_code":"2301.0",
    "gn:admin3_code":"230150.0",
    "gn:asciiname":"Susanita",
    "gn:country_code":"EC",
    "gn:dem":417,
    "gn:feature_class":"P",
    "gn:feature_code":"PPL",
    "gn:name":"Susanita",
    "gn:population":0,
    "gn:timezone":"America/Guayaquil",
    "iso:country":"EC",
    "wof:name":"Susanita",
    "wof:placetype":"locality"
},
  "geometry": {"coordinates":[-79.22996999999999,-0.33063],"type":"Point"}
}