{
  "type": "Feature",
  "properties": {
    "gn:admin1_code":"12.0",
    "gn:admin2_code":"1113.0",
    "gn:admin3_code":"111356.0",
    "gn:asciiname":"Las Pampas",
    "gn:country_code":"EC",
    "gn:dem":223,
    "gn:feature_class":"P",
    "gn:feature_code":"PPL",
    "gn:name":"Las Pampas",
    "gn:population":0,
    "gn:timezone":"America/Guayaquil",
    "iso:country":"EC",
    "wof:name":"Las Pampas",
    "wof:placetype":"locality"
},
  "geometry": {"coordinates":[-80.47459000000001,-4.05749],"type":"Point"}
}