{
  "type": "Feature",
  "properties": {
    "gn:admin1_code":"5.0",
    "gn:admin2_code":"401.0",
    "gn:admin3_code":"40157.0",
    "gn:asciiname":"Hacienda La Concepcion",
    "gn:country_code":"EC",
    "gn:dem":3107,
    "gn:feature_class":"P",
    "gn:feature_code":"PPL",
    "gn:name":"Hacienda La Concepci\u00f3n",
    "gn:population":0,
    "gn:timezone":"America/Bogota",
    "iso:country":"EC",
    "wof:name":"Hacienda La Concepcion",
    "wof:placetype":"locality"
},
  "geometry": {"coordinates":[-77.81267,0.81085],"type":"Point"}
}