{
  "type": "Feature",
  "properties": {
    "gn:admin1_code":"14.0",
    "gn:admin2_code":"1303.0",
    "gn:admin3_code":"130352.0",
    "gn:asciiname":"Canuto",
    "gn:country_code":"EC",
    "gn:dem":27,
    "gn:feature_class":"P",
    "gn:feature_code":"PPL",
    "gn:name":"Canuto",
    "gn:population":0,
    "gn:timezone":"America/Guayaquil",
    "iso:country":"EC",
    "name:ceb_x_preferred":[
        "Canuto"
    ],
    "name:ita_x_preferred":[
        "Canuto"
    ],
    "name:por_x_preferred":[
        "Canuto"
    ],
    "name:spa_x_preferred":[
        "Canuto"
    ],
    "name:swe_x_preferred":[
        "Canuto"
    ],
    "wof:name":"Canuto",
    "wof:placetype":"locality"
},
  "geometry": {"coordinates":[-80.12815000000001,-0.79961],"type":"Point"}
}