{
  "type": "Feature",
  "properties": {
    "gn:admin1_code":"4.0",
    "gn:admin2_code":"303.0",
    "gn:admin3_code":"30353.0",
    "gn:asciiname":"Arenal",
    "gn:country_code":"EC",
    "gn:dem":2075,
    "gn:feature_class":"P",
    "gn:feature_code":"PPL",
    "gn:name":"Arenal",
    "gn:population":0,
    "gn:timezone":"America/Guayaquil",
    "iso:country":"EC",
    "wof:name":"Arenal",
    "wof:placetype":"locality"
},
  "geometry": {"coordinates":[-79.03333000000001,-2.36667],"type":"Point"}
}