{
  "type": "Feature",
  "properties": {
    "gn:admin1_code":"10.0",
    "gn:admin2_code":"909.0",
    "gn:admin3_code":"90950.0",
    "gn:asciiname":"Hacienda Florida",
    "gn:country_code":"EC",
    "gn:dem":26,
    "gn:feature_class":"P",
    "gn:feature_code":"PPL",
    "gn:name":"Hacienda Florida",
    "gn:population":0,
    "gn:timezone":"America/Guayaquil",
    "iso:country":"EC",
    "wof:name":"Hacienda Florida",
    "wof:placetype":"locality"
},
  "geometry": {"coordinates":[-79.54800999999998,-2.27161],"type":"Point"}
}