{
  "type": "Feature",
  "properties": {
    "iso:country":"EC",
    "name:ceb_x_preferred":[
        "Guamote"
    ],
    "name:que_x_preferred":[
        "Wamuti"
    ],
    "name:swe_x_preferred":[
        "Guamote"
    ],
    "qs:gn_pop":0,
    "qs:name":"Guamote",
    "qs:name_adm0":"Ecuador",
    "qs:name_adm1":"Chimborazo",
    "qs:photos":12,
    "qs:photos_1k":2,
    "qs:photos_9k":1,
    "qs:photos_9r":2,
    "qs:photos_all":63,
    "qs:photos_sr":1,
    "qs:placetype":"LocalAdmin",
    "qs:pop_sr":"0",
    "qs:woe_adm0":23424801,
    "wof:name":"Guamote",
    "wof:placetype":"localadmin"
},
  "geometry": {"coordinates":[-78.708618,-1.930609],"type":"Point"}
}