{
  "type": "Feature",
  "properties": {
    "gn:admin1_code":"7.0",
    "gn:admin2_code":"505.0",
    "gn:admin3_code":"50552.0",
    "gn:asciiname":"Hacienda Aguamasa",
    "gn:cc2":"EC",
    "gn:country_code":"EC",
    "gn:dem":3340,
    "gn:feature_class":"P",
    "gn:feature_code":"PPL",
    "gn:name":"Hacienda Aguamasa",
    "gn:population":0,
    "gn:timezone":"America/Guayaquil",
    "iso:country":"EC",
    "wof:name":"Hacienda Aguamasa",
    "wof:placetype":"locality"
},
  "geometry": {"coordinates":[-78.71666999999999,-1.08333],"type":"Point"}
}