{
  "type": "Feature",
  "properties": {
    "gn:admin1_code":"5.0",
    "gn:admin2_code":"404.0",
    "gn:admin3_code":"40453.0",
    "gn:asciiname":"Juan Montalvo",
    "gn:country_code":"EC",
    "gn:dem":2017,
    "gn:feature_class":"P",
    "gn:feature_code":"PPL",
    "gn:name":"Juan Montalvo",
    "gn:population":0,
    "gn:timezone":"America/Guayaquil",
    "iso:country":"EC",
    "wof:name":"Juan Montalvo",
    "wof:placetype":"locality"
},
  "geometry": {"coordinates":[-78.0878,0.58685],"type":"Point"}
}