{
  "type": "Feature",
  "properties": {
    "gn:admin1_code":"5.0",
    "gn:admin2_code":"404.0",
    "gn:admin3_code":"40453.0",
    "gn:asciiname":"Juan Montalvo",
    "gn:country_code":"EC",
    "gn:dem":2017,
    "gn:feature_class":"P",
    "gn:feature_code":"PPL",
    "gn:name":"Juan Montalvo",
    "gn:population":0,
    "gn:timezone":"America/Guayaquil",
    "iso:country":"EC",
    "name:ara_x_preferred":[
        "\u062e\u0648\u0627\u0646 \u0645\u0648\u0646\u062a\u0627\u0644\u0628\u0648"
    ],
    "name:ast_x_preferred":[
        "Juan Montalvo Fiallos"
    ],
    "name:cat_x_preferred":[
        "Juan Montalvo"
    ],
    "name:deu_x_preferred":[
        "Juan Montalvo"
    ],
    "name:fra_x_preferred":[
        "Juan Montalvo"
    ],
    "name:ita_x_preferred":[
        "Juan Montalvo"
    ],
    "name:mwl_x_preferred":[
        "Juan Montalvo"
    ],
    "name:pol_x_preferred":[
        "Juan Montalvo"
    ],
    "name:por_x_preferred":[
        "Juan Montalvo"
    ],
    "name:que_x_preferred":[
        "Juan Montalvo"
    ],
    "name:ron_x_preferred":[
        "Juan Montalvo"
    ],
    "name:rus_x_preferred":[
        "\u041c\u043e\u043d\u0442\u0430\u043b\u044c\u0432\u043e"
    ],
    "name:spa_x_preferred":[
        "Juan Montalvo"
    ],
    "name:ukr_x_preferred":[
        "\u0425\u0443\u0430\u043d \u041c\u043e\u043d\u0442\u0430\u043b\u044c\u0432\u043e"
    ],
    "wof:name":"Juan Montalvo",
    "wof:placetype":"locality"
},
  "geometry": {"coordinates":[-78.0878,0.58685],"type":"Point"}
}