{
  "type": "Feature",
  "properties": {
    "gn:admin1_code":"8.0",
    "gn:asciiname":"La Ramada",
    "gn:country_code":"EC",
    "gn:dem":1292,
    "gn:feature_class":"P",
    "gn:feature_code":"PPL",
    "gn:name":"La Ramada",
    "gn:population":0,
    "gn:timezone":"America/Guayaquil",
    "iso:country":"EC",
    "wof:name":"La Ramada",
    "wof:placetype":"locality"
},
  "geometry": {"coordinates":[-79.61667,-3.26667],"type":"Point"}
}