{
  "type": "Feature",
  "properties": {
    "gn:admin1_code":"2.0",
    "gn:admin2_code":"102.0",
    "gn:admin3_code":"10251.0",
    "gn:asciiname":"Hacienda Corral Huayco",
    "gn:cc2":"EC",
    "gn:country_code":"EC",
    "gn:dem":1525,
    "gn:feature_class":"P",
    "gn:feature_code":"PPL",
    "gn:name":"Hacienda Corral Huayco",
    "gn:population":0,
    "gn:timezone":"America/Guayaquil",
    "iso:country":"EC",
    "wof:name":"Hacienda Corral Huayco",
    "wof:placetype":"locality"
},
  "geometry": {"coordinates":[-79.23333000000002,-3.25],"type":"Point"}
}