{
  "type": "Feature",
  "properties": {
    "gn:admin1_code":"9.0",
    "gn:admin2_code":"805.0",
    "gn:admin3_code":"80560.0",
    "gn:asciiname":"El Guachal",
    "gn:country_code":"EC",
    "gn:dem":5,
    "gn:feature_class":"P",
    "gn:feature_code":"PPL",
    "gn:name":"El Guachal",
    "gn:population":0,
    "gn:timezone":"America/Guayaquil",
    "iso:country":"EC",
    "wof:name":"El Guachal",
    "wof:placetype":"locality"
},
  "geometry": {"coordinates":[-78.92497,1.19299],"type":"Point"}
}