{
  "type": "Feature",
  "properties": {
    "gn:admin1_code":"2.0",
    "gn:admin2_code":"101.0",
    "gn:admin3_code":"10155.0",
    "gn:asciiname":"San Antonio",
    "gn:country_code":"EC",
    "gn:dem":2806,
    "gn:feature_class":"P",
    "gn:feature_code":"PPL",
    "gn:name":"San Antonio",
    "gn:population":0,
    "gn:timezone":"America/Guayaquil",
    "iso:country":"EC",
    "wof:name":"San Antonio",
    "wof:placetype":"locality"
},
  "geometry": {"coordinates":[-79.01130999999999,-2.81191],"type":"Point"}
}