{
  "type": "Feature",
  "properties": {
    "gn:admin1_code":"19.0",
    "gn:admin2_code":"1806.0",
    "gn:admin3_code":"180650.0",
    "gn:asciiname":"Llimpe",
    "gn:country_code":"EC",
    "gn:dem":2926,
    "gn:feature_class":"P",
    "gn:feature_code":"PPL",
    "gn:name":"Llimpe",
    "gn:population":0,
    "gn:timezone":"America/Guayaquil",
    "iso:country":"EC",
    "wof:name":"Llimpe",
    "wof:placetype":"locality"
},
  "geometry": {"coordinates":[-78.58591,-1.35954],"type":"Point"}
}