{
  "type": "Feature",
  "properties": {
    "gn:admin1_code":"10.0",
    "gn:asciiname":"Pacoba",
    "gn:country_code":"EC",
    "gn:dem":22,
    "gn:feature_class":"P",
    "gn:feature_code":"PPL",
    "gn:name":"Pacoba",
    "gn:population":0,
    "gn:timezone":"America/Guayaquil",
    "iso:country":"EC",
    "wof:name":"Pacoba",
    "wof:placetype":"locality"
},
  "geometry": {"coordinates":[-80.73333000000002,-2.13333],"type":"Point"}
}