{
  "type": "Feature",
  "properties": {
    "gn:admin1_code":"22.0",
    "gn:admin2_code":"2105.0",
    "gn:admin3_code":"210554.0",
    "gn:asciiname":"Chingual",
    "gn:country_code":"EC",
    "gn:dem":2686,
    "gn:feature_class":"P",
    "gn:feature_code":"PPL",
    "gn:name":"Chingual",
    "gn:population":0,
    "gn:timezone":"America/Guayaquil",
    "iso:country":"EC",
    "wof:name":"Chingual",
    "wof:placetype":"locality"
},
  "geometry": {"coordinates":[-77.53464,0.64211],"type":"Point"}
}