{
  "type": "Feature",
  "properties": {
    "gn:admin1_code":"19.0",
    "gn:admin2_code":"1805.0",
    "gn:admin3_code":"180550.0",
    "gn:asciiname":"Flandes",
    "gn:country_code":"EC",
    "gn:dem":2702,
    "gn:feature_class":"P",
    "gn:feature_code":"PPL",
    "gn:name":"Flandes",
    "gn:population":0,
    "gn:timezone":"America/Guayaquil",
    "iso:country":"EC",
    "wof:name":"Flandes",
    "wof:placetype":"locality"
},
  "geometry": {"coordinates":[-78.46666999999999,-1.33333],"type":"Point"}
}