{
  "type": "Feature",
  "properties": {
    "gn:admin1_code":"19.0",
    "gn:admin2_code":"1805.0",
    "gn:admin3_code":"180550.0",
    "gn:asciiname":"Flandes",
    "gn:country_code":"EC",
    "gn:dem":2702,
    "gn:feature_class":"P",
    "gn:feature_code":"PPL",
    "gn:name":"Flandes",
    "gn:population":0,
    "gn:timezone":"America/Guayaquil",
    "iso:country":"EC",
    "name:ceb_x_preferred":[
        "Flandes"
    ],
    "name:deu_x_preferred":[
        "Flandes"
    ],
    "name:fas_x_preferred":[
        "\u0641\u0644\u0627\u0646\u062f\u0633"
    ],
    "name:fra_x_preferred":[
        "Flandes"
    ],
    "name:ita_x_preferred":[
        "Flandes"
    ],
    "name:kat_x_preferred":[
        "\u10e4\u10da\u10d0\u10dc\u10d3\u10d4\u10e1\u10d8"
    ],
    "name:msa_x_preferred":[
        "Flandes"
    ],
    "name:nld_x_preferred":[
        "Flandes"
    ],
    "name:spa_x_preferred":[
        "Flandes"
    ],
    "name:swe_x_preferred":[
        "Flandes"
    ],
    "name:vie_x_preferred":[
        "Flandes"
    ],
    "name:war_x_preferred":[
        "Flandes"
    ],
    "name:zho_x_preferred":[
        "\u5f17\u862d\u5fb7\u65af"
    ],
    "wof:name":"Flandes",
    "wof:placetype":"locality"
},
  "geometry": {"coordinates":[-78.46666999999999,-1.33333],"type":"Point"}
}