{
  "type": "Feature",
  "properties": {
    "gn:admin1_code":"8.0",
    "gn:admin2_code":"710.0",
    "gn:admin3_code":"71054.0",
    "gn:asciiname":"Piedras",
    "gn:country_code":"EC",
    "gn:dem":135,
    "gn:feature_class":"P",
    "gn:feature_code":"PPL",
    "gn:name":"Piedras",
    "gn:population":0,
    "gn:timezone":"America/Guayaquil",
    "iso:country":"EC",
    "name:cat_x_preferred":[
        "Piedras"
    ],
    "name:ceb_x_preferred":[
        "Piedras"
    ],
    "name:fra_x_preferred":[
        "Piedras"
    ],
    "name:gla_x_preferred":[
        "Piedras"
    ],
    "name:ita_x_preferred":[
        "Piedras"
    ],
    "name:kat_x_preferred":[
        "\u10de\u10d8\u10d4\u10d3\u10e0\u10d0\u10e1\u10d8"
    ],
    "name:msa_x_preferred":[
        "Piedras"
    ],
    "name:nld_x_preferred":[
        "Piedras"
    ],
    "name:spa_x_preferred":[
        "Piedras"
    ],
    "name:swe_x_preferred":[
        "Piedras"
    ],
    "name:vie_x_preferred":[
        "Piedras"
    ],
    "name:war_x_preferred":[
        "Piedras"
    ],
    "name:zho_x_preferred":[
        "\u5f7c\u5fb7\u62c9\u65af"
    ],
    "wof:name":"Piedras",
    "wof:placetype":"locality"
},
  "geometry": {"coordinates":[-79.91574,-3.63698],"type":"Point"}
}