{
  "type": "Feature",
  "properties": {
    "gn:admin1_code":"6.0",
    "gn:admin2_code":"603.0",
    "gn:admin3_code":"60350.0",
    "gn:asciiname":"Hacienda Opote",
    "gn:country_code":"EC",
    "gn:dem":3442,
    "gn:feature_class":"P",
    "gn:feature_code":"PPL",
    "gn:name":"Hacienda Opote",
    "gn:population":0,
    "gn:timezone":"America/Guayaquil",
    "iso:country":"EC",
    "wof:name":"Hacienda Opote",
    "wof:placetype":"locality"
},
  "geometry": {"coordinates":[-78.76378000000003,-1.76466],"type":"Point"}
}