{
  "type": "Feature",
  "properties": {
    "gn:admin1_code":"6.0",
    "gn:admin2_code":"602.0",
    "gn:admin3_code":"60258.0",
    "gn:asciiname":"Sevilla",
    "gn:country_code":"EC",
    "gn:dem":2834,
    "gn:feature_class":"P",
    "gn:feature_code":"PPL",
    "gn:name":"Sevilla",
    "gn:population":0,
    "gn:timezone":"America/Guayaquil",
    "iso:country":"EC",
    "name:heb_x_preferred":[
        "\u05e1\u05d1\u05d9\u05dc\u05d9\u05d4"
    ],
    "wof:name":"Sevilla",
    "wof:placetype":"locality"
},
  "geometry": {"coordinates":[-78.82384,-2.27459],"type":"Point"}
}