{
  "type": "Feature",
  "properties": {
    "gn:admin1_code":"22.0",
    "gn:admin2_code":"2106.0",
    "gn:admin3_code":"210650.0",
    "gn:asciiname":"Pastaza",
    "gn:country_code":"EC",
    "gn:dem":367,
    "gn:feature_class":"P",
    "gn:feature_code":"PPL",
    "gn:name":"Pastaza",
    "gn:population":0,
    "gn:timezone":"America/Guayaquil",
    "iso:country":"EC",
    "name:bel_x_preferred":[
        "\u041f\u0430\u0441\u0442\u0430\u0441\u0430"
    ],
    "name:ceb_x_preferred":[
        "Pastaza"
    ],
    "name:fra_x_preferred":[
        "Pastaza"
    ],
    "name:nld_x_preferred":[
        "Pastaza"
    ],
    "name:rus_x_preferred":[
        "\u041f\u0430\u0441\u0442\u0430\u0441\u0430"
    ],
    "name:spa_x_preferred":[
        "Pastaza"
    ],
    "name:swe_x_preferred":[
        "Pastaza"
    ],
    "name:ukr_x_preferred":[
        "\u041f\u0430\u0441\u0442\u0430\u0441\u0430"
    ],
    "wof:name":"Pastaza",
    "wof:placetype":"locality"
},
  "geometry": {"coordinates":[-77.17610999999999,0.02634],"type":"Point"}
}