{
  "type": "Feature",
  "properties": {
    "gn:admin1_code":"18.0",
    "gn:asciiname":"Lelia",
    "gn:country_code":"EC",
    "gn:dem":694,
    "gn:feature_class":"P",
    "gn:feature_code":"PPL",
    "gn:name":"Lelia",
    "gn:population":0,
    "gn:timezone":"America/Guayaquil",
    "iso:country":"EC",
    "wof:name":"Lelia",
    "wof:placetype":"locality"
},
  "geometry": {"coordinates":[-79.03084,-0.31076],"type":"Point"}
}