{
  "type": "Feature",
  "properties": {
    "gn:admin1_code":"11.0",
    "gn:admin2_code":"1001.0",
    "gn:admin3_code":"100150.0",
    "gn:asciiname":"El Olivo",
    "gn:country_code":"EC",
    "gn:dem":2196,
    "gn:feature_class":"P",
    "gn:feature_code":"PPL",
    "gn:name":"El Olivo",
    "gn:population":0,
    "gn:timezone":"America/Guayaquil",
    "iso:country":"EC",
    "wof:name":"El Olivo",
    "wof:placetype":"locality"
},
  "geometry": {"coordinates":[-78.11176,0.36139],"type":"Point"}
}