{
  "type": "Feature",
  "properties": {
    "gn:admin1_code":"15.0",
    "gn:admin2_code":"1405.0",
    "gn:admin3_code":"140552.0",
    "gn:asciiname":"Chupianza Grande",
    "gn:country_code":"EC",
    "gn:dem":670,
    "gn:feature_class":"P",
    "gn:feature_code":"PPL",
    "gn:name":"Chupianza Grande",
    "gn:population":0,
    "gn:timezone":"America/Guayaquil",
    "iso:country":"EC",
    "wof:name":"Chupianza Grande",
    "wof:placetype":"locality"
},
  "geometry": {"coordinates":[-78.32343,-2.73219],"type":"Point"}
}