{
  "type": "Feature",
  "properties": {
    "gn:admin1_code":"19.0",
    "gn:admin2_code":"1808.0",
    "gn:admin3_code":"180857.0",
    "gn:asciiname":"Panguigua",
    "gn:country_code":"EC",
    "gn:dem":2680,
    "gn:feature_class":"P",
    "gn:feature_code":"PPL",
    "gn:name":"Panguigua",
    "gn:population":0,
    "gn:timezone":"America/Guayaquil",
    "iso:country":"EC",
    "wof:name":"Panguigua",
    "wof:placetype":"locality"
},
  "geometry": {"coordinates":[-78.54996,-1.19851],"type":"Point"}
}