{
  "type": "Feature",
  "properties": {
    "iso:country":"EC",
    "name:und_x_variant":[
        "F\u00e9lix"
    ],
    "qs:gn_country":"EC",
    "qs:gn_fcode":"PPL",
    "qs:gn_pop":0,
    "qs:name":"Yasun\u00ed",
    "qs:name_adm0":"Ecuador",
    "qs:name_adm1":"Orellana",
    "qs:photos":21,
    "qs:photos_1k":4,
    "qs:photos_9k":1,
    "qs:photos_9r":1,
    "qs:photos_all":21,
    "qs:photos_sr":1,
    "qs:placetype":"Town",
    "qs:pop_sr":"0",
    "qs:woe_adm0":23424801,
    "wof:name":"Yasun\u00ed",
    "wof:placetype":"locality"
},
  "geometry": {"coordinates":[-75.39917,-0.93548],"type":"Point"}
}