{
  "type": "Feature",
  "properties": {
    "gn:admin1_code":"12.0",
    "gn:admin2_code":"1110.0",
    "gn:admin3_code":"111050.0",
    "gn:asciiname":"Huasimo",
    "gn:country_code":"EC",
    "gn:dem":354,
    "gn:feature_class":"P",
    "gn:feature_code":"PPL",
    "gn:name":"Hu\u00e1simo",
    "gn:population":0,
    "gn:timezone":"America/Guayaquil",
    "iso:country":"EC",
    "wof:name":"Huasimo",
    "wof:placetype":"locality"
},
  "geometry": {"coordinates":[-80.13333,-3.91667],"type":"Point"}
}