{
  "type": "Feature",
  "properties": {
    "gn:admin1_code":"18.0",
    "gn:admin2_code":"1708.0",
    "gn:admin3_code":"170850.0",
    "gn:asciiname":"San Dimas",
    "gn:country_code":"EC",
    "gn:dem":571,
    "gn:feature_class":"P",
    "gn:feature_code":"PPL",
    "gn:name":"San Dimas",
    "gn:population":0,
    "gn:timezone":"America/Guayaquil",
    "iso:country":"EC",
    "wof:name":"San Dimas",
    "wof:placetype":"locality"
},
  "geometry": {"coordinates":[-78.99961,0.18858],"type":"Point"}
}