{
  "type": "Feature",
  "properties": {
    "gn:admin1_code":"10.0",
    "gn:admin2_code":"903.0",
    "gn:admin3_code":"90350.0",
    "gn:asciiname":"Hacienda El Triunfo",
    "gn:cc2":"EC",
    "gn:country_code":"EC",
    "gn:dem":85,
    "gn:feature_class":"P",
    "gn:feature_code":"PPL",
    "gn:name":"Hacienda El Triunfo",
    "gn:population":0,
    "gn:timezone":"America/Guayaquil",
    "iso:country":"EC",
    "wof:name":"Hacienda El Triunfo",
    "wof:placetype":"locality"
},
  "geometry": {"coordinates":[-79.68333,-2.95],"type":"Point"}
}