{
  "type": "Feature",
  "properties": {
    "gn:admin1_code":"19.0",
    "gn:admin2_code":"1801.0",
    "gn:admin3_code":"180168.0",
    "gn:asciiname":"Rosales",
    "gn:country_code":"EC",
    "gn:dem":2677,
    "gn:feature_class":"P",
    "gn:feature_code":"PPL",
    "gn:name":"Rosales",
    "gn:population":0,
    "gn:timezone":"America/Guayaquil",
    "iso:country":"EC",
    "wof:name":"Rosales",
    "wof:placetype":"locality"
},
  "geometry": {"coordinates":[-78.58333,-1.15],"type":"Point"}
}