{
  "type": "Feature",
  "properties": {
    "gn:admin1_code":"2.0",
    "gn:admin2_code":"114.0",
    "gn:admin3_code":"11450.0",
    "gn:asciiname":"Guachapala",
    "gn:country_code":"EC",
    "gn:dem":2356,
    "gn:feature_class":"P",
    "gn:feature_code":"PPL",
    "gn:name":"Guachapala",
    "gn:population":0,
    "gn:timezone":"America/Guayaquil",
    "iso:country":"EC",
    "wof:name":"Guachapala",
    "wof:placetype":"locality"
},
  "geometry": {"coordinates":[-78.71252,-2.77246],"type":"Point"}
}