{
  "type": "Feature",
  "properties": {
    "gn:admin1_code":"10.0",
    "gn:admin2_code":"919.0",
    "gn:admin3_code":"91951.0",
    "gn:asciiname":"Payana",
    "gn:country_code":"EC",
    "gn:dem":5,
    "gn:feature_class":"P",
    "gn:feature_code":"PPL",
    "gn:name":"Payana",
    "gn:population":0,
    "gn:timezone":"America/Guayaquil",
    "iso:country":"EC",
    "name:spa_x_preferred":[
        "Payana"
    ],
    "wof:name":"Payana",
    "wof:placetype":"locality"
},
  "geometry": {"coordinates":[-79.76666999999998,-1.75],"type":"Point"}
}