{
  "type": "Feature",
  "properties": {
    "gn:admin1_code":"7.0",
    "gn:admin2_code":"504.0",
    "gn:admin3_code":"50457.0",
    "gn:asciiname":"Guayacan",
    "gn:country_code":"EC",
    "gn:dem":445,
    "gn:feature_class":"P",
    "gn:feature_code":"PPL",
    "gn:name":"Guayac\u00e1n",
    "gn:population":0,
    "gn:timezone":"America/Guayaquil",
    "iso:country":"EC",
    "wof:name":"Guayacan",
    "wof:placetype":"locality"
},
  "geometry": {"coordinates":[-79.15791,-0.87614],"type":"Point"}
}