{
  "type": "Feature",
  "properties": {
    "gn:admin1_code":"10.0",
    "gn:admin2_code":"904.0",
    "gn:admin3_code":"90450.0",
    "gn:asciiname":"Guarderas",
    "gn:country_code":"EC",
    "gn:dem":34,
    "gn:feature_class":"P",
    "gn:feature_code":"PPL",
    "gn:name":"Guarderas",
    "gn:population":0,
    "gn:timezone":"America/Guayaquil",
    "iso:country":"EC",
    "wof:name":"Guarderas",
    "wof:placetype":"locality"
},
  "geometry": {"coordinates":[-79.91296,-1.41829],"type":"Point"}
}