{
  "type": "Feature",
  "properties": {
    "gn:admin1_code":"20.0",
    "gn:admin2_code":"1901.0",
    "gn:admin3_code":"190151.0",
    "gn:asciiname":"La Yamilla",
    "gn:country_code":"EC",
    "gn:dem":1634,
    "gn:feature_class":"P",
    "gn:feature_code":"PPL",
    "gn:name":"La Yamilla",
    "gn:population":0,
    "gn:timezone":"America/Guayaquil",
    "iso:country":"EC",
    "wof:name":"La Yamilla",
    "wof:placetype":"locality"
},
  "geometry": {"coordinates":[-78.94048000000002,-4.02259],"type":"Point"}
}