{
  "type": "Feature",
  "properties": {
    "iso:country":"EC",
    "name:ita_x_preferred":[
        "Cantone di El Tambo"
    ],
    "name:kat_x_preferred":[
        "\u10d4\u10da-\u10e2\u10d0\u10db\u10d1\u10dd\u10e1 \u10d9\u10d0\u10dc\u10e2\u10dd\u10dc\u10d8"
    ],
    "name:por_x_preferred":[
        "El Tambo"
    ],
    "name:que_x_preferred":[
        "Tampu kiti"
    ],
    "name:spa_x_preferred":[
        "Cant\u00f3n El Tambo"
    ],
    "name:unk_x_variant":[
        "Baquerizo"
    ],
    "name:zho_x_preferred":[
        "\u57c3\u723e\u5766\u535a\u7e23"
    ],
    "qs:gn_country":"EC",
    "qs:gn_fcode":"PPL",
    "qs:gn_pop":0,
    "qs:name":"El Tambo",
    "qs:name_adm0":"Ecuador",
    "qs:name_adm1":"Canar",
    "qs:photos":6,
    "qs:photos_1k":1,
    "qs:photos_9k":1,
    "qs:photos_9r":1,
    "qs:photos_all":6,
    "qs:photos_sr":1,
    "qs:placetype":"LocalAdmin",
    "qs:pop_sr":"0",
    "qs:woe_adm0":23424801,
    "wd:wordcount":77,
    "wof:name":"El Tambo",
    "wof:placetype":"localadmin"
},
  "geometry": {"coordinates":[-78.92783,-2.51074],"type":"Point"}
}