{
  "type": "Feature",
  "properties": {
    "gn:admin1_code":"18.0",
    "gn:admin2_code":"1702.0",
    "gn:admin3_code":"170256.0",
    "gn:asciiname":"Santo Domingo",
    "gn:country_code":"EC",
    "gn:dem":2995,
    "gn:feature_class":"P",
    "gn:feature_code":"PPL",
    "gn:name":"Santo Domingo",
    "gn:population":0,
    "gn:timezone":"America/Guayaquil",
    "iso:country":"EC",
    "wof:name":"Santo Domingo",
    "wof:placetype":"locality"
},
  "geometry": {"coordinates":[-78.11667,0.06667],"type":"Point"}
}