{
  "type": "Feature",
  "properties": {
    "iso:country":"EC",
    "name:ces_x_preferred":[
        "Ingapirca"
    ],
    "name:dan_x_preferred":[
        "Ingapirca"
    ],
    "name:deu_x_preferred":[
        "Ingapirca"
    ],
    "name:fra_x_preferred":[
        "Ingapirca"
    ],
    "name:glg_x_preferred":[
        "Ingapirca"
    ],
    "name:kat_x_preferred":[
        "\u10d8\u10dc\u10d2\u10d0\u10de\u10d8\u10e0\u10d9\u10d0"
    ],
    "name:lit_x_preferred":[
        "Ingapirka"
    ],
    "name:nld_x_preferred":[
        "Ingapirca"
    ],
    "name:nno_x_preferred":[
        "Ingapirca"
    ],
    "name:por_x_preferred":[
        "Ingapirca"
    ],
    "name:que_x_preferred":[
        "Inkapirka"
    ],
    "name:rus_x_preferred":[
        "\u0418\u043d\u0433\u0430\u043f\u0438\u0440\u043a\u0430"
    ],
    "name:spa_x_preferred":[
        "Ingapirca"
    ],
    "name:ukr_x_preferred":[
        "\u0406\u043d\u0433\u0430\u043f\u0456\u0440\u043a\u0430"
    ],
    "qs:gn_country":"EC",
    "qs:gn_fcode":"PPL",
    "qs:gn_pop":0,
    "qs:name":"Ingapirca",
    "qs:name_adm0":"Ecuador",
    "qs:name_adm1":"Canar",
    "qs:photos":2,
    "qs:photos_1k":1,
    "qs:photos_9k":1,
    "qs:photos_9r":5,
    "qs:photos_all":326,
    "qs:photos_sr":1,
    "qs:placetype":"LocalAdmin",
    "qs:pop_sr":"0",
    "qs:woe_adm0":23424801,
    "wd:wordcount":501,
    "wof:name":"Ingapirca",
    "wof:placetype":"localadmin"
},
  "geometry": {"coordinates":[-78.87741,-2.54435],"type":"Point"}
}