{
  "type": "Feature",
  "properties": {
    "gn:admin1_code":"10.0",
    "gn:asciiname":"Hacienda Vera",
    "gn:cc2":"EC",
    "gn:country_code":"EC",
    "gn:dem":90,
    "gn:feature_class":"P",
    "gn:feature_code":"PPL",
    "gn:name":"Hacienda Vera",
    "gn:population":0,
    "gn:timezone":"America/Guayaquil",
    "iso:country":"EC",
    "wof:name":"Hacienda Vera",
    "wof:placetype":"locality"
},
  "geometry": {"coordinates":[-80.25,-2.23333],"type":"Point"}
}