{
  "type": "Feature",
  "properties": {
    "gn:admin1_code":"13.0",
    "gn:admin2_code":"1203.0",
    "gn:admin3_code":"120350.0",
    "gn:asciiname":"Juntas",
    "gn:country_code":"EC",
    "gn:dem":301,
    "gn:feature_class":"P",
    "gn:feature_code":"PPL",
    "gn:name":"Juntas",
    "gn:population":0,
    "gn:timezone":"America/Guayaquil",
    "iso:country":"EC",
    "wof:name":"Juntas",
    "wof:placetype":"locality"
},
  "geometry": {"coordinates":[-79.25,-1.91667],"type":"Point"}
}