{
  "type": "Feature",
  "properties": {
    "gn:admin1_code":"6.0",
    "gn:admin2_code":"601.0",
    "gn:admin3_code":"60150.0",
    "gn:asciiname":"Hacienda San Jose",
    "gn:cc2":"EC",
    "gn:country_code":"EC",
    "gn:dem":2749,
    "gn:feature_class":"P",
    "gn:feature_code":"PPL",
    "gn:name":"Hacienda San Jos\u00e9",
    "gn:population":0,
    "gn:timezone":"America/Guayaquil",
    "iso:country":"EC",
    "wof:name":"Hacienda San Jose",
    "wof:placetype":"locality"
},
  "geometry": {"coordinates":[-78.65000000000001,-1.68333],"type":"Point"}
}