{
  "type": "Feature",
  "properties": {
    "gn:admin1_code":"13.0",
    "gn:admin2_code":"1206.0",
    "gn:admin3_code":"120651.0",
    "gn:asciiname":"Ricaurte",
    "gn:country_code":"EC",
    "gn:dem":10,
    "gn:feature_class":"P",
    "gn:feature_code":"PPL",
    "gn:name":"Ricaurte",
    "gn:population":0,
    "gn:timezone":"America/Guayaquil",
    "iso:country":"EC",
    "name:bar_x_preferred":[
        "Ricaurte"
    ],
    "name:ceb_x_preferred":[
        "Ricaurte"
    ],
    "name:deu_x_preferred":[
        "Ricaurte"
    ],
    "name:fra_x_preferred":[
        "Ricaurte"
    ],
    "name:ita_x_preferred":[
        "Ricaurte"
    ],
    "name:nld_x_preferred":[
        "Ricaurte"
    ],
    "name:por_x_preferred":[
        "Ricaurte"
    ],
    "name:sco_x_preferred":[
        "Ricaurte"
    ],
    "name:spa_x_preferred":[
        "Ricaurte"
    ],
    "name:swe_x_preferred":[
        "Ricaurte"
    ],
    "wof:name":"Ricaurte",
    "wof:placetype":"locality"
},
  "geometry": {"coordinates":[-79.43735,-1.57838],"type":"Point"}
}