{
  "type": "Feature",
  "properties": {
    "gn:admin1_code":"11.0",
    "gn:admin2_code":"1003.0",
    "gn:admin3_code":"100353.0",
    "gn:asciiname":"Hacienda Peribuela",
    "gn:country_code":"EC",
    "gn:dem":2465,
    "gn:feature_class":"P",
    "gn:feature_code":"PPL",
    "gn:name":"Hacienda Peribuela",
    "gn:population":0,
    "gn:timezone":"America/Guayaquil",
    "iso:country":"EC",
    "wof:name":"Hacienda Peribuela",
    "wof:placetype":"locality"
},
  "geometry": {"coordinates":[-78.25811,0.38423],"type":"Point"}
}