{
  "type": "Feature",
  "properties": {
    "gn:admin1_code":"12.0",
    "gn:admin2_code":"1113.0",
    "gn:admin3_code":"111356.0",
    "gn:asciiname":"Chaguarhuayco",
    "gn:country_code":"EC",
    "gn:dem":279,
    "gn:feature_class":"P",
    "gn:feature_code":"PPL",
    "gn:name":"Chaguarhuayco",
    "gn:population":0,
    "gn:timezone":"America/Guayaquil",
    "iso:country":"EC",
    "wof:name":"Chaguarhuayco",
    "wof:placetype":"locality"
},
  "geometry": {"coordinates":[-80.31681,-4.02],"type":"Point"}
}