{
  "type": "Feature",
  "properties": {
    "gn:admin1_code":"7.0",
    "gn:admin2_code":"501.0",
    "gn:admin3_code":"50152.0",
    "gn:asciiname":"Hacienda Putzalahua",
    "gn:country_code":"EC",
    "gn:dem":3453,
    "gn:feature_class":"P",
    "gn:feature_code":"PPL",
    "gn:name":"Hacienda Putzalahua",
    "gn:population":0,
    "gn:timezone":"America/Guayaquil",
    "iso:country":"EC",
    "wof:name":"Hacienda Putzalahua",
    "wof:placetype":"locality"
},
  "geometry": {"coordinates":[-78.56233,-0.96402],"type":"Point"}
}