{
  "type": "Feature",
  "properties": {
    "gn:admin1_code":"10.0",
    "gn:admin2_code":"916.0",
    "gn:admin3_code":"91650.0",
    "gn:asciiname":"Maranon",
    "gn:country_code":"EC",
    "gn:dem":5,
    "gn:feature_class":"P",
    "gn:feature_code":"PPL",
    "gn:name":"Mara\u00f1\u00f3n",
    "gn:population":0,
    "gn:timezone":"America/Guayaquil",
    "iso:country":"EC",
    "wof:name":"Maranon",
    "wof:placetype":"locality"
},
  "geometry": {"coordinates":[-79.78333000000001,-1.88333],"type":"Point"}
}