{
  "type": "Feature",
  "properties": {
    "iso:country":"EC",
    "qs:gn_country":"EC",
    "qs:gn_fcode":"PPL",
    "qs:gn_pop":0,
    "qs:name":"R\u00edo Verde",
    "qs:name_adm0":"Ecuador",
    "qs:name_adm1":"Tungurahua",
    "qs:photos":76,
    "qs:photos_1k":15,
    "qs:photos_9k":1,
    "qs:photos_9r":3,
    "qs:photos_all":76,
    "qs:photos_sr":3,
    "qs:placetype":"Town",
    "qs:pop_sr":"0",
    "qs:woe_adm0":23424801,
    "wof:name":"R\u00edo Verde",
    "wof:placetype":"locality"
},
  "geometry": {"coordinates":[-78.3006,-1.40292],"type":"Point"}
}