{
  "type": "Feature",
  "properties": {
    "iso:country":"EC",
    "qs:gn_country":"EC",
    "qs:gn_fcode":"PPL",
    "qs:gn_pop":0,
    "qs:name":"San Pablo",
    "qs:name_adm0":"Ecuador",
    "qs:name_adm1":"Santa Elena",
    "qs:photos":111,
    "qs:photos_1k":22,
    "qs:photos_9k":1,
    "qs:photos_9r":3,
    "qs:photos_all":111,
    "qs:photos_sr":3,
    "qs:placetype":"Town",
    "qs:pop_sr":"0",
    "qs:woe_adm0":23424801,
    "wof:name":"San Pablo",
    "wof:placetype":"locality"
},
  "geometry": {"coordinates":[-80.77383,-2.14192],"type":"Point"}
}