{
  "type": "Feature",
  "properties": {
    "iso:country":"EC",
    "name:bre_x_preferred":[
        "San Pablo"
    ],
    "name:cat_x_preferred":[
        "San Pablo"
    ],
    "name:ceb_x_preferred":[
        "San Pablo"
    ],
    "name:ces_x_preferred":[
        "San Pablo"
    ],
    "name:deu_x_preferred":[
        "San Pablo"
    ],
    "name:fas_x_preferred":[
        "\u0633\u0627\u0646 \u067e\u0627\u0628\u0644\u0648"
    ],
    "name:fra_x_preferred":[
        "San Pablo"
    ],
    "name:ilo_x_preferred":[
        "San Pablo"
    ],
    "name:ita_x_preferred":[
        "San Pablo"
    ],
    "name:jpn_x_preferred":[
        "\u30b5\u30f3\u30fb\u30d1\u30d6\u30ed"
    ],
    "name:kor_x_preferred":[
        "\uc0b0\ud30c\ube14\ub85c"
    ],
    "name:nds_x_preferred":[
        "San Pablo"
    ],
    "name:nld_x_preferred":[
        "San Pablo"
    ],
    "name:pol_x_preferred":[
        "San Pablo"
    ],
    "name:por_x_preferred":[
        "San Pablo"
    ],
    "name:que_x_preferred":[
        "San Pawlu"
    ],
    "name:rus_x_preferred":[
        "\u0421\u0430\u043d-\u041f\u0430\u0431\u043b\u043e"
    ],
    "name:sco_x_preferred":[
        "San Pablo"
    ],
    "name:spa_x_preferred":[
        "San Pablo"
    ],
    "name:srp_x_preferred":[
        "\u0421\u0430\u043d \u041f\u0430\u0431\u043b\u043e"
    ],
    "name:swe_x_preferred":[
        "San Pablo"
    ],
    "name:tgl_x_preferred":[
        "San Pablo"
    ],
    "name:vol_x_preferred":[
        "San Pablo"
    ],
    "name:war_x_preferred":[
        "San Pablo"
    ],
    "qs:gn_country":"EC",
    "qs:gn_fcode":"PPL",
    "qs:gn_pop":0,
    "qs:name":"San Pablo",
    "qs:name_adm0":"Ecuador",
    "qs:name_adm1":"Santa Elena",
    "qs:photos":111,
    "qs:photos_1k":22,
    "qs:photos_9k":1,
    "qs:photos_9r":3,
    "qs:photos_all":111,
    "qs:photos_sr":3,
    "qs:placetype":"Town",
    "qs:pop_sr":"0",
    "qs:woe_adm0":23424801,
    "wof:name":"San Pablo",
    "wof:placetype":"locality"
},
  "geometry": {"coordinates":[-80.77383,-2.14192],"type":"Point"}
}