{
  "type": "Feature",
  "properties": {
    "gn:admin1_code":"10.0",
    "gn:asciiname":"Montanita",
    "gn:country_code":"EC",
    "gn:dem":5,
    "gn:feature_class":"P",
    "gn:feature_code":"PPL",
    "gn:name":"Monta\u00f1ita",
    "gn:population":0,
    "gn:timezone":"America/Guayaquil",
    "iso:country":"EC",
    "wof:name":"Montanita",
    "wof:placetype":"locality"
},
  "geometry": {"coordinates":[-80.75,-1.83333],"type":"Point"}
}