{
  "type": "Feature",
  "properties": {
    "gn:admin1_code":"7.0",
    "gn:admin2_code":"504.0",
    "gn:admin3_code":"50450.0",
    "gn:asciiname":"Hacienda Chaupi",
    "gn:country_code":"EC",
    "gn:dem":3242,
    "gn:feature_class":"P",
    "gn:feature_code":"PPL",
    "gn:name":"Hacienda Chaupi",
    "gn:population":0,
    "gn:timezone":"America/Guayaquil",
    "iso:country":"EC",
    "wof:name":"Hacienda Chaupi",
    "wof:placetype":"locality"
},
  "geometry": {"coordinates":[-78.7513,-0.95932],"type":"Point"}
}