{
  "type": "Feature",
  "properties": {
    "gn:admin1_code":"4.0",
    "gn:admin2_code":"303.0",
    "gn:admin3_code":"30363.0",
    "gn:asciiname":"Chilchil",
    "gn:country_code":"EC",
    "gn:dem":1136,
    "gn:feature_class":"P",
    "gn:feature_code":"PPL",
    "gn:name":"Chilchil",
    "gn:population":0,
    "gn:timezone":"America/Guayaquil",
    "iso:country":"EC",
    "wof:name":"Chilchil",
    "wof:placetype":"locality"
},
  "geometry": {"coordinates":[-79.16667,-2.45],"type":"Point"}
}