{
  "type": "Feature",
  "properties": {
    "gn:admin1_code":"18.0",
    "gn:admin2_code":"1702.0",
    "gn:admin3_code":"170251.0",
    "gn:asciiname":"Ascazubi Alto",
    "gn:country_code":"EC",
    "gn:dem":2643,
    "gn:feature_class":"P",
    "gn:feature_code":"PPL",
    "gn:name":"Asc\u00e1zubi Alto",
    "gn:population":0,
    "gn:timezone":"America/Guayaquil",
    "iso:country":"EC",
    "wof:name":"Ascazubi Alto",
    "wof:placetype":"locality"
},
  "geometry": {"coordinates":[-78.28333000000001,-0.08333],"type":"Point"}
}