{
  "type": "Feature",
  "properties": {
    "gn:admin1_code":"22.0",
    "gn:admin2_code":"2104.0",
    "gn:admin3_code":"210450.0",
    "gn:asciiname":"Cushmas",
    "gn:country_code":"EC",
    "gn:dem":271,
    "gn:feature_class":"P",
    "gn:feature_code":"PPL",
    "gn:name":"Cushmas",
    "gn:population":0,
    "gn:timezone":"America/Guayaquil",
    "iso:country":"EC",
    "wof:name":"Cushmas",
    "wof:placetype":"locality"
},
  "geometry": {"coordinates":[-76.66667,-0.11667],"type":"Point"}
}