{
  "type": "Feature",
  "properties": {
    "gn:admin1_code":"8.0",
    "gn:admin2_code":"712.0",
    "gn:admin3_code":"71253.0",
    "gn:asciiname":"La Avanzada",
    "gn:cc2":"EC",
    "gn:country_code":"EC",
    "gn:dem":117,
    "gn:feature_class":"P",
    "gn:feature_code":"PPL",
    "gn:name":"La Avanzada",
    "gn:population":0,
    "gn:timezone":"America/Guayaquil",
    "iso:country":"EC",
    "wof:name":"La Avanzada",
    "wof:placetype":"locality"
},
  "geometry": {"coordinates":[-79.98333000000002,-3.55],"type":"Point"}
}