{
  "type": "Feature",
  "properties": {
    "gn:admin1_code":"10.0",
    "gn:asciiname":"Cienaga de Afuera",
    "gn:cc2":"EC",
    "gn:country_code":"EC",
    "gn:dem":138,
    "gn:feature_class":"P",
    "gn:feature_code":"PPL",
    "gn:name":"Ci\u00e9naga de Afuera",
    "gn:population":0,
    "gn:timezone":"America/Guayaquil",
    "iso:country":"EC",
    "wof:name":"Cienaga de Afuera",
    "wof:placetype":"locality"
},
  "geometry": {"coordinates":[-80.36667,-2.33333],"type":"Point"}
}