{
  "type": "Feature",
  "properties": {
    "gn:admin1_code":"9.0",
    "gn:admin2_code":"807.0",
    "gn:admin3_code":"80754.0",
    "gn:asciiname":"Bocana",
    "gn:country_code":"EC",
    "gn:dem":19,
    "gn:feature_class":"P",
    "gn:feature_code":"PPL",
    "gn:name":"Bocana",
    "gn:population":0,
    "gn:timezone":"America/Guayaquil",
    "iso:country":"EC",
    "name:ceb_x_preferred":[
        "Bocana"
    ],
    "name:por_x_preferred":[
        "Bocana"
    ],
    "name:rus_x_preferred":[
        "Bocana"
    ],
    "name:spa_x_preferred":[
        "Bocana"
    ],
    "name:swe_x_preferred":[
        "Bocana"
    ],
    "name:ukr_x_preferred":[
        "Bocana"
    ],
    "name:vie_x_preferred":[
        "Bocana"
    ],
    "name:war_x_preferred":[
        "Bocana"
    ],
    "wof:name":"Bocana",
    "wof:placetype":"locality"
},
  "geometry": {"coordinates":[-79.30046,1.07997],"type":"Point"}
}