{
  "type": "Feature",
  "properties": {
    "gn:admin1_code":"9.0",
    "gn:admin2_code":"804.0",
    "gn:admin3_code":"80454.0",
    "gn:asciiname":"Viche",
    "gn:country_code":"EC",
    "gn:dem":35,
    "gn:feature_class":"P",
    "gn:feature_code":"PPL",
    "gn:name":"Viche",
    "gn:population":0,
    "gn:timezone":"America/Guayaquil",
    "iso:country":"EC",
    "wof:name":"Viche",
    "wof:placetype":"locality"
},
  "geometry": {"coordinates":[-79.54084,0.65848],"type":"Point"}
}