{
  "type": "Feature",
  "properties": {
    "gn:admin1_code":"18.0",
    "gn:admin2_code":"1701.0",
    "gn:admin3_code":"170160.0",
    "gn:asciiname":"Hacienda San Rafael",
    "gn:cc2":"EC",
    "gn:country_code":"EC",
    "gn:dem":2919,
    "gn:feature_class":"P",
    "gn:feature_code":"PPL",
    "gn:name":"Hacienda San Rafael",
    "gn:population":0,
    "gn:timezone":"America/Guayaquil",
    "iso:country":"EC",
    "wof:name":"Hacienda San Rafael",
    "wof:placetype":"locality"
},
  "geometry": {"coordinates":[-78.26666999999998,-0.13333],"type":"Point"}
}