{
  "type": "Feature",
  "properties": {
    "gn:admin1_code":"10.0",
    "gn:asciiname":"Cangrejo",
    "gn:country_code":"EC",
    "gn:dem":14,
    "gn:feature_class":"P",
    "gn:feature_code":"PPL",
    "gn:name":"Cangrejo",
    "gn:population":0,
    "gn:timezone":"America/Guayaquil",
    "iso:country":"EC",
    "wof:name":"Cangrejo",
    "wof:placetype":"locality"
},
  "geometry": {"coordinates":[-80.76666999999998,-2.13333],"type":"Point"}
}