{
  "type": "Feature",
  "properties": {
    "gn:admin1_code":"18.0",
    "gn:admin2_code":"1701.0",
    "gn:admin3_code":"170150.0",
    "gn:asciiname":"Cotocollao",
    "gn:country_code":"EC",
    "gn:dem":2871,
    "gn:feature_class":"P",
    "gn:feature_code":"PPL",
    "gn:name":"Cotocollao",
    "gn:population":0,
    "gn:timezone":"America/Guayaquil",
    "iso:country":"EC",
    "wof:name":"Cotocollao",
    "wof:placetype":"locality"
},
  "geometry": {"coordinates":[-78.50367,-0.12291],"type":"Point"}
}