{
  "type": "Feature",
  "properties": {
    "gn:admin1_code":"2.0",
    "gn:admin2_code":"115.0",
    "gn:admin3_code":"11550.0",
    "gn:asciiname":"Chaupitranca",
    "gn:country_code":"EC",
    "gn:dem":733,
    "gn:feature_class":"P",
    "gn:feature_code":"PPL",
    "gn:name":"Chaupitranca",
    "gn:population":0,
    "gn:timezone":"America/Guayaquil",
    "iso:country":"EC",
    "wof:name":"Chaupitranca",
    "wof:placetype":"locality"
},
  "geometry": {"coordinates":[-79.56667,-3.01667],"type":"Point"}
}