{
  "type": "Feature",
  "properties": {
    "gn:admin1_code":"2.0",
    "gn:admin2_code":"101.0",
    "gn:admin3_code":"10162.0",
    "gn:asciiname":"Carishao",
    "gn:country_code":"EC",
    "gn:dem":2546,
    "gn:feature_class":"P",
    "gn:feature_code":"PPL",
    "gn:name":"Carishao",
    "gn:population":0,
    "gn:timezone":"America/Guayaquil",
    "iso:country":"EC",
    "wof:name":"Carishao",
    "wof:placetype":"locality"
},
  "geometry": {"coordinates":[-78.95,-2.86667],"type":"Point"}
}