{
  "type": "Feature",
  "properties": {
    "gn:admin1_code":"15.0",
    "gn:admin2_code":"1405.0",
    "gn:admin3_code":"140556.0",
    "gn:asciiname":"Tayuza",
    "gn:country_code":"EC",
    "gn:dem":588,
    "gn:feature_class":"P",
    "gn:feature_code":"PPL",
    "gn:name":"Tayuza",
    "gn:population":0,
    "gn:timezone":"America/Guayaquil",
    "iso:country":"EC",
    "wof:name":"Tayuza",
    "wof:placetype":"locality"
},
  "geometry": {"coordinates":[-78.23801999999998,-2.69908],"type":"Point"}
}