{
  "type": "Feature",
  "properties": {
    "iso:country":"EC",
    "qs:gn_pop":0,
    "qs:name":"Montecristi",
    "qs:name_adm0":"Ecuador",
    "qs:name_adm1":"Manabi",
    "qs:photos":4,
    "qs:photos_1k":1,
    "qs:photos_9k":1,
    "qs:photos_9r":4,
    "qs:photos_all":172,
    "qs:photos_sr":1,
    "qs:placetype":"LocalAdmin",
    "qs:pop_sr":"0",
    "qs:woe_adm0":23424801,
    "wof:name":"Montecristi",
    "wof:placetype":"localadmin"
},
  "geometry": {"coordinates":[-80.65441,-1.041841],"type":"Point"}
}