{
  "type": "Feature",
  "properties": {
    "gn:admin1_code":"19.0",
    "gn:admin2_code":"1801.0",
    "gn:admin3_code":"180153.0",
    "gn:asciiname":"Hacienda Chaupi",
    "gn:cc2":"EC",
    "gn:country_code":"EC",
    "gn:dem":2856,
    "gn:feature_class":"P",
    "gn:feature_code":"PPL",
    "gn:name":"Hacienda Chaupi",
    "gn:population":0,
    "gn:timezone":"America/Guayaquil",
    "iso:country":"EC",
    "wof:name":"Hacienda Chaupi",
    "wof:placetype":"locality"
},
  "geometry": {"coordinates":[-78.61667,-1.16667],"type":"Point"}
}