{
  "type": "Feature",
  "properties": {
    "gn:admin1_code":"7.0",
    "gn:admin2_code":"501.0",
    "gn:admin3_code":"50152.0",
    "gn:asciiname":"Hacienda Guanilin de Leon",
    "gn:country_code":"EC",
    "gn:dem":2800,
    "gn:feature_class":"P",
    "gn:feature_code":"PPL",
    "gn:name":"Hacienda Guanil\u00edn de Le\u00f3n",
    "gn:population":0,
    "gn:timezone":"America/Guayaquil",
    "iso:country":"EC",
    "wof:name":"Hacienda Guanilin de Leon",
    "wof:placetype":"locality"
},
  "geometry": {"coordinates":[-78.58280000000001,-0.97657],"type":"Point"}
}