{
  "type": "Feature",
  "properties": {
    "iso:country":"EC",
    "name:deu_x_preferred":[
        "San Antonio de Pichincha"
    ],
    "name:lit_x_preferred":[
        "San Antonio de Pi\u010din\u010da"
    ],
    "name:que_x_preferred":[
        "Lulumpampa kitilli"
    ],
    "name:spa_x_preferred":[
        "San Antonio"
    ],
    "name:unk_x_variant":[
        "San Antonio de Pichincha"
    ],
    "qs:gn_country":"EC",
    "qs:gn_fcode":"PPL",
    "qs:gn_pop":0,
    "qs:name":"San Antonio",
    "qs:name_adm0":"Ecuador",
    "qs:name_adm1":"Pichincha",
    "qs:photos":1168,
    "qs:photos_1k":237,
    "qs:photos_9k":5,
    "qs:photos_9r":7,
    "qs:photos_all":1168,
    "qs:photos_sr":11,
    "qs:placetype":"Town",
    "qs:pop_sr":"0",
    "qs:woe_adm0":23424801,
    "wd:wordcount":170,
    "wof:name":"San Antonio",
    "wof:placetype":"locality"
},
  "geometry": {"coordinates":[-78.44687999999999,-0.00662],"type":"Point"}
}