{
  "type": "Feature",
  "properties": {
    "gn:admin1_code":"6.0",
    "gn:admin2_code":"601.0",
    "gn:admin3_code":"60161.0",
    "gn:asciiname":"Hacienda El Troje",
    "gn:country_code":"EC",
    "gn:dem":2724,
    "gn:feature_class":"P",
    "gn:feature_code":"PPL",
    "gn:name":"Hacienda El Troje",
    "gn:population":0,
    "gn:timezone":"America/Guayaquil",
    "iso:country":"EC",
    "wof:name":"Hacienda El Troje",
    "wof:placetype":"locality"
},
  "geometry": {"coordinates":[-78.61784,-1.69732],"type":"Point"}
}