{
  "type": "Feature",
  "properties": {
    "gn:admin1_code":"15.0",
    "gn:admin2_code":"1409.0",
    "gn:admin3_code":"140953.0",
    "gn:asciiname":"Tsentzakentza",
    "gn:country_code":"EC",
    "gn:dem":284,
    "gn:feature_class":"P",
    "gn:feature_code":"PPL",
    "gn:name":"Tsentzakentza",
    "gn:population":0,
    "gn:timezone":"America/Guayaquil",
    "iso:country":"EC",
    "wof:name":"Tsentzakentza",
    "wof:placetype":"locality"
},
  "geometry": {"coordinates":[-77.40604,-2.54354],"type":"Point"}
}