{
  "type": "Feature",
  "properties": {
    "gn:admin1_code":"12.0",
    "gn:admin2_code":"1103.0",
    "gn:admin3_code":"110351.0",
    "gn:asciiname":"El Tambo",
    "gn:country_code":"EC",
    "gn:dem":1596,
    "gn:feature_class":"P",
    "gn:feature_code":"PPL",
    "gn:name":"El Tambo",
    "gn:population":0,
    "gn:timezone":"America/Guayaquil",
    "iso:country":"EC",
    "name:ceb_x_preferred":[
        "El Tambo"
    ],
    "name:fas_x_preferred":[
        "\u0627\u0644 \u062a\u0627\u0645\u0628\u0648"
    ],
    "name:fra_x_preferred":[
        "El Tambo"
    ],
    "name:ita_x_preferred":[
        "El Tambo"
    ],
    "name:nld_x_preferred":[
        "El Tambo"
    ],
    "name:swe_x_preferred":[
        "El Tambo"
    ],
    "wof:name":"El Tambo",
    "wof:placetype":"locality"
},
  "geometry": {"coordinates":[-79.30824,-4.07249],"type":"Point"}
}