{
  "type": "Feature",
  "properties": {
    "gn:admin1_code":"12.0",
    "gn:admin2_code":"1108.0",
    "gn:admin3_code":"110850.0",
    "gn:asciiname":"Hacienda Senegal",
    "gn:cc2":"EC",
    "gn:country_code":"EC",
    "gn:dem":900,
    "gn:feature_class":"P",
    "gn:feature_code":"PPL",
    "gn:name":"Hacienda Senegal",
    "gn:population":0,
    "gn:timezone":"America/Guayaquil",
    "iso:country":"EC",
    "wof:name":"Hacienda Senegal",
    "wof:placetype":"locality"
},
  "geometry": {"coordinates":[-79.88333,-4.36667],"type":"Point"}
}