{
  "type": "Feature",
  "properties": {
    "gn:admin1_code":"12.0",
    "gn:admin2_code":"1113.0",
    "gn:admin3_code":"111350.0",
    "gn:asciiname":"El Huasimo",
    "gn:country_code":"EC",
    "gn:dem":151,
    "gn:feature_class":"P",
    "gn:feature_code":"PPL",
    "gn:name":"El Hu\u00e1simo",
    "gn:population":0,
    "gn:timezone":"America/Guayaquil",
    "iso:country":"EC",
    "wof:name":"El Huasimo",
    "wof:placetype":"locality"
},
  "geometry": {"coordinates":[-80.31667,-4.43333],"type":"Point"}
}