{
  "type": "Feature",
  "properties": {
    "gn:admin1_code":"10.0",
    "gn:admin2_code":"910.0",
    "gn:admin3_code":"91050.0",
    "gn:asciiname":"Hacienda Las Pilas",
    "gn:country_code":"EC",
    "gn:dem":20,
    "gn:feature_class":"P",
    "gn:feature_code":"PPL",
    "gn:name":"Hacienda Las Pilas",
    "gn:population":0,
    "gn:timezone":"America/Guayaquil",
    "iso:country":"EC",
    "wof:name":"Hacienda Las Pilas",
    "wof:placetype":"locality"
},
  "geometry": {"coordinates":[-79.57323000000002,-2.22545],"type":"Point"}
}