{
  "type": "Feature",
  "properties": {
    "gn:admin1_code":"11.0",
    "gn:admin2_code":"1004.0",
    "gn:admin3_code":"100455.0",
    "gn:asciiname":"Quillopamba",
    "gn:country_code":"EC",
    "gn:dem":2740,
    "gn:feature_class":"P",
    "gn:feature_code":"PPL",
    "gn:name":"Quillopamba",
    "gn:population":0,
    "gn:timezone":"America/Guayaquil",
    "iso:country":"EC",
    "wof:name":"Quillopamba",
    "wof:placetype":"locality"
},
  "geometry": {"coordinates":[-78.32384999999999,0.25926],"type":"Point"}
}