{
  "type": "Feature",
  "properties": {
    "gn:admin1_code":"20.0",
    "gn:admin2_code":"1903.0",
    "gn:admin3_code":"190352.0",
    "gn:asciiname":"Campamento El Mirador",
    "gn:country_code":"EC",
    "gn:dem":2496,
    "gn:feature_class":"P",
    "gn:feature_code":"PPL",
    "gn:name":"Campamento El Mirador",
    "gn:population":0,
    "gn:timezone":"America/Guayaquil",
    "iso:country":"EC",
    "wof:name":"Campamento El Mirador",
    "wof:placetype":"locality"
},
  "geometry": {"coordinates":[-78.77,-4.63917],"type":"Point"}
}