{
  "type": "Feature",
  "properties": {
    "gn:admin1_code":"3.0",
    "gn:admin2_code":"201.0",
    "gn:admin3_code":"20157.0",
    "gn:asciiname":"San Simon",
    "gn:country_code":"EC",
    "gn:dem":2650,
    "gn:feature_class":"P",
    "gn:feature_code":"PPL",
    "gn:name":"San Sim\u00f3n",
    "gn:population":0,
    "gn:timezone":"America/Guayaquil",
    "iso:country":"EC",
    "wof:name":"San Simon",
    "wof:placetype":"locality"
},
  "geometry": {"coordinates":[-78.99011999999998,-1.64114],"type":"Point"}
}