{
  "type": "Feature",
  "properties": {
    "gn:admin1_code":"18.0",
    "gn:asciiname":"Tangaiche",
    "gn:country_code":"EC",
    "gn:dem":2676,
    "gn:feature_class":"P",
    "gn:feature_code":"PPL",
    "gn:name":"Tangaiche",
    "gn:population":0,
    "gn:timezone":"America/Guayaquil",
    "iso:country":"EC",
    "wof:name":"Tangaiche",
    "wof:placetype":"locality"
},
  "geometry": {"coordinates":[-78.58771,-1.28882],"type":"Point"}
}