{
  "type": "Feature",
  "properties": {
    "gn:admin1_code":"18.0",
    "gn:admin2_code":"1702.0",
    "gn:admin3_code":"170256.0",
    "gn:asciiname":"San Miguel del Prado",
    "gn:country_code":"EC",
    "gn:dem":2979,
    "gn:feature_class":"P",
    "gn:feature_code":"PPL",
    "gn:name":"San Miguel del Prado",
    "gn:population":0,
    "gn:timezone":"America/Guayaquil",
    "iso:country":"EC",
    "wof:name":"San Miguel del Prado",
    "wof:placetype":"locality"
},
  "geometry": {"coordinates":[-78.16413,0.11317],"type":"Point"}
}