{
  "type": "Feature",
  "properties": {
    "gn:admin1_code":"18.0",
    "gn:admin2_code":"1701.0",
    "gn:admin3_code":"170171.0",
    "gn:asciiname":"Calera",
    "gn:country_code":"EC",
    "gn:dem":2557,
    "gn:feature_class":"P",
    "gn:feature_code":"PPL",
    "gn:name":"Calera",
    "gn:population":0,
    "gn:timezone":"America/Guayaquil",
    "iso:country":"EC",
    "name:cat_x_preferred":[
        "Calera"
    ],
    "name:ceb_x_preferred":[
        "Calera"
    ],
    "name:deu_x_preferred":[
        "Calera"
    ],
    "name:ido_x_preferred":[
        "Calera"
    ],
    "name:ita_x_preferred":[
        "Calera"
    ],
    "name:nld_x_preferred":[
        "Calera"
    ],
    "name:pol_x_preferred":[
        "Calera"
    ],
    "name:por_x_preferred":[
        "Calera"
    ],
    "name:ron_x_preferred":[
        "Calera"
    ],
    "name:rus_x_preferred":[
        "\u041a\u0430\u043b\u0435\u0440\u0430"
    ],
    "name:sco_x_preferred":[
        "Calera"
    ],
    "name:spa_x_preferred":[
        "Calera"
    ],
    "name:srp_x_preferred":[
        "\u041a\u0430\u043b\u0435\u0440\u0430"
    ],
    "name:swe_x_preferred":[
        "Calera"
    ],
    "name:vol_x_preferred":[
        "Calera"
    ],
    "wof:name":"Calera",
    "wof:placetype":"locality"
},
  "geometry": {"coordinates":[-78.56667,-0.03333],"type":"Point"}
}