{
  "type": "Feature",
  "properties": {
    "gn:admin1_code":"10.0",
    "gn:admin2_code":"922.0",
    "gn:admin3_code":"92250.0",
    "gn:asciiname":"Hacienda Delicia",
    "gn:country_code":"EC",
    "gn:dem":26,
    "gn:feature_class":"P",
    "gn:feature_code":"PPL",
    "gn:name":"Hacienda Delicia",
    "gn:population":0,
    "gn:timezone":"America/Guayaquil",
    "iso:country":"EC",
    "wof:name":"Hacienda Delicia",
    "wof:placetype":"locality"
},
  "geometry": {"coordinates":[-79.38605,-1.9978],"type":"Point"}
}