{
  "type": "Feature",
  "properties": {
    "gn:admin1_code":"11.0",
    "gn:admin2_code":"1002.0",
    "gn:admin3_code":"100251.0",
    "gn:asciiname":"Hacienda Santiago de Monjas",
    "gn:country_code":"EC",
    "gn:dem":2001,
    "gn:feature_class":"P",
    "gn:feature_code":"PPL",
    "gn:name":"Hacienda Santiago de Monjas",
    "gn:population":0,
    "gn:timezone":"America/Guayaquil",
    "iso:country":"EC",
    "wof:name":"Hacienda Santiago de Monjas",
    "wof:placetype":"locality"
},
  "geometry": {"coordinates":[-78.16112,0.3894],"type":"Point"}
}