{
  "type": "Feature",
  "properties": {
    "gn:admin1_code":"6.0",
    "gn:admin2_code":"602.0",
    "gn:admin3_code":"60253.0",
    "gn:asciiname":"Guasuntos",
    "gn:country_code":"EC",
    "gn:dem":2522,
    "gn:feature_class":"P",
    "gn:feature_code":"PPL",
    "gn:name":"Guasuntos",
    "gn:population":0,
    "gn:timezone":"America/Guayaquil",
    "iso:country":"EC",
    "wof:name":"Guasuntos",
    "wof:placetype":"locality"
},
  "geometry": {"coordinates":[-78.81329000000002,-2.23255],"type":"Point"}
}