{
  "type": "Feature",
  "properties": {
    "gn:admin1_code":"9.0",
    "gn:admin2_code":"807.0",
    "gn:admin3_code":"80753.0",
    "gn:asciiname":"Lagartillo",
    "gn:country_code":"EC",
    "gn:dem":8,
    "gn:feature_class":"P",
    "gn:feature_code":"PPL",
    "gn:name":"Lagartillo",
    "gn:population":0,
    "gn:timezone":"America/Guayaquil",
    "iso:country":"EC",
    "wof:name":"Lagartillo",
    "wof:placetype":"locality"
},
  "geometry": {"coordinates":[-79.25,1.05833],"type":"Point"}
}