{
  "type": "Feature",
  "properties": {
    "gn:admin1_code":"18.0",
    "gn:admin2_code":"1701.0",
    "gn:admin3_code":"170156.0",
    "gn:asciiname":"Hacienda Santo Domingo",
    "gn:country_code":"EC",
    "gn:dem":2691,
    "gn:feature_class":"P",
    "gn:feature_code":"PPL",
    "gn:name":"Hacienda Santo Domingo",
    "gn:population":0,
    "gn:timezone":"America/Guayaquil",
    "iso:country":"EC",
    "wof:name":"Hacienda Santo Domingo",
    "wof:placetype":"locality"
},
  "geometry": {"coordinates":[-78.48539,-0.26281],"type":"Point"}
}