{
  "type": "Feature",
  "properties": {
    "gn:admin1_code":"10.0",
    "gn:admin2_code":"928.0",
    "gn:admin3_code":"92850.0",
    "gn:asciiname":"Zamora",
    "gn:cc2":"EC",
    "gn:country_code":"EC",
    "gn:dem":23,
    "gn:feature_class":"P",
    "gn:feature_code":"PPL",
    "gn:name":"Zamora",
    "gn:population":0,
    "gn:timezone":"America/Guayaquil",
    "iso:country":"EC",
    "wof:name":"Zamora",
    "wof:placetype":"locality"
},
  "geometry": {"coordinates":[-80.11667,-1.83333],"type":"Point"}
}