{
  "type": "Feature",
  "properties": {
    "gn:admin1_code":"10.0",
    "gn:admin2_code":"911.0",
    "gn:admin3_code":"91153.0",
    "gn:asciiname":"Santa Rosa de Flandes",
    "gn:country_code":"EC",
    "gn:dem":4,
    "gn:feature_class":"P",
    "gn:feature_code":"PPL",
    "gn:name":"Santa Rosa de Flandes",
    "gn:population":0,
    "gn:timezone":"America/Guayaquil",
    "iso:country":"EC",
    "wof:name":"Santa Rosa de Flandes",
    "wof:placetype":"locality"
},
  "geometry": {"coordinates":[-79.64654,-2.63465],"type":"Point"}
}