{
  "type": "Feature",
  "properties": {
    "gn:admin1_code":"6.0",
    "gn:admin2_code":"601.0",
    "gn:admin3_code":"60151.0",
    "gn:asciiname":"Hacienda Amula",
    "gn:country_code":"EC",
    "gn:dem":3478,
    "gn:feature_class":"P",
    "gn:feature_code":"PPL",
    "gn:name":"Hacienda Amul\u00e1",
    "gn:population":0,
    "gn:timezone":"America/Guayaquil",
    "iso:country":"EC",
    "wof:name":"Hacienda Amula",
    "wof:placetype":"locality"
},
  "geometry": {"coordinates":[-78.72454,-1.69354],"type":"Point"}
}