{
  "type": "Feature",
  "properties": {
    "gn:admin1_code":"11.0",
    "gn:admin2_code":"1003.0",
    "gn:admin3_code":"100353.0",
    "gn:asciiname":"Pinan",
    "gn:country_code":"EC",
    "gn:dem":3148,
    "gn:feature_class":"P",
    "gn:feature_code":"PPL",
    "gn:name":"Pi\u00f1\u00e1n",
    "gn:population":0,
    "gn:timezone":"America/Guayaquil",
    "iso:country":"EC",
    "wof:name":"Pinan",
    "wof:placetype":"locality"
},
  "geometry": {"coordinates":[-78.43333,0.53333],"type":"Point"}
}