{
  "type": "Feature",
  "properties": {
    "iso:country":"EC",
    "name:spa_x_colloquial":[
        "C. del Seguro Urbanizacion",
        "C. del Seguro, Urbanizacion"
    ],
    "name:spa_x_preferred":[
        "C. del Seguro Urbanizaci\u00f3n"
    ],
    "name:spa_x_variant":[
        "C. del Seguro, Urbanizaci\u00f3n"
    ],
    "name:unk_x_variant":[
        "C. del Seguro Urbanizaci\u00f3n"
    ],
    "qs:gn_adm0_cc":"EC",
    "qs:gn_local":3657509,
    "qs:local_max":931,
    "qs:local_sum":931,
    "qs:localhoods":1,
    "qs:name":"C. del Seguro Urbanizaci\u00f3n",
    "qs:name_adm0":"Ecuador",
    "qs:name_adm1":"Guayas",
    "qs:name_adm2":"Guayaquil",
    "qs:name_lau":"Guayaquil",
    "qs:name_local":"Guayaquil",
    "qs:photo_max":113,
    "qs:photo_sum":931,
    "qs:placetype":"Suburb",
    "qs:quad_count":63,
    "qs:woe_adm0":23424801,
    "qs:woe_adm1":2345211,
    "qs:woe_adm2":26809700,
    "qs:woe_lau":26810032,
    "qs:woe_local":375733,
    "qs:woe_ver":"7.10.0",
    "wof:lang":[
        "spa"
    ],
    "wof:name":"C. del Seguro Urbanizaci\u00f3n",
    "wof:placetype":"neighbourhood"
},
  "geometry": {"coordinates":[-79.893939,-2.217179],"type":"Point"}
}