{
  "type": "Feature",
  "properties": {
    "gn:admin1_code":"8.0",
    "gn:admin2_code":"709.0",
    "gn:admin3_code":"70952.0",
    "gn:asciiname":"Pitahuina",
    "gn:country_code":"EC",
    "gn:dem":112,
    "gn:feature_class":"P",
    "gn:feature_code":"PPL",
    "gn:name":"Pitahui\u00f1a",
    "gn:population":0,
    "gn:timezone":"America/Guayaquil",
    "iso:country":"EC",
    "wof:name":"Pitahuina",
    "wof:placetype":"locality"
},
  "geometry": {"coordinates":[-79.70326999999997,-3.31664],"type":"Point"}
}