{
  "type": "Feature",
  "properties": {
    "gn:admin1_code":"1.0",
    "gn:admin2_code":"2002.0",
    "gn:admin3_code":"200251.0",
    "gn:asciiname":"Tomas de Berlanga",
    "gn:country_code":"EC",
    "gn:dem":137,
    "gn:feature_class":"P",
    "gn:feature_code":"PPL",
    "gn:name":"Tom\u00e1s de Berlanga",
    "gn:population":0,
    "gn:timezone":"Pacific/Galapagos",
    "iso:country":"EC",
    "wof:name":"Tomas de Berlanga",
    "wof:placetype":"locality"
},
  "geometry": {"coordinates":[-91.00471,-0.87235],"type":"Point"}
}