{
  "type": "Feature",
  "properties": {
    "gn:admin1_code":"19.0",
    "gn:admin2_code":"1807.0",
    "gn:admin3_code":"180750.0",
    "gn:asciiname":"Pucara",
    "gn:country_code":"EC",
    "gn:dem":2587,
    "gn:feature_class":"P",
    "gn:feature_code":"PPL",
    "gn:name":"Pucar\u00e1",
    "gn:population":0,
    "gn:timezone":"America/Guayaquil",
    "iso:country":"EC",
    "wof:name":"Pucara",
    "wof:placetype":"locality"
},
  "geometry": {"coordinates":[-78.52676,-1.35652],"type":"Point"}
}