{
  "type": "Feature",
  "properties": {
    "gn:admin1_code":"12.0",
    "gn:admin2_code":"1104.0",
    "gn:admin3_code":"110455.0",
    "gn:asciiname":"Juripilaca",
    "gn:country_code":"EC",
    "gn:dem":1686,
    "gn:feature_class":"P",
    "gn:feature_code":"PPL",
    "gn:name":"Juripilaca",
    "gn:population":0,
    "gn:timezone":"America/Guayaquil",
    "iso:country":"EC",
    "wof:name":"Juripilaca",
    "wof:placetype":"locality"
},
  "geometry": {"coordinates":[-80.06667,-4.11667],"type":"Point"}
}