{
  "type": "Feature",
  "properties": {
    "gn:admin1_code":"14.0",
    "gn:admin2_code":"1313.0",
    "gn:admin3_code":"131351.0",
    "gn:asciiname":"Ayacucho",
    "gn:country_code":"EC",
    "gn:dem":70,
    "gn:feature_class":"P",
    "gn:feature_code":"PPL",
    "gn:name":"Ayacucho",
    "gn:population":0,
    "gn:timezone":"America/Guayaquil",
    "iso:country":"EC",
    "wof:name":"Ayacucho",
    "wof:placetype":"locality"
},
  "geometry": {"coordinates":[-80.28667,-1.1575],"type":"Point"}
}