{
  "type": "Feature",
  "properties": {
    "gn:admin1_code":"2.0",
    "gn:admin2_code":"108.0",
    "gn:admin3_code":"10850.0",
    "gn:asciiname":"Pilches",
    "gn:country_code":"EC",
    "gn:dem":970,
    "gn:feature_class":"P",
    "gn:feature_code":"PPL",
    "gn:name":"Pilches",
    "gn:population":0,
    "gn:timezone":"America/Guayaquil",
    "iso:country":"EC",
    "wof:name":"Pilches",
    "wof:placetype":"locality"
},
  "geometry": {"coordinates":[-79.31667,-3.33333],"type":"Point"}
}