{
  "type": "Feature",
  "properties": {
    "gn:admin1_code":"18.0",
    "gn:admin2_code":"1701.0",
    "gn:admin3_code":"170179.0",
    "gn:asciiname":"Hacienda Chiche Tobar",
    "gn:country_code":"EC",
    "gn:dem":2416,
    "gn:feature_class":"P",
    "gn:feature_code":"PPL",
    "gn:name":"Hacienda Chiche Tobar",
    "gn:population":0,
    "gn:timezone":"America/Guayaquil",
    "iso:country":"EC",
    "wof:name":"Hacienda Chiche Tobar",
    "wof:placetype":"locality"
},
  "geometry": {"coordinates":[-78.36775,-0.19649],"type":"Point"}
}