{
  "type": "Feature",
  "properties": {
    "gn:admin1_code":"6.0",
    "gn:admin2_code":"601.0",
    "gn:admin3_code":"60161.0",
    "gn:asciiname":"Hacienda Guaslan Bajo",
    "gn:country_code":"EC",
    "gn:dem":2834,
    "gn:feature_class":"P",
    "gn:feature_code":"PPL",
    "gn:name":"Hacienda Guasl\u00e1n Bajo",
    "gn:population":0,
    "gn:timezone":"America/Guayaquil",
    "iso:country":"EC",
    "wof:name":"Hacienda Guaslan Bajo",
    "wof:placetype":"locality"
},
  "geometry": {"coordinates":[-78.66348000000001,-1.72525],"type":"Point"}
}