{
  "type": "Feature",
  "properties": {
    "gn:admin1_code":"9.0",
    "gn:admin2_code":"804.0",
    "gn:admin3_code":"80450.0",
    "gn:asciiname":"Duana",
    "gn:country_code":"EC",
    "gn:dem":126,
    "gn:feature_class":"P",
    "gn:feature_code":"PPL",
    "gn:name":"Duana",
    "gn:population":0,
    "gn:timezone":"America/Guayaquil",
    "iso:country":"EC",
    "wof:name":"Duana",
    "wof:placetype":"locality"
},
  "geometry": {"coordinates":[-79.40854,0.31004],"type":"Point"}
}