{
  "type": "Feature",
  "properties": {
    "gn:admin1_code":"22.0",
    "gn:admin2_code":"2101.0",
    "gn:admin3_code":"210153.0",
    "gn:asciiname":"Dios Pena",
    "gn:country_code":"EC",
    "gn:dem":279,
    "gn:feature_class":"P",
    "gn:feature_code":"PPL",
    "gn:name":"Dios Pe\u00f1a",
    "gn:population":0,
    "gn:timezone":"America/Guayaquil",
    "iso:country":"EC",
    "wof:name":"Dios Pena",
    "wof:placetype":"locality"
},
  "geometry": {"coordinates":[-76.81833,0.24583],"type":"Point"}
}