{
  "type": "Feature",
  "properties": {
    "gn:admin1_code":"9.0",
    "gn:admin2_code":"807.0",
    "gn:admin3_code":"80750.0",
    "gn:asciiname":"Rio Verde",
    "gn:country_code":"EC",
    "gn:dem":13,
    "gn:feature_class":"P",
    "gn:feature_code":"PPL",
    "gn:name":"R\u00edo Verde",
    "gn:population":0,
    "gn:timezone":"America/Guayaquil",
    "iso:country":"EC",
    "wof:name":"Rio Verde",
    "wof:placetype":"locality"
},
  "geometry": {"coordinates":[-79.41221,1.07278],"type":"Point"}
}