{
  "type": "Feature",
  "properties": {
    "gn:admin1_code":"18.0",
    "gn:admin2_code":"1707.0",
    "gn:admin3_code":"170751.0",
    "gn:asciiname":"Tandayapa",
    "gn:country_code":"EC",
    "gn:dem":1657,
    "gn:feature_class":"P",
    "gn:feature_code":"PPL",
    "gn:name":"Tandayapa",
    "gn:population":0,
    "gn:timezone":"America/Guayaquil",
    "iso:country":"EC",
    "wof:name":"Tandayapa",
    "wof:placetype":"locality"
},
  "geometry": {"coordinates":[-78.76666999999998,-0.01667],"type":"Point"}
}