{
  "type": "Feature",
  "properties": {
    "gn:admin1_code":"13.0",
    "gn:admin2_code":"1211.0",
    "gn:admin3_code":"121150.0",
    "gn:asciiname":"El Triunfo",
    "gn:country_code":"EC",
    "gn:dem":123,
    "gn:feature_class":"P",
    "gn:feature_code":"PPL",
    "gn:name":"El Triunfo",
    "gn:population":0,
    "gn:timezone":"America/Guayaquil",
    "iso:country":"EC",
    "name:ceb_x_preferred":[
        "El Triunfo"
    ],
    "name:deu_x_preferred":[
        "El Triunfo"
    ],
    "name:ita_x_preferred":[
        "El Triunfo"
    ],
    "name:nld_x_preferred":[
        "El Triunfo"
    ],
    "name:pol_x_preferred":[
        "El Triunfo"
    ],
    "name:rus_x_preferred":[
        "\u042d\u043b\u044c-\u0422\u0440\u0438\u0443\u043d\u0444\u043e"
    ],
    "name:spa_x_preferred":[
        "El Triunfo"
    ],
    "name:srp_x_preferred":[
        "\u0415\u043b \u0422\u0440\u0438\u0443\u043d\u0444\u043e"
    ],
    "name:swe_x_preferred":[
        "El Triunfo"
    ],
    "wof:name":"El Triunfo",
    "wof:placetype":"locality"
},
  "geometry": {"coordinates":[-79.33162,-0.87781],"type":"Point"}
}