{
  "type": "Feature",
  "properties": {
    "gn:admin1_code":"6.0",
    "gn:admin2_code":"607.0",
    "gn:admin3_code":"60756.0",
    "gn:asciiname":"Hacienda La Delicia",
    "gn:cc2":"EC",
    "gn:country_code":"EC",
    "gn:dem":2995,
    "gn:feature_class":"P",
    "gn:feature_code":"PPL",
    "gn:name":"Hacienda La Delicia",
    "gn:population":0,
    "gn:timezone":"America/Guayaquil",
    "iso:country":"EC",
    "wof:name":"Hacienda La Delicia",
    "wof:placetype":"locality"
},
  "geometry": {"coordinates":[-78.68333,-1.58333],"type":"Point"}
}