{
  "type": "Feature",
  "properties": {
    "gn:admin1_code":"10.0",
    "gn:asciiname":"Manantial",
    "gn:country_code":"EC",
    "gn:dem":20,
    "gn:feature_class":"P",
    "gn:feature_code":"PPL",
    "gn:name":"Manantial",
    "gn:population":0,
    "gn:timezone":"America/Guayaquil",
    "iso:country":"EC",
    "wof:name":"Manantial",
    "wof:placetype":"locality"
},
  "geometry": {"coordinates":[-80.66667,-1.98333],"type":"Point"}
}