{
  "type": "Feature",
  "properties": {
    "gn:admin1_code":"15.0",
    "gn:admin2_code":"1409.0",
    "gn:admin3_code":"140950.0",
    "gn:asciiname":"Cushuimi",
    "gn:country_code":"EC",
    "gn:dem":297,
    "gn:feature_class":"P",
    "gn:feature_code":"PPL",
    "gn:name":"Cushuimi",
    "gn:population":0,
    "gn:timezone":"America/Guayaquil",
    "iso:country":"EC",
    "wof:name":"Cushuimi",
    "wof:placetype":"locality"
},
  "geometry": {"coordinates":[-77.72944,-2.52083],"type":"Point"}
}