{
  "type": "Feature",
  "properties": {
    "gn:admin1_code":"7.0",
    "gn:admin2_code":"501.0",
    "gn:admin3_code":"50154.0",
    "gn:asciiname":"Joseguango Bajo",
    "gn:country_code":"EC",
    "gn:dem":2924,
    "gn:feature_class":"P",
    "gn:feature_code":"PPL",
    "gn:name":"Jos\u00e9guango Bajo",
    "gn:population":0,
    "gn:timezone":"America/Guayaquil",
    "iso:country":"EC",
    "wof:name":"Joseguango Bajo",
    "wof:placetype":"locality"
},
  "geometry": {"coordinates":[-78.59426999999999,-0.81574],"type":"Point"}
}