{
  "type": "Feature",
  "properties": {
    "gn:admin1_code":"2.0",
    "gn:admin2_code":"103.0",
    "gn:admin3_code":"10356.0",
    "gn:asciiname":"Cuchil",
    "gn:country_code":"EC",
    "gn:dem":2573,
    "gn:feature_class":"P",
    "gn:feature_code":"PPL",
    "gn:name":"Cuchil",
    "gn:population":0,
    "gn:timezone":"America/Guayaquil",
    "iso:country":"EC",
    "wof:name":"Cuchil",
    "wof:placetype":"locality"
},
  "geometry": {"coordinates":[-78.75,-2.91667],"type":"Point"}
}