{
  "type": "Feature",
  "properties": {
    "gn:admin1_code":"2.0",
    "gn:admin2_code":"102.0",
    "gn:admin3_code":"10250.0",
    "gn:asciiname":"Sinchay",
    "gn:country_code":"EC",
    "gn:dem":2074,
    "gn:feature_class":"P",
    "gn:feature_code":"PPL",
    "gn:name":"Sinchay",
    "gn:population":0,
    "gn:timezone":"America/Guayaquil",
    "iso:country":"EC",
    "wof:name":"Sinchay",
    "wof:placetype":"locality"
},
  "geometry": {"coordinates":[-79.15000000000001,-3.18333],"type":"Point"}
}