{
  "type": "Feature",
  "properties": {
    "gn:admin1_code":"10.0",
    "gn:admin2_code":"906.0",
    "gn:admin3_code":"90656.0",
    "gn:asciiname":"San Roberto",
    "gn:country_code":"EC",
    "gn:dem":9,
    "gn:feature_class":"P",
    "gn:feature_code":"PPL",
    "gn:name":"San Roberto",
    "gn:population":0,
    "gn:timezone":"America/Guayaquil",
    "iso:country":"EC",
    "wof:name":"San Roberto",
    "wof:placetype":"locality"
},
  "geometry": {"coordinates":[-79.96666999999999,-1.98333],"type":"Point"}
}