{
  "type": "Feature",
  "properties": {
    "gn:admin1_code":"2.0",
    "gn:admin2_code":"104.0",
    "gn:admin3_code":"10452.0",
    "gn:asciiname":"Yarizagua",
    "gn:country_code":"EC",
    "gn:dem":2044,
    "gn:feature_class":"P",
    "gn:feature_code":"PPL",
    "gn:name":"Yarizagua",
    "gn:population":0,
    "gn:timezone":"America/Guayaquil",
    "iso:country":"EC",
    "wof:name":"Yarizagua",
    "wof:placetype":"locality"
},
  "geometry": {"coordinates":[-79.22575999999999,-3.30281],"type":"Point"}
}