{
  "type": "Feature",
  "properties": {
    "gn:admin1_code":"18.0",
    "gn:admin2_code":"1701.0",
    "gn:admin3_code":"170183.0",
    "gn:asciiname":"Hacienda Guambi",
    "gn:country_code":"EC",
    "gn:dem":2463,
    "gn:feature_class":"P",
    "gn:feature_code":"PPL",
    "gn:name":"Hacienda Guambi",
    "gn:population":0,
    "gn:timezone":"America/Guayaquil",
    "iso:country":"EC",
    "wof:name":"Hacienda Guambi",
    "wof:placetype":"locality"
},
  "geometry": {"coordinates":[-78.34843000000002,-0.17744],"type":"Point"}
}