{
  "type": "Feature",
  "properties": {
    "gn:admin1_code":"11.0",
    "gn:admin2_code":"1006.0",
    "gn:admin3_code":"100654.0",
    "gn:asciiname":"Hacienda La Quesera",
    "gn:country_code":"EC",
    "gn:dem":2221,
    "gn:feature_class":"P",
    "gn:feature_code":"PPL",
    "gn:name":"Hacienda La Quesera",
    "gn:population":0,
    "gn:timezone":"America/Guayaquil",
    "iso:country":"EC",
    "wof:name":"Hacienda La Quesera",
    "wof:placetype":"locality"
},
  "geometry": {"coordinates":[-78.23313,0.38593],"type":"Point"}
}