{
  "type": "Feature",
  "properties": {
    "gn:admin1_code":"9.0",
    "gn:asciiname":"Pianguapi",
    "gn:country_code":"EC",
    "gn:dem":-9999,
    "gn:feature_class":"P",
    "gn:feature_code":"PPL",
    "gn:name":"Pianguap\u00ed",
    "gn:population":0,
    "gn:timezone":"America/Guayaquil",
    "iso:country":"EC",
    "wof:name":"Pianguapi",
    "wof:placetype":"locality"
},
  "geometry": {"coordinates":[-78.91667,1.43333],"type":"Point"}
}