{
  "type": "Feature",
  "properties": {
    "gn:admin1_code":"1.0",
    "gn:admin2_code":"2001.0",
    "gn:admin3_code":"200152.0",
    "gn:asciiname":"La Baronesa",
    "gn:country_code":"EC",
    "gn:dem":183,
    "gn:feature_class":"P",
    "gn:feature_code":"PPL",
    "gn:name":"La Baronesa",
    "gn:population":0,
    "gn:timezone":"Pacific/Galapagos",
    "iso:country":"EC",
    "wof:name":"La Baronesa",
    "wof:placetype":"locality"
},
  "geometry": {"coordinates":[-90.43389000000001,-1.34853],"type":"Point"}
}