{
  "type": "Feature",
  "properties": {
    "gn:admin1_code":"23.0",
    "gn:admin2_code":"1504.0",
    "gn:admin3_code":"150452.0",
    "gn:asciiname":"Linares",
    "gn:country_code":"EC",
    "gn:dem":1595,
    "gn:feature_class":"P",
    "gn:feature_code":"PPL",
    "gn:name":"Linares",
    "gn:population":0,
    "gn:timezone":"America/Guayaquil",
    "iso:country":"EC",
    "name:arg_x_preferred":[
        "Linars"
    ],
    "name:ast_x_preferred":[
        "\u1e36\u1e37inares"
    ],
    "name:cat_x_preferred":[
        "Linares"
    ],
    "name:ceb_x_preferred":[
        "Linares"
    ],
    "name:deu_x_preferred":[
        "Linares"
    ],
    "name:eus_x_preferred":[
        "Linares"
    ],
    "name:fas_x_preferred":[
        "\u0644\u06cc\u0646\u0627\u0631\u0633"
    ],
    "name:fra_x_preferred":[
        "Linares"
    ],
    "name:glg_x_preferred":[
        "Linares"
    ],
    "name:hun_x_preferred":[
        "Linares"
    ],
    "name:hye_x_preferred":[
        "\u053c\u056b\u0576\u0561\u0580\u0565\u057d"
    ],
    "name:ita_x_preferred":[
        "Linares"
    ],
    "name:jpn_x_preferred":[
        "\u30ea\u30ca\u30ec\u30b9"
    ],
    "name:kor_x_preferred":[
        "\ub9ac\ub098\ub808\uc2a4"
    ],
    "name:nld_x_preferred":[
        "Linares"
    ],
    "name:pol_x_preferred":[
        "Linares"
    ],
    "name:por_x_preferred":[
        "Linares"
    ],
    "name:ron_x_preferred":[
        "Linares"
    ],
    "name:rus_x_preferred":[
        "\u041b\u0438\u043d\u0430\u0440\u0435\u0441"
    ],
    "name:sco_x_preferred":[
        "Linares"
    ],
    "name:spa_x_preferred":[
        "Linares"
    ],
    "name:srp_x_preferred":[
        "\u041b\u0438\u043d\u0430\u0440\u0435\u0441"
    ],
    "name:swe_x_preferred":[
        "Linares"
    ],
    "name:ukr_x_preferred":[
        "\u041b\u0456\u043d\u0430\u0440\u0435\u0441"
    ],
    "name:vie_x_preferred":[
        "Linares"
    ],
    "wof:name":"Linares",
    "wof:placetype":"locality"
},
  "geometry": {"coordinates":[-77.81144999999999,-0.36779],"type":"Point"}
}