{
  "type": "Feature",
  "properties": {
    "gn:admin1_code":"23.0",
    "gn:admin2_code":"1504.0",
    "gn:admin3_code":"150452.0",
    "gn:asciiname":"Linares",
    "gn:country_code":"EC",
    "gn:dem":1595,
    "gn:feature_class":"P",
    "gn:feature_code":"PPL",
    "gn:name":"Linares",
    "gn:population":0,
    "gn:timezone":"America/Guayaquil",
    "iso:country":"EC",
    "wof:name":"Linares",
    "wof:placetype":"locality"
},
  "geometry": {"coordinates":[-77.81144999999999,-0.36779],"type":"Point"}
}