{
  "type": "Feature",
  "properties": {
    "gn:admin1_code":"14.0",
    "gn:admin2_code":"1308.0",
    "gn:admin3_code":"130850.0",
    "gn:asciiname":"El Cercado",
    "gn:country_code":"EC",
    "gn:dem":51,
    "gn:feature_class":"P",
    "gn:feature_code":"PPL",
    "gn:name":"El Cercado",
    "gn:population":0,
    "gn:timezone":"America/Guayaquil",
    "iso:country":"EC",
    "wof:name":"El Cercado",
    "wof:placetype":"locality"
},
  "geometry": {"coordinates":[-80.75417,-0.95278],"type":"Point"}
}