{
  "type": "Feature",
  "properties": {
    "gn:admin1_code":"14.0",
    "gn:admin2_code":"1314.0",
    "gn:admin3_code":"131453.0",
    "gn:asciiname":"Canitas",
    "gn:country_code":"EC",
    "gn:dem":27,
    "gn:feature_class":"P",
    "gn:feature_code":"PPL",
    "gn:name":"Ca\u00f1itas",
    "gn:population":0,
    "gn:timezone":"America/Guayaquil",
    "iso:country":"EC",
    "wof:name":"Canitas",
    "wof:placetype":"locality"
},
  "geometry": {"coordinates":[-80.4686,-0.85417],"type":"Point"}
}