{
  "type": "Feature",
  "properties": {
    "gn:admin1_code":"2.0",
    "gn:admin2_code":"101.0",
    "gn:admin3_code":"10152.0",
    "gn:asciiname":"Joyapa",
    "gn:country_code":"EC",
    "gn:dem":3005,
    "gn:feature_class":"P",
    "gn:feature_code":"PPL",
    "gn:name":"Joyapa",
    "gn:population":0,
    "gn:timezone":"America/Guayaquil",
    "iso:country":"EC",
    "wof:name":"Joyapa",
    "wof:placetype":"locality"
},
  "geometry": {"coordinates":[-79.01666999999998,-3.13333],"type":"Point"}
}