{
  "type": "Feature",
  "properties": {
    "gn:admin1_code":"3.0",
    "gn:admin2_code":"202.0",
    "gn:admin3_code":"20250.0",
    "gn:asciiname":"Chillanes",
    "gn:country_code":"EC",
    "gn:dem":2346,
    "gn:feature_class":"P",
    "gn:feature_code":"PPL",
    "gn:name":"Chillanes",
    "gn:population":0,
    "gn:timezone":"America/Guayaquil",
    "iso:country":"EC",
    "name:ceb_x_preferred":[
        "Chillanes"
    ],
    "name:que_x_preferred":[
        "Chillanes"
    ],
    "name:swe_x_preferred":[
        "Chillanes"
    ],
    "wof:name":"Chillanes",
    "wof:placetype":"locality"
},
  "geometry": {"coordinates":[-79.06631,-1.94366],"type":"Point"}
}