{
  "type": "Feature",
  "properties": {
    "gn:admin1_code":"14.0",
    "gn:asciiname":"Filan Banco",
    "gn:cc2":"EC",
    "gn:country_code":"EC",
    "gn:dem":24,
    "gn:feature_class":"P",
    "gn:feature_code":"PPL",
    "gn:name":"Filan Banco",
    "gn:population":0,
    "gn:timezone":"America/Guayaquil",
    "iso:country":"EC",
    "wof:name":"Filan Banco",
    "wof:placetype":"locality"
},
  "geometry": {"coordinates":[-80.90000000000001,-2.225],"type":"Point"}
}