{
  "type": "Feature",
  "properties": {
    "gn:admin1_code":"2.0",
    "gn:admin2_code":"108.0",
    "gn:admin3_code":"10853.0",
    "gn:asciiname":"Hacienda Hornillos",
    "gn:country_code":"EC",
    "gn:dem":3302,
    "gn:feature_class":"P",
    "gn:feature_code":"PPL",
    "gn:name":"Hacienda Hornillos",
    "gn:population":0,
    "gn:timezone":"America/Guayaquil",
    "iso:country":"EC",
    "wof:name":"Hacienda Hornillos",
    "wof:placetype":"locality"
},
  "geometry": {"coordinates":[-79.4171,-3.10668],"type":"Point"}
}