{
  "type": "Feature",
  "properties": {
    "gn:admin1_code":"17.0",
    "gn:admin2_code":"1601.0",
    "gn:admin3_code":"160158.0",
    "gn:asciiname":"Rio Corrientes",
    "gn:country_code":"EC",
    "gn:dem":239,
    "gn:feature_class":"P",
    "gn:feature_code":"PPL",
    "gn:name":"R\u00edo Corrientes",
    "gn:population":0,
    "gn:timezone":"America/Guayaquil",
    "iso:country":"EC",
    "wof:name":"Rio Corrientes",
    "wof:placetype":"locality"
},
  "geometry": {"coordinates":[-76.41667,-2.36667],"type":"Point"}
}