{
  "type": "Feature",
  "properties": {
    "gn:admin1_code":"10.0",
    "gn:admin2_code":"922.0",
    "gn:admin3_code":"92251.0",
    "gn:asciiname":"Hacienda Miraflores",
    "gn:cc2":"EC",
    "gn:country_code":"EC",
    "gn:dem":30,
    "gn:feature_class":"P",
    "gn:feature_code":"PPL",
    "gn:name":"Hacienda Miraflores",
    "gn:population":0,
    "gn:timezone":"America/Guayaquil",
    "iso:country":"EC",
    "wof:name":"Hacienda Miraflores",
    "wof:placetype":"locality"
},
  "geometry": {"coordinates":[-79.41667,-2.03333],"type":"Point"}
}