{
  "type": "Feature",
  "properties": {
    "gn:admin1_code":"9.0",
    "gn:admin2_code":"804.0",
    "gn:admin3_code":"80450.0",
    "gn:asciiname":"Chemere",
    "gn:country_code":"EC",
    "gn:dem":149,
    "gn:feature_class":"P",
    "gn:feature_code":"PPL",
    "gn:name":"Chemere",
    "gn:population":0,
    "gn:timezone":"America/Guayaquil",
    "iso:country":"EC",
    "wof:name":"Chemere",
    "wof:placetype":"locality"
},
  "geometry": {"coordinates":[-79.68226,0.17003],"type":"Point"}
}