{
  "type": "Feature",
  "properties": {
    "gn:admin1_code":"24.0",
    "gn:admin2_code":"2202.0",
    "gn:admin3_code":"220251.0",
    "gn:asciiname":"Delta",
    "gn:country_code":"EC",
    "gn:dem":216,
    "gn:feature_class":"P",
    "gn:feature_code":"PPL",
    "gn:name":"Delta",
    "gn:population":0,
    "gn:timezone":"America/Guayaquil",
    "iso:country":"EC",
    "wof:name":"Delta",
    "wof:placetype":"locality"
},
  "geometry": {"coordinates":[-75.8593,-0.59793],"type":"Point"}
}