{
  "type": "Feature",
  "properties": {
    "gn:admin1_code":"2.0",
    "gn:admin2_code":"103.0",
    "gn:admin3_code":"10357.0",
    "gn:asciiname":"Zhizhio",
    "gn:country_code":"EC",
    "gn:dem":2528,
    "gn:feature_class":"P",
    "gn:feature_code":"PPL",
    "gn:name":"Zhizhio",
    "gn:population":0,
    "gn:timezone":"America/Guayaquil",
    "iso:country":"EC",
    "wof:name":"Zhizhio",
    "wof:placetype":"locality"
},
  "geometry": {"coordinates":[-78.81354,-2.93364],"type":"Point"}
}