{
  "type": "Feature",
  "properties": {
    "gn:admin1_code":"2.0",
    "gn:admin2_code":"101.0",
    "gn:admin3_code":"10151.0",
    "gn:asciiname":"Hacienda Relojero",
    "gn:cc2":"EC",
    "gn:country_code":"EC",
    "gn:dem":3231,
    "gn:feature_class":"P",
    "gn:feature_code":"PPL",
    "gn:name":"Hacienda Relojero",
    "gn:population":0,
    "gn:timezone":"America/Guayaquil",
    "iso:country":"EC",
    "wof:name":"Hacienda Relojero",
    "wof:placetype":"locality"
},
  "geometry": {"coordinates":[-79.11667,-2.96667],"type":"Point"}
}