{
  "type": "Feature",
  "properties": {
    "gn:admin1_code":"18.0",
    "gn:admin2_code":"1705.0",
    "gn:admin3_code":"170551.0",
    "gn:asciiname":"Cotogchoa",
    "gn:country_code":"EC",
    "gn:dem":2577,
    "gn:feature_class":"P",
    "gn:feature_code":"PPL",
    "gn:name":"Cotogchoa",
    "gn:population":0,
    "gn:timezone":"America/Guayaquil",
    "iso:country":"EC",
    "wof:name":"Cotogchoa",
    "wof:placetype":"locality"
},
  "geometry": {"coordinates":[-78.45098,-0.36524],"type":"Point"}
}