{
  "type": "Feature",
  "properties": {
    "gn:admin1_code":"18.0",
    "gn:admin2_code":"1701.0",
    "gn:admin3_code":"170154.0",
    "gn:asciiname":"Hacienda El Galpon",
    "gn:cc2":"EC",
    "gn:country_code":"EC",
    "gn:dem":2965,
    "gn:feature_class":"P",
    "gn:feature_code":"PPL",
    "gn:name":"Hacienda El Galp\u00f3n",
    "gn:population":0,
    "gn:timezone":"America/Guayaquil",
    "iso:country":"EC",
    "wof:name":"Hacienda El Galpon",
    "wof:placetype":"locality"
},
  "geometry": {"coordinates":[-78.51666999999998,-0.01667],"type":"Point"}
}