{
  "type": "Feature",
  "properties": {
    "gn:admin1_code":"5.0",
    "gn:admin2_code":"403.0",
    "gn:admin3_code":"40350.0",
    "gn:asciiname":"Hacienda Ishpingo",
    "gn:country_code":"EC",
    "gn:dem":3010,
    "gn:feature_class":"P",
    "gn:feature_code":"PPL",
    "gn:name":"Hacienda Ishpingo",
    "gn:population":0,
    "gn:timezone":"America/Guayaquil",
    "iso:country":"EC",
    "wof:name":"Hacienda Ishpingo",
    "wof:placetype":"locality"
},
  "geometry": {"coordinates":[-77.94105999999999,0.60415],"type":"Point"}
}