{
  "type": "Feature",
  "properties": {
    "gn:admin1_code":"12.0",
    "gn:admin2_code":"1103.0",
    "gn:admin3_code":"110354.0",
    "gn:asciiname":"Zamba",
    "gn:country_code":"EC",
    "gn:dem":1459,
    "gn:feature_class":"P",
    "gn:feature_code":"PPL",
    "gn:name":"Zamba",
    "gn:population":0,
    "gn:timezone":"America/Guayaquil",
    "iso:country":"EC",
    "wof:name":"Zamba",
    "wof:placetype":"locality"
},
  "geometry": {"coordinates":[-79.53657,-3.91451],"type":"Point"}
}