{
  "type": "Feature",
  "properties": {
    "gn:admin1_code":"11.0",
    "gn:admin2_code":"1003.0",
    "gn:admin3_code":"100350.0",
    "gn:asciiname":"Hacienda Ocampo",
    "gn:country_code":"EC",
    "gn:dem":2462,
    "gn:feature_class":"P",
    "gn:feature_code":"PPL",
    "gn:name":"Hacienda Ocampo",
    "gn:population":0,
    "gn:timezone":"America/Guayaquil",
    "iso:country":"EC",
    "wof:name":"Hacienda Ocampo",
    "wof:placetype":"locality"
},
  "geometry": {"coordinates":[-78.27458,0.31186],"type":"Point"}
}