{
  "type": "Feature",
  "properties": {
    "gn:admin1_code":"5.0",
    "gn:admin2_code":"401.0",
    "gn:admin3_code":"40150.0",
    "gn:asciiname":"Morro",
    "gn:country_code":"EC",
    "gn:dem":2828,
    "gn:feature_class":"P",
    "gn:feature_code":"PPL",
    "gn:name":"Morro",
    "gn:population":0,
    "gn:timezone":"America/Bogota",
    "iso:country":"EC",
    "name:ceb_x_preferred":[
        "Morro"
    ],
    "name:deu_x_preferred":[
        "Morro"
    ],
    "name:fra_x_preferred":[
        "Morro"
    ],
    "name:hun_x_preferred":[
        "Morr\u00f3"
    ],
    "name:ita_x_preferred":[
        "Morro"
    ],
    "name:lat_x_preferred":[
        "Murrum"
    ],
    "name:pol_x_preferred":[
        "Morro"
    ],
    "name:por_x_preferred":[
        "Morro"
    ],
    "name:rus_x_preferred":[
        "\u041c\u043e\u0440\u0440\u043e"
    ],
    "name:sco_x_preferred":[
        "Morro"
    ],
    "name:spa_x_preferred":[
        "Morro"
    ],
    "name:swe_x_preferred":[
        "Morro"
    ],
    "wof:name":"Morro",
    "wof:placetype":"locality"
},
  "geometry": {"coordinates":[-77.66667,0.81667],"type":"Point"}
}