{
  "type": "Feature",
  "properties": {
    "gn:admin1_code":"9.0",
    "gn:admin2_code":"807.0",
    "gn:admin3_code":"80754.0",
    "gn:asciiname":"Montalvo",
    "gn:country_code":"EC",
    "gn:dem":10,
    "gn:feature_class":"P",
    "gn:feature_code":"PPL",
    "gn:name":"Montalvo",
    "gn:population":0,
    "gn:timezone":"America/Guayaquil",
    "iso:country":"EC",
    "name:ceb_x_preferred":[
        "Montalvo"
    ],
    "name:deu_x_preferred":[
        "Montalvo"
    ],
    "name:fra_x_preferred":[
        "Montalvo"
    ],
    "name:ita_x_preferred":[
        "Montalvo"
    ],
    "name:pol_x_preferred":[
        "Montalvo"
    ],
    "name:rus_x_preferred":[
        "\u041c\u043e\u043d\u0442\u0430\u043b\u044c\u0432\u043e"
    ],
    "name:spa_x_preferred":[
        "Montalvo"
    ],
    "name:swe_x_preferred":[
        "Montalvo"
    ],
    "name:ukr_x_preferred":[
        "\u041c\u043e\u043d\u0442\u0430\u043b\u044c\u0432\u043e"
    ],
    "wof:name":"Montalvo",
    "wof:placetype":"locality"
},
  "geometry": {"coordinates":[-79.31206,1.0501],"type":"Point"}
}