{
  "type": "Feature",
  "properties": {
    "gn:admin1_code":"22.0",
    "gn:admin2_code":"2105.0",
    "gn:admin3_code":"210554.0",
    "gn:asciiname":"Las Playas",
    "gn:cc2":"EC",
    "gn:country_code":"EC",
    "gn:dem":2209,
    "gn:feature_class":"P",
    "gn:feature_code":"PPL",
    "gn:name":"Las Playas",
    "gn:population":0,
    "gn:timezone":"America/Bogota",
    "iso:country":"EC",
    "wof:name":"Las Playas",
    "wof:placetype":"locality"
},
  "geometry": {"coordinates":[-77.48333000000002,0.61667],"type":"Point"}
}