{
  "type": "Feature",
  "properties": {
    "gn:admin1_code":"10.0",
    "gn:admin2_code":"911.0",
    "gn:admin3_code":"91153.0",
    "gn:asciiname":"Puerto Naranjal",
    "gn:country_code":"EC",
    "gn:dem":16,
    "gn:feature_class":"P",
    "gn:feature_code":"PPL",
    "gn:name":"Puerto Naranjal",
    "gn:population":0,
    "gn:timezone":"America/Guayaquil",
    "iso:country":"EC",
    "wof:name":"Puerto Naranjal",
    "wof:placetype":"locality"
},
  "geometry": {"coordinates":[-79.76666999999998,-2.66667],"type":"Point"}
}