{
  "type": "Feature",
  "properties": {
    "gn:admin1_code":"6.0",
    "gn:admin2_code":"604.0",
    "gn:admin3_code":"60450.0",
    "gn:asciiname":"Chambo",
    "gn:country_code":"EC",
    "gn:dem":2751,
    "gn:feature_class":"P",
    "gn:feature_code":"PPL",
    "gn:name":"Chambo",
    "gn:population":0,
    "gn:timezone":"America/Guayaquil",
    "iso:country":"EC",
    "name:que_x_preferred":[
        "Champu"
    ],
    "wof:name":"Chambo",
    "wof:placetype":"locality"
},
  "geometry": {"coordinates":[-78.59595,-1.73055],"type":"Point"}
}