{
  "type": "Feature",
  "properties": {
    "gn:admin1_code":"8.0",
    "gn:admin2_code":"703.0",
    "gn:admin3_code":"70351.0",
    "gn:asciiname":"Rancho Comisario",
    "gn:country_code":"EC",
    "gn:dem":1524,
    "gn:feature_class":"P",
    "gn:feature_code":"PPL",
    "gn:name":"Rancho Comisario",
    "gn:population":0,
    "gn:timezone":"America/Guayaquil",
    "iso:country":"EC",
    "wof:name":"Rancho Comisario",
    "wof:placetype":"locality"
},
  "geometry": {"coordinates":[-79.71666999999999,-3.55],"type":"Point"}
}