{
  "type": "Feature",
  "properties": {
    "gn:admin1_code":"19.0",
    "gn:admin2_code":"1801.0",
    "gn:admin3_code":"180166.0",
    "gn:asciiname":"Totoras",
    "gn:country_code":"EC",
    "gn:dem":2661,
    "gn:feature_class":"P",
    "gn:feature_code":"PPL",
    "gn:name":"Totoras",
    "gn:population":0,
    "gn:timezone":"America/Guayaquil",
    "iso:country":"EC",
    "wof:name":"Totoras",
    "wof:placetype":"locality"
},
  "geometry": {"coordinates":[-78.59702,-1.31558],"type":"Point"}
}