{
  "type": "Feature",
  "properties": {
    "gn:admin1_code":"8.0",
    "gn:admin2_code":"714.0",
    "gn:admin3_code":"71451.0",
    "gn:asciiname":"Hacienda Tahuin",
    "gn:cc2":"EC",
    "gn:country_code":"EC",
    "gn:dem":592,
    "gn:feature_class":"P",
    "gn:feature_code":"PPL",
    "gn:name":"Hacienda Tahuin",
    "gn:population":0,
    "gn:timezone":"America/Guayaquil",
    "iso:country":"EC",
    "wof:name":"Hacienda Tahuin",
    "wof:placetype":"locality"
},
  "geometry": {"coordinates":[-80.08333,-3.85],"type":"Point"}
}