{
  "type": "Feature",
  "properties": {
    "gn:admin1_code":"2.0",
    "gn:admin2_code":"101.0",
    "gn:admin3_code":"10171.0",
    "gn:asciiname":"Escaleras",
    "gn:country_code":"EC",
    "gn:dem":2685,
    "gn:feature_class":"P",
    "gn:feature_code":"PPL",
    "gn:name":"Escaleras",
    "gn:population":0,
    "gn:timezone":"America/Guayaquil",
    "iso:country":"EC",
    "wof:name":"Escaleras",
    "wof:placetype":"locality"
},
  "geometry": {"coordinates":[-79.05739,-3.04007],"type":"Point"}
}