{
  "type": "Feature",
  "properties": {
    "gn:admin1_code":"11.0",
    "gn:admin2_code":"1003.0",
    "gn:admin3_code":"100350.0",
    "gn:asciiname":"El Cercado",
    "gn:country_code":"EC",
    "gn:dem":2632,
    "gn:feature_class":"P",
    "gn:feature_code":"PPL",
    "gn:name":"El Cercado",
    "gn:population":0,
    "gn:timezone":"America/Guayaquil",
    "iso:country":"EC",
    "wof:name":"El Cercado",
    "wof:placetype":"locality"
},
  "geometry": {"coordinates":[-78.27619,0.33549],"type":"Point"}
}