{
  "type": "Feature",
  "properties": {
    "gn:admin1_code":"9.0",
    "gn:admin2_code":"801.0",
    "gn:admin3_code":"80152.0",
    "gn:asciiname":"El Camino",
    "gn:country_code":"EC",
    "gn:dem":42,
    "gn:feature_class":"P",
    "gn:feature_code":"PPL",
    "gn:name":"El Camino",
    "gn:population":0,
    "gn:timezone":"America/Guayaquil",
    "iso:country":"EC",
    "name:ceb_x_preferred":[
        "El Camino"
    ],
    "name:ita_x_preferred":[
        "El Camino"
    ],
    "name:swe_x_preferred":[
        "El Camino"
    ],
    "wof:name":"El Camino",
    "wof:placetype":"locality"
},
  "geometry": {"coordinates":[-79.51094000000001,0.96408],"type":"Point"}
}