{
  "type": "Feature",
  "properties": {
    "gn:admin1_code":"17.0",
    "gn:admin2_code":"1601.0",
    "gn:admin3_code":"160161.0",
    "gn:asciiname":"Jatun Molino",
    "gn:cc2":"EC",
    "gn:country_code":"EC",
    "gn:dem":413,
    "gn:feature_class":"P",
    "gn:feature_code":"PPL",
    "gn:name":"Jat\u00fan Molino",
    "gn:population":0,
    "gn:timezone":"America/Guayaquil",
    "iso:country":"EC",
    "wof:name":"Jatun Molino",
    "wof:placetype":"locality"
},
  "geometry": {"coordinates":[-77.33333,-1.83333],"type":"Point"}
}