{
  "type": "Feature",
  "properties": {
    "gn:admin1_code":"4.0",
    "gn:admin2_code":"302.0",
    "gn:admin3_code":"30250.0",
    "gn:asciiname":"Cuitum",
    "gn:country_code":"EC",
    "gn:dem":2845,
    "gn:feature_class":"P",
    "gn:feature_code":"PPL",
    "gn:name":"Cuitum",
    "gn:population":0,
    "gn:timezone":"America/Guayaquil",
    "iso:country":"EC",
    "wof:name":"Cuitum",
    "wof:placetype":"locality"
},
  "geometry": {"coordinates":[-78.90000000000001,-2.68333],"type":"Point"}
}