{
  "type": "Feature",
  "properties": {
    "iso:country":"EC",
    "name:ceb_x_preferred":[
        "Eloy Alfaro"
    ],
    "name:deu_x_preferred":[
        "Dur\u00e1n"
    ],
    "name:eng_x_preferred":[
        "Dur\u00e1n"
    ],
    "name:epo_x_preferred":[
        "Dur\u00e1n"
    ],
    "name:fra_x_preferred":[
        "Dur\u00e1n"
    ],
    "name:ita_x_preferred":[
        "Dur\u00e1n"
    ],
    "name:jpn_x_preferred":[
        "\u30a8\u30ed\u30a4\u30a2\u30eb\u30d5\u30a1\u30ed"
    ],
    "name:kat_x_preferred":[
        "\u10d3\u10e3\u10e0\u10d0\u10dc\u10d8"
    ],
    "name:kor_x_preferred":[
        "\ub450\ub780"
    ],
    "name:lit_x_preferred":[
        "Duranas"
    ],
    "name:nld_x_preferred":[
        "Dur\u00e1n"
    ],
    "name:pol_x_preferred":[
        "Dur\u00e1n"
    ],
    "name:por_x_preferred":[
        "Dur\u00e1n"
    ],
    "name:que_x_preferred":[
        "Dur\u00e1n"
    ],
    "name:rus_x_preferred":[
        "\u0414\u0443\u0440\u0430\u043d"
    ],
    "name:spa_x_preferred":[
        "Dur\u00e1n"
    ],
    "name:swe_x_preferred":[
        "Eloy Alfaro"
    ],
    "name:vol_x_preferred":[
        "Dur\u00e1n"
    ],
    "name:zho_x_preferred":[
        "\u675c\u862d"
    ],
    "qs:gn_pop":0,
    "qs:name":"Dur\u00e1n",
    "qs:name_adm0":"Ecuador",
    "qs:name_adm1":"Guayas",
    "qs:photos":216,
    "qs:photos_1k":44,
    "qs:photos_9k":1,
    "qs:photos_9r":4,
    "qs:photos_all":216,
    "qs:photos_sr":4,
    "qs:placetype":"Town",
    "qs:pop_sr":"0",
    "qs:woe_adm0":23424801,
    "wof:name":"Dur\u00e1n",
    "wof:placetype":"locality"
},
  "geometry": {"coordinates":[-79.83352600000001,-2.1667],"type":"Point"}
}