{
  "type": "Feature",
  "properties": {
    "gn:admin1_code":"4.0",
    "gn:admin2_code":"306.0",
    "gn:admin3_code":"30650.0",
    "gn:asciiname":"Sigsipamba",
    "gn:country_code":"EC",
    "gn:dem":2664,
    "gn:feature_class":"P",
    "gn:feature_code":"PPL",
    "gn:name":"Sigsipamba",
    "gn:population":0,
    "gn:timezone":"America/Guayaquil",
    "iso:country":"EC",
    "wof:name":"Sigsipamba",
    "wof:placetype":"locality"
},
  "geometry": {"coordinates":[-78.92610999999999,-2.78855],"type":"Point"}
}