{
  "type": "Feature",
  "properties": {
    "gn:admin1_code":"12.0",
    "gn:admin2_code":"1108.0",
    "gn:admin3_code":"110851.0",
    "gn:asciiname":"Larama",
    "gn:country_code":"EC",
    "gn:dem":970,
    "gn:feature_class":"P",
    "gn:feature_code":"PPL",
    "gn:name":"Larama",
    "gn:population":0,
    "gn:timezone":"America/Guayaquil",
    "iso:country":"EC",
    "wof:name":"Larama",
    "wof:placetype":"locality"
},
  "geometry": {"coordinates":[-79.90597,-4.26579],"type":"Point"}
}