{
  "type": "Feature",
  "properties": {
    "gn:admin1_code":"14.0",
    "gn:admin2_code":"1320.0",
    "gn:admin3_code":"132050.0",
    "gn:asciiname":"Rambuche",
    "gn:country_code":"EC",
    "gn:dem":77,
    "gn:feature_class":"P",
    "gn:feature_code":"PPL",
    "gn:name":"Rambuche",
    "gn:population":0,
    "gn:timezone":"America/Guayaquil",
    "iso:country":"EC",
    "wof:name":"Rambuche",
    "wof:placetype":"locality"
},
  "geometry": {"coordinates":[-80.33333,-0.23333],"type":"Point"}
}