{
  "type": "Feature",
  "properties": {
    "gn:admin1_code":"13.0",
    "gn:admin2_code":"1201.0",
    "gn:admin3_code":"120152.0",
    "gn:asciiname":"Roblecito",
    "gn:country_code":"EC",
    "gn:dem":8,
    "gn:feature_class":"P",
    "gn:feature_code":"PPL",
    "gn:name":"Roblecito",
    "gn:population":0,
    "gn:timezone":"America/Guayaquil",
    "iso:country":"EC",
    "wof:name":"Roblecito",
    "wof:placetype":"locality"
},
  "geometry": {"coordinates":[-79.41667,-1.63333],"type":"Point"}
}