{
  "type": "Feature",
  "properties": {
    "gn:admin1_code":"10.0",
    "gn:admin2_code":"901.0",
    "gn:admin3_code":"90157.0",
    "gn:asciiname":"Puna Vieja",
    "gn:country_code":"EC",
    "gn:dem":0,
    "gn:feature_class":"P",
    "gn:feature_code":"PPL",
    "gn:name":"Pun\u00e1 Vieja",
    "gn:population":0,
    "gn:timezone":"America/Guayaquil",
    "iso:country":"EC",
    "wof:name":"Puna Vieja",
    "wof:placetype":"locality"
},
  "geometry": {"coordinates":[-80.13609,-2.95571],"type":"Point"}
}