{
  "type": "Feature",
  "properties": {
    "gn:admin1_code":"12.0",
    "gn:admin2_code":"1109.0",
    "gn:admin3_code":"110950.0",
    "gn:asciiname":"Matocha",
    "gn:country_code":"EC",
    "gn:dem":1523,
    "gn:feature_class":"P",
    "gn:feature_code":"PPL",
    "gn:name":"Matocha",
    "gn:population":0,
    "gn:timezone":"America/Guayaquil",
    "iso:country":"EC",
    "wof:name":"Matocha",
    "wof:placetype":"locality"
},
  "geometry": {"coordinates":[-79.56667,-4.03333],"type":"Point"}
}