{
  "type": "Feature",
  "properties": {
    "gn:admin1_code":"10.0",
    "gn:admin2_code":"920.0",
    "gn:admin3_code":"92055.0",
    "gn:asciiname":"Puerto La Chiquita",
    "gn:country_code":"EC",
    "gn:dem":15,
    "gn:feature_class":"P",
    "gn:feature_code":"PPL",
    "gn:name":"Puerto La Chiquita",
    "gn:population":0,
    "gn:timezone":"America/Guayaquil",
    "iso:country":"EC",
    "wof:name":"Puerto La Chiquita",
    "wof:placetype":"locality"
},
  "geometry": {"coordinates":[-79.62984,-2.17916],"type":"Point"}
}