{
  "type": "Feature",
  "properties": {
    "gn:admin1_code":"13.0",
    "gn:admin2_code":"1211.0",
    "gn:admin3_code":"121150.0",
    "gn:asciiname":"Monte Nuevo",
    "gn:country_code":"EC",
    "gn:dem":641,
    "gn:feature_class":"P",
    "gn:feature_code":"PPL",
    "gn:name":"Monte Nuevo",
    "gn:population":0,
    "gn:timezone":"America/Guayaquil",
    "iso:country":"EC",
    "wof:name":"Monte Nuevo",
    "wof:placetype":"locality"
},
  "geometry": {"coordinates":[-79.11948000000002,-0.54434],"type":"Point"}
}