{
  "type": "Feature",
  "properties": {
    "gn:admin1_code":"12.0",
    "gn:admin2_code":"1113.0",
    "gn:admin3_code":"111354.0",
    "gn:asciiname":"Infiernillo",
    "gn:country_code":"EC",
    "gn:dem":542,
    "gn:feature_class":"P",
    "gn:feature_code":"PPL",
    "gn:name":"Infiernillo",
    "gn:population":0,
    "gn:timezone":"America/Guayaquil",
    "iso:country":"EC",
    "wof:name":"Infiernillo",
    "wof:placetype":"locality"
},
  "geometry": {"coordinates":[-80.29899,-4.1968],"type":"Point"}
}