{
  "type": "Feature",
  "properties": {
    "gn:admin1_code":"10.0",
    "gn:admin2_code":"906.0",
    "gn:admin3_code":"90650.0",
    "gn:asciiname":"Flor de Maria",
    "gn:country_code":"EC",
    "gn:dem":7,
    "gn:feature_class":"P",
    "gn:feature_code":"PPL",
    "gn:name":"Flor de Mar\u00eda",
    "gn:population":0,
    "gn:timezone":"America/Guayaquil",
    "iso:country":"EC",
    "wof:name":"Flor de Maria",
    "wof:placetype":"locality"
},
  "geometry": {"coordinates":[-79.99500999999999,-1.81944],"type":"Point"}
}