{
  "type": "Feature",
  "properties": {
    "gn:admin1_code":"2.0",
    "gn:admin2_code":"101.0",
    "gn:admin3_code":"10151.0",
    "gn:asciiname":"Misecata",
    "gn:country_code":"EC",
    "gn:dem":2732,
    "gn:feature_class":"P",
    "gn:feature_code":"PPL",
    "gn:name":"Misecata",
    "gn:population":0,
    "gn:timezone":"America/Guayaquil",
    "iso:country":"EC",
    "wof:name":"Misecata",
    "wof:placetype":"locality"
},
  "geometry": {"coordinates":[-79.05757,-2.90952],"type":"Point"}
}