{
  "type": "Feature",
  "properties": {
    "gn:admin1_code":"9.0",
    "gn:admin2_code":"805.0",
    "gn:admin3_code":"80561.0",
    "gn:asciiname":"Guarumo",
    "gn:country_code":"EC",
    "gn:dem":50,
    "gn:feature_class":"P",
    "gn:feature_code":"PPL",
    "gn:name":"Guarumo",
    "gn:population":0,
    "gn:timezone":"America/Guayaquil",
    "iso:country":"EC",
    "wof:name":"Guarumo",
    "wof:placetype":"locality"
},
  "geometry": {"coordinates":[-78.73850999999998,1.21196],"type":"Point"}
}