{
  "type": "Feature",
  "properties": {
    "iso:country":"EC",
    "name:cat_x_preferred":[
        "Alaus\u00ed"
    ],
    "name:ceb_x_preferred":[
        "Cant\u00f3n Alaus\u00ed"
    ],
    "name:ceb_x_variant":[
        "Alaus\u00ed"
    ],
    "name:eng_x_preferred":[
        "Alaus\u00ed"
    ],
    "name:fas_x_preferred":[
        "\u0627\u0644\u0627\u0648\u0633\u06cc"
    ],
    "name:fra_x_preferred":[
        "Alaus\u00ed"
    ],
    "name:ita_x_preferred":[
        "Cantone di Alaus\u00ed"
    ],
    "name:ita_x_variant":[
        "Alaus\u00ed"
    ],
    "name:jpn_x_preferred":[
        "\u30a2\u30e9\u30a6\u30b7"
    ],
    "name:kat_x_preferred":[
        "\u10d0\u10da\u10d0\u10e3\u10e1\u10d8\u10e1 \u10d9\u10d0\u10dc\u10e2\u10dd\u10dc\u10d8"
    ],
    "name:lit_x_preferred":[
        "Alausi"
    ],
    "name:nld_x_preferred":[
        "Alaus\u00ed"
    ],
    "name:por_x_preferred":[
        "Alaus\u00ed"
    ],
    "name:que_x_preferred":[
        "Alawsi kiti"
    ],
    "name:que_x_variant":[
        "Alawsi"
    ],
    "name:rus_x_preferred":[
        "\u0410\u043b\u0430\u0443\u0441\u0438"
    ],
    "name:spa_x_preferred":[
        "Cant\u00f3n Alaus\u00ed"
    ],
    "name:swe_x_preferred":[
        "Cant\u00f3n Alaus\u00ed"
    ],
    "name:swe_x_variant":[
        "Alaus\u00ed"
    ],
    "name:und_x_variant":[
        "Nariz del Diablo"
    ],
    "name:zho_x_preferred":[
        "\u963f\u52de\u897f\u7e23"
    ],
    "qs:gn_country":"EC",
    "qs:gn_fcode":"PPL",
    "qs:gn_pop":0,
    "qs:name":"Pistish\u00ed",
    "qs:name_adm0":"Ecuador",
    "qs:name_adm1":"Chimborazo",
    "qs:photos":41,
    "qs:photos_1k":8,
    "qs:photos_9k":1,
    "qs:photos_9r":2,
    "qs:photos_all":41,
    "qs:photos_sr":2,
    "qs:placetype":"Town",
    "qs:pop_sr":"0",
    "qs:woe_adm0":23424801,
    "wof:name":"Pistish\u00ed",
    "wof:placetype":"locality"
},
  "geometry": {"coordinates":[-78.88453,-2.24799],"type":"Point"}
}