{
  "type": "Feature",
  "properties": {
    "gn:admin1_code":"15.0",
    "gn:admin2_code":"1401.0",
    "gn:admin3_code":"140158.0",
    "gn:asciiname":"Abanico",
    "gn:country_code":"EC",
    "gn:dem":1599,
    "gn:feature_class":"P",
    "gn:feature_code":"PPL",
    "gn:name":"Abanico",
    "gn:population":0,
    "gn:timezone":"America/Guayaquil",
    "iso:country":"EC",
    "wof:name":"Abanico",
    "wof:placetype":"locality"
},
  "geometry": {"coordinates":[-78.20199000000002,-2.14311],"type":"Point"}
}