{
  "type": "Feature",
  "properties": {
    "gn:admin1_code":"18.0",
    "gn:admin2_code":"1703.0",
    "gn:admin3_code":"170350.0",
    "gn:asciiname":"Santa Ana de Pedregal",
    "gn:country_code":"EC",
    "gn:dem":3462,
    "gn:feature_class":"P",
    "gn:feature_code":"PPL",
    "gn:name":"Santa Ana de Pedregal",
    "gn:population":0,
    "gn:timezone":"America/Guayaquil",
    "iso:country":"EC",
    "wof:name":"Santa Ana de Pedregal",
    "wof:placetype":"locality"
},
  "geometry": {"coordinates":[-78.47920000000001,-0.52856],"type":"Point"}
}