{
  "type": "Feature",
  "properties": {
    "gn:admin1_code":"13.0",
    "gn:admin2_code":"1206.0",
    "gn:admin3_code":"120651.0",
    "gn:asciiname":"Trinidad",
    "gn:country_code":"EC",
    "gn:dem":15,
    "gn:feature_class":"P",
    "gn:feature_code":"PPL",
    "gn:name":"Trinidad",
    "gn:population":0,
    "gn:timezone":"America/Guayaquil",
    "iso:country":"EC",
    "wof:name":"Trinidad",
    "wof:placetype":"locality"
},
  "geometry": {"coordinates":[-79.46666999999999,-1.56667],"type":"Point"}
}