{
  "type": "Feature",
  "properties": {
    "gn:admin1_code":"10.0",
    "gn:admin2_code":"903.0",
    "gn:admin3_code":"90350.0",
    "gn:asciiname":"Hacienda La Italia",
    "gn:country_code":"EC",
    "gn:dem":22,
    "gn:feature_class":"P",
    "gn:feature_code":"PPL",
    "gn:name":"Hacienda La Italia",
    "gn:population":0,
    "gn:timezone":"America/Guayaquil",
    "iso:country":"EC",
    "wof:name":"Hacienda La Italia",
    "wof:placetype":"locality"
},
  "geometry": {"coordinates":[-79.74228000000002,-2.91979],"type":"Point"}
}