{
  "type": "Feature",
  "properties": {
    "gn:admin1_code":"10.0",
    "gn:admin2_code":"908.0",
    "gn:admin3_code":"90850.0",
    "gn:asciiname":"Hacienda Las Americas",
    "gn:cc2":"EC",
    "gn:country_code":"EC",
    "gn:dem":59,
    "gn:feature_class":"P",
    "gn:feature_code":"PPL",
    "gn:name":"Hacienda Las Am\u00e9ricas",
    "gn:population":0,
    "gn:timezone":"America/Guayaquil",
    "iso:country":"EC",
    "wof:name":"Hacienda Las Americas",
    "wof:placetype":"locality"
},
  "geometry": {"coordinates":[-79.63333,-1.05],"type":"Point"}
}