{
  "type": "Feature",
  "properties": {
    "iso:country":"EC",
    "qs:gn_pop":0,
    "qs:name":"Saquisili",
    "qs:name_adm0":"Ecuador",
    "qs:name_adm1":"Cotopaxi",
    "qs:photos":1,
    "qs:photos_1k":1,
    "qs:photos_9k":2,
    "qs:photos_9r":5,
    "qs:photos_all":464,
    "qs:photos_sr":1,
    "qs:placetype":"LocalAdmin",
    "qs:pop_sr":"0",
    "qs:woe_adm0":23424801,
    "wof:name":"Saquisili",
    "wof:placetype":"localadmin"
},
  "geometry": {"coordinates":[-78.669662,-0.829999],"type":"Point"}
}