{
  "type": "Feature",
  "properties": {
    "gn:admin1_code":"2.0",
    "gn:admin2_code":"102.0",
    "gn:admin3_code":"10251.0",
    "gn:asciiname":"Lentag",
    "gn:country_code":"EC",
    "gn:dem":1556,
    "gn:feature_class":"P",
    "gn:feature_code":"PPL",
    "gn:name":"Lentag",
    "gn:population":0,
    "gn:timezone":"America/Guayaquil",
    "iso:country":"EC",
    "wof:name":"Lentag",
    "wof:placetype":"locality"
},
  "geometry": {"coordinates":[-79.24101,-3.24528],"type":"Point"}
}