{
  "type": "Feature",
  "properties": {
    "gn:admin1_code":"20.0",
    "gn:admin2_code":"1909.0",
    "gn:admin3_code":"190950.0",
    "gn:asciiname":"Paquisha",
    "gn:country_code":"EC",
    "gn:dem":822,
    "gn:feature_class":"P",
    "gn:feature_code":"PPL",
    "gn:name":"Paquisha",
    "gn:population":0,
    "gn:timezone":"America/Guayaquil",
    "iso:country":"EC",
    "wof:name":"Paquisha",
    "wof:placetype":"locality"
},
  "geometry": {"coordinates":[-78.67562,-3.93391],"type":"Point"}
}