{
  "type": "Feature",
  "properties": {
    "gn:admin1_code":"7.0",
    "gn:admin2_code":"501.0",
    "gn:admin3_code":"50156.0",
    "gn:asciiname":"Rumipamba Villacis",
    "gn:country_code":"EC",
    "gn:dem":3095,
    "gn:feature_class":"P",
    "gn:feature_code":"PPL",
    "gn:name":"Rumipamba Villac\u00eds",
    "gn:population":0,
    "gn:timezone":"America/Guayaquil",
    "iso:country":"EC",
    "wof:name":"Rumipamba Villacis",
    "wof:placetype":"locality"
},
  "geometry": {"coordinates":[-78.56235,-0.7495],"type":"Point"}
}