{
  "type": "Feature",
  "properties": {
    "iso:country":"EC",
    "name:ceb_x_preferred":[
        "El Triunfo"
    ],
    "name:deu_x_preferred":[
        "El Triunfo"
    ],
    "name:eng_x_preferred":[
        "El Triunfo"
    ],
    "name:fra_x_preferred":[
        "El Triunfo"
    ],
    "name:hbs_x_preferred":[
        "El Triunfo"
    ],
    "name:ita_x_preferred":[
        "El Triunfo"
    ],
    "name:nld_x_preferred":[
        "El Triunfo"
    ],
    "name:pol_x_preferred":[
        "El Triunfo"
    ],
    "name:por_x_preferred":[
        "El Triunfo"
    ],
    "name:rus_x_preferred":[
        "\u042d\u043b\u044c-\u0422\u0440\u0438\u0443\u043d\u0444\u043e"
    ],
    "name:spa_x_preferred":[
        "El Triunfo"
    ],
    "name:srp_x_preferred":[
        "\u0415\u043b \u0422\u0440\u0438\u0443\u043d\u0444\u043e"
    ],
    "name:swe_x_preferred":[
        "El Triunfo"
    ],
    "name:zho_x_preferred":[
        "\u8607\u65af\u5361\u723e\u7e23"
    ],
    "qs:gn_country":"EC",
    "qs:gn_fcode":"PPL",
    "qs:gn_pop":32282,
    "qs:name":"El Triunfo",
    "qs:name_adm0":"Ecuador",
    "qs:name_adm1":"Guayas",
    "qs:photos":0,
    "qs:photos_1k":0,
    "qs:photos_9k":0,
    "qs:photos_9r":0,
    "qs:photos_all":0,
    "qs:photos_sr":0,
    "qs:placetype":"Town",
    "qs:pop_sr":"7",
    "qs:woe_adm0":23424801,
    "wd:wordcount":51,
    "wof:name":"El Triunfo",
    "wof:placetype":"locality",
    "wof:population":32282
},
  "geometry": {"coordinates":[-79.96666999999999,-1.93333],"type":"Point"}
}