{
  "type": "Feature",
  "properties": {
    "gn:admin1_code":"18.0",
    "gn:admin2_code":"1701.0",
    "gn:admin3_code":"170163.0",
    "gn:asciiname":"Hacienda La Victoria",
    "gn:cc2":"EC",
    "gn:country_code":"EC",
    "gn:dem":2252,
    "gn:feature_class":"P",
    "gn:feature_code":"PPL",
    "gn:name":"Hacienda La Victoria",
    "gn:population":0,
    "gn:timezone":"America/Guayaquil",
    "iso:country":"EC",
    "wof:name":"Hacienda La Victoria",
    "wof:placetype":"locality"
},
  "geometry": {"coordinates":[-78.31667,-0.05],"type":"Point"}
}