{
  "type": "Feature",
  "properties": {
    "gn:admin1_code":"19.0",
    "gn:admin2_code":"1802.0",
    "gn:admin3_code":"180253.0",
    "gn:asciiname":"Agoyan",
    "gn:country_code":"EC",
    "gn:dem":2298,
    "gn:feature_class":"P",
    "gn:feature_code":"PPL",
    "gn:name":"Agoy\u00e1n",
    "gn:population":0,
    "gn:timezone":"America/Guayaquil",
    "iso:country":"EC",
    "wof:name":"Agoyan",
    "wof:placetype":"locality"
},
  "geometry": {"coordinates":[-78.31667,-1.38333],"type":"Point"}
}