{
  "type": "Feature",
  "properties": {
    "gn:admin1_code":"26.0",
    "gn:admin2_code":"2301.0",
    "gn:admin3_code":"230150.0",
    "gn:asciiname":"San Pablo de Chila",
    "gn:country_code":"EC",
    "gn:dem":380,
    "gn:feature_class":"P",
    "gn:feature_code":"PPL",
    "gn:name":"San Pablo de Chila",
    "gn:population":0,
    "gn:timezone":"America/Guayaquil",
    "iso:country":"EC",
    "wof:name":"San Pablo de Chila",
    "wof:placetype":"locality"
},
  "geometry": {"coordinates":[-79.2589,-0.20583],"type":"Point"}
}