{
  "type": "Feature",
  "properties": {
    "gn:admin1_code":"13.0",
    "gn:admin2_code":"1204.0",
    "gn:admin3_code":"120451.0",
    "gn:asciiname":"Puerto Pechiche",
    "gn:country_code":"EC",
    "gn:dem":24,
    "gn:feature_class":"P",
    "gn:feature_code":"PPL",
    "gn:name":"Puerto Pechiche",
    "gn:population":0,
    "gn:timezone":"America/Guayaquil",
    "iso:country":"EC",
    "wof:name":"Puerto Pechiche",
    "wof:placetype":"locality"
},
  "geometry": {"coordinates":[-79.56667,-1.43333],"type":"Point"}
}