{
  "type": "Feature",
  "properties": {
    "gn:admin1_code":"5.0",
    "gn:admin2_code":"405.0",
    "gn:admin3_code":"40552.0",
    "gn:asciiname":"Hacienda El Salado",
    "gn:country_code":"EC",
    "gn:dem":2742,
    "gn:feature_class":"P",
    "gn:feature_code":"PPL",
    "gn:name":"Hacienda El Salado",
    "gn:population":0,
    "gn:timezone":"America/Guayaquil",
    "iso:country":"EC",
    "wof:name":"Hacienda El Salado",
    "wof:placetype":"locality"
},
  "geometry": {"coordinates":[-77.78100000000001,0.59181],"type":"Point"}
}