{
  "type": "Feature",
  "properties": {
    "gn:admin1_code":"18.0",
    "gn:admin2_code":"1701.0",
    "gn:admin3_code":"170150.0",
    "gn:asciiname":"Hacienda El Conde",
    "gn:cc2":"EC",
    "gn:country_code":"EC",
    "gn:dem":2978,
    "gn:feature_class":"P",
    "gn:feature_code":"PPL",
    "gn:name":"Hacienda El Conde",
    "gn:population":0,
    "gn:timezone":"America/Guayaquil",
    "iso:country":"EC",
    "wof:name":"Hacienda El Conde",
    "wof:placetype":"locality"
},
  "geometry": {"coordinates":[-78.53333000000001,-0.31667],"type":"Point"}
}