{
  "type": "Feature",
  "properties": {
    "gn:admin1_code":"5.0",
    "gn:admin2_code":"401.0",
    "gn:admin3_code":"40153.0",
    "gn:asciiname":"Hacienda San Joaquin",
    "gn:country_code":"EC",
    "gn:dem":3173,
    "gn:feature_class":"P",
    "gn:feature_code":"PPL",
    "gn:name":"Hacienda San Joaqu\u00edn",
    "gn:population":0,
    "gn:timezone":"America/Guayaquil",
    "iso:country":"EC",
    "wof:name":"Hacienda San Joaquin",
    "wof:placetype":"locality"
},
  "geometry": {"coordinates":[-77.71758,0.69863],"type":"Point"}
}