{
  "type": "Feature",
  "properties": {
    "gn:admin1_code":"3.0",
    "gn:admin2_code":"205.0",
    "gn:admin3_code":"20551.0",
    "gn:asciiname":"Balzapamba",
    "gn:country_code":"EC",
    "gn:dem":732,
    "gn:feature_class":"P",
    "gn:feature_code":"PPL",
    "gn:name":"Balzapamba",
    "gn:population":0,
    "gn:timezone":"America/Guayaquil",
    "iso:country":"EC",
    "wof:name":"Balzapamba",
    "wof:placetype":"locality"
},
  "geometry": {"coordinates":[-79.18616999999998,-1.76701],"type":"Point"}
}