{
  "type": "Feature",
  "properties": {
    "gn:admin1_code":"11.0",
    "gn:admin2_code":"1003.0",
    "gn:admin3_code":"100352.0",
    "gn:asciiname":"Junin",
    "gn:country_code":"EC",
    "gn:dem":1283,
    "gn:feature_class":"P",
    "gn:feature_code":"PPL",
    "gn:name":"Jun\u00edn",
    "gn:population":0,
    "gn:timezone":"America/Guayaquil",
    "iso:country":"EC",
    "wof:name":"Junin",
    "wof:placetype":"locality"
},
  "geometry": {"coordinates":[-78.66195,0.27546],"type":"Point"}
}