{
  "type": "Feature",
  "properties": {
    "gn:admin1_code":"10.0",
    "gn:admin2_code":"904.0",
    "gn:admin3_code":"90450.0",
    "gn:asciiname":"Hacienda Guarumito",
    "gn:cc2":"EC",
    "gn:country_code":"EC",
    "gn:dem":35,
    "gn:feature_class":"P",
    "gn:feature_code":"PPL",
    "gn:name":"Hacienda Guarumito",
    "gn:population":0,
    "gn:timezone":"America/Guayaquil",
    "iso:country":"EC",
    "wof:name":"Hacienda Guarumito",
    "wof:placetype":"locality"
},
  "geometry": {"coordinates":[-79.96666999999999,-1.36667],"type":"Point"}
}