{
  "type": "Feature",
  "properties": {
    "iso:country":"EC",
    "qs:gn_pop":0,
    "qs:name":"Pa\u00f1acocha",
    "qs:name_adm0":"Ecuador",
    "qs:name_adm1":"Sucumbios",
    "qs:photos":42,
    "qs:photos_1k":9,
    "qs:photos_9k":1,
    "qs:photos_9r":4,
    "qs:photos_all":175,
    "qs:photos_sr":2,
    "qs:placetype":"LocalAdmin",
    "qs:pop_sr":"0",
    "qs:woe_adm0":23424801,
    "wof:name":"Pa\u00f1acocha",
    "wof:placetype":"localadmin"
},
  "geometry": {"coordinates":[-76.11753899999999,-0.408308],"type":"Point"}
}