{
  "type": "Feature",
  "properties": {
    "gn:admin1_code":"6.0",
    "gn:admin2_code":"607.0",
    "gn:admin3_code":"60754.0",
    "gn:asciiname":"San Andres",
    "gn:country_code":"EC",
    "gn:dem":3007,
    "gn:feature_class":"P",
    "gn:feature_code":"PPL",
    "gn:name":"San Andr\u00e9s",
    "gn:population":0,
    "gn:timezone":"America/Guayaquil",
    "iso:country":"EC",
    "wof:name":"San Andres",
    "wof:placetype":"locality"
},
  "geometry": {"coordinates":[-78.70251,-1.59216],"type":"Point"}
}