{
  "type": "Feature",
  "properties": {
    "gn:admin1_code":"12.0",
    "gn:admin2_code":"1113.0",
    "gn:admin3_code":"111350.0",
    "gn:asciiname":"Catamaillo",
    "gn:country_code":"EC",
    "gn:dem":232,
    "gn:feature_class":"P",
    "gn:feature_code":"PPL",
    "gn:name":"Catamaillo",
    "gn:population":0,
    "gn:timezone":"America/Guayaquil",
    "iso:country":"EC",
    "wof:name":"Catamaillo",
    "wof:placetype":"locality"
},
  "geometry": {"coordinates":[-80.22277,-4.35187],"type":"Point"}
}