{
  "type": "Feature",
  "properties": {
    "gn:admin1_code":"7.0",
    "gn:admin2_code":"501.0",
    "gn:admin3_code":"50162.0",
    "gn:asciiname":"Chambapata",
    "gn:country_code":"EC",
    "gn:dem":3541,
    "gn:feature_class":"P",
    "gn:feature_code":"PPL",
    "gn:name":"Chambapata",
    "gn:population":0,
    "gn:timezone":"America/Guayaquil",
    "iso:country":"EC",
    "wof:name":"Chambapata",
    "wof:placetype":"locality"
},
  "geometry": {"coordinates":[-78.8137,-0.75318],"type":"Point"}
}