{
  "type": "Feature",
  "properties": {
    "gn:admin1_code":"2.0",
    "gn:admin2_code":"102.0",
    "gn:admin3_code":"10252.0",
    "gn:asciiname":"Cuchiloma",
    "gn:country_code":"EC",
    "gn:dem":2602,
    "gn:feature_class":"P",
    "gn:feature_code":"PPL",
    "gn:name":"Cuchiloma",
    "gn:population":0,
    "gn:timezone":"America/Guayaquil",
    "iso:country":"EC",
    "wof:name":"Cuchiloma",
    "wof:placetype":"locality"
},
  "geometry": {"coordinates":[-79.21666999999999,-3.15],"type":"Point"}
}