{
  "type": "Feature",
  "properties": {
    "gn:admin1_code":"22.0",
    "gn:admin2_code":"2105.0",
    "gn:admin3_code":"210553.0",
    "gn:asciiname":"La Barquilla",
    "gn:cc2":"EC",
    "gn:country_code":"EC",
    "gn:dem":847,
    "gn:feature_class":"P",
    "gn:feature_code":"PPL",
    "gn:name":"La Barquilla",
    "gn:population":0,
    "gn:timezone":"America/Guayaquil",
    "iso:country":"EC",
    "wof:name":"La Barquilla",
    "wof:placetype":"locality"
},
  "geometry": {"coordinates":[-77.46306,0.30472],"type":"Point"}
}