{
  "type": "Feature",
  "properties": {
    "gn:admin1_code":"4.0",
    "gn:asciiname":"Jumcamal",
    "gn:country_code":"EC",
    "gn:dem":1149,
    "gn:feature_class":"P",
    "gn:feature_code":"PPL",
    "gn:name":"Jumcamal",
    "gn:population":0,
    "gn:timezone":"America/Guayaquil",
    "iso:country":"EC",
    "wof:name":"Jumcamal",
    "wof:placetype":"locality"
},
  "geometry": {"coordinates":[-79.06496,-2.23255],"type":"Point"}
}