{
  "type": "Feature",
  "properties": {
    "gn:admin1_code":"0.0",
    "gn:asciiname":"La Cuarenta",
    "gn:country_code":"EC",
    "gn:dem":161,
    "gn:feature_class":"P",
    "gn:feature_code":"PPL",
    "gn:name":"La Cuarenta",
    "gn:population":0,
    "gn:timezone":"America/Guayaquil",
    "iso:country":"EC",
    "wof:name":"La Cuarenta",
    "wof:placetype":"locality"
},
  "geometry": {"coordinates":[-79.50613,-0.53699],"type":"Point"}
}