{
  "type": "Feature",
  "properties": {
    "gn:admin1_code":"18.0",
    "gn:admin2_code":"1702.0",
    "gn:admin3_code":"170252.0",
    "gn:asciiname":"Paccha",
    "gn:country_code":"EC",
    "gn:dem":3447,
    "gn:feature_class":"P",
    "gn:feature_code":"PPL",
    "gn:name":"Paccha",
    "gn:population":0,
    "gn:timezone":"America/Guayaquil",
    "iso:country":"EC",
    "wof:name":"Paccha",
    "wof:placetype":"locality"
},
  "geometry": {"coordinates":[-78.18333,-0.06667],"type":"Point"}
}