{
  "type": "Feature",
  "properties": {
    "gn:admin1_code":"19.0",
    "gn:admin2_code":"1807.0",
    "gn:admin3_code":"180750.0",
    "gn:asciiname":"Pingue",
    "gn:country_code":"EC",
    "gn:dem":2059,
    "gn:feature_class":"P",
    "gn:feature_code":"PPL",
    "gn:name":"Pingue",
    "gn:population":0,
    "gn:timezone":"America/Guayaquil",
    "iso:country":"EC",
    "wof:name":"Pingue",
    "wof:placetype":"locality"
},
  "geometry": {"coordinates":[-78.49979999999999,-1.38108],"type":"Point"}
}