{
  "type": "Feature",
  "properties": {
    "gn:admin1_code":"10.0",
    "gn:admin2_code":"901.0",
    "gn:admin3_code":"90150.0",
    "gn:asciiname":"Hacienda San Juano",
    "gn:cc2":"EC",
    "gn:country_code":"EC",
    "gn:dem":65,
    "gn:feature_class":"P",
    "gn:feature_code":"PPL",
    "gn:name":"Hacienda San Juano",
    "gn:population":0,
    "gn:timezone":"America/Guayaquil",
    "iso:country":"EC",
    "wof:name":"Hacienda San Juano",
    "wof:placetype":"locality"
},
  "geometry": {"coordinates":[-80.23333000000002,-2.31667],"type":"Point"}
}