{
  "type": "Feature",
  "properties": {
    "gn:admin1_code":"10.0",
    "gn:admin2_code":"916.0",
    "gn:admin3_code":"91650.0",
    "gn:asciiname":"Violeta",
    "gn:country_code":"EC",
    "gn:dem":87,
    "gn:feature_class":"P",
    "gn:feature_code":"PPL",
    "gn:name":"Violeta",
    "gn:population":0,
    "gn:timezone":"America/Guayaquil",
    "iso:country":"EC",
    "name:cat_x_preferred":[
        "Violeta"
    ],
    "name:ceb_x_preferred":[
        "Violeta"
    ],
    "name:glg_x_preferred":[
        "Violeta"
    ],
    "name:por_x_preferred":[
        "Violeta"
    ],
    "name:spa_x_preferred":[
        "Violeta"
    ],
    "name:swe_x_preferred":[
        "Violeta"
    ],
    "wof:name":"Violeta",
    "wof:placetype":"locality"
},
  "geometry": {"coordinates":[-79.75,-1.93333],"type":"Point"}
}