{
  "type": "Feature",
  "properties": {
    "iso:country":"EC",
    "name:ceb_x_preferred":[
        "Zaruma"
    ],
    "name:deu_x_preferred":[
        "Zaruma"
    ],
    "name:eng_x_preferred":[
        "Zaruma"
    ],
    "name:fra_x_preferred":[
        "Zaruma"
    ],
    "name:ita_x_preferred":[
        "Zaruma"
    ],
    "name:jpn_x_preferred":[
        "\u30b5\u30eb\u30de"
    ],
    "name:lit_x_preferred":[
        "Saruma"
    ],
    "name:nld_x_preferred":[
        "Zaruma"
    ],
    "name:pol_x_preferred":[
        "Zaruma"
    ],
    "name:que_x_preferred":[
        "Saruma"
    ],
    "name:spa_x_preferred":[
        "Zaruma"
    ],
    "name:swe_x_preferred":[
        "Zaruma"
    ],
    "name:unk_x_variant":[
        "Zaruma"
    ],
    "name:war_x_preferred":[
        "Zaruma"
    ],
    "qs:gn_country":"EC",
    "qs:gn_fcode":"PPL",
    "qs:gn_pop":12505,
    "qs:name":"Zarumilla",
    "qs:name_adm0":"Per\u00fa",
    "qs:name_adm1":"Tumbes",
    "qs:photos":209,
    "qs:photos_1k":42,
    "qs:photos_9k":1,
    "qs:photos_9r":4,
    "qs:photos_all":209,
    "qs:photos_sr":4,
    "qs:placetype":"Town",
    "qs:pop_sr":"6",
    "qs:woe_adm0":23424919,
    "wof:name":"Zarumilla",
    "wof:placetype":"locality",
    "wof:population":12505
},
  "geometry": {"coordinates":[-79.61174,-3.69132],"type":"Point"}
}