{
  "type": "Feature",
  "properties": {
    "gn:admin1_code":"10.0",
    "gn:admin2_code":"908.0",
    "gn:admin3_code":"90850.0",
    "gn:asciiname":"Hacienda Porvenir",
    "gn:country_code":"EC",
    "gn:dem":71,
    "gn:feature_class":"P",
    "gn:feature_code":"PPL",
    "gn:name":"Hacienda Porvenir",
    "gn:population":0,
    "gn:timezone":"America/Guayaquil",
    "iso:country":"EC",
    "wof:name":"Hacienda Porvenir",
    "wof:placetype":"locality"
},
  "geometry": {"coordinates":[-79.65116999999999,-1.09976],"type":"Point"}
}