{
  "type": "Feature",
  "properties": {
    "gn:admin1_code":"13.0",
    "gn:admin2_code":"1201.0",
    "gn:admin3_code":"120153.0",
    "gn:asciiname":"San Roman",
    "gn:country_code":"EC",
    "gn:dem":19,
    "gn:feature_class":"P",
    "gn:feature_code":"PPL",
    "gn:name":"San Rom\u00e1n",
    "gn:population":0,
    "gn:timezone":"America/Guayaquil",
    "iso:country":"EC",
    "wof:name":"San Roman",
    "wof:placetype":"locality"
},
  "geometry": {"coordinates":[-79.34014999999999,-1.89557],"type":"Point"}
}