{
  "type": "Feature",
  "properties": {
    "gn:admin1_code":"6.0",
    "gn:admin2_code":"607.0",
    "gn:admin3_code":"60751.0",
    "gn:asciiname":"Guanando",
    "gn:country_code":"EC",
    "gn:dem":2469,
    "gn:feature_class":"P",
    "gn:feature_code":"PPL",
    "gn:name":"Guanando",
    "gn:population":0,
    "gn:timezone":"America/Guayaquil",
    "iso:country":"EC",
    "wof:name":"Guanando",
    "wof:placetype":"locality"
},
  "geometry": {"coordinates":[-78.54387,-1.54054],"type":"Point"}
}