{
  "type": "Feature",
  "properties": {
    "gn:admin1_code":"10.0",
    "gn:asciiname":"Puerto Salinas",
    "gn:country_code":"EC",
    "gn:dem":1,
    "gn:feature_class":"P",
    "gn:feature_code":"PPL",
    "gn:name":"Puerto Salinas",
    "gn:population":0,
    "gn:timezone":"America/Guayaquil",
    "iso:country":"EC",
    "wof:name":"Puerto Salinas",
    "wof:placetype":"locality"
},
  "geometry": {"coordinates":[-80.01666999999998,-2.63333],"type":"Point"}
}