{
  "type": "Feature",
  "properties": {
    "gn:admin1_code":"9.0",
    "gn:admin2_code":"802.0",
    "gn:admin3_code":"80255.0",
    "gn:asciiname":"Santiago Playa de Oro",
    "gn:country_code":"EC",
    "gn:dem":66,
    "gn:feature_class":"P",
    "gn:feature_code":"PPL",
    "gn:name":"Santiago Playa de Oro",
    "gn:population":0,
    "gn:timezone":"America/Guayaquil",
    "iso:country":"EC",
    "wof:name":"Santiago Playa de Oro",
    "wof:placetype":"locality"
},
  "geometry": {"coordinates":[-78.79458000000002,0.87628],"type":"Point"}
}