{
  "type": "Feature",
  "properties": {
    "gn:admin1_code":"4.0",
    "gn:admin2_code":"301.0",
    "gn:admin3_code":"30160.0",
    "gn:asciiname":"Gum",
    "gn:country_code":"EC",
    "gn:dem":2918,
    "gn:feature_class":"P",
    "gn:feature_code":"PPL",
    "gn:name":"Gum",
    "gn:population":0,
    "gn:timezone":"America/Guayaquil",
    "iso:country":"EC",
    "name:ceb_x_preferred":[
        "Gum"
    ],
    "name:epo_x_preferred":[
        "GUM"
    ],
    "name:nld_x_preferred":[
        "Gum"
    ],
    "name:ron_x_preferred":[
        "Gum\u0103"
    ],
    "name:rus_x_preferred":[
        "\u0413\u0423\u041c"
    ],
    "name:swe_x_preferred":[
        "GUM"
    ],
    "name:vie_x_preferred":[
        "G\u00f4m"
    ],
    "wof:name":"Gum",
    "wof:placetype":"locality"
},
  "geometry": {"coordinates":[-78.67636,-2.641],"type":"Point"}
}