{
  "type": "Feature",
  "properties": {
    "gn:admin1_code":"18.0",
    "gn:admin2_code":"1701.0",
    "gn:admin3_code":"170168.0",
    "gn:asciiname":"Cariyacu",
    "gn:country_code":"EC",
    "gn:dem":1224,
    "gn:feature_class":"P",
    "gn:feature_code":"PPL",
    "gn:name":"Cariyacu",
    "gn:population":0,
    "gn:timezone":"America/Guayaquil",
    "iso:country":"EC",
    "wof:name":"Cariyacu",
    "wof:placetype":"locality"
},
  "geometry": {"coordinates":[-78.60921999999999,0.16117],"type":"Point"}
}