{
  "type": "Feature",
  "properties": {
    "iso:country":"EC",
    "name:bre_x_preferred":[
        "Quiroga"
    ],
    "name:ceb_x_preferred":[
        "Quiroga"
    ],
    "name:deu_x_preferred":[
        "Quiroga"
    ],
    "name:fra_x_preferred":[
        "Quiroga"
    ],
    "name:glg_x_preferred":[
        "Quiroga"
    ],
    "name:hun_x_preferred":[
        "Quiroga"
    ],
    "name:jpn_x_preferred":[
        "\u30ad\u30ed\u30ac"
    ],
    "name:nds_x_preferred":[
        "Quiroga"
    ],
    "name:nld_x_preferred":[
        "Quiroga"
    ],
    "name:rus_x_preferred":[
        "\u041a\u0438\u0440\u043e\u0433\u0430"
    ],
    "name:sco_x_preferred":[
        "Quiroga"
    ],
    "name:spa_x_preferred":[
        "Quiroga"
    ],
    "name:swe_x_preferred":[
        "Quiroga"
    ],
    "name:ukr_x_preferred":[
        "\u041a\u0456\u0440\u043e\u0433\u0430"
    ],
    "qs:gn_pop":0,
    "qs:name":"Quiroga",
    "qs:name_adm0":"Ecuador",
    "qs:name_adm1":"Imbabura",
    "qs:photos":4,
    "qs:photos_1k":1,
    "qs:photos_9k":1,
    "qs:photos_9r":1,
    "qs:photos_all":21,
    "qs:photos_sr":1,
    "qs:placetype":"LocalAdmin",
    "qs:pop_sr":"0",
    "qs:woe_adm0":23424801,
    "wof:name":"Quiroga",
    "wof:placetype":"localadmin"
},
  "geometry": {"coordinates":[-78.282394,0.30607],"type":"Point"}
}