{
  "type": "Feature",
  "properties": {
    "gn:admin1_code":"12.0",
    "gn:admin2_code":"1112.0",
    "gn:admin3_code":"111252.0",
    "gn:asciiname":"Los Llanitos",
    "gn:country_code":"EC",
    "gn:dem":1335,
    "gn:feature_class":"P",
    "gn:feature_code":"PPL",
    "gn:name":"Los Llanitos",
    "gn:population":0,
    "gn:timezone":"America/Guayaquil",
    "iso:country":"EC",
    "name:ita_x_preferred":[
        "Los Llanitos"
    ],
    "name:spa_x_preferred":[
        "Los Llanitos"
    ],
    "name:zho_x_preferred":[
        "\u6d1b\u65af\u5229\u4e9e\u5c3c\u6258\u65af"
    ],
    "wof:name":"Los Llanitos",
    "wof:placetype":"locality"
},
  "geometry": {"coordinates":[-79.74373,-4.39296],"type":"Point"}
}