{
  "type": "Feature",
  "properties": {
    "gn:admin1_code":"5.0",
    "gn:admin2_code":"403.0",
    "gn:admin3_code":"40351.0",
    "gn:asciiname":"El Goaltal",
    "gn:country_code":"EC",
    "gn:dem":1313,
    "gn:feature_class":"P",
    "gn:feature_code":"PPL",
    "gn:name":"El Goaltal",
    "gn:population":0,
    "gn:timezone":"America/Guayaquil",
    "iso:country":"EC",
    "wof:name":"El Goaltal",
    "wof:placetype":"locality"
},
  "geometry": {"coordinates":[-78.15864000000001,0.80465],"type":"Point"}
}