{
  "type": "Feature",
  "properties": {
    "gn:admin1_code":"20.0",
    "gn:admin2_code":"1904.0",
    "gn:admin3_code":"190450.0",
    "gn:asciiname":"Guando",
    "gn:country_code":"EC",
    "gn:dem":1301,
    "gn:feature_class":"P",
    "gn:feature_code":"PPL",
    "gn:name":"Guando",
    "gn:population":0,
    "gn:timezone":"America/Guayaquil",
    "iso:country":"EC",
    "wof:name":"Guando",
    "wof:placetype":"locality"
},
  "geometry": {"coordinates":[-78.92308,-3.57247],"type":"Point"}
}