{
  "type": "Feature",
  "properties": {
    "gn:admin1_code":"15.0",
    "gn:admin2_code":"1410.0",
    "gn:admin3_code":"141051.0",
    "gn:asciiname":"Cangas",
    "gn:country_code":"EC",
    "gn:dem":585,
    "gn:feature_class":"P",
    "gn:feature_code":"PPL",
    "gn:name":"Cangas",
    "gn:population":0,
    "gn:timezone":"America/Guayaquil",
    "iso:country":"EC",
    "wof:name":"Cangas",
    "wof:placetype":"locality"
},
  "geometry": {"coordinates":[-77.9225,-2.91472],"type":"Point"}
}