{
  "type": "Feature",
  "properties": {
    "gn:admin1_code":"4.0",
    "gn:admin2_code":"301.0",
    "gn:admin3_code":"30157.0",
    "gn:asciiname":"Rivera",
    "gn:country_code":"EC",
    "gn:dem":2724,
    "gn:feature_class":"P",
    "gn:feature_code":"PPL",
    "gn:name":"Rivera",
    "gn:population":0,
    "gn:timezone":"America/Guayaquil",
    "iso:country":"EC",
    "name:ara_x_preferred":[
        "\u0631\u064a\u0641\u064a\u0631\u0627"
    ],
    "name:ast_x_preferred":[
        "Rivera"
    ],
    "name:ben_x_preferred":[
        "\u09b0\u09bf\u09ac\u09c7\u09b0\u09be"
    ],
    "name:bul_x_preferred":[
        "\u0420\u0438\u0432\u0435\u0440\u0430"
    ],
    "name:cat_x_preferred":[
        "Rivera"
    ],
    "name:ceb_x_preferred":[
        "Rivera"
    ],
    "name:ces_x_preferred":[
        "Rivera"
    ],
    "name:dan_x_preferred":[
        "Rivera"
    ],
    "name:deu_x_preferred":[
        "Rivera"
    ],
    "name:fas_x_preferred":[
        "\u0631\u06cc\u0648\u0631\u0627"
    ],
    "name:fra_x_preferred":[
        "Rivera"
    ],
    "name:heb_x_preferred":[
        "\u05e8\u05d9\u05d1\u05e8\u05d4"
    ],
    "name:hrv_x_preferred":[
        "Rivera"
    ],
    "name:hye_x_preferred":[
        "\u054c\u056b\u057e\u0565\u0580\u0561"
    ],
    "name:ita_x_preferred":[
        "Rivera"
    ],
    "name:jpn_x_preferred":[
        "\u30ea\u30d9\u30e9"
    ],
    "name:kat_x_preferred":[
        "\u10e0\u10d8\u10d5\u10d4\u10e0\u10d0"
    ],
    "name:kor_x_preferred":[
        "\ub9ac\ubca0\ub77c"
    ],
    "name:lit_x_preferred":[
        "Rivera"
    ],
    "name:nld_x_preferred":[
        "Rivera"
    ],
    "name:nor_x_preferred":[
        "Rivera"
    ],
    "name:pol_x_preferred":[
        "Rivera"
    ],
    "name:por_x_preferred":[
        "Rivera"
    ],
    "name:que_x_preferred":[
        "Rivera"
    ],
    "name:rus_x_preferred":[
        "\u0420\u0438\u0432\u0435\u0440\u0430"
    ],
    "name:slk_x_preferred":[
        "Rivera"
    ],
    "name:spa_x_preferred":[
        "Rivera"
    ],
    "name:swe_x_preferred":[
        "Rivera"
    ],
    "name:tha_x_preferred":[
        "\u0e23\u0e34\u0e40\u0e1a\u0e23\u0e32"
    ],
    "name:tur_x_preferred":[
        "Rivera"
    ],
    "name:ukr_x_preferred":[
        "\u0420\u0456\u0432\u0435\u0440\u0430"
    ],
    "name:urd_x_preferred":[
        "\u0631\u06cc\u0648\u06cc\u0631\u0627"
    ],
    "name:vol_x_preferred":[
        "Rivera"
    ],
    "name:war_x_preferred":[
        "Rivera"
    ],
    "name:zho_x_preferred":[
        "\u91cc\u97e6\u62c9"
    ],
    "wof:name":"Rivera",
    "wof:placetype":"locality"
},
  "geometry": {"coordinates":[-78.65000000000001,-2.58333],"type":"Point"}
}