{
  "type": "Feature",
  "properties": {
    "gn:admin1_code":"8.0",
    "gn:admin2_code":"710.0",
    "gn:admin3_code":"71050.0",
    "gn:asciiname":"Zarumaurcu",
    "gn:cc2":"EC",
    "gn:country_code":"EC",
    "gn:dem":991,
    "gn:feature_class":"P",
    "gn:feature_code":"PPL",
    "gn:name":"Zarumaurcu",
    "gn:population":0,
    "gn:timezone":"America/Guayaquil",
    "iso:country":"EC",
    "wof:name":"Zarumaurcu",
    "wof:placetype":"locality"
},
  "geometry": {"coordinates":[-79.65000000000001,-3.66667],"type":"Point"}
}