{
  "type": "Feature",
  "properties": {
    "iso:country":"EC",
    "name:unk_x_variant":[
        "A. Maldonado"
    ],
    "qs:gn_country":"EC",
    "qs:gn_fcode":"PPL",
    "qs:gn_pop":0,
    "qs:name":"San Roque",
    "qs:name_adm0":"Ecuador",
    "qs:name_adm1":"El Oro",
    "qs:photos":366,
    "qs:photos_1k":74,
    "qs:photos_9k":2,
    "qs:photos_9r":5,
    "qs:photos_all":366,
    "qs:photos_sr":6,
    "qs:placetype":"Town",
    "qs:pop_sr":"0",
    "qs:woe_adm0":23424801,
    "wof:name":"San Roque",
    "wof:placetype":"locality"
},
  "geometry": {"coordinates":[-79.67231,-3.72629],"type":"Point"}
}