{
  "type": "Feature",
  "properties": {
    "gn:admin1_code":"11.0",
    "gn:admin2_code":"1002.0",
    "gn:admin3_code":"100253.0",
    "gn:asciiname":"Hacienda San Ricardo",
    "gn:cc2":"EC",
    "gn:country_code":"EC",
    "gn:dem":2197,
    "gn:feature_class":"P",
    "gn:feature_code":"PPL",
    "gn:name":"Hacienda San Ricardo",
    "gn:population":0,
    "gn:timezone":"America/Guayaquil",
    "iso:country":"EC",
    "wof:name":"Hacienda San Ricardo",
    "wof:placetype":"locality"
},
  "geometry": {"coordinates":[-78.18333,0.36667],"type":"Point"}
}