{
  "type": "Feature",
  "properties": {
    "gn:admin1_code":"9.0",
    "gn:admin2_code":"802.0",
    "gn:admin3_code":"80263.0",
    "gn:asciiname":"Atahualpa",
    "gn:country_code":"EC",
    "gn:dem":65,
    "gn:feature_class":"P",
    "gn:feature_code":"PPL",
    "gn:name":"Atahualpa",
    "gn:population":0,
    "gn:timezone":"America/Guayaquil",
    "iso:country":"EC",
    "wof:name":"Atahualpa",
    "wof:placetype":"locality"
},
  "geometry": {"coordinates":[-78.98333000000002,0.86667],"type":"Point"}
}