{
  "type": "Feature",
  "properties": {
    "gn:admin1_code":"11.0",
    "gn:admin2_code":"1001.0",
    "gn:admin3_code":"100152.0",
    "gn:asciiname":"Hacienda Cochicaranqui",
    "gn:cc2":"EC",
    "gn:country_code":"EC",
    "gn:dem":2693,
    "gn:feature_class":"P",
    "gn:feature_code":"PPL",
    "gn:name":"Hacienda Cochicaranqui",
    "gn:population":0,
    "gn:timezone":"America/Guayaquil",
    "iso:country":"EC",
    "wof:name":"Hacienda Cochicaranqui",
    "wof:placetype":"locality"
},
  "geometry": {"coordinates":[-78.08333,0.25],"type":"Point"}
}