{
  "type": "Feature",
  "properties": {
    "gn:admin1_code":"26.0",
    "gn:admin2_code":"2301.0",
    "gn:admin3_code":"230157.0",
    "gn:asciiname":"Santa Maria del Toachi",
    "gn:country_code":"EC",
    "gn:dem":349,
    "gn:feature_class":"P",
    "gn:feature_code":"PPL",
    "gn:name":"Santa Mar\u00eda del Toachi",
    "gn:population":0,
    "gn:timezone":"America/Guayaquil",
    "iso:country":"EC",
    "wof:name":"Santa Maria del Toachi",
    "wof:placetype":"locality"
},
  "geometry": {"coordinates":[-79.22742,-0.63715],"type":"Point"}
}