{
  "type": "Feature",
  "properties": {
    "gn:admin1_code":"5.0",
    "gn:admin2_code":"401.0",
    "gn:admin3_code":"40157.0",
    "gn:asciiname":"Gonzalez Suarez",
    "gn:cc2":"EC",
    "gn:country_code":"EC",
    "gn:dem":3281,
    "gn:feature_class":"P",
    "gn:feature_code":"PPL",
    "gn:name":"Gonz\u00e1lez Su\u00e1rez",
    "gn:population":0,
    "gn:timezone":"America/Guayaquil",
    "iso:country":"EC",
    "wof:name":"Gonzalez Suarez",
    "wof:placetype":"locality"
},
  "geometry": {"coordinates":[-77.84999999999999,0.78333],"type":"Point"}
}