{
  "type": "Feature",
  "properties": {
    "gn:admin1_code":"18.0",
    "gn:admin2_code":"1701.0",
    "gn:admin3_code":"170172.0",
    "gn:asciiname":"Pacto",
    "gn:country_code":"EC",
    "gn:dem":1212,
    "gn:feature_class":"P",
    "gn:feature_code":"PPL",
    "gn:name":"Pacto",
    "gn:population":0,
    "gn:timezone":"America/Guayaquil",
    "iso:country":"EC",
    "name:por_x_preferred":[
        "Pacto"
    ],
    "name:spa_x_preferred":[
        "Pacto"
    ],
    "wof:name":"Pacto",
    "wof:placetype":"locality"
},
  "geometry": {"coordinates":[-78.76564999999999,0.14532],"type":"Point"}
}