{
  "type": "Feature",
  "properties": {
    "gn:admin1_code":"8.0",
    "gn:admin2_code":"708.0",
    "gn:admin3_code":"70851.0",
    "gn:asciiname":"El Ingenio",
    "gn:country_code":"EC",
    "gn:dem":578,
    "gn:feature_class":"P",
    "gn:feature_code":"PPL",
    "gn:name":"El Ingenio",
    "gn:population":0,
    "gn:timezone":"America/Guayaquil",
    "iso:country":"EC",
    "wof:name":"El Ingenio",
    "wof:placetype":"locality"
},
  "geometry": {"coordinates":[-79.93037,-3.73495],"type":"Point"}
}