{
  "type": "Feature",
  "properties": {
    "gn:admin1_code":"12.0",
    "gn:admin2_code":"1113.0",
    "gn:admin3_code":"111353.0",
    "gn:asciiname":"Pilares",
    "gn:country_code":"EC",
    "gn:dem":268,
    "gn:feature_class":"P",
    "gn:feature_code":"PPL",
    "gn:name":"Pilares",
    "gn:population":0,
    "gn:timezone":"America/Guayaquil",
    "iso:country":"EC",
    "name:ita_x_preferred":[
        "Pilares"
    ],
    "name:por_x_preferred":[
        "Pilares"
    ],
    "wof:name":"Pilares",
    "wof:placetype":"locality"
},
  "geometry": {"coordinates":[-80.43333,-4.36667],"type":"Point"}
}