{
  "type": "Feature",
  "properties": {
    "gn:admin1_code":"2.0",
    "gn:asciiname":"Mollepungo",
    "gn:country_code":"EC",
    "gn:dem":1542,
    "gn:feature_class":"P",
    "gn:feature_code":"PPL",
    "gn:name":"Mollepungo",
    "gn:population":0,
    "gn:timezone":"America/Guayaquil",
    "iso:country":"EC",
    "wof:name":"Mollepungo",
    "wof:placetype":"locality"
},
  "geometry": {"coordinates":[-79.65000000000001,-3.23333],"type":"Point"}
}