{
  "type": "Feature",
  "properties": {
    "gn:admin1_code":"10.0",
    "gn:admin2_code":"919.0",
    "gn:admin3_code":"91950.0",
    "gn:asciiname":"Mina de Oro",
    "gn:country_code":"EC",
    "gn:dem":5,
    "gn:feature_class":"P",
    "gn:feature_code":"PPL",
    "gn:name":"Mina de Oro",
    "gn:population":0,
    "gn:timezone":"America/Guayaquil",
    "iso:country":"EC",
    "wof:name":"Mina de Oro",
    "wof:placetype":"locality"
},
  "geometry": {"coordinates":[-79.84869,-1.79959],"type":"Point"}
}