{
  "type": "Feature",
  "properties": {
    "gn:admin1_code":"15.0",
    "gn:admin2_code":"1410.0",
    "gn:admin3_code":"141051.0",
    "gn:asciiname":"Tsawantas",
    "gn:country_code":"EC",
    "gn:dem":327,
    "gn:feature_class":"P",
    "gn:feature_code":"PPL",
    "gn:name":"Tsawantas",
    "gn:population":0,
    "gn:timezone":"America/Guayaquil",
    "iso:country":"EC",
    "wof:name":"Tsawantas",
    "wof:placetype":"locality"
},
  "geometry": {"coordinates":[-77.94516,-2.8799],"type":"Point"}
}