{
  "type": "Feature",
  "properties": {
    "gn:admin1_code":"7.0",
    "gn:admin2_code":"501.0",
    "gn:admin3_code":"50151.0",
    "gn:asciiname":"Hacienda Cuchitingue",
    "gn:country_code":"EC",
    "gn:dem":3247,
    "gn:feature_class":"P",
    "gn:feature_code":"PPL",
    "gn:name":"Hacienda Cuchitingue",
    "gn:population":0,
    "gn:timezone":"America/Guayaquil",
    "iso:country":"EC",
    "wof:name":"Hacienda Cuchitingue",
    "wof:placetype":"locality"
},
  "geometry": {"coordinates":[-78.53012,-0.84552],"type":"Point"}
}