{
  "type": "Feature",
  "properties": {
    "gn:admin1_code":"10.0",
    "gn:admin2_code":"907.0",
    "gn:admin3_code":"90750.0",
    "gn:asciiname":"Canta Gallo",
    "gn:country_code":"EC",
    "gn:dem":8,
    "gn:feature_class":"P",
    "gn:feature_code":"PPL",
    "gn:name":"Canta Gallo",
    "gn:population":0,
    "gn:timezone":"America/Guayaquil",
    "iso:country":"EC",
    "name:ita_x_preferred":[
        "Canta Gallo"
    ],
    "name:spa_x_preferred":[
        "Canta Gallo"
    ],
    "name:zho_x_preferred":[
        "\u574e\u5854\u52a0\u6d1b"
    ],
    "wof:name":"Canta Gallo",
    "wof:placetype":"locality"
},
  "geometry": {"coordinates":[-79.8331,-2.18489],"type":"Point"}
}