{
  "type": "Feature",
  "properties": {
    "gn:admin1_code":"4.0",
    "gn:admin2_code":"301.0",
    "gn:admin3_code":"30156.0",
    "gn:asciiname":"Cuncate",
    "gn:country_code":"EC",
    "gn:dem":3265,
    "gn:feature_class":"P",
    "gn:feature_code":"PPL",
    "gn:name":"Cuncate",
    "gn:population":0,
    "gn:timezone":"America/Guayaquil",
    "iso:country":"EC",
    "wof:name":"Cuncate",
    "wof:placetype":"locality"
},
  "geometry": {"coordinates":[-78.65000000000001,-2.61667],"type":"Point"}
}