{
  "type": "Feature",
  "properties": {
    "gn:admin1_code":"2.0",
    "gn:admin2_code":"101.0",
    "gn:admin3_code":"10152.0",
    "gn:asciiname":"Hacienda Carpatos",
    "gn:cc2":"EC",
    "gn:country_code":"EC",
    "gn:dem":3248,
    "gn:feature_class":"P",
    "gn:feature_code":"PPL",
    "gn:name":"Hacienda C\u00e1rpatos",
    "gn:population":0,
    "gn:timezone":"America/Guayaquil",
    "iso:country":"EC",
    "wof:name":"Hacienda Carpatos",
    "wof:placetype":"locality"
},
  "geometry": {"coordinates":[-79.03333000000001,-3.11667],"type":"Point"}
}