{
  "type": "Feature",
  "properties": {
    "gn:admin1_code":"12.0",
    "gn:asciiname":"Guatara",
    "gn:country_code":"EC",
    "gn:dem":484,
    "gn:feature_class":"P",
    "gn:feature_code":"PPL",
    "gn:name":"Guatara",
    "gn:population":0,
    "gn:timezone":"America/Lima",
    "iso:country":"EC",
    "wof:name":"Guatara",
    "wof:placetype":"locality"
},
  "geometry": {"coordinates":[-80.01666999999998,-4.36667],"type":"Point"}
}