{
  "type": "Feature",
  "properties": {
    "gn:admin1_code":"19.0",
    "gn:admin2_code":"1805.0",
    "gn:admin3_code":"180550.0",
    "gn:asciiname":"El Mundo",
    "gn:cc2":"EC",
    "gn:country_code":"EC",
    "gn:dem":2510,
    "gn:feature_class":"P",
    "gn:feature_code":"PPL",
    "gn:name":"El Mundo",
    "gn:population":0,
    "gn:timezone":"America/Guayaquil",
    "iso:country":"EC",
    "wof:name":"El Mundo",
    "wof:placetype":"locality"
},
  "geometry": {"coordinates":[-78.48333000000002,-1.28333],"type":"Point"}
}