{
  "type": "Feature",
  "properties": {
    "gn:admin1_code":"19.0",
    "gn:admin2_code":"1805.0",
    "gn:admin3_code":"180550.0",
    "gn:asciiname":"El Mundo",
    "gn:cc2":"EC",
    "gn:country_code":"EC",
    "gn:dem":2510,
    "gn:feature_class":"P",
    "gn:feature_code":"PPL",
    "gn:name":"El Mundo",
    "gn:population":0,
    "gn:timezone":"America/Guayaquil",
    "iso:country":"EC",
    "name:ceb_x_preferred":[
        "El Mundo"
    ],
    "name:fin_x_preferred":[
        "El Mundo"
    ],
    "name:fra_x_preferred":[
        "El Mundo"
    ],
    "name:jpn_x_preferred":[
        "\u30a8\u30eb\u30fb\u30e0\u30f3\u30c9"
    ],
    "name:por_x_preferred":[
        "El Mundo"
    ],
    "name:spa_x_preferred":[
        "El Mundo"
    ],
    "name:srp_x_preferred":[
        "\u0415\u043b \u041c\u0443\u043d\u0434\u043e"
    ],
    "name:swe_x_preferred":[
        "El Mundo"
    ],
    "wof:name":"El Mundo",
    "wof:placetype":"locality"
},
  "geometry": {"coordinates":[-78.48333000000002,-1.28333],"type":"Point"}
}