{
  "type": "Feature",
  "properties": {
    "gn:admin1_code":"7.0",
    "gn:admin2_code":"504.0",
    "gn:admin3_code":"50450.0",
    "gn:asciiname":"Hacienda Alpamala de Velasco",
    "gn:cc2":"EC",
    "gn:country_code":"EC",
    "gn:dem":2969,
    "gn:feature_class":"P",
    "gn:feature_code":"PPL",
    "gn:name":"Hacienda Alpamala de Velasco",
    "gn:population":0,
    "gn:timezone":"America/Guayaquil",
    "iso:country":"EC",
    "wof:name":"Hacienda Alpamala de Velasco",
    "wof:placetype":"locality"
},
  "geometry": {"coordinates":[-78.66667,-1.05],"type":"Point"}
}