{
  "type": "Feature",
  "properties": {
    "gn:admin1_code":"15.0",
    "gn:admin2_code":"1405.0",
    "gn:admin3_code":"140551.0",
    "gn:asciiname":"Tres Ranchos",
    "gn:country_code":"EC",
    "gn:dem":1320,
    "gn:feature_class":"P",
    "gn:feature_code":"PPL",
    "gn:name":"Tres Ranchos",
    "gn:population":0,
    "gn:timezone":"America/Guayaquil",
    "iso:country":"EC",
    "wof:name":"Tres Ranchos",
    "wof:placetype":"locality"
},
  "geometry": {"coordinates":[-78.41667,-2.71667],"type":"Point"}
}