{
  "type": "Feature",
  "properties": {
    "gn:admin1_code":"5.0",
    "gn:admin2_code":"406.0",
    "gn:admin3_code":"40650.0",
    "gn:asciiname":"Hacienda Cuatis Cevallos",
    "gn:cc2":"EC",
    "gn:country_code":"EC",
    "gn:dem":2822,
    "gn:feature_class":"P",
    "gn:feature_code":"PPL",
    "gn:name":"Hacienda Cuatis Cevallos",
    "gn:population":0,
    "gn:timezone":"America/Guayaquil",
    "iso:country":"EC",
    "wof:name":"Hacienda Cuatis Cevallos",
    "wof:placetype":"locality"
},
  "geometry": {"coordinates":[-77.73333000000002,0.63333],"type":"Point"}
}