{
  "type": "Feature",
  "properties": {
    "gn:admin1_code":"4.0",
    "gn:admin2_code":"303.0",
    "gn:admin3_code":"30355.0",
    "gn:asciiname":"Molobog",
    "gn:country_code":"EC",
    "gn:dem":3225,
    "gn:feature_class":"P",
    "gn:feature_code":"PPL",
    "gn:name":"Molobog",
    "gn:population":0,
    "gn:timezone":"America/Guayaquil",
    "iso:country":"EC",
    "wof:name":"Molobog",
    "wof:placetype":"locality"
},
  "geometry": {"coordinates":[-78.88973,-2.59891],"type":"Point"}
}