{
  "type": "Feature",
  "properties": {
    "gn:admin1_code":"18.0",
    "gn:admin2_code":"1707.0",
    "gn:admin3_code":"170750.0",
    "gn:asciiname":"Huila",
    "gn:country_code":"EC",
    "gn:dem":997,
    "gn:feature_class":"P",
    "gn:feature_code":"PPL",
    "gn:name":"Huila",
    "gn:population":0,
    "gn:timezone":"America/Guayaquil",
    "iso:country":"EC",
    "name:ceb_x_preferred":[
        "Huila"
    ],
    "name:deu_x_preferred":[
        "Huila"
    ],
    "name:fra_x_preferred":[
        "Huila"
    ],
    "name:kor_x_preferred":[
        "\uc6b0\uc77c\ub77c"
    ],
    "name:nld_x_preferred":[
        "Huila"
    ],
    "name:rus_x_preferred":[
        "\u0423\u0438\u043b\u0430"
    ],
    "name:sco_x_preferred":[
        "Huila"
    ],
    "name:spa_x_preferred":[
        "Huila"
    ],
    "name:swe_x_preferred":[
        "Huila"
    ],
    "name:ukr_x_preferred":[
        "\u0423\u0457\u043b\u0430"
    ],
    "wof:name":"Huila",
    "wof:placetype":"locality"
},
  "geometry": {"coordinates":[-78.88333,0.05],"type":"Point"}
}