{
  "type": "Feature",
  "properties": {
    "gn:admin1_code":"5.0",
    "gn:asciiname":"Jijon y Caamano",
    "gn:country_code":"EC",
    "gn:dem":872,
    "gn:feature_class":"P",
    "gn:feature_code":"PPL",
    "gn:name":"Jij\u00f3n y Caama\u00f1o",
    "gn:population":0,
    "gn:timezone":"America/Guayaquil",
    "iso:country":"EC",
    "wof:name":"Jijon y Caamano",
    "wof:placetype":"locality"
},
  "geometry": {"coordinates":[-78.26519999999999,0.77199],"type":"Point"}
}