{
  "type": "Feature",
  "properties": {
    "iso:country":"EC",
    "name:arg_x_preferred":[
        "Salinas"
    ],
    "name:bul_x_preferred":[
        "\u0421\u0430\u043b\u0438\u043d\u0430\u0441"
    ],
    "name:cat_x_preferred":[
        "Salinas"
    ],
    "name:ceb_x_preferred":[
        "Salinas"
    ],
    "name:ces_x_preferred":[
        "Salinas"
    ],
    "name:deu_x_preferred":[
        "Salinas"
    ],
    "name:epo_x_preferred":[
        "Salinas"
    ],
    "name:eus_x_preferred":[
        "Salinas"
    ],
    "name:fas_x_preferred":[
        "\u0633\u0627\u0644\u06cc\u0646\u0627\u0633"
    ],
    "name:fra_x_preferred":[
        "Salinas"
    ],
    "name:hun_x_preferred":[
        "Salinas"
    ],
    "name:ita_x_preferred":[
        "Salinas"
    ],
    "name:jpn_x_preferred":[
        "\u30b5\u30ea\u30ca\u30b9"
    ],
    "name:kor_x_preferred":[
        "\uc0b4\ub9ac\ub098\uc2a4"
    ],
    "name:lit_x_preferred":[
        "Salinasas"
    ],
    "name:nld_x_preferred":[
        "Salinas"
    ],
    "name:nor_x_preferred":[
        "Salinas"
    ],
    "name:oci_x_preferred":[
        "Salinas"
    ],
    "name:pol_x_preferred":[
        "Salinas"
    ],
    "name:por_x_preferred":[
        "Salinas"
    ],
    "name:que_x_preferred":[
        "Salinas"
    ],
    "name:ron_x_preferred":[
        "Salinas"
    ],
    "name:rus_x_preferred":[
        "\u0440\u0435\u043a\u0430 \u0421\u0430\u043b\u0438\u043d\u0430\u0441"
    ],
    "name:rus_x_variant":[
        "\u0421\u0430\u043b\u0438\u043d\u0430\u0441"
    ],
    "name:sco_x_preferred":[
        "Salinas"
    ],
    "name:spa_x_preferred":[
        "Salinas"
    ],
    "name:srp_x_preferred":[
        "\u0421\u0430\u043b\u0438\u043d\u0430\u0441"
    ],
    "name:swe_x_preferred":[
        "Salinas River"
    ],
    "name:swe_x_variant":[
        "Salinas"
    ],
    "name:tur_x_preferred":[
        "Salinas"
    ],
    "name:ukr_x_preferred":[
        "\u0421\u0430\u043b\u0456\u043d\u0430\u0441"
    ],
    "name:urd_x_preferred":[
        "\u0633\u0627\u0644\u06cc\u0646\u0627\u0633"
    ],
    "name:vie_x_preferred":[
        "S\u00f4ng Salinas"
    ],
    "name:vie_x_variant":[
        "Salinas"
    ],
    "name:vol_x_preferred":[
        "Salinas"
    ],
    "name:war_x_preferred":[
        "Salinas"
    ],
    "name:zho_x_preferred":[
        "\u8428\u5229\u7eb3\u65af"
    ],
    "qs:gn_pop":0,
    "qs:name":"Salinas",
    "qs:name_adm0":"Ecuador",
    "qs:name_adm1":"Imbabura",
    "qs:photos":1,
    "qs:photos_1k":1,
    "qs:photos_9k":1,
    "qs:photos_9r":1,
    "qs:photos_all":20,
    "qs:photos_sr":1,
    "qs:placetype":"LocalAdmin",
    "qs:pop_sr":"0",
    "qs:woe_adm0":23424801,
    "wof:name":"Salinas",
    "wof:placetype":"localadmin"
},
  "geometry": {"coordinates":[-78.13273599999999,0.504029],"type":"Point"}
}