{
  "type": "Feature",
  "properties": {
    "iso:country":"EC",
    "qs:gn_pop":0,
    "qs:name":"Salinas",
    "qs:name_adm0":"Ecuador",
    "qs:name_adm1":"Imbabura",
    "qs:photos":1,
    "qs:photos_1k":1,
    "qs:photos_9k":1,
    "qs:photos_9r":1,
    "qs:photos_all":20,
    "qs:photos_sr":1,
    "qs:placetype":"LocalAdmin",
    "qs:pop_sr":"0",
    "qs:woe_adm0":23424801,
    "wof:name":"Salinas",
    "wof:placetype":"localadmin"
},
  "geometry": {"coordinates":[-78.13273599999999,0.504029],"type":"Point"}
}