{
  "type": "Feature",
  "properties": {
    "gn:admin1_code":"10.0",
    "gn:asciiname":"Rio Seco",
    "gn:country_code":"EC",
    "gn:dem":157,
    "gn:feature_class":"P",
    "gn:feature_code":"PPL",
    "gn:name":"R\u00edo Seco",
    "gn:population":0,
    "gn:timezone":"America/Guayaquil",
    "iso:country":"EC",
    "wof:name":"Rio Seco",
    "wof:placetype":"locality"
},
  "geometry": {"coordinates":[-80.25806999999998,-2.13443],"type":"Point"}
}