{
  "type": "Feature",
  "properties": {
    "gn:admin1_code":"9.0",
    "gn:admin2_code":"804.0",
    "gn:admin3_code":"80455.0",
    "gn:asciiname":"Virgencita",
    "gn:country_code":"EC",
    "gn:dem":182,
    "gn:feature_class":"P",
    "gn:feature_code":"PPL",
    "gn:name":"Virgencita",
    "gn:population":0,
    "gn:timezone":"America/Guayaquil",
    "iso:country":"EC",
    "wof:name":"Virgencita",
    "wof:placetype":"locality"
},
  "geometry": {"coordinates":[-79.56864,0.06028],"type":"Point"}
}