{
  "type": "Feature",
  "properties": {
    "iso:country":"EC",
    "name:fas_x_preferred":[
        "\u0645\u0627\u0631\u06cc\u0627\u0646"
    ],
    "name:ita_x_preferred":[
        "Marian"
    ],
    "name:nld_x_preferred":[
        "Marian"
    ],
    "name:por_x_preferred":[
        "Marian"
    ],
    "name:rus_x_preferred":[
        "\u041c\u0430\u0440\u044c\u044f\u043d"
    ],
    "qs:gn_country":"EC",
    "qs:gn_fcode":"PPL",
    "qs:gn_pop":0,
    "qs:name":"Marian",
    "qs:name_adm0":"Ecuador",
    "qs:name_adm1":"Sucumbios",
    "qs:photos":48,
    "qs:photos_1k":10,
    "qs:photos_9k":1,
    "qs:photos_9r":2,
    "qs:photos_all":48,
    "qs:photos_sr":2,
    "qs:placetype":"Town",
    "qs:pop_sr":"0",
    "qs:woe_adm0":23424801,
    "wd:wordcount":265,
    "wof:name":"Marian",
    "wof:placetype":"locality"
},
  "geometry": {"coordinates":[-76.33333,-0.03333],"type":"Point"}
}