{
  "type": "Feature",
  "properties": {
    "gn:admin1_code":"8.0",
    "gn:admin2_code":"705.0",
    "gn:admin3_code":"70550.0",
    "gn:asciiname":"Obispopamba",
    "gn:country_code":"EC",
    "gn:dem":3023,
    "gn:feature_class":"P",
    "gn:feature_code":"PPL",
    "gn:name":"Obispopamba",
    "gn:population":0,
    "gn:timezone":"America/Guayaquil",
    "iso:country":"EC",
    "wof:name":"Obispopamba",
    "wof:placetype":"locality"
},
  "geometry": {"coordinates":[-79.61667,-3.48333],"type":"Point"}
}