{
  "type": "Feature",
  "properties": {
    "gn:admin1_code":"19.0",
    "gn:admin2_code":"1808.0",
    "gn:admin3_code":"180853.0",
    "gn:asciiname":"Guapa",
    "gn:cc2":"EC",
    "gn:country_code":"EC",
    "gn:dem":4108,
    "gn:feature_class":"P",
    "gn:feature_code":"PPL",
    "gn:name":"Guapa",
    "gn:population":0,
    "gn:timezone":"America/Guayaquil",
    "iso:country":"EC",
    "name:fra_x_preferred":[
        "Guapa"
    ],
    "name:spa_x_preferred":[
        "Guapa"
    ],
    "wof:name":"Guapa",
    "wof:placetype":"locality"
},
  "geometry": {"coordinates":[-78.45,-1.16667],"type":"Point"}
}