{
  "type": "Feature",
  "properties": {
    "gn:admin1_code":"2.0",
    "gn:admin2_code":"104.0",
    "gn:admin3_code":"10451.0",
    "gn:asciiname":"Cochapata",
    "gn:country_code":"EC",
    "gn:dem":2663,
    "gn:feature_class":"P",
    "gn:feature_code":"PPL",
    "gn:name":"Cochapata",
    "gn:population":0,
    "gn:timezone":"America/Guayaquil",
    "iso:country":"EC",
    "wof:name":"Cochapata",
    "wof:placetype":"locality"
},
  "geometry": {"coordinates":[-79.08620000000001,-3.38906],"type":"Point"}
}