{
  "type": "Feature",
  "properties": {
    "gn:country":"EC",
    "gn:fcode":"BAR",
    "gn:pop":500000,
    "iso:country":"EC",
    "qs:name":"Bar Discoteca May Day",
    "qs:photos_9r":0,
    "qs:photos_sr":0,
    "qs:pop_sr":"10",
    "wof:name":"Bar Discoteca May Day",
    "wof:placetype":"locality",
    "wof:population":500000
},
  "geometry": {"coordinates":[-79.02075000000001,-2.89815],"type":"Point"}
}