{
  "type": "Feature",
  "properties": {
    "gn:admin1_code":"2.0",
    "gn:admin2_code":"101.0",
    "gn:admin3_code":"10150.0",
    "gn:asciiname":"Molinopamba",
    "gn:country_code":"EC",
    "gn:dem":2509,
    "gn:feature_class":"P",
    "gn:feature_code":"PPL",
    "gn:name":"Molinopamba",
    "gn:population":0,
    "gn:timezone":"America/Guayaquil",
    "iso:country":"EC",
    "wof:name":"Molinopamba",
    "wof:placetype":"locality"
},
  "geometry": {"coordinates":[-78.96288,-2.87213],"type":"Point"}
}