{
  "type": "Feature",
  "properties": {
    "gn:admin1_code":"2.0",
    "gn:admin2_code":"103.0",
    "gn:admin3_code":"10358.0",
    "gn:asciiname":"El Guayan",
    "gn:country_code":"EC",
    "gn:dem":2659,
    "gn:feature_class":"P",
    "gn:feature_code":"PPL",
    "gn:name":"El Guayan",
    "gn:population":0,
    "gn:timezone":"America/Guayaquil",
    "iso:country":"EC",
    "wof:name":"El Guayan",
    "wof:placetype":"locality"
},
  "geometry": {"coordinates":[-78.88959,-2.91007],"type":"Point"}
}