{
  "type": "Feature",
  "properties": {
    "gn:admin1_code":"7.0",
    "gn:admin2_code":"501.0",
    "gn:admin3_code":"50156.0",
    "gn:asciiname":"Hacienda Callo Mancheno",
    "gn:cc2":"EC",
    "gn:country_code":"EC",
    "gn:dem":3031,
    "gn:feature_class":"P",
    "gn:feature_code":"PPL",
    "gn:name":"Hacienda Callo Mancheno",
    "gn:population":0,
    "gn:timezone":"America/Guayaquil",
    "iso:country":"EC",
    "wof:name":"Hacienda Callo Mancheno",
    "wof:placetype":"locality"
},
  "geometry": {"coordinates":[-78.59999999999999,-0.75],"type":"Point"}
}