{
  "type": "Feature",
  "properties": {
    "gn:admin1_code":"19.0",
    "gn:admin2_code":"1808.0",
    "gn:admin3_code":"180855.0",
    "gn:asciiname":"Hacienda Andahualo",
    "gn:cc2":"EC",
    "gn:country_code":"EC",
    "gn:dem":3038,
    "gn:feature_class":"P",
    "gn:feature_code":"PPL",
    "gn:name":"Hacienda Andahualo",
    "gn:population":0,
    "gn:timezone":"America/Guayaquil",
    "iso:country":"EC",
    "wof:name":"Hacienda Andahualo",
    "wof:placetype":"locality"
},
  "geometry": {"coordinates":[-78.51666999999998,-1.08333],"type":"Point"}
}