{
  "type": "Feature",
  "properties": {
    "gn:admin1_code":"18.0",
    "gn:admin2_code":"1703.0",
    "gn:admin3_code":"170350.0",
    "gn:asciiname":"Chisinche",
    "gn:country_code":"EC",
    "gn:dem":3124,
    "gn:feature_class":"P",
    "gn:feature_code":"PPL",
    "gn:name":"Chisinche",
    "gn:population":0,
    "gn:timezone":"America/Guayaquil",
    "iso:country":"EC",
    "wof:name":"Chisinche",
    "wof:placetype":"locality"
},
  "geometry": {"coordinates":[-78.58951,-0.56174],"type":"Point"}
}