{
  "type": "Feature",
  "properties": {
    "gn:admin1_code":"10.0",
    "gn:admin2_code":"925.0",
    "gn:admin3_code":"92550.0",
    "gn:asciiname":"La Carolina",
    "gn:country_code":"EC",
    "gn:dem":3,
    "gn:feature_class":"P",
    "gn:feature_code":"PPL",
    "gn:name":"La Carolina",
    "gn:population":0,
    "gn:timezone":"America/Guayaquil",
    "iso:country":"EC",
    "wof:name":"La Carolina",
    "wof:placetype":"locality"
},
  "geometry": {"coordinates":[-80.01666999999998,-1.91667],"type":"Point"}
}