{
  "type": "Feature",
  "properties": {
    "gn:admin1_code":"10.0",
    "gn:admin2_code":"925.0",
    "gn:admin3_code":"92550.0",
    "gn:asciiname":"La Carolina",
    "gn:country_code":"EC",
    "gn:dem":3,
    "gn:feature_class":"P",
    "gn:feature_code":"PPL",
    "gn:name":"La Carolina",
    "gn:population":0,
    "gn:timezone":"America/Guayaquil",
    "iso:country":"EC",
    "name:ara_x_preferred":[
        "\u0644\u0627 \u0643\u0627\u0631\u0648\u0644\u064a\u0646\u0627"
    ],
    "name:cat_x_preferred":[
        "La Carolina"
    ],
    "name:ceb_x_preferred":[
        "La Carolina"
    ],
    "name:deu_x_preferred":[
        "La Carolina"
    ],
    "name:eus_x_preferred":[
        "La Carolina"
    ],
    "name:fas_x_preferred":[
        "\u0644\u0627 \u06a9\u0627\u0631\u0644\u06cc\u0646\u0627"
    ],
    "name:fin_x_preferred":[
        "La Carolina"
    ],
    "name:fra_x_preferred":[
        "La Carolina"
    ],
    "name:hat_x_preferred":[
        "La Carolina"
    ],
    "name:hun_x_preferred":[
        "La Carolina"
    ],
    "name:hye_x_preferred":[
        "\u053c\u0561 \u053f\u0561\u0580\u0578\u056c\u056b\u0576\u0561"
    ],
    "name:ita_x_preferred":[
        "La Carolina"
    ],
    "name:jpn_x_preferred":[
        "\u30e9\u30fb\u30ab\u30ed\u30ea\u30ca"
    ],
    "name:msa_x_preferred":[
        "La Carolina"
    ],
    "name:nld_x_preferred":[
        "La Carolina"
    ],
    "name:oci_x_preferred":[
        "La Carolina"
    ],
    "name:pol_x_preferred":[
        "La Carolina"
    ],
    "name:por_x_preferred":[
        "La Carolina"
    ],
    "name:ron_x_preferred":[
        "La Carolina"
    ],
    "name:rus_x_preferred":[
        "\u041b\u0430-\u041a\u0430\u0440\u043e\u043b\u0438\u043d\u0430"
    ],
    "name:spa_x_preferred":[
        "La Carolina"
    ],
    "name:sqi_x_preferred":[
        "La Carolina"
    ],
    "name:tur_x_preferred":[
        "La Carolina"
    ],
    "name:ukr_x_preferred":[
        "\u041b\u0430-\u041a\u0430\u0440\u043e\u043b\u0456\u043d\u0430"
    ],
    "name:vie_x_preferred":[
        "La Carolina"
    ],
    "name:war_x_preferred":[
        "La Carolina"
    ],
    "name:zho_x_preferred":[
        "\u62c9\u5361\u7f57\u5229\u7eb3"
    ],
    "wof:name":"La Carolina",
    "wof:placetype":"locality"
},
  "geometry": {"coordinates":[-80.01666999999998,-1.91667],"type":"Point"}
}