{
  "type": "Feature",
  "properties": {
    "iso:country":"EC",
    "name:ceb_x_preferred":[
        "Guamote"
    ],
    "name:dan_x_preferred":[
        "Guamote"
    ],
    "name:dut_x_preferred":[
        "Guamote"
    ],
    "name:eng_x_preferred":[
        "Guamote"
    ],
    "name:ger_x_preferred":[
        "Guamote"
    ],
    "name:que_x_preferred":[
        "Wamuti"
    ],
    "name:swe_x_preferred":[
        "Guamote"
    ],
    "qs:gn_country":"EC",
    "qs:gn_fcode":"PPL",
    "qs:gn_pop":0,
    "qs:name":"Guamote",
    "qs:name_adm0":"Ecuador",
    "qs:name_adm1":"Chimborazo",
    "qs:photos":51,
    "qs:photos_1k":10,
    "qs:photos_9k":1,
    "qs:photos_9r":2,
    "qs:photos_all":51,
    "qs:photos_sr":2,
    "qs:placetype":"Town",
    "qs:pop_sr":"7",
    "qs:woe_adm0":23424801,
    "wof:name":"Guamote",
    "wof:placetype":"locality"
},
  "geometry": {"coordinates":[-78.70954999999999,-1.93307],"type":"Point"}
}