{
  "type": "Feature",
  "properties": {
    "iso:country":"EC",
    "name:ceb_x_preferred":[
        "Calceta"
    ],
    "name:deu_x_preferred":[
        "Calceta"
    ],
    "name:eng_x_preferred":[
        "Calceta"
    ],
    "name:fra_x_preferred":[
        "Calceta"
    ],
    "name:lit_x_preferred":[
        "Kalseta"
    ],
    "name:nld_x_preferred":[
        "Calceta"
    ],
    "name:pol_x_preferred":[
        "Calceta"
    ],
    "name:que_x_preferred":[
        "Calceta"
    ],
    "name:spa_x_preferred":[
        "Calceta"
    ],
    "name:swe_x_preferred":[
        "Calceta"
    ],
    "name:und_x_variant":[
        "Bol\u00edvar"
    ],
    "qs:gn_country":"EC",
    "qs:gn_fcode":"PPL",
    "qs:gn_pop":17286,
    "qs:name":"Calceta",
    "qs:name_adm0":"Ecuador",
    "qs:name_adm1":"Manabi",
    "qs:photos":0,
    "qs:photos_1k":0,
    "qs:photos_9k":1,
    "qs:photos_9r":1,
    "qs:photos_all":6,
    "qs:photos_sr":0,
    "qs:placetype":"LocalAdmin",
    "qs:pop_sr":"6",
    "qs:woe_adm0":23424801,
    "wd:wordcount":98,
    "wof:name":"Calceta",
    "wof:placetype":"localadmin",
    "wof:population":17286
},
  "geometry": {"coordinates":[-80.16388999999999,-0.84582],"type":"Point"}
}