{
  "type": "Feature",
  "properties": {
    "gn:admin1_code":"20.0",
    "gn:admin2_code":"1901.0",
    "gn:admin3_code":"190152.0",
    "gn:asciiname":"El Carmelo",
    "gn:country_code":"EC",
    "gn:dem":1119,
    "gn:feature_class":"P",
    "gn:feature_code":"PPL",
    "gn:name":"El Carmelo",
    "gn:population":0,
    "gn:timezone":"America/Guayaquil",
    "iso:country":"EC",
    "wof:name":"El Carmelo",
    "wof:placetype":"locality"
},
  "geometry": {"coordinates":[-78.85791999999999,-3.8231],"type":"Point"}
}