{
  "type": "Feature",
  "properties": {
    "gn:admin1_code":"10.0",
    "gn:admin2_code":"911.0",
    "gn:admin3_code":"91154.0",
    "gn:asciiname":"Churute",
    "gn:country_code":"EC",
    "gn:dem":16,
    "gn:feature_class":"P",
    "gn:feature_code":"PPL",
    "gn:name":"Churute",
    "gn:population":0,
    "gn:timezone":"America/Guayaquil",
    "iso:country":"EC",
    "wof:name":"Churute",
    "wof:placetype":"locality"
},
  "geometry": {"coordinates":[-79.75476,-2.5252],"type":"Point"}
}