{
  "type": "Feature",
  "properties": {
    "gn:admin1_code":"10.0",
    "gn:admin2_code":"904.0",
    "gn:admin3_code":"90450.0",
    "gn:asciiname":"La Isabel",
    "gn:country_code":"EC",
    "gn:dem":25,
    "gn:feature_class":"P",
    "gn:feature_code":"PPL",
    "gn:name":"La Isabel",
    "gn:population":0,
    "gn:timezone":"America/Guayaquil",
    "iso:country":"EC",
    "wof:name":"La Isabel",
    "wof:placetype":"locality"
},
  "geometry": {"coordinates":[-79.88424999999999,-1.30356],"type":"Point"}
}