{
  "type": "Feature",
  "properties": {
    "gn:admin1_code":"6.0",
    "gn:admin2_code":"604.0",
    "gn:admin3_code":"60450.0",
    "gn:asciiname":"Guilbud",
    "gn:country_code":"EC",
    "gn:dem":2963,
    "gn:feature_class":"P",
    "gn:feature_code":"PPL",
    "gn:name":"Guilbud",
    "gn:population":0,
    "gn:timezone":"America/Guayaquil",
    "iso:country":"EC",
    "wof:name":"Guilbud",
    "wof:placetype":"locality"
},
  "geometry": {"coordinates":[-78.58333,-1.73333],"type":"Point"}
}