{
  "type": "Feature",
  "properties": {
    "iso:country":"EC",
    "name:eng_x_preferred":[
        "Mera"
    ],
    "name:nld_x_preferred":[
        "Mera"
    ],
    "name:que_x_preferred":[
        "Mera kitilli"
    ],
    "name:spa_x_preferred":[
        "Mera"
    ],
    "name:zho_x_preferred":[
        "\u6885\u62c9"
    ],
    "qs:gn_country":"EC",
    "qs:gn_fcode":"PPL",
    "qs:gn_pop":0,
    "qs:name":"Mera",
    "qs:name_adm0":"Ecuador",
    "qs:name_adm1":"Pastaza",
    "qs:photos":9,
    "qs:photos_1k":2,
    "qs:photos_9k":1,
    "qs:photos_9r":1,
    "qs:photos_all":9,
    "qs:photos_sr":1,
    "qs:placetype":"Town",
    "qs:pop_sr":"0",
    "qs:woe_adm0":23424801,
    "wof:name":"Mera",
    "wof:placetype":"locality"
},
  "geometry": {"coordinates":[-78.11394,-1.46097],"type":"Point"}
}