{
  "type": "Feature",
  "properties": {
    "gn:admin1_code":"10.0",
    "gn:asciiname":"Puerto Balsas",
    "gn:country_code":"EC",
    "gn:dem":2,
    "gn:feature_class":"P",
    "gn:feature_code":"PPL",
    "gn:name":"Puerto Balsas",
    "gn:population":0,
    "gn:timezone":"America/Guayaquil",
    "iso:country":"EC",
    "wof:name":"Puerto Balsas",
    "wof:placetype":"locality"
},
  "geometry": {"coordinates":[-79.89966,-2.5759],"type":"Point"}
}