{
  "type": "Feature",
  "properties": {
    "gn:admin1_code":"9.0",
    "gn:admin2_code":"802.0",
    "gn:admin3_code":"80260.0",
    "gn:asciiname":"Selva Alegre",
    "gn:country_code":"EC",
    "gn:dem":41,
    "gn:feature_class":"P",
    "gn:feature_code":"PPL",
    "gn:name":"Selva Alegre",
    "gn:population":0,
    "gn:timezone":"America/Guayaquil",
    "iso:country":"EC",
    "wof:name":"Selva Alegre",
    "wof:placetype":"locality"
},
  "geometry": {"coordinates":[-78.85979,0.93132],"type":"Point"}
}