{
  "type": "Feature",
  "properties": {
    "gn:admin1_code":"2.0",
    "gn:admin2_code":"105.0",
    "gn:admin3_code":"10553.0",
    "gn:asciiname":"Aguas Blancas",
    "gn:country_code":"EC",
    "gn:dem":2411,
    "gn:feature_class":"P",
    "gn:feature_code":"PPL",
    "gn:name":"Aguas Blancas",
    "gn:population":0,
    "gn:timezone":"America/Guayaquil",
    "iso:country":"EC",
    "name:bre_x_preferred":[
        "Aguas Blancas"
    ],
    "name:ceb_x_preferred":[
        "Aguas Blancas"
    ],
    "name:deu_x_preferred":[
        "Aguas Blancas"
    ],
    "name:ita_x_preferred":[
        "Aguas Blancas"
    ],
    "name:nld_x_preferred":[
        "Aguas Blancas"
    ],
    "name:spa_x_preferred":[
        "Aguas Blancas"
    ],
    "name:swe_x_preferred":[
        "Aguas Blancas"
    ],
    "wof:name":"Aguas Blancas",
    "wof:placetype":"locality"
},
  "geometry": {"coordinates":[-78.75629000000001,-2.7991],"type":"Point"}
}