{
  "type": "Feature",
  "properties": {
    "gn:admin1_code":"18.0",
    "gn:admin2_code":"1701.0",
    "gn:admin3_code":"170179.0",
    "gn:asciiname":"Hacienda Alban",
    "gn:cc2":"EC",
    "gn:country_code":"EC",
    "gn:dem":2308,
    "gn:feature_class":"P",
    "gn:feature_code":"PPL",
    "gn:name":"Hacienda Alb\u00e1n",
    "gn:population":0,
    "gn:timezone":"America/Guayaquil",
    "iso:country":"EC",
    "wof:name":"Hacienda Alban",
    "wof:placetype":"locality"
},
  "geometry": {"coordinates":[-78.38333,-0.16667],"type":"Point"}
}