{
  "type": "Feature",
  "properties": {
    "gn:admin1_code":"13.0",
    "gn:admin2_code":"1201.0",
    "gn:admin3_code":"120152.0",
    "gn:asciiname":"Caracol",
    "gn:country_code":"EC",
    "gn:dem":11,
    "gn:feature_class":"P",
    "gn:feature_code":"PPL",
    "gn:name":"Caracol",
    "gn:population":0,
    "gn:timezone":"America/Guayaquil",
    "iso:country":"EC",
    "wof:name":"Caracol",
    "wof:placetype":"locality"
},
  "geometry": {"coordinates":[-79.46381,-1.67157],"type":"Point"}
}