{
  "type": "Feature",
  "properties": {
    "gn:admin1_code":"12.0",
    "gn:admin2_code":"1101.0",
    "gn:admin3_code":"110161.0",
    "gn:asciiname":"Caranango",
    "gn:country_code":"EC",
    "gn:dem":1483,
    "gn:feature_class":"P",
    "gn:feature_code":"PPL",
    "gn:name":"Caranango",
    "gn:population":0,
    "gn:timezone":"America/Guayaquil",
    "iso:country":"EC",
    "wof:name":"Caranango",
    "wof:placetype":"locality"
},
  "geometry": {"coordinates":[-79.26666999999998,-4.25],"type":"Point"}
}