{
  "type": "Feature",
  "properties": {
    "gn:admin1_code":"10.0",
    "gn:admin2_code":"905.0",
    "gn:admin3_code":"90550.0",
    "gn:asciiname":"Guabitos",
    "gn:country_code":"EC",
    "gn:dem":37,
    "gn:feature_class":"P",
    "gn:feature_code":"PPL",
    "gn:name":"Guabitos",
    "gn:population":0,
    "gn:timezone":"America/Guayaquil",
    "iso:country":"EC",
    "wof:name":"Guabitos",
    "wof:placetype":"locality"
},
  "geometry": {"coordinates":[-80.11159000000001,-1.56751],"type":"Point"}
}