{
  "type": "Feature",
  "properties": {
    "iso:country":"EC",
    "qs:gn_pop":0,
    "qs:name":"Nanegalito",
    "qs:name_adm0":"Ecuador",
    "qs:name_adm1":"Pichincha",
    "qs:photos":9,
    "qs:photos_1k":2,
    "qs:photos_9k":1,
    "qs:photos_9r":1,
    "qs:photos_all":9,
    "qs:photos_sr":1,
    "qs:placetype":"LocalAdmin",
    "qs:pop_sr":"0",
    "qs:woe_adm0":23424801,
    "wof:name":"Nanegalito",
    "wof:placetype":"localadmin"
},
  "geometry": {"coordinates":[-78.707167,0.020833],"type":"Point"}
}