{
  "type": "Feature",
  "properties": {
    "gn:admin1_code":"18.0",
    "gn:admin2_code":"1705.0",
    "gn:admin3_code":"170550.0",
    "gn:asciiname":"Cotogchoa",
    "gn:country_code":"EC",
    "gn:dem":2627,
    "gn:feature_class":"P",
    "gn:feature_code":"PPL",
    "gn:name":"Cotogchoa",
    "gn:population":0,
    "gn:timezone":"America/Guayaquil",
    "iso:country":"EC",
    "wof:name":"Cotogchoa",
    "wof:placetype":"locality"
},
  "geometry": {"coordinates":[-78.43405,-0.36741],"type":"Point"}
}