{
  "type": "Feature",
  "properties": {
    "gn:admin1_code":"22.0",
    "gn:asciiname":"Puerto San Miguel",
    "gn:country_code":"EC",
    "gn:dem":273,
    "gn:feature_class":"P",
    "gn:feature_code":"PPL",
    "gn:name":"Puerto San Miguel",
    "gn:population":0,
    "gn:timezone":"America/Guayaquil",
    "iso:country":"EC",
    "wof:name":"Puerto San Miguel",
    "wof:placetype":"locality"
},
  "geometry": {"coordinates":[-76.84416999999998,0.24083],"type":"Point"}
}