{
  "type": "Feature",
  "properties": {
    "gn:admin1_code":"2.0",
    "gn:admin2_code":"101.0",
    "gn:admin3_code":"10166.0",
    "gn:asciiname":"Vivin",
    "gn:country_code":"EC",
    "gn:dem":2850,
    "gn:feature_class":"P",
    "gn:feature_code":"PPL",
    "gn:name":"Vivin",
    "gn:population":0,
    "gn:timezone":"America/Guayaquil",
    "iso:country":"EC",
    "wof:name":"Vivin",
    "wof:placetype":"locality"
},
  "geometry": {"coordinates":[-78.97915,-2.80632],"type":"Point"}
}