{
  "type": "Feature",
  "properties": {
    "gn:admin1_code":"24.0",
    "gn:admin2_code":"2204.0",
    "gn:admin3_code":"220452.0",
    "gn:asciiname":"Cacao Punto",
    "gn:cc2":"EC",
    "gn:country_code":"EC",
    "gn:dem":267,
    "gn:feature_class":"P",
    "gn:feature_code":"PPL",
    "gn:name":"Cacao Punto",
    "gn:population":0,
    "gn:timezone":"America/Guayaquil",
    "iso:country":"EC",
    "wof:name":"Cacao Punto",
    "wof:placetype":"locality"
},
  "geometry": {"coordinates":[-77.13333,-0.65],"type":"Point"}
}