{
  "type": "Feature",
  "properties": {
    "gn:admin1_code":"10.0",
    "gn:asciiname":"Morilla",
    "gn:country_code":"EC",
    "gn:dem":27,
    "gn:feature_class":"P",
    "gn:feature_code":"PPL",
    "gn:name":"Morilla",
    "gn:population":0,
    "gn:timezone":"America/Guayaquil",
    "iso:country":"EC",
    "wof:name":"Morilla",
    "wof:placetype":"locality"
},
  "geometry": {"coordinates":[-80.75134,-2.19024],"type":"Point"}
}