{
  "type": "Feature",
  "properties": {
    "gn:admin1_code":"5.0",
    "gn:admin2_code":"404.0",
    "gn:admin3_code":"40451.0",
    "gn:asciiname":"Hacienda La Loma",
    "gn:country_code":"EC",
    "gn:dem":1421,
    "gn:feature_class":"P",
    "gn:feature_code":"PPL",
    "gn:name":"Hacienda La Loma",
    "gn:population":0,
    "gn:timezone":"America/Guayaquil",
    "iso:country":"EC",
    "wof:name":"Hacienda La Loma",
    "wof:placetype":"locality"
},
  "geometry": {"coordinates":[-78.12878000000001,0.62141],"type":"Point"}
}