{
  "type": "Feature",
  "properties": {
    "gn:admin1_code":"17.0",
    "gn:admin2_code":"1602.0",
    "gn:admin3_code":"160251.0",
    "gn:asciiname":"Madre Tierra",
    "gn:country_code":"EC",
    "gn:dem":942,
    "gn:feature_class":"P",
    "gn:feature_code":"PPL",
    "gn:name":"Madre Tierra",
    "gn:population":0,
    "gn:timezone":"America/Guayaquil",
    "iso:country":"EC",
    "wof:name":"Madre Tierra",
    "wof:placetype":"locality"
},
  "geometry": {"coordinates":[-78.03305,-1.543],"type":"Point"}
}