{
  "type": "Feature",
  "properties": {
    "gn:admin1_code":"4.0",
    "gn:admin2_code":"303.0",
    "gn:admin3_code":"30356.0",
    "gn:asciiname":"Hacienda Vende Leche",
    "gn:cc2":"EC",
    "gn:country_code":"EC",
    "gn:dem":3058,
    "gn:feature_class":"P",
    "gn:feature_code":"PPL",
    "gn:name":"Hacienda Vende Leche",
    "gn:population":0,
    "gn:timezone":"America/Guayaquil",
    "iso:country":"EC",
    "wof:name":"Hacienda Vende Leche",
    "wof:placetype":"locality"
},
  "geometry": {"coordinates":[-78.88333,-2.55],"type":"Point"}
}