{
  "type": "Feature",
  "properties": {
    "gn:admin1_code":"12.0",
    "gn:admin2_code":"1116.0",
    "gn:admin3_code":"111651.0",
    "gn:asciiname":"La Tingue",
    "gn:country_code":"EC",
    "gn:dem":1516,
    "gn:feature_class":"P",
    "gn:feature_code":"PPL",
    "gn:name":"La Tingue",
    "gn:population":0,
    "gn:timezone":"America/Guayaquil",
    "iso:country":"EC",
    "wof:name":"La Tingue",
    "wof:placetype":"locality"
},
  "geometry": {"coordinates":[-79.57545,-3.90851],"type":"Point"}
}