{
  "type": "Feature",
  "properties": {
    "gn:admin1_code":"11.0",
    "gn:asciiname":"Hacienda Santa Rosa",
    "gn:cc2":"EC",
    "gn:country_code":"EC",
    "gn:dem":1600,
    "gn:feature_class":"P",
    "gn:feature_code":"PPL",
    "gn:name":"Hacienda Santa Rosa",
    "gn:population":0,
    "gn:timezone":"America/Guayaquil",
    "iso:country":"EC",
    "wof:name":"Hacienda Santa Rosa",
    "wof:placetype":"locality"
},
  "geometry": {"coordinates":[-78.15000000000001,0.65],"type":"Point"}
}