{
  "type": "Feature",
  "properties": {
    "gn:admin1_code":"8.0",
    "gn:admin2_code":"714.0",
    "gn:admin3_code":"71451.0",
    "gn:asciiname":"Canas",
    "gn:country_code":"EC",
    "gn:dem":580,
    "gn:feature_class":"P",
    "gn:feature_code":"PPL",
    "gn:name":"Ca\u00f1as",
    "gn:population":0,
    "gn:timezone":"America/Guayaquil",
    "iso:country":"EC",
    "name:ceb_x_preferred":[
        "Canas"
    ],
    "name:deu_x_preferred":[
        "Canas"
    ],
    "name:nld_x_preferred":[
        "Canas"
    ],
    "name:por_x_preferred":[
        "Canas"
    ],
    "name:ron_x_preferred":[
        "Canas"
    ],
    "name:rus_x_preferred":[
        "\u041a\u0430\u043d\u0430\u0441"
    ],
    "name:swe_x_preferred":[
        "Canas"
    ],
    "wof:name":"Canas",
    "wof:placetype":"locality"
},
  "geometry": {"coordinates":[-80.08333,-3.83333],"type":"Point"}
}