{
  "type": "Feature",
  "properties": {
    "gn:admin1_code":"7.0",
    "gn:admin2_code":"501.0",
    "gn:admin3_code":"50158.0",
    "gn:asciiname":"Hacienda La Compania",
    "gn:country_code":"EC",
    "gn:dem":2950,
    "gn:feature_class":"P",
    "gn:feature_code":"PPL",
    "gn:name":"Hacienda La Compa\u00f1\u00eda",
    "gn:population":0,
    "gn:timezone":"America/Guayaquil",
    "iso:country":"EC",
    "wof:name":"Hacienda La Compania",
    "wof:placetype":"locality"
},
  "geometry": {"coordinates":[-78.68383,-0.86149],"type":"Point"}
}