{
  "type": "Feature",
  "properties": {
    "gn:admin1_code":"10.0",
    "gn:admin2_code":"913.0",
    "gn:admin3_code":"91350.0",
    "gn:asciiname":"Jacinto",
    "gn:country_code":"EC",
    "gn:dem":11,
    "gn:feature_class":"P",
    "gn:feature_code":"PPL",
    "gn:name":"Jacinto",
    "gn:population":0,
    "gn:timezone":"America/Guayaquil",
    "iso:country":"EC",
    "wof:name":"Jacinto",
    "wof:placetype":"locality"
},
  "geometry": {"coordinates":[-79.89093000000003,-1.68781],"type":"Point"}
}