{
  "type": "Feature",
  "properties": {
    "gn:admin1_code":"11.0",
    "gn:admin2_code":"1002.0",
    "gn:admin3_code":"100253.0",
    "gn:asciiname":"Hacienda San Jose de Cobuendo",
    "gn:country_code":"EC",
    "gn:dem":2282,
    "gn:feature_class":"P",
    "gn:feature_code":"PPL",
    "gn:name":"Hacienda San Jos\u00e9 de Cobuendo",
    "gn:population":0,
    "gn:timezone":"America/Guayaquil",
    "iso:country":"EC",
    "wof:name":"Hacienda San Jose de Cobuendo",
    "wof:placetype":"locality"
},
  "geometry": {"coordinates":[-78.17241999999997,0.36169],"type":"Point"}
}