{
  "type": "Feature",
  "properties": {
    "gn:admin1_code":"8.0",
    "gn:admin2_code":"709.0",
    "gn:admin3_code":"70951.0",
    "gn:asciiname":"Calichana",
    "gn:country_code":"EC",
    "gn:dem":35,
    "gn:feature_class":"P",
    "gn:feature_code":"PPL",
    "gn:name":"Calichana",
    "gn:population":0,
    "gn:timezone":"America/Guayaquil",
    "iso:country":"EC",
    "wof:name":"Calichana",
    "wof:placetype":"locality"
},
  "geometry": {"coordinates":[-79.80538,-3.38348],"type":"Point"}
}