{
  "type": "Feature",
  "properties": {
    "gn:admin1_code":"12.0",
    "gn:admin2_code":"1102.0",
    "gn:admin3_code":"110250.0",
    "gn:asciiname":"El Toldo",
    "gn:country_code":"EC",
    "gn:dem":2001,
    "gn:feature_class":"P",
    "gn:feature_code":"PPL",
    "gn:name":"El Toldo",
    "gn:population":0,
    "gn:timezone":"America/Guayaquil",
    "iso:country":"EC",
    "wof:name":"El Toldo",
    "wof:placetype":"locality"
},
  "geometry": {"coordinates":[-79.55096999999998,-4.41043],"type":"Point"}
}