{
  "type": "Feature",
  "properties": {
    "gn:admin1_code":"10.0",
    "gn:admin2_code":"901.0",
    "gn:admin3_code":"90150.0",
    "gn:asciiname":"Hacienda Esmeraldita",
    "gn:country_code":"EC",
    "gn:dem":36,
    "gn:feature_class":"P",
    "gn:feature_code":"PPL",
    "gn:name":"Hacienda Esmeraldita",
    "gn:population":0,
    "gn:timezone":"America/Guayaquil",
    "iso:country":"EC",
    "wof:name":"Hacienda Esmeraldita",
    "wof:placetype":"locality"
},
  "geometry": {"coordinates":[-80.18339,-2.30679],"type":"Point"}
}