{
  "type": "Feature",
  "properties": {
    "gn:admin1_code":"10.0",
    "gn:admin2_code":"920.0",
    "gn:admin3_code":"92050.0",
    "gn:asciiname":"El Deleite",
    "gn:country_code":"EC",
    "gn:dem":4,
    "gn:feature_class":"P",
    "gn:feature_code":"PPL",
    "gn:name":"El Deleite",
    "gn:population":0,
    "gn:timezone":"America/Guayaquil",
    "iso:country":"EC",
    "wof:name":"El Deleite",
    "wof:placetype":"locality"
},
  "geometry": {"coordinates":[-79.65000000000001,-2.06667],"type":"Point"}
}