{
  "type": "Feature",
  "properties": {
    "gn:admin1_code":"12.0",
    "gn:admin2_code":"1114.0",
    "gn:admin3_code":"111453.0",
    "gn:asciiname":"Cerro Milagros",
    "gn:country_code":"EC",
    "gn:dem":1050,
    "gn:feature_class":"P",
    "gn:feature_code":"PPL",
    "gn:name":"Cerro Milagros",
    "gn:population":0,
    "gn:timezone":"America/Guayaquil",
    "iso:country":"EC",
    "wof:name":"Cerro Milagros",
    "wof:placetype":"locality"
},
  "geometry": {"coordinates":[-80.14622,-4.08887],"type":"Point"}
}