{
  "type": "Feature",
  "properties": {
    "gn:admin1_code":"9.0",
    "gn:admin2_code":"805.0",
    "gn:admin3_code":"80556.0",
    "gn:asciiname":"Huimbicito",
    "gn:country_code":"EC",
    "gn:dem":36,
    "gn:feature_class":"P",
    "gn:feature_code":"PPL",
    "gn:name":"Huimbicito",
    "gn:population":0,
    "gn:timezone":"America/Guayaquil",
    "iso:country":"EC",
    "wof:name":"Huimbicito",
    "wof:placetype":"locality"
},
  "geometry": {"coordinates":[-78.7681,1.0117],"type":"Point"}
}