{
  "type": "Feature",
  "properties": {
    "gn:admin1_code":"26.0",
    "gn:admin2_code":"2301.0",
    "gn:admin3_code":"230156.0",
    "gn:asciiname":"La Reforma",
    "gn:country_code":"EC",
    "gn:dem":722,
    "gn:feature_class":"P",
    "gn:feature_code":"PPL",
    "gn:name":"La Reforma",
    "gn:population":0,
    "gn:timezone":"America/Guayaquil",
    "iso:country":"EC",
    "name:cym_x_preferred":[
        "La Reforma"
    ],
    "name:nld_x_preferred":[
        "Reforma"
    ],
    "name:por_x_preferred":[
        "La Reforma"
    ],
    "wof:name":"La Reforma",
    "wof:placetype":"locality"
},
  "geometry": {"coordinates":[-79.18307,-0.44764],"type":"Point"}
}