{
  "type": "Feature",
  "properties": {
    "iso:country":"EC",
    "name:fas_x_preferred":[
        "\u0641\u0631\u0648\u062f\u06af\u0627\u0647 \u0628\u06cc\u0646\u200c\u0627\u0644\u0645\u0644\u0644\u06cc \u06a9\u0627\u062a\u0648\u067e\u06a9\u0633\u06cc"
    ],
    "name:fra_x_preferred":[
        "a\u00e9roport du Cotopaxi"
    ],
    "name:jpn_x_preferred":[
        "\u30b3\u30c8\u30d1\u30af\u30b7\u56fd\u969b\u7a7a\u6e2f"
    ],
    "name:kor_x_preferred":[
        "\ucf54\ud1a0\ud30d\uc2dc \uad6d\uc81c\uacf5\ud56d"
    ],
    "name:msa_x_preferred":[
        "Lapangan Terbang Antarabangsa Cotopaxi"
    ],
    "name:pol_x_preferred":[
        "Port lotniczy Latacunga"
    ],
    "name:ron_x_preferred":[
        "Aeroportul Cotopaxi"
    ],
    "name:tgk_x_preferred":[
        "\u0424\u0443\u0440\u0443\u0434\u0433\u043e\u04b3\u0438 \u0431\u0438\u043d\u200c\u0430\u043b\u043c\u0438\u043b\u0430\u043b\u04e3 \u043a\u043e\u0442\u0443\u043f\u043a\u0441\u0438"
    ],
    "name:zho_x_preferred":[
        "\u62c9\u5854\u6606\u52a0"
    ],
    "oa:elevation_ft":"9205",
    "oa:type":"large_airport",
    "woe:hierarchy":{
        "country_id":23424801,
        "county_id":26809578,
        "localadmin_id":26810123,
        "planet_id":1,
        "state_id":2345208
    },
    "wof:name":"Cotopaxi Airport",
    "wof:placetype":"campus"
},
  "geometry": {"coordinates":[-78.615833333333,-0.90694444444444],"type":"Point"}
}