{
  "type": "Feature",
  "properties": {
    "iso:country":"EC",
    "oa:elevation_ft":"9205",
    "oa:type":"large_airport",
    "woe:hierarchy":{
        "country_id":23424801,
        "county_id":26809578,
        "localadmin_id":26810123,
        "planet_id":1,
        "state_id":2345208
    },
    "wof:name":"Cotopaxi Airport",
    "wof:placetype":"campus"
},
  "geometry": {"coordinates":[-78.615833333333,-0.90694444444444],"type":"Point"}
}