{
  "type": "Feature",
  "properties": {
    "gn:admin1_code":"9.0",
    "gn:admin2_code":"803.0",
    "gn:admin3_code":"80357.0",
    "gn:asciiname":"San Gregorio",
    "gn:country_code":"EC",
    "gn:dem":2,
    "gn:feature_class":"P",
    "gn:feature_code":"PPL",
    "gn:name":"San Gregorio",
    "gn:population":0,
    "gn:timezone":"America/Guayaquil",
    "iso:country":"EC",
    "wof:name":"San Gregorio",
    "wof:placetype":"locality"
},
  "geometry": {"coordinates":[-79.97081999999997,0.52889],"type":"Point"}
}