{
  "type": "Feature",
  "properties": {
    "gn:admin1_code":"12.0",
    "gn:admin2_code":"1102.0",
    "gn:admin3_code":"110251.0",
    "gn:asciiname":"Copradia",
    "gn:country_code":"EC",
    "gn:dem":1925,
    "gn:feature_class":"P",
    "gn:feature_code":"PPL",
    "gn:name":"Copradia",
    "gn:population":0,
    "gn:timezone":"America/Guayaquil",
    "iso:country":"EC",
    "wof:name":"Copradia",
    "wof:placetype":"locality"
},
  "geometry": {"coordinates":[-79.73333000000002,-4.25],"type":"Point"}
}