{
  "type": "Feature",
  "properties": {
    "iso:country":"EC",
    "name:ceb_x_preferred":[
        "Machachi"
    ],
    "name:deu_x_preferred":[
        "Machachi"
    ],
    "name:eng_x_preferred":[
        "Machachi"
    ],
    "name:fra_x_preferred":[
        "Machachi"
    ],
    "name:nld_x_preferred":[
        "Machachi"
    ],
    "name:pol_x_preferred":[
        "Machachi"
    ],
    "name:por_x_preferred":[
        "Machachi"
    ],
    "name:que_x_preferred":[
        "Machachi"
    ],
    "name:spa_x_preferred":[
        "Machachi"
    ],
    "name:swe_x_preferred":[
        "Machachi"
    ],
    "name:und_x_variant":[
        "Ciudad de Machachi"
    ],
    "name:urd_x_preferred":[
        "\u0645\u0627\u0686\u0627\u0686\u06cc"
    ],
    "qs:gn_country":"EC",
    "qs:gn_fcode":"PPL",
    "qs:gn_pop":25742,
    "qs:name":"Machachi",
    "qs:name_adm0":"Ecuador",
    "qs:name_adm1":"Pichincha",
    "qs:photos":75,
    "qs:photos_1k":15,
    "qs:photos_9k":1,
    "qs:photos_9r":2,
    "qs:photos_all":75,
    "qs:photos_sr":2,
    "qs:placetype":"Town",
    "qs:pop_sr":"7",
    "qs:woe_adm0":23424801,
    "wd:wordcount":180,
    "wof:name":"Machachi",
    "wof:placetype":"locality",
    "wof:population":25742
},
  "geometry": {"coordinates":[-78.56712,-0.51011],"type":"Point"}
}