{
  "type": "Feature",
  "properties": {
    "gn:admin1_code":"10.0",
    "gn:admin2_code":"906.0",
    "gn:admin3_code":"90656.0",
    "gn:asciiname":"El Baldaco",
    "gn:country_code":"EC",
    "gn:dem":6,
    "gn:feature_class":"P",
    "gn:feature_code":"PPL",
    "gn:name":"El Baldaco",
    "gn:population":0,
    "gn:timezone":"America/Guayaquil",
    "iso:country":"EC",
    "wof:name":"El Baldaco",
    "wof:placetype":"locality"
},
  "geometry": {"coordinates":[-79.93333,-1.91667],"type":"Point"}
}